Workbook
Name _\a: #REF!
Name __\a: #REF!
Name _\AUTOEXEC: #REF!
Name __\AUTOEXEC: #REF!
Name ___\AUTOEXEC: #REF!
Name ____\AUTOEXEC: #REF!
Name _\HOMEPOS: #REF!
Name __\HOMEPOS: #REF!
Name _\k: #REF!
Name __\k: #REF!
Name ___\k: #REF!
Name ____\k: #REF!
Name _\m: #REF!
Name __\m: #REF!
Name ___\m: #REF!
Name ____\m: #REF!
Name _\n: #REF!
Name __\n: #REF!
Name _\o: #REF!
Name __\o: #REF!
Name _\s: #REF!
Name __\s: #REF!
Name ___\s: #REF!
Name ____\s: #REF!
Name _\z: #REF!
Name __\z: #REF!
Name ___\z: #REF!
Name ____\z: #REF!
Name ___________________a2: #REF!
Name ___________________a2: #REF!
Name __________________a2: #REF!
Name __________________a2: #REF!
Name _________________a2: #REF!
Name _________________a2: #REF!
Name ________________a2: #REF!
Name ________________a2: #REF!
Name ________________k116: '[1]Зап-3- СЦБ'!#REF!
Name ________________k116: '[1]Зап-3- СЦБ'!#REF!
Name ________________k116: '[1]Зап-3- СЦБ'!#REF!
Name ________________k116: '[1]Зап-3- СЦБ'!#REF!
Name ________________k121: '[1]Зап-3- СЦБ'!#REF!
Name ________________k121: '[1]Зап-3- СЦБ'!#REF!
Name ________________k121: '[1]Зап-3- СЦБ'!#REF!
Name ________________k121: '[1]Зап-3- СЦБ'!#REF!
Name _______________a2: #REF!
Name _______________a2: #REF!
Name ______________a2: #REF!
Name ______________a2: #REF!
Name ______________k116: '[1]Зап-3- СЦБ'!#REF!
Name ______________k116: '[1]Зап-3- СЦБ'!#REF!
Name ______________k116: '[1]Зап-3- СЦБ'!#REF!
Name ______________k116: '[1]Зап-3- СЦБ'!#REF!
Name ______________k121: '[1]Зап-3- СЦБ'!#REF!
Name ______________k121: '[1]Зап-3- СЦБ'!#REF!
Name ______________k121: '[1]Зап-3- СЦБ'!#REF!
Name ______________k121: '[1]Зап-3- СЦБ'!#REF!
Name _____________a2: #REF!
Name _____________a2: #REF!
Name _____________k116: '[1]Зап-3- СЦБ'!#REF!
Name _____________k116: '[1]Зап-3- СЦБ'!#REF!

Sheet Обложка ДКС

Sheet Тит. лист ДКС

Sheet Тит. лист СГТ

Sheet Содержание
A2: СОДЕРЖАНИЕ
A4: №пп | B4: Обозначение | C4: Наименование | D4: стр.
A5: 1 | B5: 2 | C5: 3 | D5: =C5+1 -> 4
C6: Том 9.2.10
A7: 1 | B7: Сводная смета БЦ | C7: Сводная смета на проектные работы и инженерные изыскания (базисный уровень цен)
A8: =A7+1 -> 2 | B8: Сводная смета ТЦ | C8: Сводная смета на проектные работы и инженерные изыскания (текущий уровень цен)
A9: =A8+1 -> 3 | B9: Исполнительная смета №1.1 | C9: Исполнительная смета на проектные (изыскательские) работы
A10: =A9+1 -> 4 | B10: Смета №1.2 | C10: Смета на инженерно-геодезические изыскания (восстановление и закрепление оси Ж.Д.)
A11: =A10+1 -> 5 | B11: Смета №1.3 | C11: Смета на инженерно-геодезические изыскания (восстановление и закрепление оси трассы А.Д.)
A12: =A11+1 -> 6 | B12: Исполнительная смета №2 | C12: Исполнительная смета на инженерно-гидрометеорологические изыскания
A13: =A12+1 -> 7 | B13: Смета №3 | C13: Инженерно-экологические изыскания
A14: =A13+1 -> 8 | B14: Исполнительная смета №4 | C14: Исполнительная смета на полевые инженерно-геологические работы
A15: =A14+1 -> 9 | B15: Смета №5 | C15: Геофизические работы
A16: =A15+1 -> 10 | B16: Смета №6 | C16: Смета на проектные (изыскательские) работы (пути железнодорожные)
A17: =A16+1 -> 11 | B17: Смета №7 | C17: Смета на проектные (изыскательские) работы (искусственные сооружения)
A18: =A17+1 -> 12 | B18: Смета №8 | C18: Смета на проектные и изыскательские работы (здания и сооружения)
A19: =A18+1 -> 13 | B19: Смета №9 | C19: Смета на проектные и изыскательские работы (водоснабжение и водоотведение)
... A26: =A25+1 -> 20 | B26: Смета №16 | C26: Обследование на участке автомобильной дороги «Подъезд к д. Шоша»

Sheet БЦ
F1: Форма 1пс
A4: СВОДНАЯ СМЕТА
A5: на проектные работы и инженерные изыскания
C6: Организация пассажирского сообщения от станции Москва - Октябрьская - Пассажирская до проектируемого транспортно-пересадочного узла «Завидово» через остановочный пункт Путепроводная Октябрьской железной дороги Этап 2. Строительство железнодорожной линии от примыкания к Октябрьской железной дороге до проектируемого ТПУ «Завидово»
B7: Наименование предприятия,
B8: здания, сооружения
B10: Заказчик | C10: ГКУ "Дирекция ТДФ"
B11: Генеральный проектировщик | C11: ООО "ДСК"
B12: Проектная организация | C12: ОАО "Сибгипротранс"
A14: Составлена в уровне цен на ________________ 20__ г.
A15: № п/п | B15: Наименование смет на проектные работы и инженерные изыскания, затрат | C15: Ссылка на №№смет по формам 2п и 3п | D15: Сметная стоимость, тыс. руб.
D16: инженерных изысканий | E16: проектных работ
A17: 1 | B17: Изыскательские работы
A18: 1 | B18: Инженерно-геодезические изыскания. | C18: 1.1 (ф.2п) | D18: ='№1.1 ИГДИ'!K57 -> 34.28575
A19: 2 | B19: Инженерно-геодезические изыскания. | C19: 1.2 (ф.2п) | D19: ='№1.2 ИГДИ Разбивка ж.д.'!K62 -> 123.30821
A20: 3 | B20: Инженерно-геодезические изыскания. | C20: 1.3 (ф.2п) | D20: ='№1.3 ИГДИ Разбивка а.д.'!K64 -> 7.7589755
A21: 4 | B21: Инженерно-гидрометеорологические изыскания | C21: 2 (ф.2п) | D21: ='№2 ИГМИ'!L263 -> 331.70383
A22: 5 | B22: Инженерно-экологические изыскания. | C22: 3 (ф.2п) | D22: ='№3 ИЭИ'!I45 -> 105.74729
A23: 6 | B23: Инженерно-геологические изыскания. | C23: 4 (ф.2п) | D23: ='№4 ИГИ'!O119 -> 2377.68
A24: 7 | B24: Инженерно-геофизические изыскания. | C24: 5 (ф.2п) | D24: ='№5 ИГФИ'!O64 -> 393.2853
A25: 8 | B25: Обследование на участке автомобильной дороги | C25: 16 (ф.3П) | D25: ='№16 Обследования ОР2'!D20 -> 11.976329
B26: Всего по изыскательским работам | D26: =SUM(D18:D24) -> 3373.7694
B27: Проектная документация
A28: 9 | B28: Пути железнодорожные | C28: 6 (ф.2п) | E28: ='№6 ПД ПЖ'!E37 -> 1205.1736
A29: 10 | B29: Искусственные сооружения | C29: 7 (ф.2п) | E29: ='№7 ПД ИССО'!E55 -> 239.1524
A30: 11 | B30: Здания и сооружения | C30: 8 (ф.2п) | E30: ='№8 ПД Здания'!E51 -> 1966.14
A31: 12 | B31: Водоснабжение и водоотведение | C31: 9 (ф.2п) | E31: ='№9 ПД Водоснабжение'!E31 -> 632.3188
A32: 13 | B32: Электроснабжение и электросовещение | C32: 10 (ф.2п) | E32: ='№10 ПД ЭС'!E725 -> 1549.4105
A33: 14 | B33: Электроснабжение (Тяговая подстанция, Пункт питания) | C33: 11 (ф.2п) | E33: ='№11 УГТ ПД ЭС Тяговые'!I112 -> 497.5484
A34: 15 | B34: Контактная сеть | C34: 12 (ф.2п) | E34: ='№12 УГТ ПД КС'!F52 -> 625.51276
A35: 16 | B35: Устройства СЦБ | C35: 13 (ф.2п) | E35: ='№13 УГТ ПД СЦБ'!I88 -> 2188.948
A36: 17 | B36: Подъездные автомобильные дороги | C36: 14 (ф.2п) | E36: ='№14 ПД АД Подъездные'!G22 -> 80.6084
A37: 18 | B37: Автомобильная дорога Ж.д. переезд | C37: 15 (ф.2п) | E37: ='№15 ПД АД Ж,Д, переезд'!G23 -> 147.168
B38: Всего проектных работ | E38: =SUM(E28:F37) -> 9131.9809
B40: Рабочая документация
A41: 19 | B41: Пути железнодорожные | C41: 6 (ф.2п) | E41: ='№6 ПД ПЖ'!E38 -> 1807.7604
A42: 20 | B42: Искусственные сооружения | C42: 7 (ф.2п) | E42: ='№7 ПД ИССО'!E56 -> 358.7286
A43: 21 | B43: Здания и сооружения | C43: 8 (ф.2п) | E43: ='№8 ПД Здания'!E52 -> 2949.21
A44: 22 | B44: Водоснабжение и водоотведение | C44: 9 (ф.2п) | E44: ='№9 ПД Водоснабжение'!E32 -> 948.4782
A45: 23 | B45: Электроснабжение и электросовещение | C45: 10 (ф.2п) | E45: ='№10 ПД ЭС'!E726 -> 2324.1157
A46: 24 | B46: Электроснабжение (Тяговая подстанция, Пункт питания) | C46: 11 (ф.2п) | E46: ='№11 УГТ ПД ЭС Тяговые'!I113 -> 746.3226
A47: 25 | B47: Контактная сеть | C47: 12 (ф.2п) | E47: ='№12 УГТ ПД КС'!F53 -> 938.26914
A48: 26 | B48: Устройства СЦБ | C48: 13 (ф.2п) | E48: ='№13 УГТ ПД СЦБ'!I89 -> 3283.422
A49: 27 | B49: Подъездные автомобильные дороги | C49: 14 (ф.2п) | E49: ='№14 ПД АД Подъездные'!G23 -> 120.9126
A50: 28 | B50: Автомобильная дорога Ж.д. переезд | C50: 15 (ф.2п) | E50: ='№15 ПД АД Ж,Д, переезд'!G24 -> 220.752
B51: Всего по рабочей документации | E51: =SUM(E41:E50) -> 13697.971
B52: Всего в базовом уровне цен 2001 года | D52: =D26 -> 3373.7694 | E52: =E51+E38 -> 22829.952 | F52: =ROUND(E52,0) -> 22830
B53: Переход от цен на 01.01.2001г к ценам на 01.01.2000г (К=1,266 на ИИ, К=1,19 на ПД) | D53: =D52/1.266 -> 2664.9047 | E53: =E52/1.19 -> 19184.834
B54: Всего по смете в уровне цен на 01.01.2000г | D54: =D53+E53 -> 21849.738
A57: ЗАКАЗЧИК | C57: ПОДРЯДЧИК
A58: И.о. директора ГКУ "Дирекция ТДФ" | C58: Генеральный директор ООО "ДСК"
A61: Е.Г. Скрастынь | C61: С.В. Голубев
A62: М.П. | C62: М.П.
A67: ГИП ОАО "Сибгипротранс" | D67: В.А. Сычев

Sheet 1кв 2024
F1: Форма 1пс
A3: СВОДНАЯ СМЕТА
A4: на проектные работы и инженерные изыскания
C5: Организация пассажирского сообщения от станции Москва - Октябрьская - Пассажирская до проектируемого транспортно-пересадочного узла «Завидово» через остановочный пункт Путепроводная Октябрьской железной дороги Этап 2. Строительство железнодорожной линии от примыкания к Октябрьской железной дороге до проектируемого ТПУ «Завидово»
B6: Наименование предприятия,
B7: здания, сооружения
B9: Заказчик | C9: ГКУ "Дирекция ТДФ"
B10: Генеральный проектировщик | C10: ООО "ДСК"
B11: Проектная организация | C11: ОАО "Сибгипротранс"
A13: Составлена в уровне цен на 1 квартал 2024 г.
A14: № п/п | B14: Наименование смет на проектные работы и инженерные изыскания, затрат | C14: Ссылка на №№смет по формам 2п и 3п | D14: Сметная стоимость, тыс. руб.
D15: инженерных изысканий | E15: проектных работ
A16: 1 | B16: Изыскательские работы
A17: 1 | B17: Инженерно-геодезические изыскания. | C17: 1.1 (ф.2п) | D17: ='№1.1 ИГДИ'!K60 -> 199.88592
A18: 2 | B18: Инженерно-геодезические изыскания. | C18: 1.2 (ф.2п) | D18: ='№1.2 ИГДИ Разбивка ж.д.'!K65 -> 718.88688
A19: 3 | B19: Инженерно-геодезические изыскания. | C19: 1.3 (ф.2п) | D19: ='№1.3 ИГДИ Разбивка а.д.'!K67 -> 45.234827
A20: 4 | B20: Инженерно-гидрометеорологические изыскания | C20: 2 (ф.2п) | D20: ='№2 ИГМИ'!L261 -> 1933.8333
A21: 5 | B21: Инженерно-экологические изыскания. | C21: 3 (ф.2п) | D21: ='№3 ИЭИ'!I44 -> 616.50671
A22: 6 | B22: Инженерно-геологические изыскания. | C22: 4 (ф.2п) | D22: ='№4 ИГИ'!O117 -> 13861.875
A23: 7 | B23: Инженерно-геофизические изыскания. | C23: 5 (ф.2п) | D23: ='№5 ИГФИ'!O63 -> 2292.8533
A24: 8 | B24: Обследование на участке автомобильной дороги | C24: 16 (ф.3П) | D24: ='№16 Обследования ОР2'!D19 -> 69.822
B25: Всего по изыскательским работам | D25: =SUM(D17:D23) -> 19669.075
B26: Проектная документация
A27: 9 | B27: Пути железнодорожные | C27: 6 (ф.2п) | E27: ='№6 ПД ПЖ'!E41 -> 7002.0586
A28: 10 | B28: Искусственные сооружения | C28: 7 (ф.2п) | E28: ='№7 ПД ИССО'!E59 -> 1389.4754
A29: 11 | B29: Здания и сооружения | C29: 8 (ф.2п) | E29: ='№8 ПД Здания'!E55 -> 11423.273
A30: 12 | B30: Водоснабжение и водоотведение | C30: 9 (ф.2п) | E30: ='№9 ПД Водоснабжение'!E35 -> 3673.7722
A31: 13 | B31: Электроснабжение и электросовещение | C31: 10 (ф.2п) | E31: ='№10 ПД ЭС'!E729 -> 9002.075
A32: 14 | B32: Электроснабжение (Тяговая подстанция, Пункт питания) | C32: 11 (ф.2п) | E32: ='№11 УГТ ПД ЭС Тяговые'!I116 -> 2890.7562
A33: 15 | B33: Контактная сеть | C33: 12 (ф.2п) | E33: ='№12 УГТ ПД КС'!F56 -> 3634.2291
A34: 16 | B34: Устройства СЦБ | C34: 13 (ф.2п) | E34: ='№13 УГТ ПД СЦБ'!I92 -> 12717.788
A35: 17 | B35: Подъездные автомобильные дороги | C35: 14 (ф.2п) | E35: ='№14 ПД АД Подъездные'!G25 -> 468.336
A36: 18 | B36: Автомобильная дорога Ж.д. переезд | C36: 15 (ф.2п) | E36: ='№15 ПД АД Ж,Д, переезд'!G26 -> 855.048
B37: Всего проектных работ | E37: =SUM(E27:F36) -> 53056.812
B39: Рабочая документация
A40: 19 | B40: Пути железнодорожные | C40: 6 (ф.2п) | E40: ='№6 ПД ПЖ'!E42 -> 10503.088
A41: 20 | B41: Искусственные сооружения | C41: 7 (ф.2п) | E41: ='№7 ПД ИССО'!E60 -> 2084.2132
A42: 21 | B42: Здания и сооружения | C42: 8 (ф.2п) | E42: ='№8 ПД Здания'!E56 -> 17134.91
A43: 22 | B43: Водоснабжение и водоотведение | C43: 9 (ф.2п) | E43: ='№9 ПД Водоснабжение'!E36 -> 5510.6583
A44: 23 | B44: Электроснабжение и электросовещение | C44: 10 (ф.2п) | E44: ='№10 ПД ЭС'!E730 -> 13503.112
A45: 24 | B45: Электроснабжение (Тяговая подстанция, Пункт питания) | C45: 11 (ф.2п) | E45: ='№11 УГТ ПД ЭС Тяговые'!I117 -> 4336.1343
A46: 25 | B46: Контактная сеть | C46: 12 (ф.2п) | E46: ='№12 УГТ ПД КС'!F57 -> 5451.3437
A47: 26 | B47: Устройства СЦБ | C47: 13 (ф.2п) | E47: ='№13 УГТ ПД СЦБ'!I93 -> 19076.682
A48: 27 | B48: Подъездные автомобильные дороги | C48: 14 (ф.2п) | E48: ='№14 ПД АД Подъездные'!G25 -> 468.336
A49: 28 | B49: Автомобильная дорога Ж.д. переезд | C49: 15 (ф.2п) | E49: ='№15 ПД АД Ж,Д, переезд'!G27 -> 1282.572
B50: Всего по рабочей документации | E50: =SUM(E40:F49) -> 79351.05
B51: Всего в уровне цен на 1 квартал 2024 года | D51: =D25 -> 19669.075 | E51: =E50+E37 -> 132407.86
B52: Итого в уровне цен на 1 квартал 2024 года | D52: =D51+E51 -> 152076.94
A55: ЗАКАЗЧИК | C55: ПОДРЯДЧИК
A56: И.о. директора ГКУ "Дирекция ТДФ" | C56: Генеральный директор ООО "ДСК"
A59: Е.Г. Скрастынь | C59: С.В. Голубев
A60: М.П. | C60: М.П.
A65: ГИП ОАО "Сибгипротранс" | D65: В.А. Сычев

Sheet №1.1 ИГДИ
H1: Форма №2п
B2: Приложение к договору №
B3: (договору, дополнительному соглашению, наряд-заказу)
B5: Исполнительная смета № 1.1
B6: на проектные (изыскательские) работы
B7: Стадия проектирования | C7: Проектная документация
B8: Наименование строительства | C8: Организация пассажирского сообщения от станции Москва-Октябрьская-Пассажирская до проектируемого ТПУ "Завидово" через остановочный пункт Путепроводная Октябрьской железной дороги. Этап 2. Строительство железнодорожной линии от примыкания к Октябрьской железной дороге до проектируемого ТПУ «Завидово»
B9: Наменование проектной
B10: (изыскательской) организации | C10: ОАО "Сибгипротранс"
B11: Наименоваеие организации- | C11: ООО "ДСК"
B12: заказчика
C14: №№ частей, глав, | D14: Расчет стоимости
C15: таблиц, $$ и пунк- | D15: а+вх
A16: № | B16: Характеристика предприятия, здания, | C16: тов указаний к раз- | D16: или объем строитель- | K16: Стоимость
A17: пп | B17: сооружения или виды работ | C17: делу или главе | D17: но монтажных работ | K17: (руб.)
C18: Сборника цен на | D18: х%:100
C19: проектные и изыс- | D19: или количество х цена
C20: кательские работы
A21: 1 | B21: 2 | C21: 3 | D21: 4 | K21: 5
B22: Инженерно-геодезические работы СБЦ-2004г.
A25: 1 | B25: Создание инженерно-топографичес- | C25: Тб.9, §11 | D25: Полевые работы
B26: ких планов М 1:1000, сечение гори-
B27: зонталей 0,5м | D27: 2258 | E27: * | F27: 4.6 | G27: * | H27: 1.55 | K27: =D27*F27*H27 -> 16099.54
B28: Категория сложности II,
B29: застроенная территория
B30: Объём работ: 4,6 га | D30: Камеральные работы
B31: К- 1,2 применение комп.технологий | C31: Об.указания п.15д | D31: 734 | E31: * | F31: 4.6 | G31: * | H31: 1.2 | I31: * | J31: 1.15 | K31: =D31*F31*H31*J31 -> 4659.432
B32: К-1,55 за съемку подзем. коммуникац. | C32: Тб.9, прим. 4
B33: с помощью трубокабелеискателя и
B34: составление плана подземных коммун.
B35: на застр.территории.
B36: К-1,15 за камер.обработ. в поле | C36: Об.указания п.14
B39: Итого | K39: =SUM(K23:K37) -> 20758.972
B40: в т.ч. Полевые работы | K40: =K27 -> 16099.54
B41: Камеральные работы | K41: =K31 -> 4659.432
B42: Прочие расходы
A44: 2 | B44: Расходы по внутреннему транспорту | C44: Тб.4 §3 | D44: =K39 -> 20758.972 | E44: * | F44: 0.1375 | K44: =ROUND(D44*F44,0) -> 2854
B45: при расст. до 15 км, при сметн.
B46: стоимости пол. работ до 75т.р.
B47: 0.1375
A49: 3 | B49: Расходы по внешнему транспорту | C49: Тб.5 §6 | D49: =K39 -> 20758.972 | E49: + | F49: =K44 -> 2854 | G49: * | H49: 0.392 | K49: =ROUND((D49+F49)*H49,0) -> 9256
B50: при расстоянии св.2000 км
B51: и продолжительности работ до 2 мес.
B52: 0.392
A54: 4 | B54: Расходы по организации и ликвидации | C54: Общие указания | D54: =K39+K44 -> 23612.972 | E54: * | F54: 0.06 | K54: =D54*F54 -> 1416.7783
B55: работ 6% | C55: п. 13
B57: Итого по п.п.1-4(в базовых ценах) | K57: =(K39+K44+K49+K54)/1000 -> 34.28575
C58: письмо
A59: 5 | B59: С учётом инфляционного | C59: Минстроя России
B60: коэффициента на I кв. 2024 года - 5,83 | C60: №13023-ИФ/09 | D60: =K57 -> 34.28575 | E60: * | F60: 5.83 | K60: =D60*F60 -> 199.88592
C61: от 07.03.2024г.
B64: Составил: | H64: Д.С. Медведев

Sheet №1.2 ИГДИ Разбивка ж.д.
H1: Форма №2п
B2: Приложение к доп соглашению №
B3: (договору, дополнительному соглашению, наряд-заказу)
B5: СМЕТА №1.2
B6: на инженерно-геодезические изыскания
B7: Стадия проектирования
B8: Наименование строительства | C8: Организация пассажирского сообщения от станции Москва-Октябрьская-Пассажирская до проектируемого ТПУ "Завидово" через остановочный пункт Путепроводная Октябрьской железной дороги. Этап 2. Строительство железнодорожной линии от примыкания к Октябрьской железной дороге до проектируемого ТПУ «Завидово» Восстановление и закрепление оси Ж.Д.
B14: Наменование проектной
B15: (изыскательской) организации | C15: ОАО "Сибгипротранс"
B16: Наименоваеие организации-
B17: заказчика | C17: Заказчик: ООО "ДСК"
C20: №№ частей, глав, | D20: Расчет стоимости
C21: таблиц, $$ и пунк- | D21: а+вх
A22: № | B22: Характеристика предприятия, здания, | C22: тов указаний к раз- | D22: или объем строитель- | K22: Стоимость
A23: пп | B23: сооружения или виды работ | C23: делу или главе | D23: но монтажных работ | K23: (руб.)
C24: Сборника цен на | D24: х%:100
C25: проектные и изыс- | D25: или количество х цена
C26: кательские работы
A27: 1 | B27: 2 | C27: 3 | D27: 4 | K27: 5
B28: Инженерно-геодезические работы изыскания для строительства СБЦ-2006г.
B30: Восстановление трассы | C30: Тб.16, §1 | D30: 3189 | E30: * | F30: 11.86 | K30: =D30*F30 -> 37821.54
B31: железной дороги.
A32: 1 | B32: .Категория сложности II
B33: Объём работ -11,86 км
B35: Закрепление трасс проектируемых | C35: Тб.16, §4 | D35: 1838 | E35: * | F35: 11.86 | K35: =D35*F35 -> 21798.68
B36: железных дорог. Категория
B37: сложности.Категория сложности II
A38: 2 | B38: Объём работ -11,86 км
B41: Изготовление и установка центров. | C41: Тб.10, §5 | D41: 213 | E41: * | F41: 195 | K41: =D41*F41 -> 41535
B42: Пункт разбивочной сети: деревянный
A43: 3 | B43: столб, пень (оформленный под столб),
B44: трубка на бетоне (на глубину до 0,7 м).
B45: Категория грунтов II
B46: Объём работ -195 знаков
B48: Итого по п.п. 1-3 | K48: =K30+K35+K41 -> 101155.22
B49: Прочие расходы
B51: Расходы по внешнему транспорту | D51: =K48 -> 101155.22 | E51: * | F51: 0.392 | K51: =D51*F51 -> 39652.846
A52: 4 | B52: при расстоянии св. 2000 км | C52: Тб.5 §6
B53: и продолжительности работ до 2 мес.
B54: 0.392
A56: 5 | B56: Расходы по внутреннему транспорту | C56: Тб.4 §4 | D56: =K48 -> 101155.22 | E56: * | F56: 0.15 | K56: =D56*F56 -> 15173.283
B57: при расст. от 15 до 20 км, при сметн.
B58: стоимости пол. работ св. 75 до 150 т.р.
B59: 0.15
A60: 6 | B60: Расходы по организации и ликвидации | C60: Общие указания | D60: =K48 -> 101155.22 | E60: + | F60: =K56 -> 15173.283 | G60: * | H60: 0.06 | K60: =(D60+F60)*H60 -> 6979.7102
B61: работ 6% | C61: п. 13
B62: Итого по п.п.1-6 | K62: =(K48+K56+K60)/1000 -> 123.30821
C63: письмо
A64: 7 | B64: С учётом инфляционного | C64: Минстроя России
B65: коэффициента на I кв. 2024 года - 5,83 | C65: №13023-ИФ/09 | D65: =K62 -> 123.30821 | E65: * | F65: 5.83 | K65: =D65*F65 -> 718.88688
C66: от 07.03.2024г.
B68: Составил | H68: Д.С. Медведев

Sheet №1.3 ИГДИ Разбивка а.д.
H1: Форма №2п
B2: Приложение к доп соглашению №
B3: (договору, дополнительному соглашению, наряд-заказу)
B5: СМЕТА №1.3
B6: на инженерно-геодезические изыскания
B7: Стадия проектирования
B8: Наименование строительства | C8: Организация пассажирского сообщения от станции Москва-Октябрьская-Пассажирская до проектируемого ТПУ "Завидово" через остановочный пункт Путепроводная Октябрьской железной дороги. Этап 2. Строительство железнодорожной линии от примыкания к Октябрьской железной дороге до проектируемого ТПУ «Завидово» Восстановление и закрепление оси трассы А.Д.
B14: Наменование проектной
B15: (изыскательской) организации | C15: ОАО "Сибгипротранс"
B16: Наименоваеие организации-
B17: заказчика | C17: Заказчик: ООО "ДСК"
C20: №№ частей, глав, | D20: Расчет стоимости
C21: таблиц, $$ и пунк- | D21: а+вх
A22: № | B22: Характеристика предприятия, здания, | C22: тов указаний к раз- | D22: или объем строитель- | K22: Стоимость
A23: пп | B23: сооружения или виды работ | C23: делу или главе | D23: но монтажных работ | K23: (руб.)
C24: Сборника цен на | D24: х%:100
C25: проектные и изыс- | D25: или количество х цена
C26: кательские работы
A27: 1 | B27: 2 | C27: 3 | D27: 4 | K27: 5
B28: Инженерно-геодезические работы изыскания для строительства СБЦ-2006г.
B30: Восстановление трасс | C30: Тб.16, §1 | D30: 3189 | E30: * | F30: 0.08 | G30: * | H30: 1.2 | K30: =D30*F30*H30 -> 306.144
B31: автомобильных дорог. Категория
A32: 1 | B32: сложности.Категория сложности II
B33: Объём работ -0,08 км
B34: К- 1,2 при длинне трасс до 5км | C34: Тб.16, прим.1
B37: Закрепление трасс проектируемых | C37: Тб.16, §4 | D37: 1838 | E37: * | F37: 0.08 | G37: * | H37: 1.2 | K37: =D37*F37*H37 -> 176.448
B38: автомобильных дорог. Категория
B39: сложности.Категория сложности II
A40: 2 | B40: Объём работ -0,08 км
B41: К- 1,2 при длинне трасс до 5км | C41: Тб.16, прим.1
B43: Изготовление и установка центров. | C43: Тб.10, §5 | D43: 323 | E43: * | F43: 18 | K43: =D43*F43 -> 5814
B44: Пункт разбивочной сети: деревянный
A45: 3 | B45: столб, пень (оформленный под столб),
B46: трубка на бетоне (на глубину до 0,7 м).
B47: Категория грунтов II
B48: Объём работ -18 знаков
B50: Итого по п.п. 1-3 | K50: =K30+K37+K43 -> 6296.592
B51: Прочие расходы
B53: Расходы по внешнему транспорту | D53: =K50 -> 6296.592 | E53: * | F53: 0.392 | K53: =D53*F53 -> 2468.2641
A54: 4 | B54: при расстоянии св. 2000 км | C54: Тб.5 §6
B55: и продолжительности работ до 2 мес.
B56: 0.392
A58: 5 | B58: Расходы по внутреннему транспорту | C58: Тб.4 §4 | D58: =K50 -> 6296.592 | E58: * | F58: 0.1625 | K58: =D58*F58 -> 1023.1962
B59: при расст. от 15 до 20 км, при сметн.
B60: стоимости пол. работ до. 75 т.р.
B61: 0.1625
A62: 6 | B62: Расходы по организации и ликвидации | C62: Общие указания | D62: =K50 -> 6296.592 | E62: + | F62: =K58 -> 1023.1962 | G62: * | H62: 0.06 | K62: =(D62+F62)*H62 -> 439.18729
B63: работ 6% | C63: п. 13
B64: Итого по п.п.1-6 | K64: =(K50+K58+K62)/1000 -> 7.7589755
C65: письмо
A66: 7 | B66: С учётом инфляционного | C66: Минстроя России
B67: коэффициента на I кв. 2024 года - 5,83 | C67: №13023-ИФ/09 | D67: =K64 -> 7.7589755 | E67: * | F67: 5.83 | K67: =D67*F67 -> 45.234827
C68: от 07.03.2024г.
B71: Составил | H71: Д.С. Медведев

Sheet №2 ИГМИ
L1: Форма 2п
A2: Приложение к договору
D4: ИСПОЛНИТЕЛЬНАЯ СМЕТА № 2
A5: на инженерно-гидрометеорологические изыскания
A7: Стадия проектирования | E7: Проектная и рабочая документация
A8: Наименование строительства | E8: Организация пассажирского сообщения от станции Москва - Октябрьская - Пассажирская до проектируемого транспортно-пересадочного узла «Завидово» через остановочный пункт Путепроводная Октябрьской железной дороги Этап 2. Строительство железнодорожной линии от примыкания к Октябрьской железной дороге до проектируемого ТПУ «Завидово»
A10: Наименование проектно
A11: (изыскательской) организации | E11: ОАО "СИБГИПРОТРАНС"
A13: Наименование организации-
A14: заказчика
A16: №№ | B16: Характеристика предприятия, | E16: №№ частей, глав, | G16: Расчет стоимости | L16: Стоимость
A17: пп | B17: здания, сооружения или виды | E17: таблиц, и пунктов | G17: а+ вх | L17: (рублей)
C18: работ | E18: указаний к разделу | G18: или объем строи-
E19: или главе Сборника | G19: тельно монтажных
E20: цен на проектные | G20: работ х% : 100
E21: и изыскательские | G21: или количество
E22: работы для | G22: х цена
E23: строительства
A24: 1 | C24: 2 | E24: 3 | G24: 4 | L24: 5
A25: Справочник базовых цен на инженерные изыскания для строительства , СБЦ - 2001. Инженерно-гидрографические работы.Инженерно-гидрометеорологические изыскания на реках.(цены приведены к базисному уровню на 01.01.91)
A26: 1.Полевые гидрологические и гидрографические работы
A27: 1 | B27: Рекогносцировочное | E27: СБЦ-01 | G27: Полевые работы
B28: обследование рек | E28: табл.43 | G28: 1 | H28: * | I28: 30 | L28: =G28*I28 -> 30
B29: Категория сложности - II | E29: пар.1 | G29: Камеральные работы
B30: Объем работ -1.0 км | G30: 1 | H30: * | I30: 10 | L30: =G30*I30 -> 10
A32: 2 | B32: Рекогносцировочное | E32: СБЦ-01 | G32: Полевые работы
B33: обследование бассейнов (станция) | E33: табл.43 | G33: 1.3 | H33: * | I33: 20 | L33: =G33*I33 -> 26
B34: Категория сложности - II | E34: пар.2 | G34: Камеральные работы
B35: Объем работ - 1.3 км | G35: 1.3 | H35: * | I35: 7 | L35: =G35*I35 -> 9.1
A37: 3 | B37: Разбивка и нивелирование | E37: СБЦ-01 | G37: Полевые работы
B38: морфометрического створа | E38: табл.24, пар. 1 | G38: 0.2 | H38: * | I38: 161 | L38: =G38*I38 -> 32.2
B39: Категория сложности - II | G39: Камеральные работы
B40: Объем работ - 0.2 км | G40: 0.2 | H40: * | I40: 14 | L40: =G40*I40 -> 2.8
B42: в т.ч. Р.Дойбица
A44: 4 | B44: Определение мгновенного уклона
B45: поверхности воды в реке при
B46: количестве урезных кольев
B47: на 1 км длины реки, 3 шт. | E47: т.26, пар.3 | G47: Полевые работы
B48: Объём - 1 определение | E48: п.14 общ.указ. | G48: 1 | H48: * | I48: 174 | L48: =G48*I48 -> 174
B49: Категория сложности - II
B51: Промер глубин | E51: СБЦ-01 | G51: Полевые работы
B52: на участке акватории 1:1000 | E52: табл. 9, пар.21 | G52: 0 | H52: * | I52: 42 | L52: =G52*I52 -> 0
B53: Объём - га | G53: Камеральные работы
G54: 0 | H54: * | I54: 7.5 | L54: =G54*I54 -> 0
B56: Разбивка промерного створа
B57: при ширине реки до 100 м | E57: СБЦ-01 | G57: Полевые работы
B58: Объем - 0 створ | E58: табл. 44, пар.7 | G58: 0 | H58: * | I58: 33 | L58: =G58*I58 -> 0
A60: 5 | B60: Промер глубин | E60: СБЦ-01 | G60: Полевые работы
B61: Объем - 1 профиль (Р.Дойбица) | E61: табл. 48, пар.3 | G61: 1 | H61: * | I61: 19 | L61: =G61*I61 -> 19
A63: 6 | B63: Гидроморфологич. изыскания | E63: СБЦ-01 | G63: Полевые работы
B64: при ширине долины до 1 км | E64: табл.20, пар. 1 | G64: 0.2 | H64: * | I64: 272 | L64: =G64*I64 -> 54.4
B65: Категория сложности - II
B66: Объем работ - 0.2 км
A68: 7 | B68: Установление высот высоких и
B69: других характерных уровней | E69: СБЦ-01 | G69: Полевые работы
B70: воды прошлых лет | E70: табл.25, пар.1 | G70: 0 | H70: * | I70: 133 | L70: =G70*I70 -> 0
B71: Категория сложности - II
B72: Объем работ - 0 компл.
B74: Измерение расхода воды | E74: СБЦ-01 | G74: Полевые работы
B75: детальным способом | E75: табл.48, пар.1 | G75: 0 | H75: * | I75: 78 | L75: =G75*I75 -> 0
B76: при ширине реки до 20 м | G76: Камеральные работы
B77: Объем работ -3 измерения | G77: 0 | H77: * | I77: 17 | J77: * | K77: 1.15 | L77: =G77*I77*K77 -> 0
B78: для водотоков на мост. пер.
B79: при наличии стока
A81: 8 | B81: Фотоработы. | E81: СБЦ-01 | G81: Полевые работы
B82: Объем 11 снимков | E82: табл.48, пар.15 | G82: 11 | H82: * | I82: 7 | L82: =G82*I82 -> 77
B84: Итого пп. 1- 8: | L84: =SUM(L27:L82) -> 434.5
B85: в том числе полевые работы | L85: =L28+L82+L33+L48+L52+L70+L75+L64+L38 -> 393.6
B86: в том числе камеральные работы | L86: =L30+L35+L40+L77 -> 21.9
A88: 9 | B88: Проведение работ в неблагоприятный | E88: т.2, пар.3 | I88: =L84 -> 434.5 | J88: * | K88: 1.3 | L88: =I88*K88 -> 564.85
B89: период (7 мес.)
B90: в том числе полевые работы | L90: =L85*K88 -> 511.68
B91: в том числе камеральные работы | L91: =L86*K88 -> 28.47
A93: 10 | B93: Расходы по внутреннему
B94: транспорту. % от сметной стои- | E94: т.4, пар.2 | G94: =L90 -> 511.68 | H94: * | I94: 0.1125 | L94: =G94*I94 -> 57.564
B95: мости полевых изыскательских
B96: работ от 5 до 10 тыс.руб.и расстоянии
B97: от базы 20-25 км
A99: 11 | B99: Расходы по внешнему транспор- | E99: т.5, пар.6 | G99: =L88 -> 564.85 | H99: + | I99: =L94 -> 57.564 | J99: * | K99: 0.392 | L99: =(G99+I99)*K99 -> 243.98629
B100: ту при расстоянии св. 2000 км
A102: 12 | B102: Расходы по организации и
B103: ликвидации работ | E103: п.13 общ.указ., | G103: =L88 -> 564.85 | H103: + | I103: =L94 -> 57.564 | J103: * | K103: 0.06 | L103: =(G103+L94)*K104*0.06 -> 93.3621
E104: прим. 1 | J104: * | K104: 2.5
B105: Итого пп. 1- 12: | L105: =L88+L94+L99+L103 -> 959.76239
A107: 13 | B107: Районная надбавка на полевые | E107: СБЦ-01
B108: работы. Районный коэффициент | E108: п.8 (д,е), табл.3, | I108: =L105 -> 959.76239 | J108: * | K108: 0 | L108: =I108*K108 -> 0
B109: к зар. плате 1.3 (для полевых партий ) | E109: Прил.4 п.9
B111: Итого пп. 1-13: | L111: =L105+L108 -> 959.76239
A112: 2. Камеральные гидрометеорологические работы
A114: 1 | B114: Составление морф.профиля | E114: СБЦ-01 | G114: 2 | H114: * | I114: 6.7 | L114: =G114*I114 -> 13.4
B115: Категория сложности - II | E115: табл.39, пар.1
B116: Объем работ - 2 профиля по 1 дм
A119: 2 | B119: Составление таблицы | E119: СБЦ - 01 | G119: 1 | H119: * | I119: 105 | L119: =G119*I119 -> 105
B120: гидрологической изученности | E120: тб. 51
B121: Объем работ - 1 таблица | E121: пар.2
A123: 3 | B123: Составление схемы гидрометео- | E123: СБЦ - 01 | G123: 3 | H123: * | I123: 61 | L123: =G123*I123 -> 183
B124: рологической изуч., схемы гидрографич. | E124: тб.51, пар.3
B125: схема вдсб.басс.
B126: Объем работ - 3 схемы
A128: 4 | B128: Систематизация материалов | E128: СБЦ - 01 | G128: 334 | H128: * | I128: 10 | L128: =G128*I128 -> 3340
...

Sheet №3 ИЭИ
A1: Смета № 4
A2: на инженерно-экологические изыскания
A3: Наименование объекта изысканий | C3: «Организация пассажирского сообщения от станции Москва – Октябрьская – Пассажирская до проектируемого ТПУ «Завидово» через остановочный пункт Путепроводная Октябрьской железной дороги Этап 2. Строительство железнодорожной линии от примыкания к Октябрьской железной дороге до проектируемого ТПУ «Завидово»
A4: Заказчик: | C4: Государственное казенное учреждение Тверской области «Дирекция территориального дорожного фонда Тверской области
A5: Исполнитель: | C5: ОАО «Сибгипротранс»
A6: Сметный расчет составлен по следующим документам:
A7: СБЦ-99. Инженерно-геологические и инженерно-экологические изыскания для строительства
A8: № пп | B8: Виды работ | C8: Таблица, параграф | D8: Единицы измерения | E8: Цена единицы работ, руб. | F8: Коэффициенты | H8: Объем работ | I8: Стоимость, руб.
A9: ПОДГОТОВИТЕЛЬНЫЕ РАБОТЫ
B10: Составление и согласование программы исследований | C10: т.81 п.1 | D10: прогр. | E10: 200 | G10: 1.25 | H10: 1 | I10: =H10*E10*G10 -> 250
B11: Районный коэффициент к сметной стоимости | C11: т.3 п.3 | G11: 1.1
B12: Итого по подготовительным работам: | I12: =(I10)*G11 -> 275
A13: ПОЛЕВЫЕ РАБОТЫ
B14: Маршрутное обследование для составления инженерно-экологических карт м-ба 1:25000 при удовлетворительной проходимости | C14: т.10 п.2 | D14: км | E14: 16.6 | F14: 1.3 | H14: 18.5 | I14: =H14*E14*F14 -> 399.23
B15: Описание точек наблюдений при составлении инженерно-экологических карт (МЭД) | C15: т.11 п.2 | D15: 1 точка | E15: 11.7 | G15: 0.3 | H15: 370 | I15: =H15*E15*G15 -> 1298.7
B16: Отбор объединённых проб почво-грунтов для анализа на загрязнённость по химическим показателям (методами конверта) | C16: т.60 п.7 | D16: 1 проба | E16: 6.9 | F16: 0.9 | H16: 30 | I16: =H16*F16*E16 -> 186.3
B17: Отбор объединённых проб почво-грунтов для анализа на ЕРН | C17: т.60 п.7 | D17: 1 проба | E17: 6.9 | F17: 1.2 | H17: 12 | I17: =H17*F17*E17 -> 99.36
B18: Итого полевых работ: | I18: =SUM(I14:I17) -> 1983.59
A19: ЛАБОРАТОРНЫЕ РАБОТЫ
A20: Почвы (6)
B21: Водородный показатель рН водной вытяжки | C21: табл. 70, § 14 | D21: проба | E21: 2 | H21: 6 | I21: =H21*E21 -> 12
B22: Ртуть | C22: табл. 70, § 57 | D22: проба | E22: 7.8 | H22: 6 | I22: =PRODUCT(E22,H22) -> 46.8
B23: Мышьяк | C23: табл. 70, § 57 | D23: проба | E23: 7.8 | H23: 6 | I23: =H23*E23 -> 46.8
B24: Медь, цинк | C24: табл. 70, § 57 | D24: проба | E24: =7.8*2 -> 15.6 | H24: 6 | I24: =PRODUCT(E24,H24) -> 93.6
B25: Свинец | C25: табл. 70, § 57 | D25: проба | E25: 7.8 | H25: 6 | I25: =H25*E25 -> 46.8
B26: Кадмий | C26: табл. 70, § 57 | D26: проба | E26: 7.8 | H26: 6 | I26: =PRODUCT(E26,H26) -> 46.8
B27: Никель | C27: табл. 70, § 57 | D27: проба | E27: 7.8 | H27: 6 | I27: =H27*E27 -> 46.8
B28: Нефтяные углеводороды | C28: табл. 70, § 63 | D28: проба | E28: 19.7 | H28: 6 | I28: =PRODUCT(E28,H28) -> 118.2
B29: Бенз(а)пирен | C29: табл. 70, § 66 | D29: проба | E29: 95.8 | H29: 6 | I29: =H29*E29 -> 574.8
B30: Определение радионуклидов хроматомасс-спектрометрическим методом | C30: табл. 70, § 69 | D30: проба | E30: 147.4 | H30: 6 | I30: =PRODUCT(E30,H30) -> 884.4
B31: Итого лабораторных работ: | I31: =SUM(I21:I30) -> 1917
A32: КАМЕРАЛЬНЫЕ РАБОТЫ
B33: Составление инженерно-экологических карт м-ба 1: 25000 при удовлетворительной проходимости | C33: т.10 п.2 | D33: км | E33: 1.7 | F33: 1.3 | H33: 18.5 | I33: =H33*F33*E33 -> 40.885
B34: Описание точек наблюдений при составлении инженерно-экологических карт (МЭД) | C34: т.11 п.2 | D34: 1 точка | E34: 7.5 | F34: 1.15 | G34: 0.3 | H34: 370 | I34: =H34*E34*F34*G34 -> 957.375
B35: Обработка лабораторных анализов | C35: т.86 п.6 | D35: % | E35: 20 | I35: =I31*(E35/100) -> 383.4
B36: Итого камеральных работ: | I36: =I33+I34+I35 -> 1381.66
B37: Составление технического отчёта | C37: т.87 п.1 | D37: % | E37: 21 | I37: =SUM(I36+I18)*(E37/100) -> 706.7025
B38: Итого камеральных работ с учетом районного коэффициента: Новосибирская обл., г.Новосибирск | G38: 1.1 | I38: =SUM(I33:I37)*G38 -> 3817.0248
A39: ПРОЧИЕ РАСХОДЫ
B40: Внутренний транспорт при расстоянии 20-25 км и стоимости полевых работ до 5 тыс. руб. | C40: т.4 п.5 | D40: % | E40: 18.75 | I40: =I18*E40/100 -> 371.92313
B41: Внешний транспорт при расстоянии от 1000 до 2000 | C41: т. 5 п.5 | D41: % | E41: 32.2 | I41: =(I18+I40)*E41/100 -> 758.47523
B42: Организация и ликвид. работ | C42: ОУ п.13 | D42: % | E42: 6 | I42: =(I18+I41)*E42/100 -> 164.52391
B43: ИТОГО в ценах СБЦ-99 | I43: =SUM(I12,I18,I38,I31,I40,I41,I42)/1000 -> 9.287537
B44: ИТОГО с индексом сметной стоимости изыскательских работ 1 кв. 2024 г. (К =66,38 Письмо Минстроя России от 07.03.2024 N 13023-ИФ/09) | I44: =(SUM(I12,I18,I38,I31,I40,I41,I42)*66.38)/1000 -> 616.50671
B45: Переход цен от I кв. 2024г к ценам 01.01.2001г (К=5,83) | I45: =I44/5.83 -> 105.74729
B47: Составил | E47: Д.В. Половников

Sheet №4 ИГИ
A1: ИСПОЛНИТЕЛЬНАЯ СМЕТА № 4
A2: на полевые инженерно-геологические работы
A4: Стадия проектирования | D4: Проектная документация
A5: Наименование строительства | D5: Организация пассажирского сообщения от станции Москва-Октябрьская-Пассажирская до проектируемого транспортно-пересадочного узла "Завидово" через остановочный пункт Путепроводная Октябрьской железной дороги Этап 2. Строительство железнодорожной линии от примыкания к Октябрьской железной дороге до проектируемого ТПУ «Завидово»
A6: Наименование организации | D6: ООО "ДСК"
A7: подрядчика
A8: Наименование изыскательской | D8: ОАО "Сибгипротранс"
A9: организации
A10: № п/п | B10: виды работ | D10: Обоснование стоимости | E10: Расчёт стоимости | O10: Стоимость (рублей)
B11: Наименование | C11: кол-во
A12: 1 | B12: 2 | D12: 3 | E12: 4 | O12: 5
A13: ИНЖЕНЕРНО-ГЕОЛОГИЧЕСКИЕ РАБОТЫ
A14: СБЦ-99 Справочник базовых цен на инженерно-геологические и инженерно-экологические изыскания для строительства (цены приведены к базисному уровню на 01.01.1991г). Москва 1999г
A15: Категория сложности инженерно-геологических условий III (сложная)
A16: Продолжительность неблагоприятного периода 6,5 мес (15-20/X по 1-5/V)
A17: I. ПОЛЕВЫЕ РАБОТЫ
A18: 1 | B18: Инженерно-геологическое рекогносцировочное обследование трассы район II кат.сложности при удовлетворительной проходимости | C18: 29.54 | D18: табл.9, п.2 | J18: =SUM(C18) -> 29.54 | K18: * | L18: 27 | O18: =SUM(J18*L18) -> 797.58
B19: Буровые работы
A20: 2 | B20: Бурение скважин колонковым способом Ø св.160мм глубиной до 15м в грунтах: | D20: табл.17
B21: II категории, п.м. | C21: 654.7 | D21: п.1 | G21: =SUM(C21) -> 654.7 | H21: * | J21: 38.4 | K21: * | L21: 0.9 | O21: =ROUND(G21*J21*L21,0) -> 22626
B22: III категории, п.м. | C22: 730.3 | G22: =SUM(C22) -> 730.3 | H22: * | J22: 42.6 | K22: * | L22: 0.9 | O22: =ROUND(G22*J22*L22,0) -> 28000
B23: Всего метров: | C23: =SUM(C21:C22) -> 1385
B24: К-0,9 бурение без устройства циркуляционной системы | D24: табл.17, прим.
A25: 3 | B25: Бурение скважин колонковым способом Ø до 160мм глубиной св. 15 до 25м в грунтах: | D25: табл.17
B26: III категории, п.м. | C26: 70 | G26: =SUM(C26) -> 70 | H26: * | J26: 36.2 | K26: * | L26: 0.9 | O26: =ROUND(G26*J26*L26,0) -> 2281
B27: Всего метров: | C27: =SUM(C26:C26) -> 70
A28: 4 | B28: Бурение скважин колонковым способом Ø до 160мм глубиной св.25 до 50 м в грунтах: | D28: табл.17
B29: III категории, п.м. | C29: 100 | G29: =SUM(C29) -> 100 | H29: * | J29: 31.3 | K29: * | L29: 0.95 | O29: =ROUND(G29*J29*L29,0) -> 2974
B30: Всего метров: | C30: =SUM(C29:C29) -> 100
B31: Бурение скважин колонковым способом Ø до 160мм глубиной св.50 м в грунтах:
B33: III категории, п.м. | C33: 5 | G33: =SUM(C33) -> 5 | H33: * | J33: 27.5 | K33: * | L33: 0.95 | O33: =ROUND(G33*J33*L33,0) -> 131
B34: К-0,9 К-0,95 бурение без устройства циркуляционной системы | D34: табл.17, прим.
A35: 5 | B35: Гидрогеологические наблюдения при бурении скважин Ø до 160мм. глубиной до 25м | D35: табл.18, п.1 | J35: 911.9 | K35: * | L35: 1.6 | M35: * | N35: 0.6 | O35: =ROUND(J35*L35*N35,0) -> 875
B36: К-0,6 -гидрогеологические наблюдения без "тартания" | D36: Часть 2, Глава 4, п.8
A37: 6 | B37: Гидрогеологические наблюдения при бурении скважин Ø до 160мм. Глубиной св.25 до 50 м | D37: табл.18, п.1 | J37: 110.8 | K37: * | L37: 1.8 | M37: * | N37: 0.6 | O37: =ROUND(J37*L37*N37,0) -> 120
B38: К-0,6 -гидрогеологические наблюдения без "тартания" | D38: Часть 2, Глава 4, п.8
A39: 7 | B39: Гидрогеологические наблюдения при бурении скважин Ø до 160мм. глубиной св.50,0м | D39: табл.18, п.1 | J39: 48.3 | K39: * | L39: 2 | M39: * | N39: 0.6 | O39: =ROUND(J39*L39*N39,0) -> 58
B40: К-0,6 -гидрогеологические наблюдения без "тартания"
A41: 8 | B41: Крепление скважин при бурении Ø до 160мм - 50% | D41: табл.18, п.4 | J41: 1064 | K41: * | L41: 2.1 | M41: * | N41: 0.5 | O41: =ROUND(J41*L41*N41,0) -> 1117
B42: Горнопроходческие работы
A43: 9 | B43: Проходка шурфов глубиной до 2,5 м сечением до 2,5 м2 в грунтах
B44: II категории, п.м. | C44: 13.2 | G44: =SUM(C44) -> 13.2 | I44: * | J44: 34.4 | O44: =ROUND(G44*J44,0) -> 454
B45: III категории, п.м. | C45: 7.65 | G45: =SUM(C45) -> 7.65 | I45: * | J45: 42.1 | O45: =ROUND(G45*J45,0) -> 322
B46: Итого по п.п.1-9 | O46: =SUM(O18:O45) -> 59755.58
B47: Полевые исследования грунтов и отбор проб
A48: 10 | B48: Отбор монолитов связных грунтов с глубины, м | D48: табл.57
B49: до 10м, мон | C49: 149 | D49: п.1 | J49: =SUM(C49) -> 149 | K49: * | L49: 22.9 | O49: =ROUND(J49*L49,0) -> 3412
B50: св.10 до 20, мон. | C50: 36 | D50: п.2 | J50: =SUM(C50) -> 36 | K50: * | L50: 30.6 | O50: =ROUND(J50*L50,0) -> 1102
B51: св.20 до 30, мон. | C51: 30 | D51: п.3 | J51: =SUM(C51) -> 30 | K51: * | L51: 36.8 | O51: =ROUND(J51*L51,0) -> 1104
B52: св.30 до 40, мон. | C52: 24 | D52: п.4 | J52: =SUM(C52) -> 24 | K52: * | L52: 38.8 | O52: =ROUND(J52*L52,0) -> 931
B53: св.40, мон. | C53: 7 | D53: п.5 | J53: =SUM(C53) -> 7 | K53: * | L53: 42.7 | O53: =ROUND(J53*L53,0) -> 299
A54: 11 | B54: Статическое зондирование грунтов непрерывным вдавливанием зонда со скоростью не свыше 1 м/мин до глубины: | D54: табл.45, п.5
B55: св.10 до 15 м, испыт. | C55: 8 | J55: =SUM(C55) -> 8 | K55: * | L55: 172.5 | O55: =ROUND(J55*L55,0) -> 1380
B56: св.20 до 25 м, испыт. | C56: 7 | G56: =SUM(C56) -> 7 | I56: * | J56: 216.8 | O56: =ROUND(G56*J56,0) -> 1518
A57: 12 | B57: Испытание грунтов в буровых скважинах на глубине до 10 м вертикальной статической нагрузкой штампом площадью 600 см2 удельным давлением, МПа: | D57: табл.54
B58: св.0,3 до 0,5 МПа | C58: 4 | D58: п.16 | J58: 4 | K58: * | L58: 487 | O58: =ROUND(J58*L58,0) -> 1948
A59: 13 | B59: Испытание грунтов методом вращательного среза до глубины 10 м, испыт. | C59: 6 | D59: табл.46, п.1 | J59: =SUM(C59) -> 6 | K59: * | L59: 30.4 | O59: =ROUND(J59*L59,0) -> 182
B60: Итого п.п.10-13 | O60: =SUM(O48:O59) -> 11876
A61: Итого по разделу I (полевые работы) | O61: =SUM(O46,O60) -> 71631.58
A62: II. ЛАБОРАТОРНЫЕ РАБОТЫ
B63: Глинистые грунты
A64: 14 | B64: Консистенция при нарушенной структуре | C64: 448 | D64: табл.63, п.3 | J64: =SUM(C64) -> 448 | K64: * | L64: 18.2 | O64: =ROUND(J64*L64,0) -> 8154
A65: 15 | B65: Полный комплекс определений физических свойств | C65: 133 | D65: табл.63, п.8 | J65: =SUM(C65) -> 133 | K65: * | L65: 47.1 | O65: =ROUND(J65*L65,0) -> 6264
A66: 15а | B66: Гранулометрический анализ ситовым методом пипетки, опр. | C66: 44 | D66: табл.63, п.21 | J66: =SUM(C66) -> 44 | K66: * | L66: 19.6 | O66: =ROUND(J66*L66,0) -> 862
A67: 16 | B67: Полный комплекс физико-механических свойств грунта. С определением сопротивления грунта срезу (консолидированный срез) под нагрузкой до 0,6 МПа | C67: 57 | D67: табл.63, п.25 | J67: =SUM(C67) -> 57 | K67: * | L67: 193 | O67: =ROUND(J67*L67,0) -> 11001
A68: 17 | B68: Сокращенный комплекс физико-механических свойств грунта. Показатели сжимаемости и сопутствующие определения при компрессионных испытаниях по одной ветви с нагрузкой до 0,6 МПа | C68: 40 | D68: табл.63, п.17 | J68: =SUM(C68) -> 40 | K68: * | L68: 101.9 | O68: =ROUND(J68*L68,0) -> 4076
A69: 18 | B69: Сокращенный комплекс физико-механических свойств грунта при неконсолидированном срезе с нагрузкой до 0,6 МПа | C69: 16 | D69: табл.63, п.13 | J69: =SUM(C69) -> 16 | L69: 114.4 | O69: =ROUND(J69*L69,0) -> 1830
A70: 19 | B70: Определение характеристик прочности и деформируемости при трехосном сжатии | C70: 42 | D70: табл.66, п.4 | J70: =SUM(C70) -> 42 | K70: * | L70: 741.4 | O70: =ROUND(J70*L70,0) -> 31139
A71: 20 | B71: Определение содержания органических веществ, опр. | C71: 4 | D71: табл.70, п.11 | J71: =SUM(C71) -> 4 | K71: * | L71: 8.6 | O71: =ROUND(J71*L71,0) -> 34
B72: Песчаные и крупнообломочные грунты
A73: 21 | B73: Гранулометрический анализ ситовым методом с разделением на фракции от 10 до 0,5мм, опр. | C73: 136 | D73: табл.64, п.6 | J73: =SUM(C73) -> 136 | K73: * | L73: 4 | O73: =ROUND(J73*L73,0) -> 544
A74: 22 | B74: То же с разделением на фракции 0,5; 0,25; 0,1 мм (с кипячением и промывкой) | C74: 19 | D74: табл.64. п.7 | J74: =SUM(C74) -> 19 | K74: * | L74: 6.7 | O74: =ROUND(J74*L74,0) -> 127
A75: 23 | B75: Влажность | C75: 7 | D75: табл.64. п.1 | J75: 13 | K75: * | L75: 1.9 | O75: =ROUND(J75*L75,0) -> 25
A76: 24 | B76: Полный комплекс определений физических свойств | C76: 10 | D76: табл.65, п.1 | J76: =SUM(C76) -> 10 | K76: * | L76: 45.5 | O76: =ROUND(J76*L76,0) -> 455
B77: Биогенные грунты
A78: 25 | B78: Влажность торфа | C78: 5 | D78: табл.69, п.1 | J78: =SUM(C78) -> 5 | K78: * | L78: 5.3 | O78: =ROUND(J78*L78,0) -> 27
A79: 26 | B79: Степень разложения торфа | C79: 5 | D79: табл.69, п.5 | J79: =SUM(C79) -> 5 | L79: 4.9 | O79: =ROUND(J79*L79,0) -> 25
B80: Исследование химического состава грунтов и воды
A81: 27 | B81: Корроз. активность грунтов по отношению к стали, опр | C81: 30 | D81: табл.75, п.4 | J81: =SUM(C81) -> 30 | K81: * | L81: 18.2 | O81: =ROUND(J81*L81,0) -> 546
A82: 28 | B82: Анализ водной вытяжки, опр. | C82: 24 | D82: табл.71,п.2 | J82: =SUM(C82) -> 24 | K82: * | L82: 58.3 | O82: =ROUND(J82*L82,0) -> 1399
A83: 29 | B83: Подготовка водной вытяжки | C83: 24 | D83: табл.71, п.83 | J83: =SUM(C83) -> 24 | K83: * | L83: 3.8 | O83: =ROUND(J83*L83,0) -> 91
A84: 30 | B84: Химический анализ воды, опр. | C84: 5 | D84: табл.73, п.1 | J84: =SUM(C84) -> 5 | K84: * | L84: 96.2 | O84: =ROUND(J84*L84,0) -> 481
A85: Итогопо разделу II (лабораторные работы) | O85: =SUM(O64:O84) -> 67080
A86: III. КАМЕРАЛЬНЫЕ РАБОТЫ
A87: 31 | B87: Составление программы работ для районов II кат. сложности на площадь изысканий до 1 кв. км, при средней глубине скважин св. 10 до 15 м | D87: табл.81, п.3 | J87: 1 | K87: * | L87: 800 | M87: * | N87: 1.25 | O87: =ROUND(J87*L87*N87,0) -> 1000
B88: К-1,25 для районов II категории сложности | D88: табл.81, прим.1
A89: 32 | B89: Камеральная обработка инженерно-геологической рекогносцировки при удовлетворительной проходимости в районе II категории сложности | C89: =SUM(C18) -> 29.54 | D89: Табл.9,п.2 | J89: =SUM(C89) -> 29.54 | K89: * | L89: 18.5 | O89: =SUM(J89*L89) -> 546.49
A90: 33 | B90: Камеральная обработка материалов буровых и горнопроходческих работ c гидрогеологическими наблюдениями, п.м. | D90: табл.82
B91: без гидрогеологических наблюдений | C91: 507.3 | D91: п.1 | J91: =SUM(C91) -> 507.3 | K91: * | L91: 10.7 | M91: * | N91: 1.2 | O91: =ROUND(J91*L91,0) -> 5428
B92: с гидрогеологическими наблюдениями | C92: 1073.55 | D92: п.2 | J92: =SUM(C92) -> 1073.55 | K92: * | L92: 10.7 | M92: * | N92: 1.2 | O92: =ROUND(J92*L92,0) -> 11487
B93: К-1,2 составление предварительных геологических и литологических профилей в зависимости от сложности инженерно-геологических условий | D93: табл.82, прим.3
A94: 34 | B94: Камеральная обработка полевого испытания грунтов: | D94: табл.83
B95: статическое зондирование на глубину
B96: св.10 до 15 м, испыт. | C96: =SUM(C55) -> 8 | D96: п.3 | J96: =SUM(C96) -> 8 | K96: * | L96: 38.3 | O96: =ROUND(J96*L96,0) -> 306
B97: св.20 до 25 м, испыт. | C97: =SUM(C56) -> 7 | D97: п.3 | J97: =SUM(C97) -> 7 | K97: * | L97: 48.2 | O97: =ROUND(J97*L97,0) -> 337
B98: вращательный срез | C98: =SUM(C59) -> 6 | D98: п.4 | J98: =SUM(C98) -> 6 | K98: * | L98: 8.1 | O98: =ROUND(J98*L98,0) -> 49
B99: штамповые испытания | C99: =SUM(C58) -> 4 | J99: =SUM(C99) -> 4 | K99: * | L99: 94.7 | O99: =ROUND(J99*L99,0) -> 379
A100: 35 | B100: Обработка лабораторных даных: | D100: табл.86
B101: глинистых грунтов 20% | D101: п.1 | J101: =SUM(O64:O71) -> 63360 | K101: * | L101: 0.2 | O101: =ROUND(J101*L101,0) -> 12672
B102: песчаных и крупнообломочных 15% | D102: п.2 | J102: =SUM(O73:O76) -> 1151 | K102: * | L102: 0.15 | O102: =ROUND(J102*L102,0) -> 173
...

Sheet №5 ИГФИ
A1: СМ | O1: Форма №2п
A2: С М Е Т А №5
A3: геофизические работы
A5: Стадия проектирования | D5: Проектная документация
A6: Наименование строительства | D6: Организация пассажирского сообщения от станции Москва - Октябрьская - Пассажирская до проектируемого транспортно-пересадочного узла «Завидово» через остановочный пункт Путепроводная Октябрьской железной дороги Этап 2. Строительство железнодорожной линии от примыкания к октябрьской железной дороге до проектируемого тпу «завидово»
A7: Наименование организации заказчика | D7: ООО "ДСК"
A8: Наименование проектной (изыскательской) организации | D8: ОАО "Сибгипротранс"
A9: № п/п | B9: виды работ | D9: № частей, глав, таблиц,пунктов, указаний к разделу или главе Сборника цен | E9: Расчёт стоимости объём строительно-монтажных работ х% : 100 или количества х цена | O9: Стоимость (рублей)
B10: Наименование | C10: кол-во
A11: 1 | B11: 2 | C11: 3 | D11: 4 | E11: 5 | O11: 6
A12: СЦР-82 -Сборник цен на изыскательские работы для капитального строительства
A13: Категория сложности для сейсморазведки, электроразведки - III (глава 16. Геофизические работы. Общие положения)
A14: Категория сложности для определения коррозионной активности грунтов и интенсивности блуждающих токов - II (Глава 16. Геофизические работы. стр. 279)
A15: Продолжительность неблагоприятного периода 6,5 месяцев с 20/X по 5/V
A16: Полевые работы
A17: Сейсморазведка
A18: 1 | B18: Сейсморазведка (сейсмотомография (МПВ, МОВ) 48 канальной сейсмостанцией, при возбуждении колебаний ударами кувалды при шаге наблюдений до 5м. | C18: 192 | D18: таб.258, п.83 | G18: =SUM(C18) -> 192 | I18: * | J18: 10 | K18: * | L18: 1.1 | O18: =ROUND(G18*J18*L18,0) -> 2112
B19: Коэффициенты:
B20: К 1- механические и электрические помехи | C20: 1.1 | D20: Глава 16, п.5
A21: Электроразведочные работы
A22: 2 | B22: Георадарное зондирование , физ.набл. | C22: 4000 | D22: таб. 270, п.1(применительно) | G22: =SUM(C22) -> 4000 | I22: * | J22: 1 | O22: =ROUND(G22*J22,0) -> 4000
A23: 3 | B23: Измерение удельного электирческого сопротивления грунта четырехэлектродной установкой при расстоянии между точками св.100 до 200 м | C23: 150 | D23: таб. 267, п.3. | G23: =SUM(C23) -> 150 | I23: * | J23: 1.5 | K23: * | L23: =SUM(C29) -> 1.32 | O23: =ROUND(G23*J23*L23,0) -> 297
B24: Коэффициенты:
B25: К 1- механические и электрические помехи | C25: 1.1 | D25: Глава 16, п.5
B26: К 2 - переноска оборудования с профиля на профиль на расстояние до 200м | C26: 1.2 | D26: Глава 16, п.6
B27: К 3 - заземление электродов в сухих породах в случае подлива воды | C27: 1 | D27: табл.265, п. 3
B28: К 4 - разность потенциалов до 0,3 мВ, неустойчивые точки ПС | C28: 1 | D28: табл.265, п. 4
B29: Кобщ = | C29: =SUM(C25*C26*C27*C28) -> 1.32
A30: 4 | B30: Измерение разности потенциалов между двумя точками земли при расстоянии до 200м (интенсивность блуждающих токов). Измерение самопишушими приборами при длительности записи до 1 ч, измерение | C30: 18 | D30: табл.283, п.2 | G30: =SUM(C30) -> 18 | I30: * | J30: 15 | K30: * | L30: =SUM(C34) -> 1.1 | O30: =ROUND(G30*J30*L30,0) -> 297
B31: Коэффициенты:
B32: К 1- механические и электрические помехи | C32: 1.1 | D32: Глава 16, п.5
B33: К 2 - расстояние св.200 до 500 м | C33: 1 | D33: табл.283, прим.
B34: Кобщ = | C34: =SUM(C32*C33) -> 1.1
A35: 5 | B35: Вертикальное электрическое зондирование с поверхности земли четырехэлекродной установкой (в модификации электротомографии) Длина установки св 25 до 500 м | C35: =64*3 -> 192 | D35: табл.267, п.4 | G35: 192 | I35: * | J35: 13.5 | K35: * | L35: 1.1 | O35: =ROUND(G35*J35*L35,0) -> 2851
B36: Коэффициенты:
B37: К 1- механические и электрические помехи | C37: 1.1 | D37: Глава 16, п.5
B38: Кобщ = | C38: =C37 -> 1.1
A39: Итого по п.п. 1-5 с учетом коэффициента | D39: прил. к постановлению Госстроя СССР №22 от 01.03.90. Общ.указ
B40: к-1,1 - метрологическое обеспечение единства точности измерений | J40: =SUM(O18:O35) -> 9557 | K40: * | L40: 1.1 | O40: =ROUND(J40*L40,0) -> 10513
A41: 6 | B41: Планово-высотная привязка точек геофизической разведки | C41: =SUM(C18+C30+C35+70) -> 472 | D41: табл.78, п.2, кат III | J41: =SUM(C41) -> 472 | K41: * | L41: 4.2 | O41: =ROUND(J41*L41,0) -> 1982
A42: Итого полевые работы | J42: =SUM(O40:O41) -> 12495 | K42: * | L42: 1.2 | O42: =SUM(J42*L42) -> 14994
A43: К-1,2 неблагоприятный период | D43: табл.2, постановление Госстроя СССР №22 от 01.03-90
A44: Камеральные работы
A45: 7 | B45: Составление программы работс ( при стоимости изысканий св.10 до 25 т.р.) | D45: СЦР-82 таб.294, п.2 | J45: 1 | K45: * | L45: 400 | O45: =ROUND(J45*L45,0) -> 400
A46: 8 | B46: Камеральная обработка сейсморазведочных работ на дневной поверхности при одном типе волн | C46: =SUM(C18) -> 192 | D46: СЦР-82 таб.291 п. 1 | G46: =SUM(C46) -> 192 | I46: * | J46: 9 | O46: =ROUND(G46*J46,0) -> 1728
A47: 9 | B47: Камеральная обработка электроразведочных работ 30% от стоимости полевых работ. Применительно к георадарным иссследованиям | D47: Гл.16. камеральные геофизические работы стр.288 (применительно) | J47: =SUM(O22)+C35 -> 4192 | K47: * | L47: 0.3 | O47: =ROUND(J47*L47,0) -> 1258
A48: 10 | B48: Камеральная обработка определения удельного электрического сопротивления. 10 опред. 150 /10 = 15 | D48: табл.293, п.1 | J48: 15 | K48: * | L48: 0.51 | O48: =ROUND(J48*L48,0) -> 8
A49: 11 | B49: Камеральная обработка материалов интенсивности блуждающих токов. Обработка результатов измерений разности потенциалов показывающими приборами | C49: =SUM(C30) -> 18 | D49: таб. 293 п.3 | J49: =SUM(C49) -> 18 | K49: * | L49: 0.53 | O49: =ROUND(J49*L49,0) -> 10
B50: Итого п.п.6-10 | O50: =SUM(O45:O49) -> 3404
A51: 12 | B51: Составление отчета по геофизическим исследованиям -10%. | D51: таб.294, п.10, | F51: ( | G51: 1000 | H51: + | I51: ( | J51: =SUM(O50) -> 3404 | K51: * | L51: 0.1 | M51: ))* | N51: 1.2 | O51: =SUM(G51+(J51*L51))*N51 -> 1608.48
B52: К-1,2 - составление отчета по комплексу методов | D52: таб.294, прим.3
A53: Итого камеральные работы | O53: =SUM(O50:O52) -> 5012.48
A54: Всего по п.п.1-11 | O54: =SUM(O42+O53) -> 20006.48
A55: Прочие расходы
A56: 13 | B56: Расходы по внутреннему транспорту 6%. | D56: таб.4, п.5 | J56: =SUM(O42) -> 14994 | K56: * | L56: 0.06 | M56: * | N56: 1.25 | O56: =ROUND(J56*L56*N56,0) -> 1125
B57: К-1,25 коэффициент к расходам по внутреннему транспорту. приложение к Постановлению Госстроя СССР №22 от 01.03.90г. Общие указания п.8
A58: 14 | B58: Расходы по внешнему транспорту 25% | D58: таб.5, п.7 | F58: ( | G58: =SUM(J56) -> 14994 | I58: + | J58: =SUM(O56) -> 1125 | K58: )* | L58: 0.25 | M58: * | N58: 1.4 | O58: =ROUND((G58+J58)*L58*N58,0) -> 5642
B59: К-1,4 коэффициент к расходам по внешнему транспорту, приложение к Постановлению Госстроя СССР №22 от 01.03.90г. Общие указания п.9
A60: 15 | B60: Расходы по организации и ликвидации геофизических работ 11% | D60: СЦР-82г, таб.6, п.3 | F60: ( | G60: =SUM(G58) -> 14994 | I60: + | J60: =SUM(O56) -> 1125 | K60: )* | L60: 0.11 | O60: =ROUND(((G60+J60)*L60),0) -> 1773
A61: Итого прочие расходы | O61: =SUM(O56:O60) -> 8540
A62: ИТОГО ПО СМЕТЕ В БАЗОВЫХ ЦЕНАХ тыс.руб | O62: =SUM(O54+O61)/1000 -> 28.54648
A63: Всего по смете с учетом индекса сметной стоимости на I квартал 2024 г. К =80,32 Письмо Минстроя России от 07.03.2024 N 13023-ИФ/09 | J63: =SUM(O62) -> 28.54648 | K63: * | L63: 80.32 | O63: =SUM(J63*L63) -> 2292.8533
A64: Переход цен от I кв. 2024г к ценам 01.01.2001г (К=5,83) | G64: тыс.руб | J64: =SUM(O63) -> 2292.8533 | K64: / | L64: 5.83 | O64: =SUM(J64/L64) -> 393.2853
B66: Составил | F66: Ю.А. Курдюков

Sheet №6 ПД ПЖ
E1: Форма № 2П
A2: Приложение к _______________________________________________________________
B3: (договору, дополнительному соглашению, наряд-заказу)
A5: СМЕТА №6
A6: на проектные (изыскательские) работы
A8: Стадия проектирования | C8: Проектная и рабочая документация
A9: Наименование строительства | C9: Организация пассажирского движения от станции
C10: Москва-Октябрьская-Пассажирская до проектируемого
C11: ТПУ "Завидово" через остановочный пункт Путепроводная
C12: Октябрьской железной дороги
C13: Этап 2. Строительство железнодорожной линии от примыкания к Октябрьской железной дороге до проектируемого ТПУ «Завидово»
C15: Пути железнодорожные
A16: Наименование проектной
A17: (изыскательской) организации | C17: ОАО "Сибгипротранс"
A19: Наименование организации-
A20: заказчика
A22: №№ п.п. | B22: Характеристика предприятия, здания, сооружения или виды работ | C22: №№ частей, глав, таблиц, $$ и пунктов указаний к разделу или главе Сборника цен на проектные и изыскательские работы для строительства | D22: Расчет стоимости а + вх или объем строительно-монтажных работ х%:100 или количество х цена | E22: Стоимость (тыс.руб.)
A23: 1 | B23: 2 | C23: 3 | D23: 4 | E23: 5
A25: 1 | B25: Новая железная дорога | C25: СБЦПР-2014 г. | D25: (5035000+141500*12,7)* | E25: =ROUND((5035000+141500*12.7)*0.9*0.49,0)/1000 -> 3012.934
B26: (электрическая тяга) | C26: "Железные | D26: *0.9*0,49
B27: Длина - 11,7 км | C27: дороги"
C28: таб.1, п.8, гр. 5,6
B29: Коэффициенты:
B30: Профильный объем земляных | C30: СБЦПР п.2.1.4
B31: работ - 34 тыс.м3/км (3 степень
B32: сложности)
B33: К1 = 0.9 - для 3-ей степени | C33: СБЦПР
B34: К2 = 2+3+5+8+2+5+6+10+8=49% | C34: таб. 51
B36: Итого | E36: =SUM(E25:E35) -> 3012.934
B37: в том числе П | E37: =E36*0.4 -> 1205.1736
B38: в том числе РД | E38: =E36*0.6 -> 1807.7604
B40: Всего с учетом индекса К=5,81 на I квартал 2024г. | C40: Письмо Минстроя России от 07.03.2024 N 13023-ИФ/09 | E40: =E36*5.81 -> 17505.147
B41: в том числе П | E41: =E40*0.4 -> 7002.0586
B42: в том числе РД | E42: =E40*0.6 -> 10503.088
B44: Начальник отдела | D44: А.В. Арбеков

Sheet №7 ПД ИССО
E1: Форма № 2П
A3: Приложение к _______________________________________________________________
B4: (договору, дополнительному соглашению, наряд-заказу)
A6: СМЕТА №7
A8: на проектные (изыскательские) работы
A10: Стадия проектирования | C10: Проектная и рабочая документация
A11: Наименование строительства | C11: Организация пассажирского движения от станции
C12: Москва-Октябрьская-Пассажирская до проектируемого
C13: ТПУ "Завидово" через остановочный пункт Путепроводная
C14: Октябрьской железной дороги
C15: Этап 2. Строительство железнодорожной линии от примыкания к Октябрьской железной дороге до проектируемого ТПУ «Завидово»
C17: Искусственные сооружения
A18: Наименование проектной
A19: (изыскательской) организации | C19: ОАО "Сибгипротранс"
A21: Наименование организации-
A22: заказчика
A24: №№ п.п. | B24: Характеристика предприятия, здания, сооружения или виды работ | C24: №№ частей, глав, таблиц, $$ и пунктов указаний к разделу или главе Сборника цен на проектные и изыскательские работы для строительства | D24: Расчет стоимости а + вх или объем строительно-монтажных работ х%:100 или количество х цена | E24: Стоимость (тыс.руб.)
A25: 1 | B25: 2 | C25: 3 | D25: 4 | E25: 5
A27: 1 | B27: Металлический путепровод | C27: СБЦП-81-2001-16 | D27: (66000+3740*51,3)* | E27: =ROUND((66000+3740*51.3)*1.1*0.95*1.1,0)/1000 -> 296.412
B28: по схеме 1х44 м | C28: "Искусственные | D28: *0,95*1,1*1,1
B29: Длина - 51,3 м | C29: сооружения"
C30: таб.1, п.6.3, гр. 6,7
B31: Коэффициенты:
B32: К1 = 0,95 - на высоту опор; | C32: СБЦП п.2.1.10
B33: К2 = 1,1 - для индивидуальных | C33: СБЦП п.2.1.15
B34: опорных частей;
B35: К3 = 1,1 - на водоотвод | C35: СБЦП п.2.1.16
A37: 2 | B37: СВСиУ для строительства | C37: СБЦП-81-2001-16 | D37: п.1*0,2 | E37: =ROUND((E27)*0.2,0) -> 59
B38: путепровода | C38: "Искусственные
C39: сооружения"
C40: таб.5, п.4, гр. 5
A42: 3 | B42: Водопропускные трубы (КЖБТ) | C42: СБЦП-81-2001-16 | D42: (6600+290*20)*1,1*16 | E42: =ROUND((6600+290*22.2)*1.1*16,0)/1000 -> 229.469
B43: Ср. длина 20 метров | C43: "Искусственные
B44: Количество - 16 штук | C44: сооружения"
C45: таб.2, п.1.4, гр. 4,5
B46: Коэффициенты:
B47: К1 = 1,1 - на замену грунта; | C47: СБЦП п.2.1.28
A49: 4 | B49: Гидравлические расчеты для | C49: СБЦП-81-2001-16 | D49: п.3*0,055 | E49: =ROUND((E42)*0.055,0) -> 13
B50: труб | C50: "Искусственные
C51: сооружения"
C52: таб.8, п.1.2, гр. 5
B54: Итого | E54: =SUM(E27:E53) -> 597.881
B55: в том числе П | E55: =E54*0.4 -> 239.1524
B56: в том числе РД | E56: =E54*0.6 -> 358.7286
B58: Всего с учетом индекса К=5,81 на I квартал 2024г. | C58: Письмо Минстроя России от 07.03.2024 N 13023-ИФ/09 | E58: =E54*5.81 -> 3473.6886
B59: в том числе П | E59: =E58*0.4 -> 1389.4754
B60: в том числе РД | E60: =E58*0.6 -> 2084.2132
B62: Начальник отдела | D62: А.В. Арбеков

Sheet №8 ПД Здания
A1: Приложение к | E1: форма №2п
B2: (договору, дополнительному соглашению)
A3: Смета №8
A4: на проектные и изыскательские работы.
B6: Стадия проектирования и | C6: Проектная и рабочая документация.
B7: наименование строительства: | C7: Организация пассажирского сообщения от станции Москва-Октябрьская-Пассажирская до проектируемого транспортно-пересадочного узла "Завидово" через остановочный пункт Путепроводная Октябрьской железной дороги. Этап 2. Строительство железнодорожной линии от примыкания к Октябрьской железной дороге до проектируемого ТПУ «Завидово»
C11: Здания и сооружения.
B12: Наименование проектной | C12: ОАО "Сибгипротранс"
B13: (изыскательской) организации
B14: Наименование организации- | C14: ООО "ДСК"
B15: заказчика
A16: №№ п.п. | B16: Характеристика предприятий, зданий, сооружений или виды работ | C16: №№ частей,глав, таблиц,и пунктов указаний к разделу или главе сборника цен на проектно -изыскательские работы для строительства | D16: Расчет стоимости а+вх или объем СМРх% : 100, или количество х цена. | E16: стоимость (тыс.руб.)
A17: 1 | B17: 2 | C17: 3 | D17: 4 | E17: 5
B18: ТПУ Завидово
A19: 1 | B19: Генеральный план территории. Расчетная площадь территории - 4 га | C19: СБЦ-2004 "Объекты промышленности химических волокон" тб.3 п.3.1. | D19: 30,938*4 | E19: =ROUND(30.938*4,2) -> 123.75
A20: =A19+1 -> 2 | B20: Вокзал на 200 пассажиров К=1,2 - на кондиционирование (п.2.10 СБЦП81-2001-09) К=1,15 - на грунтовые условия - подтапливаемая территория (п.6 Общих указаний по применению СБЦПР) | C20: СБЦП81-2001-09 "Железные дороги" тб.7 п. 1.2 | D20: (404700+3100*200)*1,2*1,15 | E20: =ROUND((404.7+3.1*250)*1.2*1.15,2) -> 1627.99
A21: =A20+1 -> 3 | B21: Платформа площадью 3080 м2 К=1,15 - на грунтовые условия - подтапливаемая территория (п.6 Общих указаний по применению СБЦПР) | C21: СБЦП81-2001-09 "Железные дороги" тб.7 п.6.3 | D21: (113000+30*308)*1,15 | E21: =ROUND((113+0.03*308)*1.15,2) -> 140.58
A22: =A21+1 -> 4 | B22: Навесы К=1,15 - на грунтовые условия - подтапливаемая территория (п.6 Общих указаний по применению СБЦПР) | C22: СБЦП81-2001-09 "Железные дороги" тб.7 п. 4.2 | D22: (122500+20*1000)*1,15 | E22: =ROUND((122.5+0.02*1000)*1.15,2) -> 163.88
A23: =A22+1 -> 5 | B23: Центральный лестничный вход на платформу с пандусом | C23: СБЦ-2014 "Железные дороги тб.10 п.18 | D23: (97180+680*10)*1,15 | E23: =ROUND((97.18+0.68*10)*1.15,2) -> 119.58
A24: =A23+1 -> 6 | B24: Турникетный павильон К=1,15 - на грунтовые условия - подтапливаемая территория (п.6 Общих указаний по применению СБЦПР) | C24: СБЦП81-2001-09 "Железные дороги" тб.7 п. 3 | D24: (259,9+0,48*120)*1,15*1,2 | E24: =ROUND((259.9+0.48*120)*1.15,2) -> 365.13
A25: =A24+1 -> 7 | B25: Периметровое ограждение территории Расчетная длина ограждения 1,5км | C25: СБЦ-2014 "Железные дороги тб.10 п.9.1 | D25: (14,950+18,360*1,5)*1,15 | E25: =ROUND((14.95+18.36*1.5)*1.15,2) -> 48.86
A26: =A25+1 -> 8 | B26: Подпорная стенка 500 м | C26: СБЦ-2014 "Железные дороги тб.10 п.11.4 | D26: (319+2,75*100)*1,15 | E26: =ROUND((319+2.75*100)*1.15,2) -> 683.1
A27: =A26+1 -> 9 | B27: Шумозащитный экран | C27: СБЦ-2014 "Железные дороги тб.10 п.10.1 | D27: 260*1,15 | E27: =ROUND(260*1.15,2) -> 299
A28: =A27+1 -> 10 | B28: Фундамент КТП, 2 шт | C28: СБЦ - 2014 "Железные дороги тб.45 п.4 | D28: 43,2*2*1,15 | E28: =ROUND(43.2*2*1.15,2) -> 99.36
A29: =A28+1 -> 11 | B29: Фундамент модульный пост ЭЦ | C29: СБЦ - 2014 "Железные дороги тб.45 п.4 | D29: (43,2+43*0,1*9)*1,15 | E29: =ROUND((43.2+43*0.1*9)*1.15,2) -> 94.19
A30: =A29+1 -> 12 | B30: Фундамент пункта питания | C30: СБЦ - 2014 "Железные дороги тб.45 п.4 | D30: (43,2+43*0,1*2)*1,15 | E30: =ROUND((43.2+43*0.1*2)*1.15,2) -> 59.57
A31: =A30+1 -> 13 | B31: Автомобильная стоянка | C31: СБЦ-2014 "Железные дороги тб.10 п.12.1 | D31: 310 | E31: =ROUND(310,2) -> 310
A32: =A31+1 -> 14 | B32: Опора поездной радиосвязи, 12 м | C32: СБЦ-81-2001-02 "Объекты связи" тб.18 п.1 | D32: (58,04+0,398*12)*1,15 | E32: =ROUND((58.04+0.398*12)*1.15,2) -> 72.24
B33: Блок пост на 10 км
A34: =A32+1 -> 15 | B34: Генеральный план территории. Расчетная площадь территории - 1 га | C34: СБЦ-2004 "Объекты промышленности химических волокон" тб.3 п.3.1. | D34: 30,938*1 | E34: =ROUND(30.938*1,2) -> 30.94
A35: =A34+1 -> 16 | B35: Фундамент модульный пост ЭЦ | C35: СБЦ - 2014 "Железные дороги тб.45 п.4 | D35: (43,2+43*0,1*9)*1,15 | E35: =ROUND((43.2+43*0.1*9)*1.15,2) -> 94.19
A36: =A35+1 -> 17 | B36: Фундамент КТП | C36: СБЦ - 2014 "Железные дороги тб.45 п.4 | D36: 43,2*1,15 | E36: =ROUND(43.2*1.15,2) -> 49.68
A37: =A36+1 -> 18 | B37: Опора поездной радиосвязи, 12 м | C37: СБЦ-81-2001-02 "Объекты связи" тб.18 п.1 | D37: (58,04+0,398*50)*1,15 | E37: =ROUND((58.04+0.398*50)*1.15,2) -> 89.63
B38: Мачта связи на Канаковском шоссе
A39: =A37+1 -> 19 | B39: Генеральный план территории. Расчетная площадь территории - 1 га | C39: СБЦ-2004 "Объекты промышленности химических волокон" тб.3 п.3.1. | D39: 30,938*1 | E39: =ROUND(30.938*1,2) -> 30.94
A40: =A39+1 -> 20 | B40: Опора поездной радиосвязи, 50 м | C40: СБЦ-81-2001-02 "Объекты связи" тб.18 п.1 | D40: (58,040+0,398*50)*1,15 | E40: =ROUND((58.04+0.398*50)*1.15,2) -> 89.63
B41: Ст.Конаковский мох
A42: =A40+1 -> 21 | B42: Генеральный план территории. Расчетная площадь территории - 1 га | C42: СБЦ-2004 "Объекты промышленности химических волокон" тб.3 п.3.1. | D42: 30,938*1 | E42: =ROUND(30.938*1,2) -> 30.94
A43: =A42+1 -> 22 | B43: Фундамент модульный пост ЭЦ | C43: СБЦ - 2014 "Железные дороги тб.45 п.4 | D43: (43,2+43*0,1*9)*1,15 | E43: =ROUND((43.2+43*0.1*9)*1.15,2) -> 94.19
A44: =A43+1 -> 23 | B44: Фундамент КТП | C44: СБЦ - 2014 "Железные дороги тб.45 п.4 | D44: 43,2*1,15 | E44: =ROUND(43.2*1.15,2) -> 49.68
A45: =A44+1 -> 24 | B45: Опора поездной радиосвязи, 50 м | C45: СБЦ-81-2001-02 "Объекты связи" тб.18 п.1 | D45: (58040+398*50)*1,15 | E45: =ROUND((58.04+0.398*50)*1.15,2) -> 89.63
B46: Тяговая подстанция на ст. Решетниково
A47: =A45+1 -> 25 | B47: Генеральный план территории. Расчетная площадь территории - 0,5 га | C47: СБЦ-2004 "Объекты промышленности химических волокон" тб.3 п.3.1. | D47: 30,938*0,5 | E47: =ROUND(30.938*0.5,2) -> 15.47
A48: =A47+1 -> 26 | B48: Фундамент КТП | C48: СБЦ - 2014 "Железные дороги тб.45 п.4 | D48: 43.2 | E48: =ROUND(43.2,2) -> 43.2
B50: ВСЕГО в базовых ценах | E50: =SUM(E19:E49) -> 4915.35
B51: Проектная документация | D51: =CONCATENATE(E50,"*0,4") -> 4915,35*0,4 | E51: =E50*0.4 -> 1966.14
B52: Рабочая документация | D52: =CONCATENATE(E44,"*0,6") -> 49,68*0,6 | E52: =E50*0.6 -> 2949.21
B54: на 1кв. 2024 | C54: Письмо Минстроя России от 07.03.2024 N 13023-ИФ/09 | D54: =CONCATENATE(E50,"*5,81") -> 4915,35*5,81 | E54: =E50*5.81 -> 28558.183
B55: Проектная документация | D55: =CONCATENATE(E54,"*0,4") -> 28558,1835*0,4 | E55: =E54*0.4 -> 11423.273
B56: Рабочая документация | D56: =CONCATENATE(E50,"*0,6") -> 4915,35*0,6 | E56: =E54*0.6 -> 17134.91
B59: Начальник отдела | D59: М.А. Чурин
B61: Составил | D61: М.А. Чурин

Sheet №9 ПД Водоснабжение
A1: Приложение к | E1: форма №2п
B2: (договору, дополнительному соглашению)
A3: Смета №9
A4: на проектные и изыскательские работы.
B6: Стадия проектирования и | C6: Проектная и рабочая документация.
B7: наименование строительства: | C7: Организация пассажирского сообщения от станции Москва-Октябрьская-Пассажирская до проектируемого транспортно-пересадочного узла "Завидово" через остановочный пункт Путепроводная Октябрьской железной дороги. Этап 2. Строительство железнодорожной линии от примыкания к Октябрьской железной дороге до проектируемого ТПУ «Завидово»
C11: Водоснабжение и водоотведение
B12: Наименование проектной | C12: ОАО "Сибгипротранс"
B13: (изыскательской) организации
B14: Наименование организации- | C14: ООО "ДСК"
B15: заказчика
A16: №№ п.п. | B16: Характеристика предприятий, зданий, сооружений или виды работ | C16: №№ частей,глав, таблиц,и пунктов указаний к разделу или главе сборника цен на проектно -изыскательские работы для строительства | D16: Расчет стоимости а+вх или объем СМРх% : 100, или количество х цена. | E16: стоимость (тыс.руб.)
A17: 1 | B17: 2 | C17: 3 | D17: 4 | E17: 5
A18: 1 | B18: Хозяйственно-питьевой водопровод 0,1 км | C18: СБЦ-2015 "Объекты водоснабжения и канализации" тб.3 п.1. | D18: (64940+34770*0,1)*1,1 | E18: =ROUND((64940+34770*0.1)*1.1,0)/1000 -> 75.259
A19: =A18+1 -> 2 | B19: Водомерный узел ,встроенный | C19: СБЦ-2008 Городские инж сооружения и коммуникации, табл. 6 п.13 | D19: 77500 | E19: =ROUND(77500,0)/1000 -> 77.5
A20: =A19+1 -> 3 | B20: Противопожарные резервуары запаса воды в районе блок-поста 10км, ёмкостью 0,01тыс. М3 (2шт) К=1,5 на 2-й резервуар | C20: СБЦ-2015 "Объекты водоснабжения и канализации" тб.5 п.10. | D20: (21960+79880*0,01)*1,5 | E20: =ROUND((21960+79880*0.01)*1.5,0)/1000 -> 34.138
A21: =A20+1 -> 4 | B21: Противопожарный водопровод 0,1 км | C21: СБЦ-2015 "Объекты водоснабжения и канализации" тб.3 п.1. | D21: (64940+34770*0,1)*1,1 | E21: =ROUND((64940+34770*0.1)*1.1,0)/1000 -> 75.259
A22: =A21+1 -> 5 | B22: Сети хоз.бытовой канализации 0,05км К=1,1 - на пластиковые трубы | C22: СБЦ-2015 "Объекты водоснабжения и канализации" тб.8 п.1. | D22: (101100+16890*0,05)*1,1 | E22: =ROUND((101100+16890*0.05)*1.1,0)/1000 -> 112.139
A23: =A22+1 -> 6 | B23: Сети ливневой канализации 0,3км К=1,1 - на пластиковые трубы | C23: СБЦ-2015 "Объекты водоснабжения и канализации" тб.8 п.1. | D23: (101100+16890*0,3)*1,1 | E23: =ROUND((101100+16890*0.3)*1.1,0)/1000 -> 116.784
A24: =A23+1 -> 7 | B24: Станция перекачки загрязненных стоков | C24: СБЦ-2015 "Объекты водоснабжения и канализации" тб.8 п.1. | D24: (147380+242530*0,15) | E24: =ROUND((147380+242530*0.15),0)/1000 -> 183.76
A25: =A24+1 -> 8 | B25: Очистные сооружения ливневых стоков К=0,7 - на привязку с внесением изменений | C25: СБЦ-2015 "Объекты водоснабжения и канализации" тб.10 п.14. | D25: (414910+34860*0,15)*0,7 | E25: =ROUND((414910+34860*0.15)*0.7,0)/1000 -> 294.097
A26: =A25+1 -> 9 | B26: Сети канализации, напорные длиной 0,5 км | C26: СБЦ-2015 "Объекты водоснабжения и канализации" тб.3 п.1. | D26: (64940+34770*0,5) | E26: =ROUND((64940+34770*0.5),0)/1000 -> 82.325
A27: =A26+1 -> 10 | B27: Противопожарные резервуары запаса воды в районе ст.Канаковский мох, ёмкостью 0,01тыс. М3 (2шт) К=1,5 на 2-й резервуар | C27: СБЦ-2015 "Объекты водоснабжения и канализации" тб.5 п.10. | D27: (21960+79880*0,01)*1,5 | E27: =ROUND((21960+79880*0.01)*1.5,0)/1000 -> 34.138
A28: =A27+1 -> 11 | B28: Противопожарный водопровод 0,1 км | C28: СБЦ-2015 "Объекты водоснабжения и канализации" тб.3 п.1. | D28: (64940+34770*0,1)*1,1 | E28: =ROUND((64940+34770*0.1)*1.1,0)/1000 -> 75.259
A29: =A28+1 -> 12 | B29: Очистные сооружения ливневых стоков на перегоне, 10 шт К=0,1 - на привязку с внесением изменений | C29: СБЦ-2015 "Объекты водоснабжения и канализации" тб.10 п.14. | D29: (414910+34860*0,15)*0,1*10 | E29: =ROUND((414910+34860*0.15)*0.1*10/1000,3) -> 420.139
A30: =A28+1 -> 12 | B30: ВСЕГО в базовых ценах | E30: =SUM(E18:E29) -> 1580.797
B31: Проектная документация | D31: =CONCATENATE(E25,"*0,4") -> 294,097*0,4 | E31: =E30*0.4 -> 632.3188
B32: Проектная документация | D32: =CONCATENATE(E30,"*0,6") -> 1580,797*0,6 | E32: =E30*0.6 -> 948.4782
A34: =A30+1 -> 13 | B34: на 1кв. 2024 | C34: Письмо Минстроя России от 07.03.2024 N 13023-ИФ/09 | D34: =CONCATENATE(E30,"*5,81") -> 1580,797*5,81 | E34: =E30*5.81 -> 9184.4306
B35: Проектная документация | D35: =CONCATENATE(E30,"*0,4") -> 1580,797*0,4 | E35: =E34*0.4 -> 3673.7722
B36: Проектная документация | D36: =CONCATENATE(E34,"*0,6") -> 9184,43057*0,6 | E36: =E34*0.6 -> 5510.6583
B38: Начальник отдела | D38: М.А. Чурин
B40: Составил | D40: М.А. Чурин

Sheet №10 ПД ЭС
E1: Приложение №________
E2: к Договору №______________
E3: от "____"_____________201_
B5: СМЕТА № 10
B6: на проектные работы
B8: Наименование предприятия, | C8: Организация пассажирского сообщения от станции Москва-Октябрьская-Пассажирская до проектируемого ТПУ "Завидово" через остановочный пункт Путепроводная Октябрьской железной дороги Этап 2. Строительство железнодорожной линии от примыкания к Октябрьской железной дороге до проектируемого ТПУ «Завидово»
B9: здания, сооружения
B12: Стадия проектных работ | C12: Проектная документация
B14: Наименование работ | C14: Электроснабжение и электросовещение (ТПУ "Завидово")
B16: Наименование проектной организации | C16: ОАО "Сибгипротранс"
B18: Наименование организации-заказчика | C18: ООО "ДСК"
C20: №№ частей, глав,
C21: таблиц и пунктов | D21: Расчет стоимости -
A22: №№ | B22: Характеристика предприятия, здания, | C22: Указаний к разделу | D22: а + вх; или - объем | E22: Стоимость
A23: п/п | B23: сооружения, или вида работ | C23: или главе Сборника | D23: строительно - монт- | E23: (руб.)
C24: цен на проектные | D24: тажных работ х
C25: и изыскательские | D25: х % : 100; или
C26: работы для строи- | D26: количество х цена
C27: тельства
A28: 1 | B28: 2 | C28: 3 | D28: 4 | E28: 5
B29: Пункт питания ТПУ Завидово
B30: Кабельные сети 10,0 кВ ТПУ Завидово | C30: СБЦП 81-2001-09 | D30: 11960*1 | E30: =11960*1 -> 11960
B31: Протяженность - 0,040 км | C31: Железнодорожные
C32: дороги
C33: 2014г
C34: табл. 17, п.1
A36: 2 | B36: Высоковольтные линии электроснабжения ВЛЗ-1 10 кВ | C36: СБЦП 81-2001-09 | D36: 133000+0,010*2270 | E36: =133000+0.01*2270 -> 133022.7
B37: тункт питания ТПУ Завидово | C37: Железнодорожные
B38: Протяженность - 0,010 км | C38: дороги
C39: 2014г
C40: табл. 21, п.1.1
A42: 3 | B42: Установка разьединителя типа Тесла-1-10/400 УХЛ1 | C42: СБЦП 81-2001-07 | D42: 11220*1*1 | E42: =11220*1*1 -> 11220
B43: Количество - 1 | C43: Коммунальные
C44: инженерные сети и
C45: сооружения
C46: 2012г
C47: табл. 37, п.12
C48: (применительно)
A50: 4 | B50: Расчет заземления ( 1 расчет) | C50: СБЦП 81-2001-07 | D50: 1740*1*0,8 | E50: =1740*1*0.8 -> 1392
C51: Коммунальные
C52: инженерные сети и
C53: сооружения
C54: табл.36, п5
C55: применительно К=0.8
A57: 5 | B57: ТП 10/0,4 кВ (КТП №1) | C57: СБЦП 81-2001-07 | D57: 68380*1 | E57: =68380*1 -> 68380
B58: Количество на площадке - 1 | C58: Коммунальные
C59: инженерные сети и
C60: сооружения
C61: 2012г
C62: табл. 37, п.4
A64: 6 | B64: Расчет токов короткого замыкания электрических | C64: СБЦП 81-2001-07 | D64: 2470*1 | E64: =2470*1 -> 2470
B65: сетей до 20 кВ | C65: Коммунальные
B66: Количество линий - 2 | C66: инженерные сети и
C67: сооружения
C68: 2012г
C69: табл. 40, п.2
A71: 7 | B71: Расчет заземления (3 расчета) | C71: СБЦП 81-2001-07 | D71: 1740*3*0,8 | E71: =1740*3*0.8 -> 4176
C72: Коммунальные
C73: инженерные сети и
C74: сооружения
C75: табл.36, п5
C76: применительно К=0.8
A78: 8 | B78: Кабельные сети 10,0 кВ ТПУ Завидово, КТП №1 | C78: СБЦП 81-2001-07 | D78: 12265+2400*37 | E78: =12265+2400*37 -> 101065
B79: Протяженность - 2,400 км | C79: Коммунальные
C80: инженерные сети и
C81: сооружения
C82: 2012г
C83: табл. 17, п.4
A85: 9 | B85: Кабельные сети 0,4 кВ ТПУ Завидово от КТП №1 | C85: СБЦП 81-2001-07 | D85: 12265+1100*37 | E85: =12265+1100*37 -> 52965
B86: Протяженность - 1,100 км | C86: Коммунальные
C87: инженерные сети и
C88: сооружения
C89: 2012г
C90: табл. 17, п.4
A92: 10 | B92: Проектирование электрических сетей 0.4 Кв | C92: СБЦП 81-2001-07 | D92: 30690+139*1 | E92: =30690+139*1 -> 30829
B93: на участке ТПУ Завидово КТП №1 | C93: Коммунальные
C94: инженерные сети и
C95: сооружения
C96: 2012г
C97: табл.41
A99: 11 | B99: Расчет токов короткого замыкания электрических | C99: СБЦП 81-2001-07 | D99: 2470*1 | E99: =2470*1 -> 2470
B100: сетей до 20 кВ | C100: Коммунальные
B101: Количество линий - 4 | C101: инженерные сети и
C102: сооружения
C103: 2012г
C104: табл. 40, п.2
A106: 12 | B106: Кабельные сети 10,0 кВ ТПУ Завидово, КТП№2 | C106: СБЦП 81-2001-07 | D106: 8265+950*41 | E106: =8265+950*41 -> 47215
B107: Протяженность - 0,950 км | C107: Коммунальные
C108: инженерные сети и
C109: сооружения
C110: 2012г
C111: табл. 17, п.4
A113: 13 | B113: КТП №2 10/0,4 Кв | C113: СБЦП 81-2001-07 | D113: 6600*1 | E113: =6600*1 -> 6600
B114: Количество на площадке - 1 | C114: Коммунальные
C115: инженерные сети и
C116: сооружения
C117: 2012г
C118: табл. 37, п.1
A120: 14 | B120: Кабельные сети 0,4 кВ ТПУ Завидово от КТП№2 | C120: СБЦП 81-2001-07 | D120: 8265+120*41 | E120: =8265+120*41 -> 13185
B121: Протяженность - 0,120 км | C121: Коммунальные
...

Sheet №11 УГТ ПД ЭС Тяговые
A1: «Адепт: Проект в 16.4» © ООО «Адепт» | D1: форма №2П от 08.04.2024г к Договору от 08.04.2024 г.
A3: Смета №11
A4: на проектные (изыскательские) работы
A6: по объекту: | D6: Организация пассажирского сообщения от станции Москва -Октябрьская-Пассажирская до проектируемого ТПУ "Завидово" через остановочный пункт Путепроводная Октябрьской железной дороги Этап 2. Строительство железнодорожной линии от примыкания к Октябрьской железной дороге до проектируемого ТПУ «Завидово»
A8: Наименование предприятия, здания, сооружения, стадии проектирования, этапа, вида проектных или изыскательских работ | D8: Система электроснабжения
A10: Наименование проектной (изыскательской) организации | D10: ОАО "Сибгипротранс"
A12: Наименование организации заказчика | D12: ООО "ДСК"
A14: № пп | B14: Характеристика предприятия, здания, сооружения или виды работ | D14: Номер частей, глав, таблиц, процентов, параграфов и пунктов указаний к разделу Справочника базовых цен на проектные и изыскательские работы для строительства | H14: Расчет стоимости: (a+bx)*Ki, или (объем строительно-монтажных работ) * проц./100 или количество x цена | I14: Стоимость, тыс. руб.
A15: 1 | B15: 2 | D15: 3 | H15: 4 | I15: 5
A16: 1 | B16: Раздел | D16: ЭЧЭ-7 Решетниково
A17: 1.1 | B17: Закрытое РУ 6-10 кВ и РУ ВЛ СЦБ с установкой функциональных блоков заводского изготовления | D17: Железные дороги. 2014 г. Таблица 15. Здания и сооружения тяговых подстанций, п.13.1 A=175.66 тыс.руб; B=25.07 тыс.руб; Осн. показ. Х=4 (1 блок) Количество = 1 | H17: (A + B * Xзад) * Количество * Кст * K1 (175.66 тыс.руб + 25.07 тыс.руб * 4) * 1 * 0.8 * 1.3 | I17: 286.9776
B18: Коэффициенты
D19: Кст = 0.8
B20: Коэффициент на переустройство | D20: K1 = 1.3
A21: 1.2 | B21: Закрытая установка трансформатора СЦБ или ТСН напряжением 10(6)/0,4-0,23 кВ. | D21: Железные дороги. 2014 г. Таблица 15. Здания и сооружения тяговых подстанций, п.14.1 A=9.55 тыс.руб; B=0.75 тыс.руб; Осн. показ. Х=1 (1 трансформатор) Количество = 2 | H21: (A + B * Xзад) * Количество * Кст * K1 (9.55 тыс.руб + 0.75 тыс.руб * 1) * 2 * 0.6 * 1.3 | I21: 16.068
B22: Коэффициенты
D23: Кст = 0.6
B24: Коэффициент на переустройство | D24: K1 = 1.3
A25: 1.3 | B25: Общие устройства и сооружения для пунктов группировки | D25: Железные дороги. 2014 г. Таблица 15. Здания и сооружения тяговых подстанций, п.13.1 A=24.58 тыс.руб; Количество = 1 (1 объект) | H25: A * Количество * Кст * K1 24.58 тыс.руб * 1 * 0.8 * 1.3 | I25: 25.5632
B26: Коэффициенты
D27: Кст = 0.8
B28: Коэффициент на переустройство | D28: K1 = 1.3
A29: 1.4 | B29: Подстанция 35/6-10 кВ со схемой РУ в виде одной рабочей секционированной выключателем системой шин | D29: Железные дороги. 2014 г. Таблица 16. Релейная защита тяговых подстанций, п.1.1 A=126 тыс.руб; Количество = 1 (1 подстанция) | H29: A * Количество * Кст * K1 * K2 126 тыс.руб * 1 * 0.9 * 2 * 1.5 | I29: 340.2
B30: Коэффициенты
D31: Кст = 0.9
B32: При использовании аппаратуры на микропроцессорной технике базовая цена определяется с применением коэффициента | D32: K1 = 2
B33: При выполнении работ по реконструкции РЗА элементов действующих ТП вводится повышающий коэффициент | D33: K2 = 1.5
A34: 1.5 | B34: Диспетчерское управление энергетическими объектами (электростанциями, подстанциями). Распределительная электросеть. | D34: Железные дороги. 2014 г. Таблица 20. Диспетчерское управление устройств электроснабжения и объектов, приравненных к ним, п.1.2 A=0.55 тыс.руб; Количество = 1 (1 КП) | H34: A * Количество * Кст 0.55 тыс.руб * 1 * 0.65 | I34: 0.3575
B35: Коэффициенты
D36: Кст = 0.65
A37: 1.6 | B37: Устройства телемеханики КП. Объекты ТС. | D37: Железные дороги. 2014 г. Таблица 20. Диспетчерское управление устройств электроснабжения и объектов, приравненных к ним, п.2.1 A=0.7 тыс.руб; Количество = 2 (4 объекта) | H37: A * Количество * Кст 0.7 тыс.руб * 2 * 0.77 | I37: 1.078
B38: Коэффициенты
D39: Кст = 0.77
A40: 1.7 | B40: Устройства телемеханики КП. Объекты ТУ. | D40: Железные дороги. 2014 г. Таблица 20. Диспетчерское управление устройств электроснабжения и объектов, приравненных к ним, п.2.2 A=1.16 тыс.руб; Количество = 2 (4 объекта) | H40: A * Количество * Кст 1.16 тыс.руб * 2 * 0.77 | I40: 1.7864
B41: Коэффициенты
D42: Кст = 0.77
A43: 1.8 | B43: Устройства телемеханики КП. Объекты ТИ. | D43: Железные дороги. 2014 г. Таблица 20. Диспетчерское управление устройств электроснабжения и объектов, приравненных к ним, п.2.3 A=2.47 тыс.руб; Количество = 2 (4 объекта) | H43: A * Количество * Кст 2.47 тыс.руб * 2 * 0.77 | I43: 3.8038
B44: Коэффициенты
D45: Кст = 0.77
A46: 1.9 | B46: Устройства телемеханики сторона (ПУ). Объекты ТС. | D46: Железные дороги. 2014 г. Таблица 20. Диспетчерское управление устройств электроснабжения и объектов, приравненных к ним, п.4.1 A=0.95 тыс.руб; Количество = 1 (8 объектов) | H46: A * Количество * Кст 0.95 тыс.руб * 1 * 0.7 | I46: 0.665
B47: Коэффициенты
D48: Кст = 0.7
A49: 1.10 | B49: Устройства телемеханики сторона (ПУ). Объекты ТУ. | D49: Железные дороги. 2014 г. Таблица 20. Диспетчерское управление устройств электроснабжения и объектов, приравненных к ним, п.4.2 A=0.7 тыс.руб; Количество = 1 (8 объектов) | H49: A * Количество * Кст 0.7 тыс.руб * 1 * 0.8 | I49: 0.56
B50: Коэффициенты
D51: Кст = 0.8
A52: 1.11 | B52: Устройства телемеханики сторона (ПУ). Объекты ТИ. | D52: Железные дороги. 2014 г. Таблица 20. Диспетчерское управление устройств электроснабжения и объектов, приравненных к ним, п.4.3 A=1.64 тыс.руб; Количество = 1 (8 объектов) | H52: A * Количество * Кст 1.64 тыс.руб * 1 * 0.8 | I52: 1.312
B53: Коэффициенты
D54: Кст = 0.8
A55: 1.12 | B55: Устройство управления (сопряжения), адаптеры | D55: Железные дороги. 2014 г. Таблица 20. Диспетчерское управление устройств электроснабжения и объектов, приравненных к ним, п.8 A=3.89 тыс.руб; Количество = 6 (1 устройство) | H55: A * Количество * Кст 3.89 тыс.руб * 6 * 0.8 | I55: 18.672
B56: Коэффициенты
D57: Кст = 0.8
A58: 1.13 | B58: Панель электропитания | D58: Железные дороги. 2014 г. Таблица 20. Диспетчерское управление устройств электроснабжения и объектов, приравненных к ним, п.9 A=3.28 тыс.руб; Количество = 1 (1 панель) | H58: A * Количество * Кст 3.28 тыс.руб * 1 * 0.9 | I58: 2.952
B59: Коэффициенты
D60: Кст = 0.9
A61: 1.14 | B61: Электрические сети напряжением до 20 кВ. Сбор нагрузок систем СЦБ перегона Решетниково-Конаково ГРЭС | D61: Коммунальные инженерные сети и сооружения, 2012 г. Раздел 3. Таблица 41. Электрические сети напряжением до 20 кВ п.1 A=30.69 тыс.руб; B=1.39 тыс.руб; Осн. показ. Х=0.2 (1 тыс. кВт присоединяемых нагрузок на шинах 0,4 кВ потребителя) Количество = 1 | H61: (A + B * Xзад) * Количество * Кст (30.69 тыс.руб + 1.39 тыс.руб * 0.2) * 1 * 0.6 | I61: 18.5808
B62: Коэффициенты
D63: Кст = 0.6
A64: 1.16 | B64: Всего ЭЧЭ-7 Решетниково: | I64: 718.5763
A65: 2 | B65: Раздел | D65: ПП СЦБ ТПУ Завидово
A66: 2.1 | B66: Закрытое РУ 6-10 кВ и РУ ВЛ СЦБ с установкой функциональных блоков заводского изготовления | D66: Железные дороги. 2014 г. Таблица 15. Здания и сооружения тяговых подстанций, п.13.1 A=175.66 тыс.руб; B=25.07 тыс.руб; Осн. показ. Х=5 (1 блок) Количество = 1 | H66: (A + B * Xзад) * Количество * Кст (175.66 тыс.руб + 25.07 тыс.руб * 5) * 1 * 0.8 | I66: 240.808
B67: Коэффициенты
D68: Кст = 0.8
A69: 2.2 | B69: Закрытая установка трансформатора СЦБ или ТСН напряжением 10(6)/0,4-0,23 кВ | D69: Железные дороги. 2014 г. Таблица 15. Здания и сооружения тяговых подстанций, п.14.1 A=9.55 тыс.руб; B=0.75 тыс.руб; Осн. показ. Х=1 (1 трансформатор) Количество = 1 | H69: (A + B * Xзад) * Количество * Кст (9.55 тыс.руб + 0.75 тыс.руб * 1) * 1 * 0.6 | I69: 6.18
B70: Коэффициенты
D71: Кст = 0.6
A72: 2.3 | B72: Общие устройства и сооружения для пунктов группировки. | D72: Железные дороги. 2014 г. Таблица 15. Здания и сооружения тяговых подстанций, п.13.1 A=24.58 тыс.руб; Количество = 1 (1 объект) | H72: A * Количество * Кст 24.58 тыс.руб * 1 * 0.8 | I72: 19.664
B73: Коэффициенты
D74: Кст = 0.8
A75: 2.4 | B75: Подстанция 35/6-10 кВ со схемой РУ в виде одной рабочей секционированной выключателем системой шин | D75: Железные дороги. 2014 г. Таблица 16. Релейная защита тяговых подстанций, п.1.1 A=126 тыс.руб; Количество = 1 (1 подстанция) | H75: A * Количество * Кст * K1 126 тыс.руб * 1 * 0.9 * 2 | I75: 226.8
B76: Коэффициенты
D77: Кст = 0.9
B78: При использовании аппаратуры на микропроцессорной технике базовая цена определяется с применением коэффициента | D78: K1 = 2
A79: 2.5 | B79: Диспетчерское управление энергетическими объектами (электростанциями, подстанциями). Распределительная электросеть. | D79: Железные дороги. 2014 г. Таблица 20. Диспетчерское управление устройств электроснабжения и объектов, приравненных к ним, п.1.2 A=0.55 тыс.руб; Количество = 1 (1 КП) | H79: A * Количество * Кст 0.55 тыс.руб * 1 * 0.65 | I79: 0.3575
B80: Коэффициенты
D81: Кст = 0.65
A82: 2.6 | B82: Устройства телемеханики КП. Объекты ТС. | D82: Железные дороги. 2014 г. Таблица 20. Диспетчерское управление устройств электроснабжения и объектов, приравненных к ним, п.2.1 A=0.7 тыс.руб; Количество = 2 (4 объекта) | H82: A * Количество * Кст 0.7 тыс.руб * 2 * 0.77 | I82: 1.078
B83: Коэффициенты
D84: Кст = 0.77
A85: 2.7 | B85: Устройства телемеханики КП. Объекты ТУ. | D85: Железные дороги. 2014 г. Таблица 20. Диспетчерское управление устройств электроснабжения и объектов, приравненных к ним, п.2.2 A=1.16 тыс.руб; Количество = 2 (4 объекта) | H85: A * Количество * Кст 1.16 тыс.руб * 2 * 0.77 | I85: 1.7864
B86: Коэффициенты
D87: Кст = 0.77
A88: 2.8 | B88: Устройства телемеханики КП. Объекты ТИ. | D88: Железные дороги. 2014 г. Таблица 20. Диспетчерское управление устройств электроснабжения и объектов, приравненных к ним, п.2.3 A=2.47 тыс.руб; Количество = 2 (4 объекта) | H88: A * Количество * Кст 2.47 тыс.руб * 2 * 0.77 | I88: 3.8038
B89: Коэффициенты
D90: Кст = 0.77
A91: 2.9 | B91: Устройства телемеханики сторона (ПУ). Объекты ТС. | D91: Железные дороги. 2014 г. Таблица 20. Диспетчерское управление устройств электроснабжения и объектов, приравненных к ним, п.4.1 A=0.95 тыс.руб; Количество = 1 (8 объектов) | H91: A * Количество * Кст 0.95 тыс.руб * 1 * 0.7 | I91: 0.665
B92: Коэффициенты
D93: Кст = 0.7
A94: 2.10 | B94: Устройства телемеханики сторона (ПУ). Объекты ТУ. | D94: Железные дороги. 2014 г. Таблица 20. Диспетчерское управление устройств электроснабжения и объектов, приравненных к ним, п.4.2 A=0.7 тыс.руб; Количество = 1 (8 объектов) | H94: A * Количество * Кст 0.7 тыс.руб * 1 * 0.8 | I94: 0.56
B95: Коэффициенты
D96: Кст = 0.8
A97: 2.11 | B97: Устройства телемеханики сторона (ПУ). Объекты ТИ. | D97: Железные дороги. 2014 г. Таблица 20. Диспетчерское управление устройств электроснабжения и объектов, приравненных к ним, п.4.3 A=1.64 тыс.руб; Количество = 1 (8 объектов) | H97: A * Количество * Кст 1.64 тыс.руб * 1 * 0.8 | I97: 1.312
B98: Коэффициенты
D99: Кст = 0.8
A100: 2.12 | B100: Устройства отображения. Прибор цифровой (индикатор). | D100: Железные дороги. 2014 г. Таблица 20. Диспетчерское управление устройств электроснабжения и объектов, приравненных к ним, п.5.1 A=0.82 тыс.руб; Количество = 1 (8 приборов) | H100: A * Количество * Кст 0.82 тыс.руб * 1 * 0.8 | I100: 0.656
B101: Коэффициенты
D102: Кст = 0.8
A103: 2.13 | B103: Устройство управления (сопряжения), адаптеры | D103: Железные дороги. 2014 г. Таблица 20. Диспетчерское управление устройств электроснабжения и объектов, приравненных к ним, п.8 A=3.89 тыс.руб; Количество = 6 (1 устройство) | H103: A * Количество * Кст 3.89 тыс.руб * 6 * 0.8 | I103: 18.672
B104: Коэффициенты
D105: Кст = 0.8
A106: 2.14 | B106: Панель электропитания | D106: Железные дороги. 2014 г. Таблица 20. Диспетчерское управление устройств электроснабжения и объектов, приравненных к ним, п.9 A=3.28 тыс.руб; Количество = 1 (1 панель) | H106: A * Количество * Кст 3.28 тыс.руб * 1 * 0.9 | I106: 2.952
...

Sheet №12 УГТ ПД КС
E1: Форма № 2П
B2: Смета № 12
B3: на проектные (изыскательские) работы
B5: Наименование стройки, стадии проектирования, вида проектных и изыскательских работ. | D5: Организация пассажирского сообщения от станции Москва-Октябрьская-Пассажирская до проектируемого ТПУ "Завидово" через остановочный пункт Путепроводная Октябрьской железной дороги Этап 2. Строительство железнодорожной линии от примыкания к Октябрьской железной дороге до проектируемого ТПУ «Завидово» Контактная сеть, ВЛ10 кВ, волновод, ВОК и ДУ Проектная документация. КС
B6: Наименование проектно- изыскательской организации | D6: ОАО "Сибгипротранс"
B8: Наименование организации- заказчика | D8: ООО "ДСК"
B10: № пп | C10: Наименование предприятия, здания,сооружения,вида работ. Показатели объёмов, мощности, производительности и др. | D10: Сборники (Справочники) цен, разделы,таблицы, пункты,обоснования коэффициентов | E10: Расчёт стоимости | F10: Стоимость (тыс.руб.)
B11: 1 | C11: 2 | D11: 3 | E11: 4 | F11: 5
D12: Справочник базовых цен на проектные работы в строительстве. СБЦП 81-2001-09 Железные дороги Москва 2014. табл. 12 п.1.2
B13: 1 | C13: Контактная сеть при развернутой длине электрифицируемых путей свыше 10 до 30 км. Участок Блок-пост - Завидово, развернутая длина контактной сети 13 км | D13: - " - табл. 12 п.1.2 | E13: (110+3.9*13.0)*1.1*1.2 | F13: =(110+3.9*13)*1.1*1.2 -> 212.124
E14: 1,1-коэф. для электрификации на постоянном токе (здесь и далее)
E17: 1,2 - коэф. Прохождения трассы в кривых свыше 25% до 50%
B18: 2 | C18: Переустройство контактной сети при развернутой длине электрифицируемых путей до 10 км. Участок Решетниково - Блок-пост, развернутая длина контактной сети 10 км | D18: - " - табл. 12 п.1.1 | E18: (108+4,1*10.0)*1.1*1.1 | F18: =(108+4.1*10)*1.1*1.1 -> 180.29
E19: 1,1- в зависимости от объема переустройства (на всем протяжении перегона в данном случае) вводится повышающий коэффициент, глава 2.2, п. 2.2.2 (здесь и далее)
B20: 3 | C20: Усиливающий провод 3 кВ на опорах контактной сети при длине линии 12 км. Участок Блок-пост - Завидово | D20: - " - табл. 12 п.4.3 | E20: (6.3+0.9*12.0)*1.1*1.2 | F20: =(6.3+0.9*12)*1.1*1.2 -> 22.572
B21: 4 | C21: Переустройство усиливающего провода 3 кВ на опорах контактной сети при длине линии 9,5 км. Участок Решетниково - Блок-пост | D21: - " - табл. 12 п.4.2 | E21: (5.3+1.0*9.5)*1.1*1.1 | F21: =(5.3+1*9.5)*1.1*1.1 -> 17.908
B22: 5 | C22: Питающие фидера 3 кВ на опорах контактной сети при длине линии 9,5 км. Участок Решетниково-Блок-пост | D22: - " - табл. 12 п.4.2 | E22: (5.3+1.0*9.5)*1.1*1.1* 1.1 | F22: =(5.3+1*9.5)*1.1*1.1 -> 17.908
B23: 6 | C23: ВЛ 10 кВ ПЭ по опорам контактной сети при длине линии 12 км. Участок Блок-пост - Завидово | D23: - " - табл. 12 п.4.3 | E23: (6.3+0.9*12.0)*1.1*1.1*1.2 | F23: =(6.3+0.9*12)*1.1*1.1*1.2 -> 24.8292
E24: 1.1-коэф. на применение провода СИП.
B25: 7 | C25: Переустройство волновода по опорам контактной сети при длине линии 9,5 км. Участок Решетниково - Блок-пост | D25: - " - табл. 12 п.4.2 | E25: (5.3+1.0*9.5)*1.1*1.1 | F25: =(5.3+1*9.5)*1.1*1.1 -> 17.908
B26: 8 | C26: Волновод по опорам контактной сети при длине линии 12 км. Участок Блок-пост - Завидово | D26: - " - табл. 12 п.4.3 | E26: (6.3+0.9*12.0)*1.1 | F26: =(6.3+0.9*12)*1.1 -> 18.81
B27: 9 | C27: Кабельная линия связи ОАО "РЖД", подвешиваемым на опорах контактной сети при длине 12 км. Участок Блок-пост - Завидово | D27: -"- Таблица 38 п.5 | E27: (78.13+6.25*12.0)*1.1*0.9 | F27: =(78.13+6.25*12)*1.1*0.9 -> 151.5987
D28: Указания к таблице 38 п.2.4.1 | E28: К=0.9 коэффициент при подвеске ВОК опорах контактной сети
B29: 10 | C29: Подключение ПС к контактной сети | D29: - " - табл. 12 п.23 | E29: 22*1.1 | F29: =22*1.1 -> 24.2
B30: 11 | C30: Расчет изгибающих моментов промежуточных опор (27 опор). Участок Блок-пост - Завидово. | D30: - " - табл. 12 п.16.1 | E30: (11.5+0.9*27)*2*1.1 | F30: =(11.5+0.9*27)*2*1.1 -> 78.76
B31: 12 | C31: Расчет изгибающих моментов промежуточных опор (10 опор). Участок Решетниково - Блок-пост | D31: - " - табл. 12 п.16.1 | E31: (11.5+0.9*10)*2*1.1 | F31: =(11.5+0.9*10)*2*1.1 -> 45.1
B32: 13 | C32: Расчет изгибающих моментов переходных опор (5 опор). Участок Блок-пост - Завидово | D32: - " - табл. 12 п.16.3 | E32: (16.5+1.48*5)*2*1.1 | F32: =(16.5+1.48*5)*2*1.1 -> 52.58
B33: 14 | C33: Расчет изгибающих моментов переходных опор (2 опоры). Участок Решетниково - Блок-пост | D33: - " - табл. 12 п.16.3 | E33: (16.5+1.48*2)*2*1.1 | F33: =(16.5+1.48*2)*2*1.1 -> 42.812
B34: 15 | C34: Расчет изгибающих моментов анкерных опор (3 опоры). Участок Блок-пост - Завидово | D34: - " - табл. 12 п.16.2 | E34: (16.5+1.48*3)*2*1.1 | F34: =(16.5+1.48*3)*2*1.1 -> 46.068
B35: 16 | C35: Расчет изгибающих моментов анкерных опор (3 опоры). Участок Решетниково - Блок-пост | D35: - " - табл. 12 п.16.2 | E35: (16.5+1.48*3)*2*1.1 | F35: =(16.5+1.48*3)*2*1.1 -> 46.068
B36: 17 | C36: Расстановка концевых опор в районе тяговой подстанции (3 опоры). Участок Решетниково-Блок-пост | D36: - " - табл. 12 п.25.2 | E36: (16.5+1.48*3)*2*1.1 | F36: =(16.5+1.48*3)*2*1.1 -> 46.068
B37: 18 | C37: Расчет фундаментов опор и их закрепление в грунте (35 опор). Участок Блок-пост - Завидово | D37: -"- Таблица 12 п.16.5 | E37: (13.59+0.94*35)*2*1.1 | F37: =(13.59+0.94*35)*2*1.1 -> 102.278
B38: 19 | C38: Расчет фундаментов опор и их закрепление в грунте (15 опор). Участок Решетниково - Блок-пост | D38: -"- Таблица 12 п.16.5 | E38: (13.59+0.94*15)*2*1.1 | F38: =(13.59+0.94*15)*2*1.1 -> 60.918
B39: 20 | C39: Подключение кабельных линий к объектам и установка клеммных шкафов при количестве подключений до 10 | D39: - " - табл. 23 п.2.1 | E39: 1.32*6*1.1 | F39: =1.32*6*1.1 -> 8.712
B40: 21 | C40: Схема питания и секциониро вания контактной сети участок свыше 10 до 30 км | D40: - " - табл. 12 п.21.1 | E40: 8.8*1.1 | F40: =8.8*1.1 -> 9.68
B41: 22 | C41: Проход контактной подвес-ки на мостах с ездой "поверху" | D41: -"- Таблица 12 п.27.1 | E41: (20.0+4.0*2)*1.1 | F41: =(20+4*2)*1.1 -> 30.8
B42: 23 | C42: Проход усиливающего провода на мостах с ездой "поверху" | D42: -"- Таблица 12 п.28.1 | E42: (9+2.6*2)*1.1 | F42: =(9+2.6*2)*1.1 -> 15.62
B43: 24 | C43: Проход ВЛ 10 кВ на мостах с ездой "поверху" | D43: -"- Таблица 12 п.28.1 | E43: (9+2.6*2)*1.1 | F43: =(9+2.6*2)*1.1*1.1 -> 17.182
B44: 25 | C44: Проход волновода на мостах с ездой "поверху" | D44: -"- Таблица 12 п.28.1 | E44: (9+2.6*2)*1.1 | F44: =(9+2.6*2)*1.1 -> 15.62
B45: 26 | C45: Разработка схемы армировки опор с учетом подвески на них дополнительных проводов (3 схемы) | D45: -"- Таблица 12 п.18 | E45: (6.6+0.55*6)*3*1.1 | F45: =(6.6+0.55*6)*3*1.1 -> 32.67
B46: 27 | C46: Пост секционирования для железнодорожных участков постоянного тока (1 ПС) | D46: -"- Таблица 18 п.5.1 | E46: (80.85*1)*1.1 | F46: =(80.85*1)*1.1 -> 88.935
B47: 28 | C47: Общие сооружения и устрйства ПС - 1 шт. | D47: -"- Таблица 15 п.13.1 | E47: (24.58*1)*1.1 | F47: =(24.58*1)*1.1 -> 27.038
B48: 29 | C48: Дистанционное управление разъединителями к/с при длине линии 2,5 км | D48: Справочник базовых цен на проектные работы в строительстве. Коммунальные инженерные сети и сооружения Москва 2012 г. Табл. 17 п.4 | E48: (12.265+0.037*2500) | F48: =(12.265+0.037*2500) -> 104.765
B49: 30 | C49: Установка разъединителей - 6 шт | D49: -"- Таблица 37 п.11 | E49: (0.66*6) | F49: =(0.66*6) -> 3.96
C50: Итого по п.п.1-30 | F50: =SUM(F12:F49) -> 1563.7819
B51: Всего по смете 2001г. | F51: =F50 -> 1563.7819
B52: ПД | F52: =F51*0.4 -> 625.51276
B53: РД | F53: =F51*0.6 -> 938.26914
B55: Всего по смете 1кв. 2024 К=5,81 | F55: =F51*5.81 -> 9085.5728
B56: ПД | F56: =F55*0.4 -> 3634.2291
B57: РД | F57: =F55*0.6 -> 5451.3437
B59: Главный инженер проекта | E59: В.А. Краснов

Sheet №13 УГТ ПД СЦБ
A1: «Адепт: Проект в 15.6» © ООО «Адепт» | D1: форма №2П от 28.11.2022г к Договору от 28.11.2022 г.
A3: Смета №13
A4: на проектные (изыскательские) работы
A6: Наименование предприятия, здания, сооружения, стадии проектирования, этапа, вида проектных или изыскательских работ | D6: Организация пассажирского сообщения от станции Москва-Октябрьская-Пассажирская до проектируемого транспортно-пересадочного узла "Завидово" через остановочный пункт Путепроводная Октябрьской железной дороги. Этап 2. Строительство железнодорожной линии от примыкания к Октябрьской железной дороге до проектируемого ТПУ «Завидово». Устройства СЦБ
A8: Наименование проектной (изыскательской) организации | D8: ОАО "Сибгипротранс"
A10: Наименование организации заказчика | D10: ООО "ДСК"
A12: № пп | B12: Характеристика предприятия, здания, сооружения или виды работ | D12: Номер частей, глав, таблиц, процентов, параграфов и пунктов указаний к разделу Справочника базовых цен на проектные и изыскательские работы для строительства | H12: Расчет стоимости: (a+bx)*Ki, или (объем строительно-монтажных работ) * проц./100 или количество x цена | I12: Стоимость, тыс. руб.
A13: 1 | B13: 2 | D13: 3 | H13: 4 | I13: 5
A14: 1 | B14: Перегон Решетниково - Блок пост 10 км Автоматическая блокировка с тональными рельсовыми цепями трехзначная. Протяженность от 20 до 50 км. АБТЦ-ЕМ - 9,5 км | D14: Железные дороги. 2014 г. Таблица 24. Автоматическая блокировка с тональными рельсовыми цепями, п.1 A=571.44 тыс.руб; B=9.95 тыс.руб; Осн. показ. Х=9.5 (1 км) Количество = 1 | H14: (A + B * X) * Количество * K1 * K2 (571.44 тыс.руб + 9.95 тыс.руб * 9.5) * 1 * 1.08 * 0.9 | I14: 647.32
B15: Коэффициенты
B16: Коэффициент на электротягу | D16: K1 = 1.08 (Ценообразующий)
B17: Стоимость проектирования автоблокировки с тональными рельсовыми цепями АБТЦ-ЕМ, АБТЦ-М определять с применением коэффициента | D17: K2 = 0.9 Глава 2.3, п.2.3.7 (Ценообразующий)
A18: 2 | B18: Перегон Решетниково - Блок пост 10 км Устройства контроля схода подвижного состава (УКСПС) | D18: Железные дороги. 2014 г. Таблица 30. Устройства контроля схода подвижного состава (УКСПС), контрольно-габаритные устройства (КГУ), п.1 A=10.4 тыс.руб.; Количество = 2 (устройство) | H18: A * Количество * Кст * Ктек * K1 10.4 тыс.руб. * 2 * 1.08 | I18: 22.46
B19: Коэффициенты
B20: Коэффициент на электротягу | D20: K1 = 1.08 (Ценообразующий)
A21: 3 | B21: Перегон Решетниково - Блок пост 10 км Системы диагностики подвижного состава КТСМ, ДИСК | D21: Железные дороги. 2014 г. Таблица 37. Системы диагностики подвижного состава, п.1 A=31 тыс.руб; B=3 тыс.руб; Осн. показ. Х=1 (1 пункт) Количество = 1 | H21: (A + B * Xзад) * Количество * Кст * Ктек * K1 (31 тыс.руб + 3 тыс.руб * 1) * 1 * 0.4 * 5.42 * 1.08 | I21: =ROUND((31+3*1)*1*0.4*5.42*1.08,2) -> 79.61
B22: Коэффициенты
B23: Стадия: Проектная документация | D23: Кст = 0.4
B24: инд.4кв.2022г.к 01.01.2001 на пр.раб. | D24: Ктек = 5.42 Письмо Минстроя России от 14.11.2022 №60112-ИФ/09
B25: Коэффициент на электротягу | D25: K1 = 1.08 (Ценообразующий)
A26: 4 | B26: Блок пост 10 км Микропроцессорная система ЭЦ. До 10 стрелок. 2 стрелки | D26: Железные дороги. 2014 г. Таблица 25. Электрическая централизация стрелок на станциях, п.1 A=411.08 тыс.руб.; B=58.33 тыс.руб.; Осн. показ. Х=2 (1 стрелка) Количество = 1 | H26: (A + B * X) * Количество * K1 * K2 (411.08 тыс.руб + 58.33 тыс.руб * 2) * 1 * 1.08 * 0.7 | I26: 398.97
B27: Коэффициенты
B28: Коэффициент на электротягу | D28: K1 = 1.08 (Ценообразующий)
B29: К'пон = Xзад / (0.5 * Xмин) | D29: K2 = 0.7 понижающий коэффициент, учитывающий разницу в трудоемкости работ по проектируемому объекту и объекту аналогу (Ценообразующий)
A30: 5 | B30: Блок пост 10 км Диспетчерская централизация (ДЦ). Контролируемый пункт (КП) на станции с диспетчерским управлением (ДУ) | D30: Железные дороги. 2014 г. Таблица 26. Микропроцессорная система диспетчерской централизации (ДЦ) и диспетчерского контроля (ДК), п.1 A=129.96 тыс.руб; B=7.78 тыс.руб; Осн. показ. Х=3 (стрелка) Количество = 1 | H30: (A + B * Xзад) * Количество * K1 (129.96 тыс.руб + 7.78 тыс.руб * 3) * 1 * 1.08 | I30: 165.56
B32: Коэффициенты
B33: Коэффициент на электротягу | D33: K1 = 1.08 (Ценообразующий)
A34: 6 | B34: Блок пост 10 км Устройства контроля схода подвижного состава (УКСПС) | D34: Железные дороги. 2014 г. Таблица 30. Устройства контроля схода подвижного состава (УКСПС), контрольно-габаритные устройства (КГУ), п.1 A=10.4 тыс.руб; Количество = 2 (устройство) | H34: A * Количество * K1 10.4 тыс.руб * 2 * 1.08 | I34: 22.46
B35: Коэффициенты
B36: Коэффициент на электротягу | D36: K1 = 1.08 (Ценообразующий)
A37: 7 | B37: Перегон Блок пост 10 км - Конаховский Мох Автоматическая блокировка с тональными рельсовыми цепями трехзначная. Протяженность от 20 до 50 км. АБТЦ-ЕМ - 7,8 км | D37: Железные дороги. 2014 г. Таблица 24. Автоматическая блокировка с тональными рельсовыми цепями, п.1 A=571.44 тыс.руб; B=9.95 тыс.руб; Осн. показ. Х=7.8 (1 км) Количество = 1 | H37: (A + B * X) * Количество * K1 * K2 (571.44 тыс.руб + 9.95 тыс.руб * 7.8) * 1 * 1.08 * 0.9 | I37: 630.88
B38: Коэффициенты
B39: Коэффициент на электротягу | D39: K1 = 1.08 (Ценообразующий)
B40: Стоимость проектирования автоблокировки с тональными рельсовыми цепями АБТЦ-ЕМ, АБТЦ-М определять с применением коэффициента | D40: K2 = 0.9 Глава 2.3, п.2.3.7 (Ценообразующий)
A41: 8 | B41: Перегон Блок пост 10 км - ТПУ Завидово Автоматическая блокировка с тональными рельсовыми цепями трехзначная. Протяженность от 20 до 50 км. МПАБ - 12 км | D41: Железные дороги. 2014 г. Таблица 24. Автоматическая блокировка с тональными рельсовыми цепями, п.1 A=571.44 тыс.руб; B=9.95 тыс.руб; Осн. показ. Х=12 (1 км) Количество = 1 | H41: (A + B * X) * Количество * K1 (571.44 тыс.руб + 9.95 тыс.руб * 12) * 1 * 1.08 | I41: 746.11
B43: Коэффициенты
B44: Коэффициент на электротягу | D44: K1 = 1.08 (Ценообразующий)
A45: 9 | B45: Перегон Блок пост 10 км - ТПУ Завидово Устройство контроля свободности перегона методом счета осей (УКП СО, ЭССО) | D45: Железные дороги. 2014 г. Таблица 28. Устройство контроля свободного перегона методом счета осей (УКП СО), п.1 A=174.4 тыс.руб; Количество = 2 (комплект) | H45: A * Количество * Кст * Ктек * K1 174.4 тыс.руб * 2 * 0.4 * 5.42 * 1.08 | I45: =ROUND(174.4*2*0.4*5.42*1.08,2) -> 816.69
B46: Коэффициенты
B47: Стадия: Проектная документация | D47: Кст = 0.4
B48: инд.4кв.2022г.к 01.01.2001 на пр.раб. | D48: Ктек = 5.42 Письмо Минстроя России от 14.11.2022 №60112-ИФ/09
B49: Коэффициент на электротягу | D49: K1 = 1.08 (Ценообразующий)
A50: 10 | B50: Перегон Блок пост 10 км - ТПУ Завидово Устройства контроля схода подвижного состава (УКСПС) | D50: Железные дороги. 2014 г. Таблица 30. Устройства контроля схода подвижного состава (УКСПС), контрольно-габаритные устройства (КГУ), п.1 A=10.4 тыс.руб; Количество = 2 (устройство) | H50: A * Количество * K1 10.4 тыс.руб * 2 * 1.08 | I50: 22.46
B51: Коэффициенты
B52: Коэффициент на электротягу | D52: K1 = 1.08 (Ценообразующий)
A53: 11 | B53: ТПУ Завидово Микропроцессорная система ЭЦ. До 10 стрелок. 1 стрелка | D53: Железные дороги. 2014 г. Таблица 25. Электрическая централизация стрелок на станциях, п.1 A=411.08 тыс.руб; B=58.33 тыс.руб; Осн. показ. Х=1 (1 стрелка) Количество = 1 | H53: (A + B * X) * Количество * K1 * K2 (411.08 тыс.руб + 58.33 тыс.руб * 1) * 1 * 1.08 * 0.7 | I53: 354.87
B55: Коэффициенты
B56: Коэффициент на электротягу | D56: K1 = 1.08 (Ценообразующий)
B57: К'пон = Xзад / (0.5 * Xмин) | D57: K2 = 0.7 понижающий коэффициент, учитывающий разницу в трудоемкости работ по проектируемому объекту и объекту аналогу (Ценообразующий)
A58: 12 | B58: ТПУ Завидово Диспетчерская централизация (ДЦ). Контролируемый пункт (КП) на станции с диспетчерским управлением (ДУ) | D58: Железные дороги. 2014 г. Таблица 26. Микропроцессорная система диспетчерской централизации (ДЦ) и диспетчерского контроля (ДК), п.1 A=129.96 тыс.руб; B=7.78 тыс.руб; Осн. показ. Х=1 (стрелка) Количество = 1 | H58: (A + B * Xзад) * Количество * K1 * K2 (129.96 тыс.руб + 7.78 тыс.руб * 1) * 1 * 1.08 | I58: 148.76
B59: Коэффициенты
B60: Коэффициент на электротягу | D60: K1 = 1.08 (Ценообразующий)
A61: 13 | B61: Станция Конаковский Мох Микропроцессорная система ЭЦ. До 10 стрелок. (Реконструкция) 4 стрелки | D61: Железные дороги. 2014 г. Таблица 25. Электрическая централизация стрелок на станциях, п.1 A=411.08 тыс.руб; B=58.33 тыс.руб; Осн. показ. Х=4 (1 стрелка) Количество = 1 | H61: (A + B * X) * Количество * K1 * K2 (411.08 тыс.руб + 58.33 тыс.руб * 4) * 1 * 1.08 * 0.8 | I61: 556.76
B62: Коэффициенты
B63: Коэффициент на электротягу | D63: K1 = 1.08 (Ценообразующий)
B64: К'пон = Xзад / (0.5 * Xмин) | D64: K2 = 0.8 понижающий коэффициент, учитывающий разницу в трудоемкости работ по проектируемому объекту и объекту аналогу (Ценообразующий)
A65: 14 | B65: Станция Конаковский Мох Диспетчерская централизация (ДЦ). Контролируемый пункт (КП) на станции с диспетчерским управлением (ДУ) | D65: Железные дороги. 2014 г. Таблица 26. Микропроцессорная система диспетчерской централизации (ДЦ) и диспетчерского контроля (ДК), п.1 A=129.96 тыс.руб; B=7.78 тыс.руб; Осн. показ. Х=4 (стрелка) Количество = 1 | H65: (A + B * Xзад) * Количество * K1 (129.96 тыс.руб + 7.78 тыс.руб * 4) * 1 * 1.08 | I65: 173.97
B66: Коэффициенты
B67: Стадия: Проектная документация | D67: Кст = 0.4
B68: инд.4кв.2022г.к 01.01.2001 на пр.раб. | D68: Ктек = 5.42 Письмо Минстроя России от 14.11.2022 №60112-ИФ/09
B69: Коэффициент на электротягу | D69: K1 = 1.08 (Ценообразующий)
A70: 15 | B70: Станция Конаковский Мох Устройства контроля схода подвижного состава (УКСПС) | D70: Железные дороги. 2014 г. Таблица 30. Устройства контроля схода подвижного состава (УКСПС), контрольно-габаритные устройства (КГУ), п.1 A=10.4 тыс.руб; Количество = 2 (устройство) | H70: A * Количество * K1 10.4 тыс.руб * 2 * 1.08 | I70: 22.46
B71: Коэффициенты
B72: Коэффициент на электротягу | D72: K1 = 1.08 (Ценообразующий)
A73: 16 | B73: Автоматическая переездная сигнализация через 1 путь с устройством заграждения (УЗП) Подъезд к д. Шоша | D73: Железные дороги. 2014 г. Таблица 31. Кодирование путей, автоматическая переездная сигнализация, п.2 A=33.03 тыс.руб; Количество = 1 (переезд) | H73: A * Количество * K1 33.03 тыс.руб * 1 * 1.08 | I73: 35.67
B74: Коэффициенты
B75: Коэффициент на электротягу | D75: K1 = 1.08 (Ценообразующий)
A76: 17 | B76: Релейная система ЭЦ. До 10 стрелок. Увязка с переездом | D76: Железные дороги. 2014 г. Таблица 25. Электрическая централизация стрелок на станциях, п.8 A=548.23 тыс.руб.; B=74.4 тыс.руб.; Осн. показ. Х=1 (1 стрелка) Количество = 1 | H76: (A + B * X) * Количество * K1 * K2 (548.23 тыс.руб + 74.4 тыс.руб * 1) * 1 * 1.08 * 0.7 | I76: 470.71
B78: Коэффициенты
B79: Коэффициент на электротягу | D79: K1 = 1.08 (Ценообразующий)
B80: К'пон = Xзад / (0.5 * Xмин) | D80: K2 = 0.7 понижающий коэффициент, учитывающий разницу в трудоемкости работ по проектируемому объекту и объекту аналогу (Ценообразующий)
A81: 18 | B81: Технологическое обеспечение автоматизированного обслуживания устройств ЖАТ с применением средств систем технической диагностики и мониторинга (ТДМ) для перегона, оборудованном автоблокировкой. Однопутный участок. | D81: Железные дороги. 2014 г. Таблица 29. Технологическое обеспечение эксплуатации устройств автоматики и телемеханики, п.1.2.1 A=3.5 тыс.руб.; B=0.3 тыс.руб.; Количество = 20 | H81: (A + B * Xзад) * Количество * K1 (3.5 тыс.руб + 0.3 тыс.руб * 0) * 20 * 1.08 | I81: 75.6
B82: Коэффициенты
B83: Коэффициент на электротягу | D83: K1 = 1.08 (Ценообразующий)
A84: 19 | B84: Диспетчерский контроль (ДК). Диагностический комплекс для МПЦ на станции с включением объектов диагностирования стрелок, блок-участков, переездов | D84: Железные дороги. 2014 г. Таблица 26. Микропроцессорная система диспетчерской централизации (ДЦ) и диспетчерского контроля (ДК), п.7 A=71.3 тыс.руб.; B=3.75 тыс.руб.; Осн. показ. Х=1 (диагностический комплекс) Количество = 1 | H84: (A + B * Xзад) * Количество * K1 (71.3 тыс.руб + 3.75 тыс.руб * 1) * 1 * 1.08 | I84: 81.05
B85: Коэффициенты
B86: Коэффициент на электротягу | D86: K1 = 1.08 (Ценообразующий)
A87: 20 | B87: Итого по смете 2001г. | I87: =ROUND((SUM($I$14:$I$84)),2) -> 5472.37
B88: ПД | I88: =I87*0.4 -> 2188.948
B89: РД | I89: =I87*0.6 -> 3283.422
A91: 21 | B91: Итого по смете 1 кв. 2024г. | D91: К=5,81 | I91: =I87*5.81 -> 31794.47
B92: ПД | I92: =I91*0.4 -> 12717.788
B93: РД | I93: =I91*0.6 -> 19076.682
B95: Составил | H95: В.А. Краснов

Sheet №14 ПД АД Подъездные
G1: Форма 2П
A2: Приложение к
D3: (договору, дополнительному соглашению)
A4: Смета № 14
A5: Проектные работы (автомобильная дорога)
A6: Наименование объекта | D6: Организация пассажирского сообщения от станции Москва-Октябрьская-Пассажирская до проектируемого ТПУ "Завидово" через остановочный пункт Путепроводная Октябрьской железной дороги. Этап 2. Строительство железнодорожной линии от примыкания к Октябрьской железной дороге до проектируемого ТПУ «Завидово». Подъездные автомобильные дороги
A8: Определение базовых цен на основании следующих документов:
A9: Методические указания по применению Справочников базовых цен на проектные работы в строительстве, 2010г. Минрегион России приказ от 29 декабря 2009г. №620 [1]
A10: СБЦП Автомобильные дороги общего пользования. 2007 г. (цены приведены на уровень 01.01.2001 г.) [3]
A11: № пп | B11: Характеристика предприятия, здания, сооружения, вида работ | C11: Ед. изм. | D11: Номер частей, глав, таблиц, процентов, параграфов и пунктов указаний к разделу Справочника базовых цен | F11: Расчет стоимости типа (a+b * Х)*Ki, где Х - объем выполняемых работ | G11: Стоимость, тыс. руб.
A12: 1 | B12: 2 | C12: 3 | D12: 4 | F12: 5 | G12: 6
A13: 1 | B13: Автомобильна дорога V кат Категория сложности - 2 | C13: км | D13: [3] Табл 2 (окончание) п.2 | F13: 194.31 | G13: =194.31 -> 194.31
D14: а = | E14: 194.31
D15: b =
A16: 2 | B16: Транспортная развязка Примыкание в одном уровне с ПСП Категория сложности - 1 Количество - 1 шт | C16: примыкание | D16: [3] Разд 4 | F16: 276,92 * 0,35 | G16: =ROUND(276.92*0.4*0.35*0.62*0.3,3) -> 7.211
D17: т.3 | E17: п.1 [1]
D18: а = | E18: 276.92
D19: b =
D20: К = 0,35 | E20: [3] - Табл.3 прим.2 Примыкание без ПСП
A21: =A16+1 -> 3 | B21: Итого по смете в базовых ценах: | G21: =SUM(G13:G20) -> 201.521
B22: ПД | G22: =G21*0.4 -> 80.6084
B23: РД | G23: =G21*0.6 -> 120.9126
A24: =A21+1 -> 4 | B24: Итого с учетом индекса изменения стоимости на I квартал 2024 г. (письмо Минстроя России от 07.03.2023 N 13023-ИФ/09) | F24: 5.81 | G24: =ROUND(G21*F24,2) -> 1170.84
B25: ПД | G25: =G24*0.4 -> 468.336
B26: РД | G26: =G24*0.6 -> 702.504
B28: Составил:_________________Курочкин А.В.

Sheet №15 ПД АД Ж,Д, переезд
G1: Форма 2П
A2: Приложение к
D3: (договору, дополнительному соглашению)
A4: Смета № 15
A5: Проектные работы (автомобильная дорога)
A6: Наименование объекта | D6: Организация пассажирского сообщения от станции Москва-Октябрьская-Пассажирская до проектируемого ТПУ "Завидово" через остановочный пункт Путепроводная Октябрьской железной дороги. Этап 2. Строительство железнодорожной линии от примыкания к Октябрьской железной дороге до проектируемого ТПУ «Завидово». Автомобильные дороги Железнодорожный переезд
A8: Определение базовых цен на основании следующих документов:
A9: Методические указания по применению Справочников базовых цен на проектные работы в строительстве, 2010г. Минрегион России приказ от 29 декабря 2009г. №620 [1]
A10: СБЦП Автомобильные дороги общего пользования. 2007 г. (цены приведены на уровень 01.01.2001 г.) [3]
A11: СБЦП 81-2001-09 Железные дороги. 2014 г. (цены приведены на уровень 01.01.2001 г.) [2]
A13: № пп | B13: Характеристика предприятия, здания, сооружения, вида работ | C13: Ед. изм. | D13: Номер частей, глав, таблиц, процентов, параграфов и пунктов указаний к разделу Справочника базовых цен | F13: Расчет стоимости типа (a+b * Х)*Ki, где Х - объем выполняемых работ | G13: Стоимость, тыс. руб.
A14: 1 | B14: 2 | C14: 3 | D14: 4 | F14: 5 | G14: 6
A15: 1 | B15: Автомобильна дорога V кат Категория сложности - 2 | C15: шт | D15: [2] Табл 50 Железнодорожные переезды п.1 | F15: 91 | G15: =F15 -> 91
D16: а = | E16: 91
D17: b =
A18: 2 | B18: Транспортная развязка Примыкание в одном уровне с ПСП Категория сложности - 1 Количество - 1 шт | C18: примыкание | D18: [3] Разд 4 | F18: 276.92 | G18: =F18 -> 276.92
D19: т.3 | E19: п.1 [1]
D20: а = | E20: 276.92
D21: b =
A22: =A18+1 -> 3 | B22: Итого по смете в базовых ценах: | G22: =SUM(G15:G21) -> 367.92
B23: ПД | G23: =G22*0.4 -> 147.168
B24: РД | G24: =G22*0.6 -> 220.752
A25: =A22+1 -> 4 | B25: Итого с учетом индекса изменения стоимости на I квартал 2024 г. (письмо Минстроя России от 07.03.2023 N 13023-ИФ/09) | F25: 5.81 | G25: =ROUND(G22*F25,2) -> 2137.62
B26: ПД | G26: =G25*0.4 -> 855.048
B27: РД | G27: =G25*0.6 -> 1282.572
B29: Составил:_________________Курочкин А.В.

Sheet №16 Обследования ОР2
H3: Форма 3П
B4: Приложение к
C5: (договору, дополнительному соглашению)
A6: СМЕТА №16
A7: Обследование на участке автомобильной дороги «Подъезд к д. Шоша»
A8: Наименование предприятия, здания, сооружения, стадии проектирования, этапа, вида проектных или изыскательских работ | C8: Организация пассажирского сообщения от станции Москва – Октябрьская – Пассажирская до проектируемого ТПУ «Завидово» через остановочный пункт Путепроводная Октябрьской железной дороги Этап 2. Строительство железнодорожной линии от примыкания к Октябрьской железной дороге до проектируемого ТПУ «Завидово»
A10: Таблица 1 - Расчет затрат на выполнение работ (оказание услуг)
A11: № п/п | B11: Вид работ (услуг) | C11: Наименование должности | D11: Кол-во рабочих ставок | E11: Количество рабочего времени, дней | F11: Итого чел-дн | G11: Стоимость единицы трудоемкости | H11: Стоимость работ (услуг), руб.
A12: 1 | B12: Сбор исходных данных для проектирования | C12: Главный инженер | D12: 1 | E12: 0.5 | F12: =D12*E12 -> 0.5 | G12: =C34 -> 5585.7939 | H12: =F12*G12 -> 2792.8969
C13: ГИП | D13: 1 | E13: 2 | F13: =D13*E13 -> 2 | G13: =C34 -> 5585.7939 | H13: =F13*G13 -> 11171.588
C14: Инженер | D14: 2 | E14: 5 | F14: =D14*E14 -> 10 | G14: =C34 -> 5585.7939 | H14: =F14*G14 -> 55857.939
A15: Затраты на оплату труда, руб. без НДС | H15: =ROUND(SUM(H12:H14),0) -> 69822 | K15: =H15 -> 69822
B17: ="Стоимость работ: "&SUBSTITUTE(PROPER(INDEX(n_4,MID(TEXT(K15,n0),1,1)+1)&INDEX(n0x,MID(TEXT(K15,n0),2,1)+1,MID(TEXT(K15,n0),3,1)+1)&IF(-MID(TEXT(K15,n0),1,3),"миллиард"&VLOOKUP(MID(TEXT(K15,n0),3,1)*AND(MID(TEXT(K15,n0),2,1)-1),мил,2),"")&INDEX(n_4,MID(TEXT(K15,n0),4,1)+1)&INDEX(n0x,MID(TEXT(K15,n0),5,1)+1,MID(TEXT(K15,n0),6,1)+1)&IF(-MID(TEXT(K15,n0),4,3),"миллион"&VLOOKUP(MID(TEXT(K15,n0),6,1)*AND(MID(TEXT(K15,n0),5,1)-1),мил,2),"")&INDEX(n_4,MID(TEXT(K15,n0),7,1)+1)&INDEX(n1x,MID(TEXT(K15,n0),8,1)+1,MID(TEXT(K15,n0),9,1)+1)&IF(-MID(TEXT(K15,n0),7,3),VLOOKUP(MID(TEXT(K15,n0),9,1)*AND(MID(TEXT(K15,n0),8,1)-1),тыс,2),"")&INDEX(n_4,MID(TEXT(K15,n0),10,1)+1)&INDEX(n0x,MID(TEXT(K15,n0),11,1)+1,MID(TEXT(K15,n0),12,1)+1)),"z"," ")&IF(TRUNC(TEXT(K15,n0)),"","Ноль ")&"рубл"&VLOOKUP(MOD(MAX(MOD(MID(TEXT(K15,n0),11,2)-11,100),9),10),{0,"ь ";1,"я ";4,"ей "},2) -> Стоимость работ: Шестьдесят девять тысяч восемьсот двадцать два рубля
B19: Итого на I кв. 2024г | C19: тыс.руб | D19: =H15/1000 -> 69.822
B20: Итого на 01.01.2001г (К=5,83) | C20: тыс.руб | D20: =D19/5.83 -> 11.976329
A22: Составил: _______________________ | C22: Сычев
A24: Проверил: _______________________
A26: Таблица 2 Расчет стоимости единицы трудоемкости
A27: № | B27: Статья | C27: Сумма, руб./мес. на 1 специалиста
A28: 1 | B28: Зарплата основных специалистов (ФОТ) по виду деятельности «Деятельность профессиональная, научная и техническая» | C28: =E78 -> 76479.2
A29: 2 | B29: Страховые взносы в ПФ, ФМС, ФСС | C29: =C28*0.302 -> 23096.718 | D29: =C29/C28 -> 0.302
A30: 3 | B30: Накладные расходы | C30: =C36 -> 9923.3746 | D30: =C30/C28 -> 0.12975259 | E30: от прямых расходов (не более 20%)
A31: 4 | B31: Итого расходы (себестоимость (СС)) | C31: =SUM(C28:C30) -> 109499.29
A32: 5 | B32: Прибыль | C32: =C31*0.05 -> 5474.9647 | D32: =C32/C31 -> 0.05
A33: 6 | B33: Стоимость 1 человеко-месяца, без НДС | C33: =SUM(C31:C32) -> 114974.26
A34: 7 | B34: Стоимость 1 человеко-дня, без НДС | C34: =C33*12/247 -> 5585.7939
A36: № | B36: Статьи накладных расходов (руб., % от ФОТ) | C36: =C37+C38+C44 -> 9923.3746 | D36: =C36/(C28) -> 0.12975259 | F36: средняя в год | G36: средняя в месяц
A37: 1. | B37: Аренда (или амортизация собственных) зданий/помещений (минимальный норматив 4,5 кв.м. на 1 человека, умноженный на 2 для учета помещений общего пользования и администрации) | C37: =F37*9/12 -> 9070.2 | D37: =C37/C28 -> 0.11859695 | F37: =G37*12 -> 12093.6 | G37: 1007.8
A38: 2. | B38: Амортизация оборудования, технических средств: | C38: =SUM(C39:C43) -> 853.1746 | D38: =C38/C28 -> 0.011155642
A39: 2.1. | B39: ПК (20000 руб. при сроке службы 3 года (2-я амортизационная группа[3])) | C39: =20000/3/12 -> 555.55556 | D39: =C39/C28 -> 0.0072641392
A40: 2.2. | B40: стол (8000 руб. при сроке службы 7 лет (4-я амортизационная группа)) | C40: =8000/7/12 -> 95.238095 | D40: =C40/C28 -> 0.001245281
A41: 2.3. | B41: стул (2000 руб. при сроке службы 7 лет (4-я амортизационная группа)) | C41: =2000/7/12 -> 23.809524 | D41: =C41/C28 -> 0.00031132025
A42: 2.4. | B42: тумба (5000 руб. при сроке службы 7 лет (4-я амортизационная группа)) | C42: =5000/7/12 -> 59.52381 | D42: =C42/C28 -> 0.00077830063
A43: 2.5. | B43: прочие (доля от шкафов для одежды, для документов, офисной оргтехники, от оборудования туалетов и т.д.) (10000 руб. при сроке службы 7 лет (4-я амортизационная группа)) | C43: =10000/7/12 -> 119.04762 | D43: =C43/C28 -> 0.0015566013
A44: 3. | B44: Прочие расходы от ФОТ: | C44: =C28*0 -> 0 | D44: =C44/C28 -> 0
A45: 3.1. | B45: содержание и ремонт зданий/помещений, сооружений и оборудования
A46: 3.2. | B46: содержание и обслуживание программных и технических средств
A47: 3.3. | B47: расходы на научно-техническую информацию
A48: 3.4. | B48: расходы на организованный набор работников, подготовку и переподготовку специалистов
A49: 3.5. | B49: оплата бухгалтерских, информационных, консультационных, банковских, транспортных и курьерских услуг
A50: 3.6. | B50: расходы на связь, средства коммуникации, интернет
A51: 3.7. | B51: иные
A53: Расчет суммарного размера тарифов страховых взносов:
A54: № | B54: Наименования тарифов страховых взносов | C54: Ставка, %
A55: 1 | B55: Тариф страховых взносов, уплачиваемых в Пенсионный фонд РФ | C55: 0.22
A56: 2 | B56: Тариф страховых взносов, уплачиваемых в Фонд социального страхования РФ | C56: 0.029
A57: 3 | B57: Тариф страховых взносов, уплачиваемых в Федеральный фонд обязательного медицинского страхования | C57: 0.051
A58: 4 | B58: Страховой тариф на обязательное социальное страхование от несчастных случаев на производстве и профессиональных заболеваний по I классу профессионального риска | C58: 0.002
A59: 5 | B59: ИТОГО суммарный размер тарифов страховых взносов | C59: =SUM(C55:C58) -> 0.302
B61: Составил:_________________Курочкин А.В.
E78: 76479.2
