Workbook

Sheet RV_DATA
A1: BuildingFinished | B1: Trud | C1: Mash | D1: Mat | E1: MatZak | F1: Oborud | G1: OborudZak | H1: ZeroStoim | I1: NegativeKoll | J1: ReUnionKollResurcy | K1: UnionOneUchRes | L1: IdLevel | M1: ViewCodes | N1: UnionCodes | O1: PEREVOZKA
A2: 1 | B2: 1 | C2: 1 | D2: 1 | E2: 1 | F2: 1 | G2: 1 | H2: 0 | I2: 1 | J2: 0 | K2: 1 | L2: 38182922 | M2: 0 | N2: 0 | O2: 0
A4: TYPE | B4: SOURCE_LINK | C4: RABMAT_EX | D4: TIP_RAB | E4: TYPE_TRUD | F4: TAB | G4: NAME | H4: EDIZM | I4: KOLL | J4: UCH | K4: PRICE_B | L4: PRICE_ED | M4: STOIM_B | N4: PRICE_C | O4: STOIM_C | P4: ZPM_B | Q4: ZPM_ED | R4: STOIM_ZPM_B | S4: ZPM_C | T4: STOIM_ZPM_C | U4: RABMAT | V4: WBS | W4: CBSI | X4: CBSII | Y4: TechSpecCVORPP | Z4: CRC_GR_RES | AA4: CRC_B | AB4: CRC_C
A6: =Source!A20 -> 3 | B6: 20 | G6: =Source!G20 -> ремонт трубы
A7: 20 | B7: 3 | C7: 2 | D7: 0 | E7: =SmtRes!AV3 -> 1 | F7: =SmtRes!I3 -> 91.01.05-084 | G7: =SmtRes!K3 -> Экскаваторы одноковшовые дизельные на гусеничном ходу, объем ковша 0,4 м3 | H7: =SmtRes!O3 -> маш.-ч | I7: =SmtRes!Y3*Source!I24 -> 1.32255 | J7: =SmtRes!AO3 -> 0 | K7: =SmtRes!AF3 -> 947.64 | M7: =ROUND(I7*K7, 2) -> 1253.3 | N7: =SmtRes!AB3 -> 1250.88 | O7: =SmtRes!DG3 -> 1654.35 | P7: =SmtRes!AG3 -> 497.4 | R7: =ROUND(I7*P7, 2) -> 657.84 | S7: =SmtRes!AC3 -> 497.4 | T7: =SmtRes!DH3 -> 657.84 | U7: 2 | Z7: =SmtRes!X3 -> 1473885390 | AA7: 1567848987 | AB7: 1216713234
A8: 20 | B8: 1 | C8: 1 | D8: 0 | E8: =SmtRes!AV1 -> 1 | F8: =SmtRes!I1 -> 1-100-20 | G8: =SmtRes!K1 -> Средний разряд работы 2,0 | H8: =SmtRes!O1 -> чел.-ч. | I8: =SmtRes!Y1*Source!I24 -> 0.2655 | J8: =SmtRes!AO1 -> 0 | K8: =SmtRes!AH1 -> 352.06 | M8: =ROUND(I8*K8, 2) -> 93.47 | N8: =SmtRes!AD1 -> 352.06 | O8: =SmtRes!DI1 -> 93.47 | P8: =SmtRes!AG1 -> 0 | R8: =ROUND(I8*P8, 2) -> 0 | S8: =SmtRes!AC1 -> 0 | T8: =SmtRes!DH1 -> 0 | U8: 1 | Z8: =SmtRes!X1 -> 370475345 | AA8: 1406990596 | AB8: 1406990596
A9: 20 | B9: 7 | C9: 2 | D9: 0 | E9: =SmtRes!AV7 -> 1 | F9: =SmtRes!I7 -> 91.14.02-001 | G9: =SmtRes!K7 -> Автомобили бортовые, грузоподъемность до 5 т | H9: =SmtRes!O7 -> маш.-ч | I9: =SmtRes!Y7*Source!I25 -> 0.0384 | J9: =SmtRes!AO7 -> 0 | K9: =SmtRes!AF7 -> 652.84 | M9: =ROUND(I9*K9, 2) -> 25.07 | N9: =SmtRes!AB7 -> 652.84 | O9: =SmtRes!DG7 -> 25.07 | P9: =SmtRes!AG7 -> 432.81 | R9: =ROUND(I9*P9, 2) -> 16.62 | S9: =SmtRes!AC7 -> 432.81 | T9: =SmtRes!DH7 -> 16.62 | U9: 2 | Z9: =SmtRes!X7 -> -849950259 | AA9: 106755230 | AB9: 106755230
A10: 20 | B10: 6 | C10: 2 | D10: 0 | E10: =SmtRes!AV6 -> 1 | F10: =SmtRes!I6 -> 91.10.05-009 | G10: =SmtRes!K6 -> Трубоукладчики, номинальная грузоподъемность 35 т | H10: =SmtRes!O6 -> маш.-ч | I10: =SmtRes!Y6*Source!I25 -> 0.992 | J10: =SmtRes!AO6 -> 0 | K10: =SmtRes!AF6 -> 4403.56 | M10: =ROUND(I10*K10, 2) -> 4368.33 | N10: =SmtRes!AB6 -> 4931.99 | O10: =SmtRes!DG6 -> 4892.53 | P10: =SmtRes!AG6 -> 707.35 | R10: =ROUND(I10*P10, 2) -> 701.69 | S10: =SmtRes!AC6 -> 707.35 | T10: =SmtRes!DH6 -> 701.69 | U10: 2 | Z10: =SmtRes!X6 -> -1505731505 | AA10: 1516374314 | AB10: 929036850
A11: 20 | B11: 4 | C11: 1 | D11: 0 | E11: =SmtRes!AV4 -> 1 | F11: =SmtRes!I4 -> 1-100-40 | G11: =SmtRes!K4 -> Средний разряд работы 4,0 | H11: =SmtRes!O4 -> чел.-ч. | I11: =SmtRes!Y4*Source!I25 -> 15.008 | J11: =SmtRes!AO4 -> 0 | K11: =SmtRes!AH4 -> 432.81 | M11: =ROUND(I11*K11, 2) -> 6495.61 | N11: =SmtRes!AD4 -> 432.81 | O11: =SmtRes!DI4 -> 6495.61 | P11: =SmtRes!AG4 -> 0 | R11: =ROUND(I11*P11, 2) -> 0 | S11: =SmtRes!AC4 -> 0 | T11: =SmtRes!DH4 -> 0 | U11: 1 | Z11: =SmtRes!X4 -> 888410196 | AA11: 795807998 | AB11: 795807998
A12: 20 | B12: 20 | C12: 3 | D12: 0 | E12: =SmtRes!AV20 -> 0 | F12: =SmtRes!I20 -> 11.1.03.01-0067 | G12: =SmtRes!K20 -> Брус обрезной хвойных пород (ель, сосна), естественной влажности, длина 2-6,5 м, ширина 100 и более мм, толщина 100 и более мм, сорт III | H12: =SmtRes!O20 -> м3 | I12: =SmtRes!Y20*Source!I27 -> 0.027 | J12: =SmtRes!AO20 -> 0 | K12: =SmtRes!AE20 -> 16655 | M12: =ROUND(I12*K12, 2) -> 449.69 | N12: =SmtRes!AA20 -> 13324 | O12: =SmtRes!DF20 -> 359.75 | P12: =SmtRes!AG20 -> 0 | R12: =ROUND(I12*P12, 2) -> 0 | S12: =SmtRes!AC20 -> 0 | T12: =SmtRes!DH20 -> 0 | U12: 3 | Z12: =SmtRes!X20 -> -831399682 | AA12: -1480605263 | AB12: -1360243399
A13: 20 | B13: 19 | C13: 3 | D13: 0 | E13: =SmtRes!AV19 -> 0 | F13: =SmtRes!I19 -> 01.3.02.09-0022 | G13: =SmtRes!K19 -> Пропан-бутан смесь техническая | H13: =SmtRes!O19 -> кг | I13: =SmtRes!Y19*Source!I27 -> 4.0656 | J13: =SmtRes!AO19 -> 0 | K13: =SmtRes!AE19 -> 41.38 | M13: =ROUND(I13*K13, 2) -> 168.23 | N13: =SmtRes!AA19 -> 57.1 | O13: =SmtRes!DF19 -> 232.15 | P13: =SmtRes!AG19 -> 0 | R13: =ROUND(I13*P13, 2) -> 0 | S13: =SmtRes!AC19 -> 0 | T13: =SmtRes!DH19 -> 0 | U13: 3 | Z13: =SmtRes!X19 -> -1568219933 | AA13: 1588463070 | AB13: 766106269
A14: 20 | B14: 18 | C14: 3 | D14: 0 | E14: =SmtRes!AV18 -> 0 | F14: =SmtRes!I18 -> 01.3.02.08-0001 | G14: =SmtRes!K18 -> Кислород газообразный технический | H14: =SmtRes!O18 -> м3 | I14: =SmtRes!Y18*Source!I27 -> 1.59 | J14: =SmtRes!AO18 -> 0 | K14: =SmtRes!AE18 -> 89 | M14: =ROUND(I14*K14, 2) -> 141.51 | N14: =SmtRes!AA18 -> 89 | O14: =SmtRes!DF18 -> 141.51 | P14: =SmtRes!AG18 -> 0 | R14: =ROUND(I14*P14, 2) -> 0 | S14: =SmtRes!AC18 -> 0 | T14: =SmtRes!DH18 -> 0 | U14: 3 | Z14: =SmtRes!X18 -> -2058989610 | AA14: 1504361348 | AB14: 1504361348
A15: 20 | B15: 17 | C15: 2 | D15: 0 | E15: =SmtRes!AV17 -> 1 | F15: =SmtRes!I17 -> 91.17.04-042 | G15: =SmtRes!K17 -> Аппараты для газовой сварки и резки | H15: =SmtRes!O17 -> маш.-ч | I15: =SmtRes!Y17*Source!I27 -> 0.44 | J15: =SmtRes!AO17 -> 0 | K15: =SmtRes!AF17 -> 4.35 | M15: =ROUND(I15*K15, 2) -> 1.91 | N15: =SmtRes!AB17 -> 5.35 | O15: =SmtRes!DG17 -> 2.35 | P15: =SmtRes!AG17 -> 0 | R15: =ROUND(I15*P15, 2) -> 0 | S15: =SmtRes!AC17 -> 0 | T15: =SmtRes!DH17 -> 0 | U15: 2 | Z15: =SmtRes!X17 -> -880363394 | AA15: 1145571634 | AB15: -51089833
A16: 20 | B16: 16 | C16: 2 | D16: 0 | E16: =SmtRes!AV16 -> 1 | F16: =SmtRes!I16 -> 91.10.05-009 | G16: =SmtRes!K16 -> Трубоукладчики, номинальная грузоподъемность 35 т | H16: =SmtRes!O16 -> маш.-ч | I16: =SmtRes!Y16*Source!I27 -> 0.75 | J16: =SmtRes!AO16 -> 0 | K16: =SmtRes!AF16 -> 4403.56 | M16: =ROUND(I16*K16, 2) -> 3302.67 | N16: =SmtRes!AB16 -> 4931.99 | O16: =SmtRes!DG16 -> 3698.99 | P16: =SmtRes!AG16 -> 707.35 | R16: =ROUND(I16*P16, 2) -> 530.51 | S16: =SmtRes!AC16 -> 707.35 | T16: =SmtRes!DH16 -> 530.51 | U16: 2 | Z16: =SmtRes!X16 -> -1505731505 | AA16: 1516374314 | AB16: 929036850
A17: 20 | B17: 14 | C17: 1 | D17: 0 | E17: =SmtRes!AV14 -> 1 | F17: =SmtRes!I14 -> 1-100-47 | G17: =SmtRes!K14 -> Средний разряд работы 4,7 | H17: =SmtRes!O14 -> чел.-ч. | I17: =SmtRes!Y14*Source!I27 -> 1.59 | J17: =SmtRes!AO14 -> 0 | K17: =SmtRes!AH14 -> 478.03 | M17: =ROUND(I17*K17, 2) -> 760.07 | N17: =SmtRes!AD14 -> 478.03 | O17: =SmtRes!DI14 -> 760.07 | P17: =SmtRes!AG14 -> 0 | R17: =ROUND(I17*P17, 2) -> 0 | S17: =SmtRes!AC14 -> 0 | T17: =SmtRes!DH14 -> 0 | U17: 1 | Z17: =SmtRes!X14 -> 1521243167 | AA17: -1434346882 | AB17: -1434346882
A18: 20 | B18: 29 | C18: 3 | D18: 0 | E18: =SmtRes!AV29 -> 0 | F18: =SmtRes!I29 -> 04.3.01.09-0014 | G18: =SmtRes!K29 -> Раствор готовый кладочный, цементный, М100 | H18: =SmtRes!O29 -> м3 | I18: =SmtRes!Y29*Source!I28 -> 0.066 | J18: =SmtRes!AO29 -> 0 | K18: =SmtRes!AE29 -> 5769.31 | M18: =ROUND(I18*K18, 2) -> 380.77 | N18: =SmtRes!AA29 -> 5769.31 | O18: =SmtRes!DF29 -> 380.77 | P18: =SmtRes!AG29 -> 0 | R18: =ROUND(I18*P18, 2) -> 0 | S18: =SmtRes!AC29 -> 0 | T18: =SmtRes!DH29 -> 0 | U18: 3 | Z18: =SmtRes!X29 -> -2089581116 | AA18: 1543752563 | AB18: 1543752563
A19: 20 | B19: 28 | C19: 3 | D19: 0 | E19: =SmtRes!AV28 -> 0 | F19: =SmtRes!I28 -> 03.2.01.01-0001 | G19: =SmtRes!K28 -> Портландцемент бездобавочный общестроительный ЦЕМ 0 32,5Н | H19: =SmtRes!O28 -> т | I19: =SmtRes!Y28*Source!I28 -> 0.02656 | J19: =SmtRes!AO28 -> 0 | K19: =SmtRes!AE28 -> 4800.85 | M19: =ROUND(I19*K19, 2) -> 127.51 | N19: =SmtRes!AA28 -> 9073.61 | O19: =SmtRes!DF28 -> 241 | P19: =SmtRes!AG28 -> 0 | R19: =ROUND(I19*P19, 2) -> 0 | S19: =SmtRes!AC28 -> 0 | T19: =SmtRes!DH28 -> 0 | U19: 3 | Z19: =SmtRes!X28 -> 269049756 | AA19: 580301888 | AB19: -1771451004
A20: 20 | B20: 27 | C20: 3 | D20: 0 | E20: =SmtRes!AV27 -> 0 | F20: =SmtRes!I27 -> 01.7.07.29-0322 | G20: =SmtRes!K27 -> Канат пропитанный (каболка) из льняного и джутового волокна, канализационный и водопроводный, отжатый, диаметр 10-100 мм | H20: =SmtRes!O27 -> кг | I20: =SmtRes!Y27*Source!I28 -> 8.4 | J20: =SmtRes!AO27 -> 0 | K20: =SmtRes!AE27 -> 152.78 | M20: =ROUND(I20*K20, 2) -> 1283.35 | N20: =SmtRes!AA27 -> 207.78 | O20: =SmtRes!DF27 -> 1745.35 | P20: =SmtRes!AG27 -> 0 | R20: =ROUND(I20*P20, 2) -> 0 | S20: =SmtRes!AC27 -> 0 | T20: =SmtRes!DH27 -> 0 | U20: 3 | Z20: =SmtRes!X27 -> 219322737 | AA20: 269364198 | AB20: 1772365322
A21: 20 | B21: 26 | C21: 3 | D21: 0 | E21: =SmtRes!AV26 -> 0 | F21: =SmtRes!I26 -> 01.7.03.01-0001 | G21: =SmtRes!K26 -> Вода | H21: =SmtRes!O26 -> м3 | I21: =SmtRes!Y26*Source!I28 -> 7.85 | J21: =SmtRes!AO26 -> 0 | K21: =SmtRes!AE26 -> 35.71 | M21: =ROUND(I21*K21, 2) -> 280.32 | N21: =SmtRes!AA26 -> 26.07 | O21: =SmtRes!DF26 -> 204.65 | P21: =SmtRes!AG26 -> 0 | R21: =ROUND(I21*P21, 2) -> 0 | S21: =SmtRes!AC26 -> 0 | T21: =SmtRes!DH26 -> 0 | U21: 3 | Z21: =SmtRes!X26 -> 1964556667 | AA21: 1781038258 | AB21: -471873250
A22: 20 | B22: 25 | C22: 3 | D22: 0 | E22: =SmtRes!AV25 -> 0 | F22: =SmtRes!I25 -> 01.1.02.10-1022 | G22: =SmtRes!K25 -> Хризотил (асбест хризотиловый), группа 6К, марки 6К-45, 6К-30, 6К-20, 6К-5 | H22: =SmtRes!O25 -> т | I22: =SmtRes!Y25*Source!I28 -> 0.0114 | J22: =SmtRes!AO25 -> 0 | K22: =SmtRes!AE25 -> 21588.35 | M22: =ROUND(I22*K22, 2) -> 246.11 | N22: =SmtRes!AA25 -> 25474.25 | O22: =SmtRes!DF25 -> 290.41 | P22: =SmtRes!AG25 -> 0 | R22: =ROUND(I22*P22, 2) -> 0 | S22: =SmtRes!AC25 -> 0 | T22: =SmtRes!DH25 -> 0 | U22: 3 | Z22: =SmtRes!X25 -> 192185020 | AA22: 728816804 | AB22: -973196742
A23: 20 | B23: 24 | C23: 2 | D23: 0 | E23: =SmtRes!AV24 -> 1 | F23: =SmtRes!I24 -> 91.14.02-001 | G23: =SmtRes!K24 -> Автомобили бортовые, грузоподъемность до 5 т | H23: =SmtRes!O24 -> маш.-ч | I23: =SmtRes!Y24*Source!I28 -> 0.048 | J23: =SmtRes!AO24 -> 0 | K23: =SmtRes!AF24 -> 652.84 | M23: =ROUND(I23*K23, 2) -> 31.34 | N23: =SmtRes!AB24 -> 652.84 | O23: =SmtRes!DG24 -> 31.34 | P23: =SmtRes!AG24 -> 432.81 | R23: =ROUND(I23*P23, 2) -> 20.77 | S23: =SmtRes!AC24 -> 432.81 | T23: =SmtRes!DH24 -> 20.77 | U23: 2 | Z23: =SmtRes!X24 -> -849950259 | AA23: 106755230 | AB23: 106755230
A24: 20 | B24: 23 | C24: 2 | D24: 0 | E24: =SmtRes!AV23 -> 1 | F24: =SmtRes!I23 -> 91.10.05-009 | G24: =SmtRes!K23 -> Трубоукладчики, номинальная грузоподъемность 35 т | H24: =SmtRes!O23 -> маш.-ч | I24: =SmtRes!Y23*Source!I28 -> 1.24 | J24: =SmtRes!AO23 -> 0 | K24: =SmtRes!AF23 -> 4403.56 | M24: =ROUND(I24*K24, 2) -> 5460.41 | N24: =SmtRes!AB23 -> 4931.99 | O24: =SmtRes!DG23 -> 6115.67 | P24: =SmtRes!AG23 -> 707.35 | R24: =ROUND(I24*P24, 2) -> 877.11 | S24: =SmtRes!AC23 -> 707.35 | T24: =SmtRes!DH23 -> 877.11 | U24: 2 | Z24: =SmtRes!X23 -> -1505731505 | AA24: 1516374314 | AB24: 929036850
A25: 20 | B25: 21 | C25: 1 | D25: 0 | E25: =SmtRes!AV21 -> 1 | F25: =SmtRes!I21 -> 1-100-40 | G25: =SmtRes!K21 -> Средний разряд работы 4,0 | H25: =SmtRes!O21 -> чел.-ч. | I25: =SmtRes!Y21*Source!I28 -> 18.76 | J25: =SmtRes!AO21 -> 0 | K25: =SmtRes!AH21 -> 432.81 | M25: =ROUND(I25*K25, 2) -> 8119.52 | N25: =SmtRes!AD21 -> 432.81 | O25: =SmtRes!DI21 -> 8119.52 | P25: =SmtRes!AG21 -> 0 | R25: =ROUND(I25*P25, 2) -> 0 | S25: =SmtRes!AC21 -> 0 | T25: =SmtRes!DH21 -> 0 | U25: 1 | Z25: =SmtRes!X21 -> 888410196 | AA25: 795807998 | AB25: 795807998
A26: 20 | B26: 32 | C26: 2 | D26: 0 | E26: =SmtRes!AV32 -> 1 | F26: =SmtRes!I32 -> 91.01.01-046 | G26: =SmtRes!K32 -> Бульдозеры, мощность 303 кВт (410 л.с.) | H26: =SmtRes!O32 -> маш.-ч | I26: =SmtRes!Y32*Source!I30 -> 0.09 | J26: =SmtRes!AO32 -> 0 | K26: =SmtRes!AF32 -> 5605.48 | M26: =ROUND(I26*K26, 2) -> 504.49 | N26: =SmtRes!AB32 -> 5605.48 | O26: =SmtRes!DG32 -> 504.49 | P26: =SmtRes!AG32 -> 707.35 | R26: =ROUND(I26*P26, 2) -> 63.66 | S26: =SmtRes!AC32 -> 707.35 | T26: =SmtRes!DH32 -> 63.66 | U26: 2 | Z26: =SmtRes!X32 -> 626856282 | AA26: -1281970117 | AB26: -1281970117
A27: =Source!A31 -> 18 | B27: 31 | C27: 2 | D27: =Source!BI31 -> 1 | E27: =Source!FS31 -> 1 | F27: =Source!F31 -> 91.01.05-104 | G27: =Source!G31 -> Экскаваторы одноковшовые дизельные на пневмоколесном ходу, объем ковша 0,4 м3 | H27: =Source!H31 -> маш.-ч | I27: =Source!I31 -> 0.09 | J27: 1 | K27: =Source!AD31 -> 1162.81 | M27: =ROUND(K27*I27, 2) -> 104.65 | N27: =Source!CQ31 -> 0 | O27: =ROUND(N27*I27, 2) -> 0 | P27: =Source!AE31 -> 497.4 | R27: =ROUND(P27*I27, 2) -> 44.77 | S27: =Source!AE31*IF(Source!BS31<> 0, Source!BS31, 1) -> 497.4 | T27: =ROUND(S27*I27, 2) -> 44.77 | U27: 2 | Z27: =Source!GF31 -> -598721075 | AA27: -1992513835 | AB27: -1937554257
A28: =Source!A32 -> 17 | B28: 32 | C28: 2 | D28: =Source!BI32 -> 1 | E28: =Source!FS32 -> 1 | F28: =Source!F32 -> 91.01.01-046 | G28: =Source!G32 -> Бульдозеры, мощность 303 кВт (410 л.с.) | H28: =Source!H32 -> маш.-ч | I28: =Source!I32 -> -0.09 | J28: 1 | K28: =Source!AD32 -> 5605.48 | M28: =ROUND(K28*I28, 2) -> -504.49 | N28: =Source!CQ32 -> 0 | O28: =ROUND(N28*I28, 2) -> 0 | P28: =Source!AE32 -> 707.35 | R28: =ROUND(P28*I28, 2) -> -63.66 | S28: =Source!AE32*IF(Source!BS32<> 0, Source!BS32, 1) -> 707.35 | T28: =ROUND(S28*I28, 2) -> -63.66 | U28: 2 | Z28: =Source!GF32 -> 626856282 | AA28: -1281970117 | AB28: 888318738
A29: 20 | B29: 44 | C29: 3 | D29: 0 | E29: =SmtRes!AV44 -> 0 | F29: =SmtRes!I44 -> 14.1.05.03-0011 | G29: =SmtRes!K44 -> Клей фенолополивинилацетальный, марка БФ-2Н | H29: =SmtRes!O44 -> т | I29: =SmtRes!Y44*Source!I33 -> 1.25e-05 | J29: =SmtRes!AO44 -> 0 | K29: =SmtRes!AE44 -> 442593.68 | M29: =ROUND(I29*K29, 2) -> 5.53 | N29: =SmtRes!AA44 -> 686020.2 | O29: =SmtRes!DF44 -> 8.58 | P29: =SmtRes!AG44 -> 0 | R29: =ROUND(I29*P29, 2) -> 0 | S29: =SmtRes!AC44 -> 0 | T29: =SmtRes!DH44 -> 0 | U29: 3 | Z29: =SmtRes!X44 -> 1435964893 | AA29: 236554803 | AB29: -910808008
A30: 20 | B30: 42 | C30: 3 | D30: 0 | E30: =SmtRes!AV42 -> 0 | F30: =SmtRes!I42 -> 01.7.20.08-0162 | G30: =SmtRes!K42 -> Ткань мешочная, ширина 950 мм, поверхностная плотность 190 г/м2 | H30: =SmtRes!O42 -> 10 м2 | I30: =SmtRes!Y42*Source!I33 -> 0.0001 | J30: =SmtRes!AO42 -> 0 | K30: =SmtRes!AE42 -> 592.04 | M30: =ROUND(I30*K30, 2) -> 0.06 | N30: =SmtRes!AA42 -> 953.18 | O30: =SmtRes!DF42 -> 0.1 | P30: =SmtRes!AG42 -> 0 | R30: =ROUND(I30*P30, 2) -> 0 | S30: =SmtRes!AC42 -> 0 | T30: =SmtRes!DH42 -> 0 | U30: 3 | Z30: =SmtRes!X42 -> -1756344661 | AA30: -1533044596 | AB30: -1094930439
A31: 20 | B31: 41 | C31: 3 | D31: 0 | E31: =SmtRes!AV41 -> 0 | F31: =SmtRes!I41 -> 01.7.20.08-0021 | G31: =SmtRes!K41 -> Брезент с огнеупорной пропиткой | H31: =SmtRes!O41 -> м2 | I31: =SmtRes!Y41*Source!I33 -> 0.0008 | J31: =SmtRes!AO41 -> 0 | K31: =SmtRes!AE41 -> 108.68 | M31: =ROUND(I31*K31, 2) -> 0.09 | N31: =SmtRes!AA41 -> 174.97 | O31: =SmtRes!DF41 -> 0.14 | P31: =SmtRes!AG41 -> 0 | R31: =ROUND(I31*P31, 2) -> 0 | S31: =SmtRes!AC41 -> 0 | T31: =SmtRes!DH41 -> 0 | U31: 3 | Z31: =SmtRes!X41 -> 2050518453 | AA31: -1943925511 | AB31: 1676897807
A32: 20 | B32: 40 | C32: 3 | D32: 0 | E32: =SmtRes!AV40 -> 0 | F32: =SmtRes!I40 -> 01.7.06.03-0002 | G32: =SmtRes!K40 -> Ленты антикоррозионные из ПВХ с липким слоем с одной стороны для изоляции трубопроводов, цвет черный, ширина 450 мм, толщина 0,4 мм | H32: =SmtRes!O40 -> м2 | I32: =SmtRes!Y40*Source!I33 -> 0.478 | J32: =SmtRes!AO40 -> 0 | K32: =SmtRes!AE40 -> 62.74 | M32: =ROUND(I32*K32, 2) -> 29.99 | N32: =SmtRes!AA40 -> 123.6 | O32: =SmtRes!DF40 -> 59.08 | P32: =SmtRes!AG40 -> 0 | R32: =ROUND(I32*P32, 2) -> 0 | S32: =SmtRes!AC40 -> 0 | T32: =SmtRes!DH40 -> 0 | U32: 3 | Z32: =SmtRes!X40 -> 1711398520 | AA32: 1396930422 | AB32: -1323178595
A33: 20 | B33: 39 | C33: 2 | D33: 0 | E33: =SmtRes!AV39 -> 1 | F33: =SmtRes!I39 -> 91.16.01-002 | G33: =SmtRes!K39 -> Электростанции передвижные, мощность 4 кВт | H33: =SmtRes!O39 -> маш.-ч | I33: =SmtRes!Y39*Source!I33 -> 0.00993 | J33: =SmtRes!AO39 -> 0 | K33: =SmtRes!AF39 -> 130.39 | M33: =ROUND(I33*K33, 2) -> 1.29 | N33: =SmtRes!AB39 -> 130.39 | O33: =SmtRes!DG39 -> 1.29 | P33: =SmtRes!AG39 -> 432.81 | R33: =ROUND(I33*P33, 2) -> 4.3 | S33: =SmtRes!AC39 -> 432.81 | T33: =SmtRes!DH39 -> 4.3 | U33: 2 | Z33: =SmtRes!X39 -> -245244677 | AA33: 1669558037 | AB33: 1669558037
A34: 20 | B34: 38 | C34: 2 | D34: 0 | E34: =SmtRes!AV38 -> 1 | F34: =SmtRes!I38 -> 91.14.02-001 | G34: =SmtRes!K38 -> Автомобили бортовые, грузоподъемность до 5 т | H34: =SmtRes!O38 -> маш.-ч | I34: =SmtRes!Y38*Source!I33 -> 0.00106 | J34: =SmtRes!AO38 -> 0 | K34: =SmtRes!AF38 -> 652.84 | M34: =ROUND(I34*K34, 2) -> 0.69 | N34: =SmtRes!AB38 -> 652.84 | O34: =SmtRes!DG38 -> 0.69 | P34: =SmtRes!AG38 -> 432.81 | R34: =ROUND(I34*P34, 2) -> 0.46 | S34: =SmtRes!AC38 -> 432.81 | T34: =SmtRes!DH38 -> 0.46 | U34: 2 | Z34: =SmtRes!X38 -> -849950259 | AA34: 106755230 | AB34: 106755230
A35: 20 | B35: 37 | C35: 2 | D35: 0 | E35: =SmtRes!AV37 -> 1 | F35: =SmtRes!I37 -> 91.10.05-009 | G35: =SmtRes!K37 -> Трубоукладчики, номинальная грузоподъемность 35 т | H35: =SmtRes!O37 -> маш.-ч | I35: =SmtRes!Y37*Source!I33 -> 0.01218 | J35: =SmtRes!AO37 -> 0 | K35: =SmtRes!AF37 -> 4403.56 | M35: =ROUND(I35*K35, 2) -> 53.64 | N35: =SmtRes!AB37 -> 4931.99 | O35: =SmtRes!DG37 -> 60.07 | P35: =SmtRes!AG37 -> 707.35 | R35: =ROUND(I35*P35, 2) -> 8.62 | S35: =SmtRes!AC37 -> 707.35 | T35: =SmtRes!DH37 -> 8.62 | U35: 2 | Z35: =SmtRes!X37 -> -1505731505 | AA35: 1516374314 | AB35: 929036850
A36: 20 | B36: 35 | C36: 1 | D36: 0 | E36: =SmtRes!AV35 -> 1 | F36: =SmtRes!I35 -> 1-100-42 | G36: =SmtRes!K35 -> Средний разряд работы 4,2 | H36: =SmtRes!O35 -> чел.-ч. | I36: =SmtRes!Y35*Source!I33 -> 0.14 | J36: =SmtRes!AO35 -> 0 | K36: =SmtRes!AH35 -> 445.73 | M36: =ROUND(I36*K36, 2) -> 62.4 | N36: =SmtRes!AD35 -> 445.73 | O36: =SmtRes!DI35 -> 62.4 | P36: =SmtRes!AG35 -> 0 | R36: =ROUND(I36*P36, 2) -> 0 | S36: =SmtRes!AC35 -> 0 | T36: =SmtRes!DH35 -> 0 | U36: 1 | Z36: =SmtRes!X35 -> 1522950421 | AA36: 2015934539 | AB36: 2015934539
A37: =Source!A34 -> 18 | B37: 34 | C37: 3 | D37: =Source!BI34 -> 1 | E37: =Source!FS34 -> 0 | F37: =Source!F34 -> 14.4.01.15-1002 | G37: =Source!G34 -> Грунтовка полимерная для повышения адгезии битумно-полимерных мастик и герметиков при герметизации деформационных швов асфальтобетонных и цементобетонных покрытий | H37: =Source!H34 -> т | I37: =Source!I34 -> 0.001 | J37: 1 | K37: =Source!AC34 -> 411791.94 | M37: =ROUND(K37*I37, 2) -> 411.79 | N37: =Source!CQ34 -> 522975.76 | O37: =ROUND(N37*I37, 2) -> 522.98 | P37: =Source!AE34 -> 0 | R37: =ROUND(P37*I37, 2) -> 0 | S37: =Source!AE34*IF(Source!BS34<> 0, Source!BS34, 1) -> 0 | T37: =ROUND(S37*I37, 2) -> 0 | U37: 3 | Z37: =Source!GF34 -> 7353553 | AA37: -248603019 | AB37: 602379180
A38: =Source!A35 -> 18 | B38: 35 | C38: 3 | D38: =Source!BI35 -> 1 | E38: =Source!FS35 -> 0 | F38: =Source!F35 -> 12.1.02.15-0041 | G38: =Source!G35 -> Материал рулонный гидроизоляционный изол, резино-битумный, без полимерных добавок | H38: =Source!H35 -> м2 | I38: =Source!I35 -> 0.85 | J38: 1 | K38: =Source!AC35 -> 126.14 | M38: =ROUND(K38*I38, 2) -> 107.22 | N38: =Source!CQ35 -> 172.81 | O38: =ROUND(N38*I38, 2) -> 146.89 | P38: =Source!AE35 -> 0 | R38: =ROUND(P38*I38, 2) -> 0 | S38: =Source!AE35*IF(Source!BS35<> 0, Source!BS35, 1) -> 0 | T38: =ROUND(S38*I38, 2) -> 0 | U38: 3 | Z38: =Source!GF35 -> -848550540 | AA38: 2142095169 | AB38: -1719168864
A39: 20 | B39: 49 | C39: 2 | D39: 0 | E39: =SmtRes!AV49 -> 1 | F39: =SmtRes!I49 -> 91.18.01-007 | G39: =SmtRes!K49 -> Компрессоры винтовые передвижные с двигателем внутреннего сгорания, давление до 0,7 МПа (7 атм), производительность до 5,4 м3/мин | H39: =SmtRes!O49 -> маш.-ч | I39: =SmtRes!Y49*Source!I36 -> 1.179 | J39: =SmtRes!AO49 -> 0 | K39: =SmtRes!AF49 -> 411.37 | M39: =ROUND(I39*K39, 2) -> 485.01 | N39: =SmtRes!AB49 -> 411.37 | O39: =SmtRes!DG49 -> 485.01 | P39: =SmtRes!AG49 -> 432.81 | R39: =ROUND(I39*P39, 2) -> 510.28 | S39: =SmtRes!AC49 -> 432.81 | T39: =SmtRes!DH49 -> 510.28 | U39: 2 | Z39: =SmtRes!X49 -> 1282244495 | AA39: -919029990 | AB39: -919029990
A40: 20 | B40: 48 | C40: 2 | D40: 0 | E40: =SmtRes!AV48 -> 1 | F40: =SmtRes!I48 -> 91.08.09-023 | G40: =SmtRes!K48 -> Трамбовки пневматические при работе от передвижных компрессорных установок | H40: =SmtRes!O48 -> маш.-ч | I40: =SmtRes!Y48*Source!I36 -> 4.725 | J40: =SmtRes!AO48 -> 0 | K40: =SmtRes!AF48 -> 2.41 | M40: =ROUND(I40*K40, 2) -> 11.39 | N40: =SmtRes!AB48 -> 2.7 | O40: =SmtRes!DG48 -> 12.76 | P40: =SmtRes!AG48 -> 0 | R40: =ROUND(I40*P40, 2) -> 0 | S40: =SmtRes!AC48 -> 0 | T40: =SmtRes!DH48 -> 0 | U40: 2 | Z40: =SmtRes!X48 -> 4789874 | AA40: 201212123 | AB40: -1275274398
A41: 20 | B41: 46 | C41: 1 | D41: 0 | E41: =SmtRes!AV46 -> 1 | F41: =SmtRes!I46 -> 1-100-30 | G41: =SmtRes!K46 -> Средний разряд работы 3,0 | H41: =SmtRes!O46 -> чел.-ч. | I41: =SmtRes!Y46*Source!I36 -> 5.6385 | J41: =SmtRes!AO46 -> 0 | K41: =SmtRes!AH46 -> 384.36 | M41: =ROUND(I41*K41, 2) -> 2167.21 | N41: =SmtRes!AD46 -> 384.36 | O41: =SmtRes!DI46 -> 2167.21 | P41: =SmtRes!AG46 -> 0 | R41: =ROUND(I41*P41, 2) -> 0 | S41: =SmtRes!AC46 -> 0 | T41: =SmtRes!DH46 -> 0 | U41: 1 | Z41: =SmtRes!X46 -> -1833565283 | AA41: -1658114278 | AB41: -1658114278
A42: 20 | B42: 55 | C42: 3 | D42: 0 | E42: =SmtRes!AV55 -> 0 | F42: =SmtRes!I55 -> 02.3.01.02-1104 | G42: =SmtRes!K55 -> Песок природный для строительных работ I класс, средний | H42: =SmtRes!O55 -> м3 | I42: =SmtRes!Y55*Source!I37 -> 57.33 | J42: =SmtRes!AO55 -> 0 | K42: =SmtRes!AE55 -> 757.36 | M42: =ROUND(I42*K42, 2) -> 43419.45 | N42: =SmtRes!AA55 -> 757.36 | O42: =SmtRes!DF55 -> 43419.45 | P42: =SmtRes!AG55 -> 0 | R42: =ROUND(I42*P42, 2) -> 0 | S42: =SmtRes!AC55 -> 0 | T42: =SmtRes!DH55 -> 0 | U42: 3 | Z42: =SmtRes!X55 -> 318135557 | AA42: -1879287007 | AB42: -1879287007
A43: 20 | B43: 54 | C43: 2 | D43: 0 | E43: =SmtRes!AV54 -> 1 | F43: =SmtRes!I54 -> 91.08.09-001 | G43: =SmtRes!K54 -> Плиты вибрационные с двигателем внутреннего сгорания, мощность до 6 кВт (8 л.с.) | H43: =SmtRes!O54 -> маш.-ч | I43: =SmtRes!Y54*Source!I37 -> 4.725 | J43: =SmtRes!AO54 -> 0 | K43: =SmtRes!AF54 -> 53.19 | M43: =ROUND(I43*K43, 2) -> 251.32 | N43: =SmtRes!AB54 -> 53.19 | O43: =SmtRes!DG54 -> 251.32 | P43: =SmtRes!AG54 -> 0 | R43: =ROUND(I43*P43, 2) -> 0 | S43: =SmtRes!AC54 -> 0 | T43: =SmtRes!DH54 -> 0 | U43: 2 | Z43: =SmtRes!X54 -> -1355227874 | AA43: 98175846 | AB43: 98175846
A44: 20 | B44: 52 | C44: 2 | D44: 0 | E44: =SmtRes!AV52 -> 1 | F44: =SmtRes!I52 -> 91.01.05-089 | G44: =SmtRes!K52 -> Экскаваторы одноковшовые дизельные на гусеничном ходу, объем ковша 1,25 м3 | H44: =SmtRes!O52 -> маш.-ч | I44: =SmtRes!Y52*Source!I37 -> 3.42 | J44: =SmtRes!AO52 -> 0 | K44: =SmtRes!AF52 -> 1524.72 | M44: =ROUND(I44*K44, 2) -> 5214.54 | N44: =SmtRes!AB52 -> 2012.63 | O44: =SmtRes!DG52 -> 6883.19 | P44: =SmtRes!AG52 -> 620.14 | R44: =ROUND(I44*P44, 2) -> 2120.88 | S44: =SmtRes!AC52 -> 620.14 | T44: =SmtRes!DH52 -> 2120.88 | U44: 2 | Z44: =SmtRes!X52 -> -972071566 | AA44: -1477793774 | AB44: -904394777
A45: 20 | B45: 50 | C45: 1 | D45: 0 | E45: =SmtRes!AV50 -> 1 | F45: =SmtRes!I50 -> 1-100-30 | G45: =SmtRes!K50 -> Средний разряд работы 3,0 | H45: =SmtRes!O50 -> чел.-ч. | I45: =SmtRes!Y50*Source!I37 -> 8.37 | J45: =SmtRes!AO50 -> 0 | K45: =SmtRes!AH50 -> 384.36 | M45: =ROUND(I45*K45, 2) -> 3217.09 | N45: =SmtRes!AD50 -> 384.36 | O45: =SmtRes!DI50 -> 3217.09 | P45: =SmtRes!AG50 -> 0 | R45: =ROUND(I45*P45, 2) -> 0 | S45: =SmtRes!AC50 -> 0 | T45: =SmtRes!DH50 -> 0 | U45: 1 | Z45: =SmtRes!X50 -> -1833565283 | AA45: -1658114278 | AB45: -1658114278
A46: =Source!A38 -> 18 | B46: 38 | C46: 2 | D46: =Source!BI38 -> 1 | E46: =Source!FS38 -> 1 | F46: =Source!F38 -> 91.01.05-104 | G46: =Source!G38 -> Экскаваторы одноковшовые дизельные на пневмоколесном ходу, объем ковша 0,4 м3 | H46: =Source!H38 -> маш.-ч | I46: =Source!I38 -> 3.42 | J46: 1 | K46: =Source!AD38 -> 1162.81 | M46: =ROUND(K46*I46, 2) -> 3976.81 | N46: =Source!CQ38 -> 0 | O46: =ROUND(N46*I46, 2) -> 0 | P46: =Source!AE38 -> 497.4 | R46: =ROUND(P46*I46, 2) -> 1701.11 | S46: =Source!AE38*IF(Source!BS38<> 0, Source!BS38, 1) -> 497.4 | T46: =ROUND(S46*I46, 2) -> 1701.11 | U46: 2 | Z46: =Source!GF38 -> -598721075 | AA46: -1992513835 | AB46: -1937554257
A47: =Source!A39 -> 17 | B47: 39 | C47: 2 | D47: =Source!BI39 -> 1 | E47: =Source!FS39 -> 1 | F47: =Source!F39 -> 91.01.05-089 | G47: =Source!G39 -> Экскаваторы одноковшовые дизельные на гусеничном ходу, объем ковша 1,25 м3 | H47: =Source!H39 -> маш.-ч | I47: =Source!I39 -> -3.42 | J47: 1 | K47: =Source!AD39 -> 1524.72 | M47: =ROUND(K47*I47, 2) -> -5214.54 | N47: =Source!CQ39 -> 0 | O47: =ROUND(N47*I47, 2) -> 0 | P47: =Source!AE39 -> 620.14 | R47: =ROUND(P47*I47, 2) -> -2120.88 | S47: =Source!AE39*IF(Source!BS39<> 0, Source!BS39, 1) -> 620.14 | T47: =ROUND(S47*I47, 2) -> -2120.88 | U47: 2 | Z47: =Source!GF39 -> -972071566 | AA47: -1477793774 | AB47: 855284677
A48: =Source!A40 -> 17 | B48: 40 | C48: 3 | D48: =Source!BI40 -> 1 | E48: =Source!FS40 -> 0 | F48: =Source!F40 -> 02.3.01.02-1104 | G48: =Source!G40 -> Песок природный для строительных работ I класс, средний | H48: =Source!H40 -> м3 | I48: =Source!I40 -> -57.33 | J48: 1 | K48: =ROUND((Source!GE40),6) -> 573.7 | M48: =ROUND(K48*I48, 2) -> -32890.22 | N48: =Source!CQ40 -> 757.36 | O48: =ROUND(N48*I48, 2) -> -43419.45 | P48: =Source!AE40 -> 0 | R48: =ROUND(P48*I48, 2) -> 0 | S48: =Source!AE40*IF(Source!BS40<> 0, Source!BS40, 1) -> 0 | T48: =ROUND(S48*I48, 2) -> 0 | U48: 3 | Z48: =Source!GF40 -> 318135557 | AA48: 1174559202 | AB48: -1879287007
A49: 999

Sheet Смета по ФСНБ 421+557прРИМ
A1: =Source!B1 -> Smeta.RU (495) 974-1589
A2: Наименование программного продукта | F2: Программа для ЭВМ «Программа: «Smeta.RU» версия 12»
A4: Наименование редакции сметных нормативов | F4: =IF(Source!CQ12 <> "", Source!CQ12, "") -> Приказ Минстроя России от 30.12.2021 г. № 1046/пр; Приказ Минстроя России от 04.08.2020 г. № 421/пр; Приказ Минстроя России от 21.12.2020 г. № 812/пр; Приказ Минстроя России от 11.12.2020 г. № 774/пр | CO4: =IF(Source!CQ12 <> "", Source!CQ12, "") -> Приказ Минстроя России от 30.12.2021 г. № 1046/пр; Приказ Минстроя России от 04.08.2020 г. № 421/пр; Приказ Минстроя России от 21.12.2020 г. № 812/пр; Приказ Минстроя России от 11.12.2020 г. № 774/пр
A6: Реквизиты приказа Минстроя России об утверждении дополнений и изменений к сметным нормативам | F6: =IF(Source!CV12 <> "", Source!CV12, "") -> Приказ Минстроя России от 18.05.2022 г. № 378/пр; Приказ Минстроя России от 26.08.2022 г. № 703/пр; Приказ Минстроя России от 26.10.2022 г. № 905/пр; Приказ Минстроя России от 27.12.2022 г. № 1133/пр; Приказ Минстроя России от 10.02.2023 г. № 84/пр; Приказ Минстроя России от 11.05.2023 г. № 335/пр; Приказ Минстроя России от 02.08.2023 г. № 551/пр; Приказ Минстроя России от 14.11.2023 г. № 817/пр; Приказ Минстроя России от 16.02.2024 г. № 102/пр; Приказ Минстроя России от 13.05.2024 г. № 323/пр; Приказ Минстроя России от 09.08.2024 г. № 524/пр; Приказ Минстроя России от 07.11.2024 г. № 747/пр; Приказ Минстроя России от 07.02.2025 г. № 69/пр; Приказ Минстроя России от 19.05.2025 г. № 299/пр; Приказ Минстроя России от 14.08.2025 г. № 490/пр; Приказ Минстроя России от 12.11.2025 г. № 696/пр; Приказ Минстроя России от 17.02.2026 г. № 91/пр; Приказ Минстроя России от 07.07.2022 г. № 557/пр; Приказ Минстроя России от 30.01.2024 г. № 55/пр; Приказ Минстроя России от 23.01.2025 г. № 30/пр; Приказ Минстроя России от 02.09.2021 г. № 636/пр; Приказ Минстроя России от 26.07.2022 г. № 611/пр; Приказ Минстроя России от 22.04.2022 г. № 317/пр | CO6: =IF(Source!CV12 <> "", Source!CV12, "") -> Приказ Минстроя России от 18.05.2022 г. № 378/пр; Приказ Минстроя России от 26.08.2022 г. № 703/пр; Приказ Минстроя России от 26.10.2022 г. № 905/пр; Приказ Минстроя России от 27.12.2022 г. № 1133/пр; Приказ Минстроя России от 10.02.2023 г. № 84/пр; Приказ Минстроя России от 11.05.2023 г. № 335/пр; Приказ Минстроя России от 02.08.2023 г. № 551/пр; Приказ Минстроя России от 14.11.2023 г. № 817/пр; Приказ Минстроя России от 16.02.2024 г. № 102/пр; Приказ Минстроя России от 13.05.2024 г. № 323/пр; Приказ Минстроя России от 09.08.2024 г. № 524/пр; Приказ Минстроя России от 07.11.2024 г. № 747/пр; Приказ Минстроя России от 07.02.2025 г. № 69/пр; Приказ Минстроя России от 19.05.2025 г. № 299/пр; Приказ Минстроя России от 14.08.2025 г. № 490/пр; Приказ Минстроя России от 12.11.2025 г. № 696/пр; Приказ Минстроя России от 17.02.2026 г. № 91/пр; Приказ Минстроя России от 07.07.2022 г. № 557/пр; Приказ Минстроя России от 30.01.2024 г. № 55/пр; Приказ Минстроя России от 23.01.2025 г. № 30/пр; Приказ Минстроя России от 02.09.2021 г. № 636/пр; Приказ Минстроя России от 26.07.2022 г. № 611/пр; Приказ Минстроя России от 22.04.2022 г. № 317/пр
A8: Реквизиты письма Минстроя России об индексах изменения сметной стоимости строительства, включаемые в федеральный реестр сметных нормативов и размещаемые в федеральной государственной информационной системе ценообразования в строительстве, подготовленного в соответствии с пунктом 85 Методики расчета индексов изменения сметной стоимости строительства, утвержденной приказом Министерства строительства и жилищно-коммунального хозяйства Российской Федерации от 5 июня 2019 г. N 326/пр | F8: Письмо Минстроя России от 25.02.2026 № 9859-ИФ/09
A10: Реквизиты нормативного правового акта об утверждении оплаты труда, утверждаемый в соответствии с пунктом 22(1) Правилами мониторинга цен, утвержденными постановлением Правительства Российской Федерации от 23 декабря 2016 г. N 1452 | F10: Постановление Правительства Тверской области от 25.04.2025 г. № 229-пп
A12: Обоснование принятых текущих цен на строительные ресурсы | F12: ФГИС ЦС, конъюнктурный анализ
A14: Наименование субъекта Российской Федерации | F14: =IF(Source!CZ12 <> "", Source!CZ12, "")
A16: Наименование зоны субъекта Российской Федерации | F16: =IF(Source!DA12 <> "", Source!DA12, "")
A19: ремонт трубы
A20: (наименование стройки)
A22: =IF(Source!G12<>"Новый объект", Source!G12, "") -> ремонт трубы
A23: (наименование объекта капитального строительства)
A25: =CONCATENATE( "ЛОКАЛЬНАЯ СМЕТА № ", Source!L20, " ",Source!CM20) -> ЛОКАЛЬНАЯ СМЕТА № Новая локальная смета
A27: =IF(Source!G20<>"Новая локальная смета", Source!G20, "") -> ремонт трубы
A28: (наименование работ и затрат)
A31: Составлен | C31: Ресурсно-индексным | D31: методом
A33: Основание
C34: (проектная и (или) иная техническая документация)
A36: Составлен(а) в текущем уровне цен на I квартал 2026 года
A38: Сметная стоимость | C38: =C41+C42+C43+C44 -> 110.67 | E38: тыс. руб.
G39: Средства на оплату труда рабочих | K39: =ROUND(SUM(AR52:AR316)/1000, 2) -> 20.92 | L39: тыс. руб.
B40: в том числе: | G40: Средства на оплату труда машинистов | K40: =ROUND(SUM(AT52:AT316)/1000, 2) -> 7.26 | L40: тыс. руб.
B41: строительных работ | C41: =ROUND((Source!F59)/1000, 2) -> 110.67 | E41: тыс. руб. | G41: Нормативные затраты труда рабочих | K41: =Source!F64 -> 49.772 | L41: чел.-ч.
B42: монтажных работ | C42: =ROUND((Source!F60)/1000, 2) -> 0 | E42: тыс. руб. | G42: Нормативные затраты труда машинистов | K42: =Source!F65 -> 12.61312 | L42: чел.-ч.
B43: оборудования | C43: =ROUND((Source!F51)/1000, 2) -> 0 | E43: тыс. руб.
B44: прочих затрат | C44: =ROUND((Source!F61)/1000, 2) -> 0 | E44: тыс. руб.
A46: № п/п | B46: Обоснование | C46: Наименование работ и затрат | D46: Единица измерения | E46: Количество | H46: Сметная стоимость, руб.
E50: на единицу измерения | F50: коэффициенты | G50: всего с учетом коэффициентов | H50: на единицу измерения в базисном уровне цен | I50: индекс | J50: на единицу измерения в текущем уровне цен | K50: коэффициенты | L50: всего в текущем уровне цен
A51: 1 | B51: 2 | C51: 3 | D51: 4 | E51: 5 | F51: 6 | G51: 7 | H51: 8 | I51: 9 | J51: 10 | K51: 11 | L51: 12
A52: 1 | B52: ГЭСН 01-01-010-38 | C52: =Source!G24 -> Разработка грунта в отвал экскаваторами, вместимость ковша 0,4 (0,3-0,45) м3, группа грунтов: 2 | D52: =Source!H24 -> 1000 м3 | E52: =Source!K24 -> 0.045 | G52: =Source!I24 -> 0.045
C53: ="Объем: "&Source!I24&"=45/"&"1000" -> Объем: 0,045=45/1000
B54: 1 | C54: ОТ (ЗТ) | D54: чел.-ч. | G54: =Source!U24 -> 0.2655 | L54: =SUM(L55:L55)-SUMIF(CE55:CE55, 1, L55:L55) -> 93.47
B55: 1-100-20 | C55: Средний разряд работы 2,0 | D55: чел.-ч. | E55: 5.9 | G55: =SmtRes!CX1 -> 0.2655 | J55: =SmtRes!CZ1 -> 352.06 | L55: =SmtRes!DI1 -> 93.47
B56: 2 | C56: ЭМ | L56: =SUM(L57:L59)-SUMIF(CE57:CE59, 1, L57:L59) -> 1654.35
C57: ОТм(ЗТм) | D57: чел.-ч. | G57: =Source!V24 -> 1.32255 | L57: =SUMIF(CE58:CE59, 1, L58:L59) -> 657.84 | CE57: 1
B58: 91.01.05-084 | C58: Экскаваторы одноковшовые дизельные на гусеничном ходу, объем ковша 0,4 м3 | D58: маш.-ч | E58: 29.39 | G58: =SmtRes!CX3 -> 1.32255 | H58: =SmtRes!CZ3 -> 947.64 | I58: =SmtRes!AJ3 -> 1.32 | J58: =ROUND(H58*I58, 2) -> 1250.88 | L58: =SmtRes!DG3 -> 1654.35
B59: 4-100-050 | C59: ОТм(ЗТм) Средний разряд машинистов 5 | D59: чел.-ч. | E59: =SmtRes!DO3*SmtRes!AT3 -> 29.39 | G59: =ROUND(E59*G52, 7) -> 1.32255 | J59: =ROUND(SmtRes!AG3/SmtRes!DO3, 2) -> 497.4 | L59: =SmtRes!DH3 -> 657.84 | CE59: 1
C60: Итого прямые затраты | L60: =L54+L56+L57 -> 2405.66
C61: ФОТ | L61: =SUM(AR52:AR64)+SUM(AS52:AS64)+SUM(AT52:AT64)+SUM(AU52:AU64)+SUM(AV52:AV64) -> 751.31
B62: Пр/812-001.1-1 | C62: НР Земляные работы, выполняемые: механизированным способом | D62: % | E62: =Source!BZ24 -> 92 | G62: =Source!AT24 -> 92 | L62: =SUM(AZ52:AZ64) -> 691.21
B63: Пр/774-001.1 | C63: СП Земляные работы, выполняемые: механизированным способом | D63: % | E63: =Source!CA24 -> 46 | G63: =Source!AU24 -> 46 | L63: =SUM(BA52:BA64) -> 345.6
C64: Всего по позиции | I64: =IF(E52<>0,K64/E52, 0) -> 76499.333 | K64: =L54+L56+L62+L63+L57 -> 3442.47 | AD64: =ROUND((Source!AT24/100)*((ROUND(SUMIF(SmtRes!AQ1:'SmtRes'!AQ3,"=1",SmtRes!AD1:'SmtRes'!AD3)*Source!I24, 2)+ROUND(SUMIF(SmtRes!AQ1:'SmtRes'!AQ3,"=1",SmtRes!AC1:'SmtRes'!AC3)*Source!I24, 2))), 2) -> 35.16 | AE64: =ROUND((Source!AU24/100)*((ROUND(SUMIF(SmtRes!AQ1:'SmtRes'!AQ3,"=1",SmtRes!AD1:'SmtRes'!AD3)*Source!I24, 2)+ROUND(SUMIF(SmtRes!AQ1:'SmtRes'!AQ3,"=1",SmtRes!AC1:'SmtRes'!AC3)*Source!I24, 2))), 2) -> 17.58 | AN64: =L54+L56+L62+L63+L57 -> 3442.47 | AO64: =L56 -> 1654.35 | AQ64: = | AR64: =L54 -> 93.47 | AT64: =L57 -> 657.84 | AV64: = | AW64: =0 -> 0 | AZ64: =Source!X24 -> 691.21 | BA64: =Source!Y24 -> 345.6 | CD64: 1
A65: 2 | B65: ГЭСН 23-01-007-05 | C65: =Source!G25 -> Демонтаж - Укладка трубопроводов из железобетонных безнапорных раструбных труб диаметром: 1000 мм | D65: =Source!H25 -> 100 м | E65: =Source!K25 -> 0.1 | G65: =Source!I25 -> 0.1
B66: 571/пр_2022_п.83_т.2_стр.1_стб.3 | C66: Разборка и (или) демонтаж строительных конструкций, систем и сетей инженерно-технического обеспечения, в том числе их элементов: сборных бетонных и железобетонных строительных конструкций ЭМ *0,8; М *0; ЗТ *0,8; ЗТм *0,8 | CW66: Разборка и (или) демонтаж строительных конструкций, систем и сетей инженерно-технического обеспечения, в том числе их элементов: сборных бетонных и железобетонных строительных конструкций ЭМ *0,8; М *0; ЗТ *0,8; ЗТм *0,8
C67: ="Объем: "&Source!I25&"=10/"&"100" -> Объем: 0,1=10/100
B68: 1 | C68: ОТ (ЗТ) | D68: чел.-ч. | G68: =Source!U25 -> 15.008 | L68: =SUM(L69:L69)-SUMIF(CE69:CE69, 1, L69:L69) -> 6495.61
B69: 1-100-40 | C69: Средний разряд работы 4,0 | D69: чел.-ч. | E69: 187.6 | F69: =ROUND(0.8,7) -> 0.8 | G69: =SmtRes!CX4 -> 15.008 | J69: =SmtRes!CZ4 -> 432.81 | L69: =SmtRes!DI4 -> 6495.61
B70: 2 | C70: ЭМ | L70: =SUM(L71:L75)-SUMIF(CE71:CE75, 1, L71:L75) -> 4917.6
C71: ОТм(ЗТм) | D71: чел.-ч. | G71: =Source!V25 -> 1.0304 | L71: =SUMIF(CE72:CE75, 1, L72:L75) -> 718.31 | CE71: 1
B72: 91.10.05-009 | C72: Трубоукладчики, номинальная грузоподъемность 35 т | D72: маш.-ч | E72: 12.4 | F72: =ROUND(0.8,7) -> 0.8 | G72: =SmtRes!CX6 -> 0.992 | H72: =SmtRes!CZ6 -> 4403.56 | I72: =SmtRes!AJ6 -> 1.12 | J72: =ROUND(H72*I72, 2) -> 4931.99 | L72: =SmtRes!DG6 -> 4892.53
B73: 4-100-090 | C73: ОТм(ЗТм) Средний разряд машинистов 9 | D73: чел.-ч. | E73: =SmtRes!DO6*SmtRes!AT6 -> 12.4 | F73: =ROUND(0.8,7) -> 0.8 | G73: =ROUND(E73*F73*G65, 7) -> 0.992 | J73: =ROUND(SmtRes!AG6/SmtRes!DO6, 2) -> 707.35 | L73: =SmtRes!DH6 -> 701.69 | CE73: 1
B74: 91.14.02-001 | C74: Автомобили бортовые, грузоподъемность до 5 т | D74: маш.-ч | E74: 0.48 | F74: =ROUND(0.8,7) -> 0.8 | G74: =SmtRes!CX7 -> 0.0384 | J74: =SmtRes!CZ7 -> 652.84 | L74: =SmtRes!DG7 -> 25.07
B75: 4-100-040 | C75: ОТм(ЗТм) Средний разряд машинистов 4 | D75: чел.-ч. | E75: =SmtRes!DO7*SmtRes!AT7 -> 0.48 | F75: =ROUND(0.8,7) -> 0.8 | G75: =ROUND(E75*F75*G65, 7) -> 0.0384 | J75: =ROUND(SmtRes!AG7/SmtRes!DO7, 2) -> 432.81 | L75: =SmtRes!DH7 -> 16.62 | CE75: 1
B76: 4 | C76: М | L76: =SUM(L77:L81)-SUMIF(CE77:CE81, 1, L77:L81) -> 0
B77: 01.1.02.10-1022 | C77: Хризотил (асбест хризотиловый), группа 6К, марки 6К-45, 6К-30, 6К-20, 6К-5 | D77: т | E77: 0.114 | F77: =ROUND(0,7) -> 0 | G77: =SmtRes!CX8 -> 0 | H77: =SmtRes!CZ8 -> 21588.35 | I77: =SmtRes!AI8 -> 1.18 | J77: =ROUND(H77*I77, 2) -> 25474.25 | L77: =SmtRes!DF8 -> 0
B78: 01.7.03.01-0001 | C78: Вода | D78: м3 | E78: 78.5 | F78: =ROUND(0,7) -> 0 | G78: =SmtRes!CX9 -> 0 | H78: =SmtRes!CZ9 -> 35.71 | I78: =SmtRes!AI9 -> 0.73 | J78: =ROUND(H78*I78, 2) -> 26.07 | L78: =SmtRes!DF9 -> 0
B79: 01.7.07.29-0322 | C79: Канат пропитанный (каболка) из льняного и джутового волокна, канализационный и водопроводный, отжатый, диаметр 10-100 мм | D79: кг | E79: 84 | F79: =ROUND(0,7) -> 0 | G79: =SmtRes!CX10 -> 0 | H79: =SmtRes!CZ10 -> 152.78 | I79: =SmtRes!AI10 -> 1.36 | J79: =ROUND(H79*I79, 2) -> 207.78 | L79: =SmtRes!DF10 -> 0
B80: 03.2.01.01-0001 | C80: Портландцемент бездобавочный общестроительный ЦЕМ 0 32,5Н | D80: т | E80: 0.2656 | F80: =ROUND(0,7) -> 0 | G80: =SmtRes!CX11 -> 0 | H80: =SmtRes!CZ11 -> 4800.85 | I80: =SmtRes!AI11 -> 1.89 | J80: =ROUND(H80*I80, 2) -> 9073.61 | L80: =SmtRes!DF11 -> 0
B81: 04.3.01.09-0014 | C81: Раствор готовый кладочный, цементный, М100 | D81: м3 | E81: 0.66 | F81: =ROUND(0,7) -> 0 | G81: =SmtRes!CX12 -> 0 | J81: =SmtRes!CZ12 -> 5769.31 | L81: =SmtRes!DF12 -> 0
B82: =EtalonRes!I13 -> 05.1.02.08 | C82: =EtalonRes!K13 -> Трубы железобетонные безнапорные раструбные | D82: =EtalonRes!O13 -> м | E82: =EtalonRes!X13 -> 99.7 | F82: =ROUND(0,7) -> 0 | G82: =ROUND(EtalonRes!AG13*Source!I25, 7) -> 0
C83: Итого прямые затраты | L83: =L68+L70+L71+L76 -> 12131.52
C84: ФОТ | L84: =SUM(AR65:AR87)+SUM(AS65:AS87)+SUM(AT65:AT87)+SUM(AU65:AU87)+SUM(AV65:AV87) -> 7213.92
B85: Пр/812-018.0-1 | C85: НР Наружные сети водопровода, канализации, теплоснабжения, газопроводы | D85: % | E85: =Source!BZ25 -> 117 | G85: =Source!AT25 -> 117 | L85: =SUM(AZ65:AZ87) -> 8440.29
B86: Пр/774-018.0 | C86: СП Наружные сети водопровода, канализации, теплоснабжения, газопроводы | D86: % | E86: =Source!CA25 -> 74 | G86: =Source!AU25 -> 74 | L86: =SUM(BA65:BA87) -> 5338.3
C87: Всего по позиции | I87: =IF(E65<>0,K87/E65, 0) -> 259101.1 | K87: =L68+L70+L76+L85+L86+L71 -> 25910.11 | AD87: =ROUND((Source!AT25/100)*((ROUND(SUMIF(SmtRes!AQ4:'SmtRes'!AQ13,"=1",SmtRes!AD4:'SmtRes'!AD13)*Source!I25, 2)+ROUND(SUMIF(SmtRes!AQ4:'SmtRes'!AQ13,"=1",SmtRes!AC4:'SmtRes'!AC13)*Source!I25, 2))), 2) -> 184.04 | AE87: =ROUND((Source!AU25/100)*((ROUND(SUMIF(SmtRes!AQ4:'SmtRes'!AQ13,"=1",SmtRes!AD4:'SmtRes'!AD13)*Source!I25, 2)+ROUND(SUMIF(SmtRes!AQ4:'SmtRes'!AQ13,"=1",SmtRes!AC4:'SmtRes'!AC13)*Source!I25, 2))), 2) -> 116.4 | AN87: =L68+L70+L76+L85+L86+L71 -> 25910.11 | AO87: =L70 -> 4917.6 | AQ87: = | AR87: =L68 -> 6495.61 | AT87: =L71 -> 718.31 | AV87: = | AW87: =L76 -> 0 | AZ87: =Source!X25 -> 8440.29 | BA87: =Source!Y25 -> 5338.3 | CD87: 1
A88: 3 | B88: ГЭСН 25-02-085-05 | C88: =Source!G27 -> Резка на бровке траншеи демонтируемых труб условным диаметром: 1000 мм | D88: =Source!H27 -> РЕЗ | E88: =Source!K27 -> 1 | G88: =Source!I27 -> 1
B89: 1 | C89: ОТ (ЗТ) | D89: чел.-ч. | G89: =Source!U27 -> 1.59 | L89: =SUM(L90:L90)-SUMIF(CE90:CE90, 1, L90:L90) -> 760.07
B90: 1-100-47 | C90: Средний разряд работы 4,7 | D90: чел.-ч. | E90: 1.59 | G90: =SmtRes!CX14 -> 1.59 | J90: =SmtRes!CZ14 -> 478.03 | L90: =SmtRes!DI14 -> 760.07
B91: 2 | C91: ЭМ | L91: =SUM(L92:L95)-SUMIF(CE92:CE95, 1, L92:L95) -> 3701.34
C92: ОТм(ЗТм) | D92: чел.-ч. | G92: =Source!V27 -> 0.75 | L92: =SUMIF(CE93:CE95, 1, L93:L95) -> 530.51 | CE92: 1
B93: 91.10.05-009 | C93: Трубоукладчики, номинальная грузоподъемность 35 т | D93: маш.-ч | E93: 0.75 | G93: =SmtRes!CX16 -> 0.75 | H93: =SmtRes!CZ16 -> 4403.56 | I93: =SmtRes!AJ16 -> 1.12 | J93: =ROUND(H93*I93, 2) -> 4931.99 | L93: =SmtRes!DG16 -> 3698.99
B94: 4-100-090 | C94: ОТм(ЗТм) Средний разряд машинистов 9 | D94: чел.-ч. | E94: =SmtRes!DO16*SmtRes!AT16 -> 0.75 | G94: =ROUND(E94*G88, 7) -> 0.75 | J94: =ROUND(SmtRes!AG16/SmtRes!DO16, 2) -> 707.35 | L94: =SmtRes!DH16 -> 530.51 | CE94: 1
B95: 91.17.04-042 | C95: Аппараты для газовой сварки и резки | D95: маш.-ч | E95: 0.44 | G95: =SmtRes!CX17 -> 0.44 | H95: =SmtRes!CZ17 -> 4.35 | I95: =SmtRes!AJ17 -> 1.23 | J95: =ROUND(H95*I95, 2) -> 5.35 | L95: =SmtRes!DG17 -> 2.35
B96: 4 | C96: М | L96: =SUM(L97:L99)-SUMIF(CE97:CE99, 1, L97:L99) -> 733.41
B97: 01.3.02.08-0001 | C97: Кислород газообразный технический | D97: м3 | E97: 1.59 | G97: =SmtRes!CX18 -> 1.59 | J97: =SmtRes!CZ18 -> 89 | L97: =SmtRes!DF18 -> 141.51
B98: 01.3.02.09-0022 | C98: Пропан-бутан смесь техническая | D98: кг | E98: 4.0656 | G98: =SmtRes!CX19 -> 4.0656 | H98: =SmtRes!CZ19 -> 41.38 | I98: =SmtRes!AI19 -> 1.38 | J98: =ROUND(H98*I98, 2) -> 57.1 | L98: =SmtRes!DF19 -> 232.15
B99: 11.1.03.01-0067 | C99: Брус обрезной хвойных пород (ель, сосна), естественной влажности, длина 2-6,5 м, ширина 100 и более мм, толщина 100 и более мм, сорт III | D99: м3 | E99: 0.027 | G99: =SmtRes!CX20 -> 0.027 | H99: =SmtRes!CZ20 -> 16655 | I99: =SmtRes!AI20 -> 0.8 | J99: =ROUND(H99*I99, 2) -> 13324 | L99: =SmtRes!DF20 -> 359.75
C100: Итого прямые затраты | L100: =L89+L91+L92+L96 -> 5725.33
C101: ФОТ | L101: =SUM(AR88:AR104)+SUM(AS88:AS104)+SUM(AT88:AT104)+SUM(AU88:AU104)+SUM(AV88:AV104) -> 1290.58
B102: Пр/812-019.0-1 | C102: НР Магистральные и промысловые трубопроводы | D102: % | E102: =Source!BZ27 -> 111 | G102: =Source!AT27 -> 111 | L102: =SUM(AZ88:AZ104) -> 1432.54
B103: Пр/774-019.0 | C103: СП Магистральные и промысловые трубопроводы | D103: % | E103: =Source!CA27 -> 60 | G103: =Source!AU27 -> 60 | L103: =SUM(BA88:BA104) -> 774.35
C104: Всего по позиции | I104: =IF(E88<>0,K104/E88, 0) -> 7932.22 | K104: =L89+L91+L96+L102+L103+L92 -> 7932.22 | AD104: =ROUND((Source!AT27/100)*((ROUND(SUMIF(SmtRes!AQ14:'SmtRes'!AQ20,"=1",SmtRes!AD14:'SmtRes'!AD20)*Source!I27, 2)+ROUND(SUMIF(SmtRes!AQ14:'SmtRes'!AQ20,"=1",SmtRes!AC14:'SmtRes'!AC20)*Source!I27, 2))), 2) -> 1315.77 | AE104: =ROUND((Source!AU27/100)*((ROUND(SUMIF(SmtRes!AQ14:'SmtRes'!AQ20,"=1",SmtRes!AD14:'SmtRes'!AD20)*Source!I27, 2)+ROUND(SUMIF(SmtRes!AQ14:'SmtRes'!AQ20,"=1",SmtRes!AC14:'SmtRes'!AC20)*Source!I27, 2))), 2) -> 711.23 | AN104: =L89+L91+L96+L102+L103+L92 -> 7932.22 | AO104: =L91 -> 3701.34 | AQ104: = | AR104: =L89 -> 760.07 | AT104: =L92 -> 530.51 | AV104: = | AW104: =L96 -> 733.41 | AZ104: =Source!X27 -> 1432.54 | BA104: =Source!Y27 -> 774.35 | CD104: 1
A105: 4 | B105: ГЭСН 23-01-007-05 | C105: =Source!G28 -> Укладка трубопроводов из железобетонных безнапорных раструбных труб диаметром: 1000 мм | D105: =Source!H28 -> 100 м | E105: =Source!K28 -> 0.1 | G105: =Source!I28 -> 0.1
C106: ="Объем: "&Source!I28&"=10/"&"100" -> Объем: 0,1=10/100
B107: 1 | C107: ОТ (ЗТ) | D107: чел.-ч. | G107: =Source!U28 -> 18.76 | L107: =SUM(L108:L108)-SUMIF(CE108:CE108, 1, L108:L108) -> 8119.52
B108: 1-100-40 | C108: Средний разряд работы 4,0 | D108: чел.-ч. | E108: 187.6 | G108: =SmtRes!CX21 -> 18.76 | J108: =SmtRes!CZ21 -> 432.81 | L108: =SmtRes!DI21 -> 8119.52
B109: 2 | C109: ЭМ | L109: =SUM(L110:L114)-SUMIF(CE110:CE114, 1, L110:L114) -> 6147.01
C110: ОТм(ЗТм) | D110: чел.-ч. | G110: =Source!V28 -> 1.288 | L110: =SUMIF(CE111:CE114, 1, L111:L114) -> 897.88 | CE110: 1
B111: 91.10.05-009 | C111: Трубоукладчики, номинальная грузоподъемность 35 т | D111: маш.-ч | E111: 12.4 | G111: =SmtRes!CX23 -> 1.24 | H111: =SmtRes!CZ23 -> 4403.56 | I111: =SmtRes!AJ23 -> 1.12 | J111: =ROUND(H111*I111, 2) -> 4931.99 | L111: =SmtRes!DG23 -> 6115.67
B112: 4-100-090 | C112: ОТм(ЗТм) Средний разряд машинистов 9 | D112: чел.-ч. | E112: =SmtRes!DO23*SmtRes!AT23 -> 12.4 | G112: =ROUND(E112*G105, 7) -> 1.24 | J112: =ROUND(SmtRes!AG23/SmtRes!DO23, 2) -> 707.35 | L112: =SmtRes!DH23 -> 877.11 | CE112: 1
B113: 91.14.02-001 | C113: Автомобили бортовые, грузоподъемность до 5 т | D113: маш.-ч | E113: 0.48 | G113: =SmtRes!CX24 -> 0.048 | J113: =SmtRes!CZ24 -> 652.84 | L113: =SmtRes!DG24 -> 31.34
B114: 4-100-040 | C114: ОТм(ЗТм) Средний разряд машинистов 4 | D114: чел.-ч. | E114: =SmtRes!DO24*SmtRes!AT24 -> 0.48 | G114: =ROUND(E114*G105, 7) -> 0.048 | J114: =ROUND(SmtRes!AG24/SmtRes!DO24, 2) -> 432.81 | L114: =SmtRes!DH24 -> 20.77 | CE114: 1
B115: 4 | C115: М | L115: =SUM(L116:L120)-SUMIF(CE116:CE120, 1, L116:L120) -> 2862.18
B116: 01.1.02.10-1022 | C116: Хризотил (асбест хризотиловый), группа 6К, марки 6К-45, 6К-30, 6К-20, 6К-5 | D116: т | E116: 0.114 | G116: =SmtRes!CX25 -> 0.0114 | H116: =SmtRes!CZ25 -> 21588.35 | I116: =SmtRes!AI25 -> 1.18 | J116: =ROUND(H116*I116, 2) -> 25474.25 | L116: =SmtRes!DF25 -> 290.41
B117: 01.7.03.01-0001 | C117: Вода | D117: м3 | E117: 78.5 | G117: =SmtRes!CX26 -> 7.85 | H117: =SmtRes!CZ26 -> 35.71 | I117: =SmtRes!AI26 -> 0.73 | J117: =ROUND(H117*I117, 2) -> 26.07 | L117: =SmtRes!DF26 -> 204.65
B118: 01.7.07.29-0322 | C118: Канат пропитанный (каболка) из льняного и джутового волокна, канализационный и водопроводный, отжатый, диаметр 10-100 мм | D118: кг | E118: 84 | G118: =SmtRes!CX27 -> 8.4 | H118: =SmtRes!CZ27 -> 152.78 | I118: =SmtRes!AI27 -> 1.36 | J118: =ROUND(H118*I118, 2) -> 207.78 | L118: =SmtRes!DF27 -> 1745.35
B119: 03.2.01.01-0001 | C119: Портландцемент бездобавочный общестроительный ЦЕМ 0 32,5Н | D119: т | E119: 0.2656 | G119: =SmtRes!CX28 -> 0.02656 | H119: =SmtRes!CZ28 -> 4800.85 | I119: =SmtRes!AI28 -> 1.89 | J119: =ROUND(H119*I119, 2) -> 9073.61 | L119: =SmtRes!DF28 -> 241
B120: 04.3.01.09-0014 | C120: Раствор готовый кладочный, цементный, М100 | D120: м3 | E120: 0.66 | G120: =SmtRes!CX29 -> 0.066 | J120: =SmtRes!CZ29 -> 5769.31 | L120: =SmtRes!DF29 -> 380.77
B121: =EtalonRes!I30 -> 05.1.02.08 | C121: =EtalonRes!K30 -> Трубы железобетонные безнапорные раструбные | D121: =EtalonRes!O30 -> м | E121: =EtalonRes!X30 -> 99.7 | G121: =ROUND(EtalonRes!AG30*Source!I28, 7) -> 9.97
...

Sheet Source
A1: 0 | B1: Smeta.RU (495) 974-1589 | D1: _PS_ | F1: 0 | G1: 0 | H1: 0 | I1: Smeta.RU | K1: 1 | L1: 28227 | M1: 38175928 | N1: 12 | O1: 1 | P1: 0 | Q1: 5
A4: 8 | B4: 1 | C4: -1 | F4: Новый проект 4 | G4: ремонт трубы | EC4: 0
A12: 1 | B12: 134 | C12: 0 | D12: =ROW(A77) -> 77 | E12: 0 | F12: Новый объект строительства | G12: ремонт трубы | I12: 0 | K12: 0 | L12: 0 | M12: 523 | O12: 0 | P12: 0 | Q12: 7 | R12: 0 | T12: 4 | V12: 0 | BB12: 0 | BH12: Сметные нормы списания | BI12: Коды ценников | BJ12: 1 | BK12: 1 | BL12: 0 | BM12: 1 | BN12: 1 | BO12: 0 | BP12: 6 | BQ12: 2 | BR12: 1 | BS12: 1 | BT12: 0 | BU12: 0 | BV12: 1 | BW12: 0 | BX12: 0 | BY12: ФСНБ-2022_И17 | BZ12: Версия 1.17.0 для ФСНБ-2022 И17 | CA12: ФСНБ-2022 - Изменения И17 | CB12: ФСНБ-2022 - Изменения И17 | CC12: ФСНБ-2022 - Изменения И17 | CD12: ФСНБ-2022 - Изменения И17 | CE12: Поправки для ФСНБ-2022 от 25.02.2026 г И17 (55/пр) Капитальный ремонт производственных зданий | CF12: 0 | CG12: 0 | CH12: 487489544 | CK12: 18 | CQ12: Приказ Минстроя России от 30.12.2021 г. № 1046/пр; Приказ Минстроя России от 04.08.2020 г. № 421/пр; Приказ Минстроя России от 21.12.2020 г. № 812/пр; Приказ Минстроя России от 11.12.2020 г. № 774/пр | CR12: ГСН | CS12: 46073 | CT12: 540 | CU12: 17 | CV12: Приказ Минстроя России от 18.05.2022 г. № 378/пр; Приказ Минстроя России от 26.08.2022 г. № 703/пр; Приказ Минстроя России от 26.10.2022 г. № 905/пр; Приказ Минстроя России от 27.12.2022 г. № 1133/пр; Приказ Минстроя России от 10.02.2023 г. № 84/пр; Приказ Минстроя России от 11.05.2023 г. № 335/пр; Приказ Минстроя России от 02.08.2023 г. № 551/пр; Приказ Минстроя России от 14.11.2023 г. № 817/пр; Приказ Минстроя России от 16.02.2024 г. № 102/пр; Приказ Минстроя России от 13.05.2024 г. № 323/пр; Приказ Минстроя России от 09.08.2024 г. № 524/пр; Приказ Минстроя России от 07.11.2024 г. № 747/пр; Приказ Минстроя России от 07.02.2025 г. № 69/пр; Приказ Минстроя России от 19.05.2025 г. № 299/пр; Приказ Минстроя России от 14.08.2025 г. № 490/пр; Приказ Минстроя России от 12.11.2025 г. № 696/пр; Приказ Минстроя России от 17.02.2026 г. № 91/пр; Приказ Минстроя России от 07.07.2022 г. № 557/пр; Приказ Минстроя России от 30.01.2024 г. № 55/пр; Приказ Минстроя России от 23.01.2025 г. № 30/пр; Приказ Минстроя России от 02.09.2021 г. № 636/пр; Приказ Минстроя России от 26.07.2022 г. № 611/пр; Приказ Минстроя России от 22.04.2022 г. № 317/пр | CY12: 0 | EC12: 0
A15: 15 | B15: 1
A18: 52 | B18: =B77 -> 134 | C18: =C77 -> 1 | D18: =D77 -> 12 | E18: =E77 -> 0 | F18: =F77 -> Новый объект строительства | G18: =G77 -> ремонт трубы | O18: =O77 -> 52656.07 | P18: =P77 -> 4333.36 | Q18: =Q77 -> 22333.26 | R18: =R77 -> 5074.08 | S18: =S77 -> 20915.37 | T18: =T77 -> 0 | U18: =U77 -> 49.772 | V18: =V77 -> 12.61312 | ... GX18: =GX77 -> 0
A20: 3 | B20: 1 | D20: =ROW(A42) -> 42 | F20: Новая локальная смета | G20: ремонт трубы | I20: 0 | K20: 0 | L20: Новая локальная смета | S20: 0 | V20: 0 | BX20: 0 | CF20: 0 | CG20: 0
A22: 52 | B22: =B42 -> 1 | C22: =C42 -> 3 | D22: =D42 -> 20 | E22: =E42 -> 0 | F22: =F42 -> Новая локальная смета | G22: =G42 -> ремонт трубы | O22: =O42 -> 52656.07 | P22: =P42 -> 4333.36 | Q22: =Q42 -> 22333.26 | R22: =R42 -> 5074.08 | S22: =S42 -> 20915.37 | T22: =T42 -> 0 | U22: =U42 -> 49.772 | V22: =V42 -> 12.61312 | ... GX22: =GX42 -> 0
A24: 17 | B24: 1 | C24: =ROW(SmtRes!A3) -> 3 | D24: =ROW(EtalonRes!A3) -> 3 | E24: 1 | F24: 01-01-010-38 | G24: Разработка грунта в отвал экскаваторами, вместимость ковша 0,4 (0,3-0,45) м3, группа грунтов: 2 | H24: 1000 м3 | I24: =ROUND(ROUND(45/1000,5),7) -> 0.045 | J24: 0 | K24: =ROUND(ROUND(45/1000,5),7) -> 0.045 | O24: =ROUND(CP24,2) -> 2405.66 | P24: =SUMIF(SmtRes!AQ1:'SmtRes'!AQ3,"=1",SmtRes!DF1:'SmtRes'!DF3) -> 0 | Q24: =SUMIF(SmtRes!AQ1:'SmtRes'!AQ3,"=1",SmtRes!DG1:'SmtRes'!DG3) -> 1654.35 | R24: =SUMIF(SmtRes!AQ1:'SmtRes'!AQ3,"=1",SmtRes!DH1:'SmtRes'!DH3) -> 657.84 | S24: =SUMIF(SmtRes!AQ1:'SmtRes'!AQ3,"=1",SmtRes!DI1:'SmtRes'!DI3) -> 93.47 | T24: =ROUND(CU24*I24,2) -> 0 | U24: =SUMIF(SmtRes!AQ1:'SmtRes'!AQ3,"=1",SmtRes!CV1:'SmtRes'!CV3) -> 0.2655 | V24: =SUMIF(SmtRes!AQ1:'SmtRes'!AQ3,"=1",SmtRes!CW1:'SmtRes'!CW3) -> 1.32255 | W24: =ROUND(CX24*I24,2) -> 0 | X24: =ROUND(CY24,2) -> 691.21 | Y24: =ROUND(CZ24,2) -> 345.6 | AA24: 38182922 | AB24: =ROUND((AC24+AD24+AF24),6) -> 29928.294 | AC24: =ROUND((0),6) -> 0 | AD24: =ROUND((((SUM(SmtRes!BR1:'SmtRes'!BR3))-(SUM(SmtRes!BS1:'SmtRes'!BS3)))+AE24),6) -> 27851.14 | AE24: =ROUND((SUM(SmtRes!BS1:'SmtRes'!BS3)),6) -> 14618.586 | AF24: =ROUND((SUM(SmtRes!BT1:'SmtRes'!BT3)),6) -> 2077.154 | AG24: =ROUND((AP24),6) -> 0 | AH24: =(SUM(SmtRes!BU1:'SmtRes'!BU3)) -> 5.9 | AI24: =(SUM(SmtRes!BV1:'SmtRes'!BV3)) -> 29.39 | AJ24: =(AS24) -> 0 | AK24: 44546.88 | AL24: 0 | AM24: 27851.14 | AN24: 14618.586 | AO24: 2077.154 | AP24: 0 | AQ24: 5.9 | AR24: 29.39 | AS24: 0 | AT24: 92 | AU24: 46 | AV24: 1 | AW24: 1 | AZ24: 1 | BA24: 1 | BB24: 1 | BC24: 1 | BH24: 0 | BI24: 1 | BJ24: ГЭСН-2022, 01-01-010-38, приказ Минстроя России от 18.05.2022 г. № 378/пр | BM24: 1001 | BN24: 0 | BP24: 0 | BQ24: 2 | BR24: 0 | BS24: 1 | BT24: 1 | BU24: 1 | BV24: 1 | BW24: 1 | BX24: 1 | BZ24: 92 | CA24: 46 | CE24: 0 | CF24: 0 | CG24: 0 | CM24: 0 | CO24: 0 | CP24: =(P24+Q24+S24+R24) -> 2405.66 | CQ24: =SUMIF(SmtRes!AQ1:'SmtRes'!AQ3,"=1",SmtRes!AA1:'SmtRes'!AA3) -> 0 | CR24: =SUMIF(SmtRes!AQ1:'SmtRes'!AQ3,"=1",SmtRes!AB1:'SmtRes'!AB3) -> 1250.88 | CS24: =SUMIF(SmtRes!AQ1:'SmtRes'!AQ3,"=1",SmtRes!AC1:'SmtRes'!AC3) -> 497.4 | CT24: =SUMIF(SmtRes!AQ1:'SmtRes'!AQ3,"=1",SmtRes!AD1:'SmtRes'!AD3) -> 352.06 | CU24: =AG24 -> 0 | CV24: =SUMIF(SmtRes!AQ1:'SmtRes'!AQ3,"=1",SmtRes!BU1:'SmtRes'!BU3) -> 5.9 | CW24: =SUMIF(SmtRes!AQ1:'SmtRes'!AQ3,"=1",SmtRes!BV1:'SmtRes'!BV3) -> 29.39 | CX24: =AJ24 -> 0 | CY24: =(((S24+R24)*AT24)/100) -> 691.2052 | CZ24: =(((S24+R24)*AU24)/100) -> 345.6026 | DN24: 0 | DO24: 0 | DP24: 1 | DQ24: 1 | DU24: 1007 | DV24: 1000 м3 | DW24: 1000 м3 | DX24: 1000 | EE24: 35227734 | EF24: 2 | EG24: Общестроительные работы | EH24: 1 | EI24: Земляные работы | EJ24: 1 | EK24: 1001 | EL24: Земляные работы, выполняемые: механизированным способом | EM24: ФЕР-01 | EQ24: 0 | ER24: 0 | ES24: 0 | ET24: 0 | EU24: 0 | EV24: 0 | EW24: 5.9 | EX24: 29.39 | EY24: 0 | FQ24: 0 | FR24: 0 | FS24: 0 | FX24: 92 | FY24: 46 | GD24: 1 | GF24: 329302311 | GG24: 2 | GH24: 1 | GI24: -2 | GJ24: 0 | GK24: 0 | GL24: =ROUND(IF(AND(BH24=3,BI24=3,FS24<>0),P24,0),2) -> 0 | GM24: =ROUND(O24+X24+Y24,2)+GX24 -> 3442.47 | GN24: =IF(OR(BI24=0,BI24=1),GM24-GX24,0) -> 3442.47 | GO24: =IF(BI24=2,GM24-GX24,0) -> 0 | GP24: =IF(BI24=4,GM24-GX24,0) -> 0 | GR24: 0 | GS24: 3 | GT24: 0 | GV24: =ROUND((GT24),6) -> 0 | GW24: 1 | GX24: =ROUND(HC24*I24,2) -> 0 | HA24: 0 | HB24: 0 | HC24: =GV24*GW24 -> 0 | HN24: Пр/812-001.1-1 | HO24: Пр/774-001.1 | HP24: Земляные работы, выполняемые: механизированным способом | HQ24: Земляные работы, выполняемые: механизированным способом | HS24: 0 | IK24: 0
A25: 17 | B25: 1 | C25: =ROW(SmtRes!A13) -> 13 | D25: =ROW(EtalonRes!A13) -> 13 | E25: 2 | F25: 23-01-007-05 | G25: Демонтаж - Укладка трубопроводов из железобетонных безнапорных раструбных труб диаметром: 1000 мм | H25: 100 м | I25: =ROUND(ROUND(10/100,5),7) -> 0.1 | J25: 0 | K25: =ROUND(ROUND(10/100,5),7) -> 0.1 | O25: =ROUND(CP25,2) -> 12131.52 | P25: =SUMIF(SmtRes!AQ4:'SmtRes'!AQ13,"=1",SmtRes!DF4:'SmtRes'!DF13) -> 0 | Q25: =SUMIF(SmtRes!AQ4:'SmtRes'!AQ13,"=1",SmtRes!DG4:'SmtRes'!DG13) -> 4917.6 | R25: =SUMIF(SmtRes!AQ4:'SmtRes'!AQ13,"=1",SmtRes!DH4:'SmtRes'!DH13) -> 718.31 | S25: =SUMIF(SmtRes!AQ4:'SmtRes'!AQ13,"=1",SmtRes!DI4:'SmtRes'!DI13) -> 6495.61 | T25: =ROUND(CU25*I25,2) -> 0 | U25: =SUMIF(SmtRes!AQ4:'SmtRes'!AQ13,"=1",SmtRes!CV4:'SmtRes'!CV13) -> 15.008 | V25: =SUMIF(SmtRes!AQ4:'SmtRes'!AQ13,"=1",SmtRes!CW4:'SmtRes'!CW13) -> 1.0304 | W25: =ROUND(CX25*I25,2) -> 0 | X25: =ROUND(CY25,2) -> 8440.29 | Y25: =ROUND(CZ25,2) -> 5338.3 | AA25: 38182922 | AB25: =ROUND((AC25+AD25+AF25),6) -> 108890.13 | AC25: =ROUND((0),6) -> 0 | AD25: =ROUND((((SUM(SmtRes!BR4:'SmtRes'!BR13))-(SUM(SmtRes!BS4:'SmtRes'!BS13)))+AE25),6) -> 43934.006 | AE25: =ROUND((SUM(SmtRes!BS4:'SmtRes'!BS13)),6) -> 7183.111 | AF25: =ROUND((SUM(SmtRes!BT4:'SmtRes'!BT13)),6) -> 64956.125 | AG25: =ROUND((AP25),6) -> 0 | AH25: =(SUM(SmtRes!BU4:'SmtRes'!BU13)) -> 150.08 | AI25: =(SUM(SmtRes!BV4:'SmtRes'!BV13)) -> 10.304 | AJ25: =(AS25) -> 0 | AK25: 168272.23 | AL25: 23180.677 | AM25: 54917.507 | AN25: 8978.8888 | AO25: 81195.156 | AP25: 0 | AQ25: 187.6 | AR25: 12.88 | AS25: 0 | AT25: 117 | AU25: 74 | AV25: 1 | AW25: 1 | AZ25: 1 | BA25: 1 | BB25: 1 | BC25: 1 | BH25: 0 | BI25: 1 | BJ25: ГЭСН-2022 доп.16, 23-01-007-05, приказ Минстроя России от 12.11.2025 г. № 696/пр | BM25: 23001 | BN25: 0 | BP25: 0 | BQ25: 2 | BR25: 0 | BS25: 1 | BT25: 1 | BU25: 1 | BV25: 1 | BW25: 1 | BX25: 1 | BZ25: 117 | CA25: 74 | CE25: 0 | CF25: 0 | CG25: 0 | CM25: 0 | CN25: демонтаж_x000D_ Поправка: 571/пр_2022_п.83_т.2_стр.1_стб.3 Наименование: Разборка и (или) демонтаж строительных конструкций, систем и сетей инженерно-технического обеспечения, в том числе их элементов: сборных бетонных и железобетонных строительных конструкций | CO25: 0 | CP25: =(P25+Q25+S25+R25) -> 12131.52 | CQ25: =SUMIF(SmtRes!AQ4:'SmtRes'!AQ13,"=1",SmtRes!AA4:'SmtRes'!AA13) -> 40551.02 | CR25: =SUMIF(SmtRes!AQ4:'SmtRes'!AQ13,"=1",SmtRes!AB4:'SmtRes'!AB13) -> 5584.83 | CS25: =SUMIF(SmtRes!AQ4:'SmtRes'!AQ13,"=1",SmtRes!AC4:'SmtRes'!AC13) -> 1140.16 | CT25: =SUMIF(SmtRes!AQ4:'SmtRes'!AQ13,"=1",SmtRes!AD4:'SmtRes'!AD13) -> 432.81 | CU25: =AG25 -> 0 | CV25: =SUMIF(SmtRes!AQ4:'SmtRes'!AQ13,"=1",SmtRes!BU4:'SmtRes'!BU13) -> 150.08 | CW25: =SUMIF(SmtRes!AQ4:'SmtRes'!AQ13,"=1",SmtRes!BV4:'SmtRes'!BV13) -> 10.304 | CX25: =AJ25 -> 0 | CY25: =(((S25+R25)*AT25)/100) -> 8440.2864 | CZ25: =(((S25+R25)*AU25)/100) -> 5338.3008 | DB25: 1 | DD25: *0 | DE25: *0,8 | DF25: *0,8 | DG25: *0,8 | DI25: *0,8 | DJ25: *0,8 | DN25: 0 | DO25: 0 | DP25: 1 | DQ25: 1 | DU25: 1003 | DV25: 100 м | DW25: 100 м | DX25: 100 | EE25: 35227794 | EF25: 2 | EG25: Общестроительные работы | EH25: 18 | EI25: Наружные сети водопровода, канализации, теплоснабжения, газопроводы | EJ25: 1 | EK25: 23001 | EL25: Наружные сети водопровода, канализации, теплоснабжения, газопроводы | EM25: ФЕР-23 | EO25: демонтаж_x000D_ Поправка: 571/пр_2022_п.83_т.2_стр.1_стб.3 | EQ25: 0 | ER25: 0 | ES25: 0 | ET25: 0 | EU25: 0 | EV25: 0 | EW25: 187.6 | EX25: 12.88 | EY25: 0 | FQ25: 0 | FR25: 0 | FS25: 0 | FX25: 117 | FY25: 74 | GD25: 1 | GF25: 751095627 | GG25: 2 | GH25: 1 | GI25: -2 | GJ25: 0 | GK25: 0 | GL25: =ROUND(IF(AND(BH25=3,BI25=3,FS25<>0),P25,0),2) -> 0 | GM25: =ROUND(O25+X25+Y25,2)+GX25 -> 25910.11 | GN25: =IF(OR(BI25=0,BI25=1),GM25-GX25,0) -> 25910.11 | GO25: =IF(BI25=2,GM25-GX25,0) -> 0 | GP25: =IF(BI25=4,GM25-GX25,0) -> 0 | GR25: 0 | GS25: 3 | GT25: 0 | GV25: =ROUND((GT25),6) -> 0 | GW25: 1 | GX25: =ROUND(HC25*I25,2) -> 0 | HA25: 0 | HB25: 0 | HC25: =GV25*GW25 -> 0 | HN25: Пр/812-018.0-1 | HO25: Пр/774-018.0 | HP25: Наружные сети водопровода, канализации, теплоснабжения, газопроводы | HQ25: Наружные сети водопровода, канализации, теплоснабжения, газопроводы | HS25: 0 | IK25: 0
A26: 18 | B26: 1 | C26: 13 | E26: 2,1 | F26: 05.1.02.08 | G26: Трубы железобетонные безнапорные раструбные | H26: м | I26: =I25*J26 -> 0 | J26: 0 | K26: 99.7 | O26: =ROUND(CP26,2) -> 0 | P26: =ROUND(CQ26*I26,2) -> 0 | Q26: =ROUND(CR26*I26,2) -> 0 | R26: =ROUND(CS26*I26,2) -> 0 | S26: =ROUND(CT26*I26,2) -> 0 | T26: =ROUND(CU26*I26,2) -> 0 | U26: =ROUND(CV26*I26,7) -> 0 | V26: =ROUND(CW26*I26,7) -> 0 | W26: =ROUND(CX26*I26,2) -> 0 | X26: =ROUND(CY26,2) -> 0 | Y26: =ROUND(CZ26,2) -> 0 | AA26: 38182922 | AB26: =ROUND((AC26+AD26+AF26),6) -> 0 | AC26: =ROUND((ES26),6) -> 0 | AD26: =ROUND((((ET26)-(EU26))+AE26),6) -> 0 | AE26: =ROUND((EU26),6) -> 0 | AF26: =ROUND((EV26),6) -> 0 | AG26: =ROUND((AP26),6) -> 0 | AH26: =(EW26) -> 0 | AI26: =(EX26) -> 0 | AJ26: =(AS26) -> 0 | AK26: 0 | AL26: 0 | AM26: 0 | AN26: 0 | AO26: 0 | AP26: 0 | AQ26: 0 | AR26: 0 | AS26: 0 | AT26: 117 | AU26: 74 | AV26: 1 | AW26: 1 | AZ26: 1 | BA26: 1 | BB26: 1 | BC26: 1 | BH26: 3 | BI26: 1 | BM26: 23001 | BN26: 0 | BP26: 0 | BQ26: 2 | BR26: 0 | BS26: 1 | BT26: 1 | BU26: 1 | BV26: 1 | BW26: 1 | BX26: 1 | BZ26: 117 | CA26: 74 | CE26: 0 | CF26: 0 | CG26: 0 | CM26: 0 | CN26: Поправка: 571/пр_2022_п.83_т.2_стр.1_стб.3_x000D_ Наименование: Разборка и (или) демонтаж строительных конструкций, систем и сетей инженерно-технического обеспечения, в том числе их элементов: сборных бетонных и железобетонных строительных конструкций | CO26: 0 | CP26: =(P26+Q26+S26+R26) -> 0 | CQ26: =ROUND(AL26*BC26,2) -> 0 | CR26: =ROUND(AM26*BB26,2) -> 0 | CS26: =ROUND(AN26*BS26,2) -> 0 | CT26: =ROUND(AO26*BA26,2) -> 0 | CU26: =AG26 -> 0 | CV26: =AH26 -> 0 | CW26: =AI26 -> 0 | CX26: =AJ26 -> 0 | CY26: =(((S26+R26)*AT26)/100) -> 0 | CZ26: =(((S26+R26)*AU26)/100) -> 0 | DN26: 0 | DO26: 0 | DP26: 1 | DQ26: 1 | DU26: 1003 | DV26: м | DW26: м | DX26: 1 | EE26: 35227794 | EF26: 2 | EG26: Общестроительные работы | EH26: 18 | EI26: Наружные сети водопровода, канализации, теплоснабжения, газопроводы | EJ26: 1 | EK26: 23001 | EL26: Наружные сети водопровода, канализации, теплоснабжения, газопроводы | EM26: ФЕР-23 | EO26: Поправка: 571/пр_2022_п.83_т.2_стр.1_стб.3 | EQ26: 0 | ER26: 0 | ES26: 0 | ET26: 0 | EU26: 0 | EV26: 0 | EW26: 0 | EX26: 0 | FQ26: 0 | FR26: 0 | FS26: 0 | FX26: 117 | FY26: 74 | GD26: 1 | GF26: 1219364707 | GG26: 2 | GH26: 1 | GI26: -2 | GJ26: 0 | GK26: 0 | GL26: =ROUND(IF(AND(BH26=3,BI26=3,FS26<>0),P26,0),2) -> 0 | GM26: =ROUND(O26+X26+Y26,2)+GX26 -> 0 | GN26: =IF(OR(BI26=0,BI26=1),GM26-GX26,0) -> 0 | GO26: =IF(BI26=2,GM26-GX26,0) -> 0 | GP26: =IF(BI26=4,GM26-GX26,0) -> 0 | GR26: 0 | GS26: 3 | GT26: 0 | GV26: =ROUND((GT26),6) -> 0 | GW26: 1 | GX26: =ROUND(HC26*I26,2) -> 0 | HA26: 0 | HB26: 0 | HC26: =GV26*GW26 -> 0 | HM26: *0 | HN26: Пр/812-018.0-1 | HO26: Пр/774-018.0 | HP26: Наружные сети водопровода, канализации, теплоснабжения, газопроводы | HQ26: Наружные сети водопровода, канализации, теплоснабжения, газопроводы | HS26: 0 | IK26: 0
A27: 17 | B27: 1 | C27: =ROW(SmtRes!A20) -> 20 | D27: =ROW(EtalonRes!A20) -> 20 | E27: 3 | F27: 25-02-085-05 | G27: Резка на бровке траншеи демонтируемых труб условным диаметром: 1000 мм | H27: РЕЗ | I27: =ROUND(ROUND(1,5),7) -> 1 | J27: 0 | K27: =ROUND(ROUND(1,5),7) -> 1 | O27: =ROUND(CP27,2) -> 5725.33 | P27: =SUMIF(SmtRes!AQ14:'SmtRes'!AQ20,"=1",SmtRes!DF14:'SmtRes'!DF20) -> 733.41 | Q27: =SUMIF(SmtRes!AQ14:'SmtRes'!AQ20,"=1",SmtRes!DG14:'SmtRes'!DG20) -> 3701.34 | R27: =SUMIF(SmtRes!AQ14:'SmtRes'!AQ20,"=1",SmtRes!DH14:'SmtRes'!DH20) -> 530.51 | S27: =SUMIF(SmtRes!AQ14:'SmtRes'!AQ20,"=1",SmtRes!DI14:'SmtRes'!DI20) -> 760.07 | T27: =ROUND(CU27*I27,2) -> 0 | U27: =SUMIF(SmtRes!AQ14:'SmtRes'!AQ20,"=1",SmtRes!CV14:'SmtRes'!CV20) -> 1.59 | V27: =SUMIF(SmtRes!AQ14:'SmtRes'!AQ20,"=1",SmtRes!CW14:'SmtRes'!CW20) -> 0.75 | W27: =ROUND(CX27*I27,2) -> 0 | X27: =ROUND(CY27,2) -> 1432.54 | Y27: =ROUND(CZ27,2) -> 774.35 | AA27: 38182922 | AB27: =ROUND((AC27+AD27+AF27),6) -> 4824.0812 | AC27: =ROUND((SUM(SmtRes!BQ14:'SmtRes'!BQ20)),6) -> 759.42953 | AD27: =ROUND((((SUM(SmtRes!BR14:'SmtRes'!BR20))-(SUM(SmtRes!BS14:'SmtRes'!BS20)))+AE27),6) -> 3304.584 | AE27: =ROUND((SUM(SmtRes!BS14:'SmtRes'!BS20)),6) -> 530.5125 | AF27: =ROUND((SUM(SmtRes!BT14:'SmtRes'!BT20)),6) -> 760.0677 | AG27: =ROUND((AP27),6) -> 0 | AH27: =(SUM(SmtRes!BU14:'SmtRes'!BU20)) -> 1.59 | AI27: =(SUM(SmtRes!BV14:'SmtRes'!BV20)) -> 0.75 | AJ27: =(AS27) -> 0 | AK27: 5354.5937 | AL27: 759.42953 | AM27: 3304.584 | AN27: 530.5125 | AO27: 760.0677 | AP27: 0 | AQ27: 1.59 | AR27: 0.75 | AS27: 0 | AT27: 111 | AU27: 60 | AV27: 1 | AW27: 1 | AZ27: 1 | BA27: 1 | BB27: 1 | BC27: 1 | BH27: 0 | BI27: 1 | BJ27: ГЭСН-2022, 25-02-085-05, приказ Минстроя России от 18.05.2022 г. № 378/пр | BM27: 25001 | BN27: 0 | BP27: 0 | BQ27: 2 | BR27: 0 | BS27: 1 | BT27: 1 | BU27: 1 | BV27: 1 | BW27: 1 | BX27: 1 | BZ27: 111 | CA27: 60 | CE27: 0 | CF27: 0 | CG27: 0 | CM27: 0 | CO27: 0 | CP27: =(P27+Q27+S27+R27) -> 5725.33 | CQ27: =SUMIF(SmtRes!AQ14:'SmtRes'!AQ20,"=1",SmtRes!AA14:'SmtRes'!AA20) -> 13470.1 | CR27: =SUMIF(SmtRes!AQ14:'SmtRes'!AQ20,"=1",SmtRes!AB14:'SmtRes'!AB20) -> 4937.34 | CS27: =SUMIF(SmtRes!AQ14:'SmtRes'!AQ20,"=1",SmtRes!AC14:'SmtRes'!AC20) -> 707.35 | CT27: =SUMIF(SmtRes!AQ14:'SmtRes'!AQ20,"=1",SmtRes!AD14:'SmtRes'!AD20) -> 478.03 | CU27: =AG27 -> 0 | CV27: =SUMIF(SmtRes!AQ14:'SmtRes'!AQ20,"=1",SmtRes!BU14:'SmtRes'!BU20) -> 1.59 | CW27: =SUMIF(SmtRes!AQ14:'SmtRes'!AQ20,"=1",SmtRes!BV14:'SmtRes'!BV20) -> 0.75 | CX27: =AJ27 -> 0 | CY27: =(((S27+R27)*AT27)/100) -> 1432.5438 | CZ27: =(((S27+R27)*AU27)/100) -> 774.348 | DN27: 0 | DO27: 0 | DP27: 1 | DQ27: 1 | DU27: 1013 | DV27: РЕЗ | DW27: РЕЗ | DX27: 1 | EE27: 35227796 | EF27: 2 | EG27: Общестроительные работы | EH27: 19 | EI27: Магистральные и промысловые трубопроводы | EJ27: 1 | EK27: 25001 | EL27: Магистаральные и промысловые водопроводы | EM27: ФЕР-25 | EQ27: 0 | ER27: 0 | ES27: 0 | ET27: 0 | EU27: 0 | EV27: 0 | EW27: 1.59 | EX27: 0.75 | EY27: 0 | FQ27: 0 | FR27: 0 | FS27: 0 | FX27: 111 | FY27: 60 | GD27: 1 | GF27: 1586047166 | GG27: 2 | GH27: 1 | GI27: -2 | GJ27: 0 | GK27: 0 | GL27: =ROUND(IF(AND(BH27=3,BI27=3,FS27<>0),P27,0),2) -> 0 | GM27: =ROUND(O27+X27+Y27,2)+GX27 -> 7932.22 | GN27: =IF(OR(BI27=0,BI27=1),GM27-GX27,0) -> 7932.22 | GO27: =IF(BI27=2,GM27-GX27,0) -> 0 | GP27: =IF(BI27=4,GM27-GX27,0) -> 0 | GR27: 0 | GS27: 3 | GT27: 0 | GV27: =ROUND((GT27),6) -> 0 | GW27: 1 | GX27: =ROUND(HC27*I27,2) -> 0 | HA27: 0 | HB27: 0 | HC27: =GV27*GW27 -> 0 | HN27: Пр/812-019.0-1 | HO27: Пр/774-019.0 | HP27: Магистральные и промысловые трубопроводы | HQ27: Магистральные и промысловые трубопроводы | HS27: 0 | IK27: 0
A28: 17 | B28: 1 | C28: =ROW(SmtRes!A30) -> 30 | D28: =ROW(EtalonRes!A30) -> 30 | E28: 4 | F28: 23-01-007-05 | G28: Укладка трубопроводов из железобетонных безнапорных раструбных труб диаметром: 1000 мм | H28: 100 м | I28: =ROUND(ROUND(10/100,5),7) -> 0.1 | J28: 0 | K28: =ROUND(ROUND(10/100,5),7) -> 0.1 | O28: =ROUND(CP28,2) -> 18026.59 | P28: =SUMIF(SmtRes!AQ21:'SmtRes'!AQ30,"=1",SmtRes!DF21:'SmtRes'!DF30) -> 2862.18 | Q28: =SUMIF(SmtRes!AQ21:'SmtRes'!AQ30,"=1",SmtRes!DG21:'SmtRes'!DG30) -> 6147.01 | R28: =SUMIF(SmtRes!AQ21:'SmtRes'!AQ30,"=1",SmtRes!DH21:'SmtRes'!DH30) -> 897.88 | S28: =SUMIF(SmtRes!AQ21:'SmtRes'!AQ30,"=1",SmtRes!DI21:'SmtRes'!DI30) -> 8119.52 | T28: =ROUND(CU28*I28,2) -> 0 | U28: =SUMIF(SmtRes!AQ21:'SmtRes'!AQ30,"=1",SmtRes!CV21:'SmtRes'!CV30) -> 18.76 | V28: =SUMIF(SmtRes!AQ21:'SmtRes'!AQ30,"=1",SmtRes!CW21:'SmtRes'!CW30) -> 1.288 | W28: =ROUND(CX28*I28,2) -> 0 | X28: =ROUND(CY28,2) -> 10550.36 | Y28: =ROUND(CZ28,2) -> 6672.88 | AA28: 38182922 | AB28: =ROUND((AC28+AD28+AF28),6) -> 159293.34 | AC28: =ROUND((SUM(SmtRes!BQ21:'SmtRes'!BQ30)),6) -> 23180.677 | AD28: =ROUND((((SUM(SmtRes!BR21:'SmtRes'!BR30))-(SUM(SmtRes!BS21:'SmtRes'!BS30)))+AE28),6) -> 54917.507 | AE28: =ROUND((SUM(SmtRes!BS21:'SmtRes'!BS30)),6) -> 8978.8888 | AF28: =ROUND((SUM(SmtRes!BT21:'SmtRes'!BT30)),6) -> 81195.156 | AG28: =ROUND((AP28),6) -> 0 | AH28: =(SUM(SmtRes!BU21:'SmtRes'!BU30)) -> 187.6 | AI28: =(SUM(SmtRes!BV21:'SmtRes'!BV30)) -> 12.88 | AJ28: =(AS28) -> 0 | AK28: 168272.23 | AL28: 23180.677 | AM28: 54917.507 | AN28: 8978.8888 | AO28: 81195.156 | AP28: 0 | AQ28: 187.6 | AR28: 12.88 | AS28: 0 | AT28: 117 | AU28: 74 | AV28: 1 | AW28: 1 | AZ28: 1 | BA28: 1 | BB28: 1 | BC28: 1 | BH28: 0 | BI28: 1 | BJ28: ГЭСН-2022 доп.16, 23-01-007-05, приказ Минстроя России от 12.11.2025 г. № 696/пр | BM28: 23001 | BN28: 0 | BP28: 0 | BQ28: 2 | BR28: 0 | BS28: 1 | BT28: 1 | BU28: 1 | BV28: 1 | BW28: 1 | BX28: 1 | BZ28: 117 | CA28: 74 | CE28: 0 | CF28: 0 | CG28: 0 | CM28: 0 | CO28: 0 | CP28: =(P28+Q28+S28+R28) -> 18026.59 | CQ28: =SUMIF(SmtRes!AQ21:'SmtRes'!AQ30,"=1",SmtRes!AA21:'SmtRes'!AA30) -> 40551.02 | CR28: =SUMIF(SmtRes!AQ21:'SmtRes'!AQ30,"=1",SmtRes!AB21:'SmtRes'!AB30) -> 5584.83 | CS28: =SUMIF(SmtRes!AQ21:'SmtRes'!AQ30,"=1",SmtRes!AC21:'SmtRes'!AC30) -> 1140.16 | CT28: =SUMIF(SmtRes!AQ21:'SmtRes'!AQ30,"=1",SmtRes!AD21:'SmtRes'!AD30) -> 432.81 | CU28: =AG28 -> 0 | CV28: =SUMIF(SmtRes!AQ21:'SmtRes'!AQ30,"=1",SmtRes!BU21:'SmtRes'!BU30) -> 187.6 | CW28: =SUMIF(SmtRes!AQ21:'SmtRes'!AQ30,"=1",SmtRes!BV21:'SmtRes'!BV30) -> 12.88 | CX28: =AJ28 -> 0 | CY28: =(((S28+R28)*AT28)/100) -> 10550.358 | CZ28: =(((S28+R28)*AU28)/100) -> 6672.876 | DN28: 0 | DO28: 0 | DP28: 1 | DQ28: 1 | DU28: 1003 | DV28: 100 м | DW28: 100 м | DX28: 100 | EE28: 35227794 | EF28: 2 | EG28: Общестроительные работы | EH28: 18 | EI28: Наружные сети водопровода, канализации, теплоснабжения, газопроводы | EJ28: 1 | EK28: 23001 | EL28: Наружные сети водопровода, канализации, теплоснабжения, газопроводы | EM28: ФЕР-23 | EQ28: 0 | ER28: 0 | ES28: 0 | ET28: 0 | EU28: 0 | EV28: 0 | EW28: 187.6 | EX28: 12.88 | EY28: 0 | FQ28: 0 | FR28: 0 | FS28: 0 | FX28: 117 | FY28: 74 | GD28: 1 | GF28: 1846504045 | GG28: 2 | GH28: 1 | GI28: -2 | GJ28: 0 | GK28: 0 | GL28: =ROUND(IF(AND(BH28=3,BI28=3,FS28<>0),P28,0),2) -> 0 | GM28: =ROUND(O28+X28+Y28,2)+GX28 -> 35249.83 | GN28: =IF(OR(BI28=0,BI28=1),GM28-GX28,0) -> 35249.83 | GO28: =IF(BI28=2,GM28-GX28,0) -> 0 | GP28: =IF(BI28=4,GM28-GX28,0) -> 0 | GR28: 0 | GS28: 3 | GT28: 0 | GV28: =ROUND((GT28),6) -> 0 | GW28: 1 | GX28: =ROUND(HC28*I28,2) -> 0 | HA28: 0 | HB28: 0 | HC28: =GV28*GW28 -> 0 | HN28: Пр/812-018.0-1 | HO28: Пр/774-018.0 | HP28: Наружные сети водопровода, канализации, теплоснабжения, газопроводы | HQ28: Наружные сети водопровода, канализации, теплоснабжения, газопроводы | HS28: 0 | IK28: 0
A29: 18 | B29: 1 | C29: 30 | E29: 4,1 | F29: 05.1.02.08 | G29: Трубы железобетонные безнапорные раструбные | H29: м | I29: =I28*J29 -> 9.97 | J29: 99.7 | K29: 99.7 | O29: =ROUND(CP29,2) -> 0 | P29: =ROUND(CQ29*I29,2) -> 0 | Q29: =ROUND(CR29*I29,2) -> 0 | R29: =ROUND(CS29*I29,2) -> 0 | S29: =ROUND(CT29*I29,2) -> 0 | T29: =ROUND(CU29*I29,2) -> 0 | U29: =ROUND(CV29*I29,7) -> 0 | V29: =ROUND(CW29*I29,7) -> 0 | W29: =ROUND(CX29*I29,2) -> 0 | X29: =ROUND(CY29,2) -> 0 | Y29: =ROUND(CZ29,2) -> 0 | AA29: 38182922 | AB29: =ROUND((AC29+AD29+AF29),6) -> 0 | AC29: =ROUND((ES29),6) -> 0 | AD29: =ROUND((((ET29)-(EU29))+AE29),6) -> 0 | AE29: =ROUND((EU29),6) -> 0 | AF29: =ROUND((EV29),6) -> 0 | AG29: =ROUND((AP29),6) -> 0 | AH29: =(EW29) -> 0 | AI29: =(EX29) -> 0 | AJ29: =(AS29) -> 0 | AK29: 0 | AL29: 0 | AM29: 0 | AN29: 0 | AO29: 0 | AP29: 0 | AQ29: 0 | AR29: 0 | AS29: 0 | AT29: 117 | AU29: 74 | AV29: 1 | AW29: 1 | AZ29: 1 | BA29: 1 | BB29: 1 | BC29: 1 | BH29: 3 | BI29: 1 | BM29: 23001 | BN29: 0 | BP29: 0 | BQ29: 2 | BR29: 0 | BS29: 1 | BT29: 1 | BU29: 1 | BV29: 1 | BW29: 1 | BX29: 1 | BZ29: 117 | CA29: 74 | CE29: 0 | CF29: 0 | CG29: 0 | CM29: 0 | CO29: 0 | CP29: =(P29+Q29+S29+R29) -> 0 | CQ29: =ROUND(AL29*BC29,2) -> 0 | CR29: =ROUND(AM29*BB29,2) -> 0 | CS29: =ROUND(AN29*BS29,2) -> 0 | CT29: =ROUND(AO29*BA29,2) -> 0 | CU29: =AG29 -> 0 | CV29: =AH29 -> 0 | CW29: =AI29 -> 0 | CX29: =AJ29 -> 0 | CY29: =(((S29+R29)*AT29)/100) -> 0 | CZ29: =(((S29+R29)*AU29)/100) -> 0 | DN29: 0 | DO29: 0 | DP29: 1 | DQ29: 1 | DU29: 1003 | DV29: м | DW29: м | DX29: 1 | EE29: 35227794 | EF29: 2 | EG29: Общестроительные работы | EH29: 18 | EI29: Наружные сети водопровода, канализации, теплоснабжения, газопроводы | EJ29: 1 | EK29: 23001 | EL29: Наружные сети водопровода, канализации, теплоснабжения, газопроводы | EM29: ФЕР-23 | EQ29: 0 | ER29: 0 | ES29: 0 | ET29: 0 | EU29: 0 | EV29: 0 | EW29: 0 | EX29: 0 | FQ29: 0 | FR29: 0 | FS29: 0 | FX29: 117 | FY29: 74 | GD29: 1 | GF29: 1219364707 | GG29: 2 | GH29: 1 | GI29: -2 | GJ29: 0 | GK29: 0 | GL29: =ROUND(IF(AND(BH29=3,BI29=3,FS29<>0),P29,0),2) -> 0 | GM29: =ROUND(O29+X29+Y29,2)+GX29 -> 0 | GN29: =IF(OR(BI29=0,BI29=1),GM29-GX29,0) -> 0 | GO29: =IF(BI29=2,GM29-GX29,0) -> 0 | GP29: =IF(BI29=4,GM29-GX29,0) -> 0 | GR29: 0 | GS29: 3 | GT29: 0 | GV29: =ROUND((GT29),6) -> 0 | GW29: 1 | GX29: =ROUND(HC29*I29,2) -> 0 | HA29: 0 | HB29: 0 | HC29: =GV29*GW29 -> 0 | HN29: Пр/812-018.0-1 | HO29: Пр/774-018.0 | HP29: Наружные сети водопровода, канализации, теплоснабжения, газопроводы | HQ29: Наружные сети водопровода, канализации, теплоснабжения, газопроводы | HS29: 0 | IK29: 0
A30: 17 | B30: 1 | C30: =ROW(SmtRes!A33) -> 33 | D30: =ROW(EtalonRes!A32) -> 32 | E30: 5 | F30: 01-01-087-01 | G30: Засыпка траншей и котлованов с перемещением грунта до 5 м бульдозерами мощностью: 303 кВт (410 л.с.), группа грунтов 1 | H30: 1000 м3 | I30: =ROUND(ROUND(100/1000,5),7) -> 0.1 | J30: 0 | K30: =ROUND(ROUND(100/1000,5),7) -> 0.1 | O30: =ROUND(CP30,2) -> 568.15 | P30: =SUMIF(SmtRes!AQ31:'SmtRes'!AQ33,"=1",SmtRes!DF31:'SmtRes'!DF33) -> 0 | Q30: =SUMIF(SmtRes!AQ31:'SmtRes'!AQ33,"=1",SmtRes!DG31:'SmtRes'!DG33) -> 504.49 | R30: =SUMIF(SmtRes!AQ31:'SmtRes'!AQ33,"=1",SmtRes!DH31:'SmtRes'!DH33) -> 63.66 | S30: =SUMIF(SmtRes!AQ31:'SmtRes'!AQ33,"=1",SmtRes!DI31:'SmtRes'!DI33) -> 0 | T30: =ROUND(CU30*I30,2) -> 0 | U30: =SUMIF(SmtRes!AQ31:'SmtRes'!AQ33,"=1",SmtRes!CV31:'SmtRes'!CV33) -> 0 | V30: =SUMIF(SmtRes!AQ31:'SmtRes'!AQ33,"=1",SmtRes!CW31:'SmtRes'!CW33) -> 0.09 | W30: =ROUND(CX30*I30,2) -> 0 | X30: =ROUND(CY30,2) -> 58.57 | Y30: =ROUND(CZ30,2) -> 29.28 | AA30: 38182922 | AB30: =ROUND((AC30+AD30+AF30),6) -> 5044.932 | AC30: =ROUND((0),6) -> 0 | AD30: =ROUND((((SUM(SmtRes!BR31:'SmtRes'!BR33))-(SUM(SmtRes!BS31:'SmtRes'!BS33)))+AE30),6) -> 5044.932 | AE30: =ROUND((SUM(SmtRes!BS31:'SmtRes'!BS33)),6) -> 636.615 | AF30: =ROUND((0),6) -> 0 | AG30: =ROUND((AP30),6) -> 0 | AH30: =(0) -> 0 | AI30: =(SUM(SmtRes!BV31:'SmtRes'!BV33)) -> 0.9 | AJ30: =(AS30) -> 0 | AK30: 5681.547 | AL30: 0 | AM30: 5044.932 | AN30: 636.615 | AO30: 0 | AP30: 0 | AQ30: 0 | AR30: 0.9 | AS30: 0 | AT30: 92 | AU30: 46 | AV30: 1 | AW30: 1 | AZ30: 1 | BA30: 1 | BB30: 1 | BC30: 1 | BH30: 0 | BI30: 1 | BJ30: ГЭСН-2022, 01-01-087-01, приказ Минстроя России от 18.05.2022 г. № 378/пр | BM30: 1001 | BN30: 0 | BP30: 0 | BQ30: 2 | BR30: 0 | BS30: 1 | BT30: 1 | BU30: 1 | BV30: 1 | BW30: 1 | BX30: 1 | BZ30: 92 | CA30: 46 | CE30: 0 | CF30: 0 | CG30: 0 | CM30: 0 | CO30: 0 | CP30: =(P30+Q30+S30+R30) -> 568.15 | CQ30: =SUMIF(SmtRes!AQ31:'SmtRes'!AQ33,"=1",SmtRes!AA31:'SmtRes'!AA33) -> 0 | CR30: =SUMIF(SmtRes!AQ31:'SmtRes'!AQ33,"=1",SmtRes!AB31:'SmtRes'!AB33) -> 5605.48 | CS30: =SUMIF(SmtRes!AQ31:'SmtRes'!AQ33,"=1",SmtRes!AC31:'SmtRes'!AC33) -> 707.35 | CT30: =SUMIF(SmtRes!AQ31:'SmtRes'!AQ33,"=1",SmtRes!AD31:'SmtRes'!AD33) -> 0 | CU30: =AG30 -> 0 | CV30: =SUMIF(SmtRes!AQ31:'SmtRes'!AQ33,"=1",SmtRes!BU31:'SmtRes'!BU33) -> 0 | CW30: =SUMIF(SmtRes!AQ31:'SmtRes'!AQ33,"=1",SmtRes!BV31:'SmtRes'!BV33) -> 0.9 | CX30: =AJ30 -> 0 | CY30: =(((S30+R30)*AT30)/100) -> 58.5672 | CZ30: =(((S30+R30)*AU30)/100) -> 29.2836 | DN30: 0 | DO30: 0 | DP30: 1 | DQ30: 1 | DU30: 1007 | DV30: 1000 м3 | DW30: 1000 м3 | DX30: 1000 | EE30: 35227734 | EF30: 2 | EG30: Общестроительные работы | EH30: 1 | EI30: Земляные работы | EJ30: 1 | EK30: 1001 | EL30: Земляные работы, выполняемые: механизированным способом | EM30: ФЕР-01 | EQ30: 0 | ER30: 0 | ES30: 0 | ET30: 0 | EU30: 0 | EV30: 0 | EW30: 0 | EX30: 0.9 | EY30: 0 | FQ30: 0 | FR30: 0 | FS30: 0 | FX30: 92 | FY30: 46 | GD30: 1 | GF30: -986908504 | GG30: 2 | GH30: 1 | GI30: -2 | GJ30: 0 | GK30: 0 | GL30: =ROUND(IF(AND(BH30=3,BI30=3,FS30<>0),P30,0),2) -> 0 | GM30: =ROUND(O30+X30+Y30,2)+GX30 -> 656 | GN30: =IF(OR(BI30=0,BI30=1),GM30-GX30,0) -> 656 | GO30: =IF(BI30=2,GM30-GX30,0) -> 0 | GP30: =IF(BI30=4,GM30-GX30,0) -> 0 | GR30: 0 | GS30: 3 | GT30: 0 | GV30: =ROUND((GT30),6) -> 0 | GW30: 1 | GX30: =ROUND(HC30*I30,2) -> 0 | HA30: 0 | HB30: 0 | HC30: =GV30*GW30 -> 0 | HN30: Пр/812-001.1-1 | HO30: Пр/774-001.1 | HP30: Земляные работы, выполняемые: механизированным способом | HQ30: Земляные работы, выполняемые: механизированным способом | HS30: 0 | IK30: 0
A31: 18 | B31: 1 | C31: 33 | E31: 5,1 | F31: 91.01.05-104 | G31: Экскаваторы одноковшовые дизельные на пневмоколесном ходу, объем ковша 0,4 м3 | H31: маш.-ч | I31: =I30*J31 -> 0.09 | J31: 0.9 | K31: 0.9 | O31: =ROUND(CP31,2) -> 175.59 | P31: =ROUND(CQ31*I31,2) -> 0 | Q31: =ROUND(CR31*I31,2) -> 130.82 | R31: =ROUND(CS31*I31,2) -> 44.77 | S31: =ROUND(CT31*I31,2) -> 0 | T31: =ROUND(CU31*I31,2) -> 0 | U31: =ROUND(CV31*I31,7) -> 0 | V31: =ROUND(CW31*I31,7) -> 0.09 | W31: =ROUND(CX31*I31,2) -> 0 | X31: =ROUND(CY31,2) -> 41.19 | Y31: =ROUND(CZ31,2) -> 20.59 | AA31: 38182922 | AB31: =ROUND((AC31+AD31+AF31),6) -> 1162.81 | AC31: =ROUND((ES31),6) -> 0 | AD31: =ROUND((((ET31)-(EU31))+AE31),6) -> 1162.81 | AE31: =ROUND((EU31),6) -> 497.4 | AF31: =ROUND((EV31),6) -> 0 | AG31: =ROUND((AP31),6) -> 0 | AH31: =(EW31) -> 0 | AI31: =(EX31) -> 1 | AJ31: =(AS31) -> 0 | AK31: 1162.81 | AL31: 0 | AM31: 1162.81 | AN31: 497.4 | AO31: 0 | AP31: 0 | AQ31: 0 | AR31: 1 | AS31: 0 | AT31: 92 | AU31: 46 | AV31: 1 | AW31: 1 | AZ31: 1 | BA31: 1 | BB31: 1.25 | BC31: 1 | BH31: 2 | BI31: 1 | BJ31: ФСЭМ-2022, 91.01.05-104, приказ Минстроя России от 18.05.2022 г. № 378/пр | BM31: 1001 | BN31: 0 | BO31: 91.01.05-104 | BP31: 1 | BQ31: 2 | BR31: 0 | BS31: 1 | BT31: 1 | BU31: 1 | BV31: 1 | BW31: 1 | BX31: 1 | BZ31: 92 | CA31: 46 | CE31: 0 | CF31: 0 | CG31: 0 | CM31: 0 | CO31: 0 | CP31: =(P31+Q31+S31+R31) -> 175.59 | CQ31: =ROUND(AL31*BC31,2) -> 0 | CR31: =ROUND(AM31*BB31,2) -> 1453.51 | CS31: =ROUND(AN31*BS31,2) -> 497.4 | CT31: =ROUND(AO31*BA31,2) -> 0 | CU31: =AG31 -> 0 | CV31: =AH31 -> 0 | CW31: =AI31 -> 1 | CX31: =AJ31 -> 0 | CY31: =(((S31+R31)*AT31)/100) -> 41.1884 | CZ31: =(((S31+R31)*AU31)/100) -> 20.5942 | DN31: 0 | DO31: 0 | DP31: 1 | DQ31: 1 | DU31: 1011 | DV31: маш.-ч | DW31: маш.-ч | DX31: 1 | EE31: 35227734 | EF31: 2 | EG31: Общестроительные работы | EH31: 1 | EI31: Земляные работы | EJ31: 1 | EK31: 1001 | EL31: Земляные работы, выполняемые: механизированным способом | EM31: ФЕР-01 | EQ31: 0 | ER31: 1162.81 | ES31: 0 | ET31: 1162.81 | EU31: 497.4 | EV31: 0 | EW31: 0 | EX31: 1 | FQ31: 0 | FR31: 0 | FS31: 1 | FX31: 92 | FY31: 46 | GD31: 1 | GF31: -598721075 | GG31: 2 | GH31: 1 | GI31: 2 | GJ31: 0 | GK31: 0 | GL31: =ROUND(IF(AND(BH31=3,BI31=3,FS31<>0),P31,0),2) -> 0 | GM31: =ROUND(O31+X31+Y31,2)+GX31 -> 237.37 | GN31: =IF(OR(BI31=0,BI31=1),GM31-GX31,0) -> 237.37 | GO31: =IF(BI31=2,GM31-GX31,0) -> 0 | GP31: =IF(BI31=4,GM31-GX31,0) -> 0 | GR31: 0 | GS31: 3 | GT31: 0 | GV31: =ROUND((GT31),6) -> 0 | GW31: 1 | GX31: =ROUND(HC31*I31,2) -> 0 | HA31: 0 | HB31: 0 | HC31: =GV31*GW31 -> 0 | HN31: Пр/812-001.1-1 | HO31: Пр/774-001.1 | HP31: Земляные работы, выполняемые: механизированным способом | HQ31: Земляные работы, выполняемые: механизированным способом | HS31: 0 | IK31: 0
A32: 17 | B32: 1 | C32: =ROW(SmtRes!A34) -> 34 | D32: =ROW(EtalonRes!A33) -> 33 | E32: 6 | F32: 91.01.01-046 | G32: Бульдозеры, мощность 303 кВт (410 л.с.) | H32: маш.-ч | I32: =ROUND(ROUND(-0.09,5),7) -> -0.09 | J32: 0 | K32: =ROUND(ROUND(-0.09,5),7) -> -0.09 | O32: =ROUND(CP32,2) -> -568.15 | P32: =ROUND(CQ32*I32,2) -> 0 | Q32: =ROUND(CR32*I32,2) -> -504.49 | R32: =ROUND(CS32*I32,2) -> -63.66 | S32: =ROUND(CT32*I32,2) -> 0 | T32: =ROUND(CU32*I32,2) -> 0 | U32: =ROUND(CV32*I32,7) -> 0 | V32: =ROUND(CW32*I32,7) -> 0 | W32: =ROUND(CX32*I32,2) -> 0 | X32: =ROUND(CY32,2) -> 0 | Y32: =ROUND(CZ32,2) -> 0 | AA32: 38182922 | AB32: =ROUND((AC32+AD32+AF32),6) -> 5605.48 | AC32: =ROUND((ES32),6) -> 0 | AD32: =ROUND((((ET32)-(EU32))+AE32),6) -> 5605.48 | AE32: =ROUND((EU32),6) -> 707.35 | AF32: =ROUND((EV32),6) -> 0 | AG32: =ROUND((AP32),6) -> 0 | AH32: =(EW32) -> 0 | AI32: =(EX32) -> 0 | AJ32: =(AS32) -> 0 | AK32: 5605.48 | AL32: 0 | AM32: 5605.48 | AN32: 707.35 | AO32: 0 | AP32: 0 | AQ32: 0 | AR32: 0 | AS32: 0 | AT32: 0 | AU32: 0 | AV32: 1 | AW32: 1 | AZ32: 1 | BA32: 1 | BB32: 1 | BC32: 1 | BH32: 2 | BI32: 1 | BJ32: ФСЭМ-2022, 91.01.01-046, приказ Минстроя России от 18.05.2022 г. № 378/пр | BM32: 400001 | BN32: 0 | BP32: 0 | BQ32: 7 | BR32: 0 | BS32: 1 | BT32: 1 | BU32: 1 | BV32: 1 | BW32: 1 | BX32: 1 | BZ32: 0 | CA32: 0 | CE32: 0 | CF32: 0 | CG32: 0 | CM32: 0 | CO32: 0 | CP32: =(P32+Q32+S32+R32) -> -568.15 | CQ32: =ROUND(AL32*BC32,2) -> 0 | CR32: =ROUND(AM32*BB32,2) -> 5605.48 | CS32: =ROUND(AN32*BS32,2) -> 707.35 | CT32: =ROUND(AO32*BA32,2) -> 0 | CU32: =AG32 -> 0 | CV32: =AH32 -> 0 | CW32: =AI32 -> 0 | CX32: =AJ32 -> 0 | CY32: =(((S32+R32)*AT32)/100) -> 0 | CZ32: =(((S32+R32)*AU32)/100) -> 0 | DN32: 0 | DO32: 0 | DP32: 1 | DQ32: 1 | DU32: 1011 | DV32: маш.-ч | DW32: маш.-ч | DX32: 1 | EE32: 35227692 | EF32: 7 | EG32: Машины и механизмы | EH32: 0 | EJ32: 1 | EK32: 400001 | EL32: Эксплуатация машин и механизмов ( ценники на ЭММ ) | EM32: ЭММ | EQ32: 0 | ER32: 5605.48 | ES32: 0 | ET32: 5605.48 | EU32: 707.35 | EV32: 0 | EW32: 0 | EX32: 0 | EY32: 0 | FQ32: 0 | FR32: 0 | FS32: 1 | FX32: 0 | FY32: 0 | GD32: 1 | GF32: 626856282 | GG32: 2 | GH32: 1 | GI32: -2 | GJ32: 0 | GK32: 0 | GL32: =ROUND(IF(AND(BH32=3,BI32=3,FS32<>0),P32,0),2) -> 0 | GM32: =ROUND(O32+X32+Y32,2)+GX32 -> -568.15 | GN32: =IF(OR(BI32=0,BI32=1),GM32-GX32,0) -> -568.15 | GO32: =IF(BI32=2,GM32-GX32,0) -> 0 | GP32: =IF(BI32=4,GM32-GX32,0) -> 0 | GR32: 0 | GS32: 7 | GT32: 0 | GV32: =ROUND((GT32),6) -> 0 | GW32: 1 | GX32: =ROUND(HC32*I32,2) -> 0 | HA32: 0 | HB32: 0 | HC32: =GV32*GW32 -> 0 | HS32: 0 | IK32: 0
A33: 17 | B33: 1 | C33: =ROW(SmtRes!A45) -> 45 | D33: =ROW(EtalonRes!A44) -> 44 | E33: 7 | F33: 22-02-011-16 | G33: Нанесение нормальной антикоррозионной изоляции из полимерных липких лент на стыки и фасонные части стальных трубопроводов диаметром: 1000 мм | H33: км | I33: =ROUND(ROUND(0.001,5),7) -> 0.001 | J33: 0 | K33: =ROUND(ROUND(0.001,5),7) -> 0.001 | O33: =ROUND(CP33,2) -> 205.73 | P33: =SUMIF(SmtRes!AQ35:'SmtRes'!AQ45,"=1",SmtRes!DF35:'SmtRes'!DF45) -> 67.9 | Q33: =SUMIF(SmtRes!AQ35:'SmtRes'!AQ45,"=1",SmtRes!DG35:'SmtRes'!DG45) -> 62.05 | R33: =SUMIF(SmtRes!AQ35:'SmtRes'!AQ45,"=1",SmtRes!DH35:'SmtRes'!DH45) -> 13.38 | S33: =SUMIF(SmtRes!AQ35:'SmtRes'!AQ45,"=1",SmtRes!DI35:'SmtRes'!DI45) -> 62.4 | T33: =ROUND(CU33*I33,2) -> 0 | U33: =SUMIF(SmtRes!AQ35:'SmtRes'!AQ45,"=1",SmtRes!CV35:'SmtRes'!CV45) -> 0.14 | V33: =SUMIF(SmtRes!AQ35:'SmtRes'!AQ45,"=1",SmtRes!CW35:'SmtRes'!CW45) -> 0.02317 | W33: =ROUND(CX33*I33,2) -> 0 | X33: =ROUND(CY33,2) -> 88.66 | Y33: =ROUND(CZ33,2) -> 56.08 | AA33: 38182922 | AB33: =ROUND((AC33+AD33+AF33),6) -> 153692.63 | AC33: =ROUND((SUM(SmtRes!BQ35:'SmtRes'!BQ45)),6) -> 35668.289 | AD33: =ROUND((((SUM(SmtRes!BR35:'SmtRes'!BR45))-(SUM(SmtRes!BS35:'SmtRes'!BS45)))+AE33),6) -> 55622.144 | AE33: =ROUND((SUM(SmtRes!BS35:'SmtRes'!BS45)),6) -> 13372.105 | AF33: =ROUND((SUM(SmtRes!BT35:'SmtRes'!BT45)),6) -> 62402.2 | AG33: =ROUND((AP33),6) -> 0 | AH33: =(SUM(SmtRes!BU35:'SmtRes'!BU45)) -> 140 | AI33: =(SUM(SmtRes!BV35:'SmtRes'!BV45)) -> 23.17 | AJ33: =(AS33) -> 0 | AK33: 167064.74 | AL33: 35668.289 | AM33: 55622.144 | AN33: 13372.105 | AO33: 62402.2 | AP33: 0 | AQ33: 140 | AR33: 23.17 | AS33: 0 | AT33: 117 | AU33: 74 | AV33: 1 | AW33: 1 | AZ33: 1 | BA33: 1 | BB33: 1 | BC33: 1 | BH33: 0 | BI33: 1 | BJ33: ГЭСН-2022 доп.7, 22-02-011-16, приказ Минстроя России от 02.08.2023 г. № 551/пр | BM33: 22001 | BN33: 0 | BP33: 0 | BQ33: 2 | BR33: 0 | BS33: 1 | BT33: 1 | BU33: 1 | BV33: 1 | BW33: 1 | BX33: 1 | BZ33: 117 | CA33: 74 | CE33: 0 | CF33: 0 | CG33: 0 | CM33: 0 | CO33: 0 | CP33: =(P33+Q33+S33+R33) -> 205.73 | CQ33: =SUMIF(SmtRes!AQ35:'SmtRes'!AQ45,"=1",SmtRes!AA35:'SmtRes'!AA45) -> 687271.95 | CR33: =SUMIF(SmtRes!AQ35:'SmtRes'!AQ45,"=1",SmtRes!AB35:'SmtRes'!AB45) -> 5715.22 | CS33: =SUMIF(SmtRes!AQ35:'SmtRes'!AQ45,"=1",SmtRes!AC35:'SmtRes'!AC45) -> 1572.97 | CT33: =SUMIF(SmtRes!AQ35:'SmtRes'!AQ45,"=1",SmtRes!AD35:'SmtRes'!AD45) -> 445.73 | CU33: =AG33 -> 0 | CV33: =SUMIF(SmtRes!AQ35:'SmtRes'!AQ45,"=1",SmtRes!BU35:'SmtRes'!BU45) -> 140 | CW33: =SUMIF(SmtRes!AQ35:'SmtRes'!AQ45,"=1",SmtRes!BV35:'SmtRes'!BV45) -> 23.17 | CX33: =AJ33 -> 0 | CY33: =(((S33+R33)*AT33)/100) -> 88.6626 | CZ33: =(((S33+R33)*AU33)/100) -> 56.0772 | DN33: 0 | DO33: 0 | DP33: 1 | DQ33: 1 | DU33: 1003 | DV33: км | DW33: км | DX33: 1000 | EE33: 35227793 | EF33: 2 | EG33: Общестроительные работы | EH33: 18 | EI33: Наружные сети водопровода, канализации, теплоснабжения, газопроводы | EJ33: 1 | EK33: 22001 | EL33: Наружные сети водопровода, канализации, теплоснабжения, газопроводы | EM33: ФЕР-22 | EQ33: 0 | ER33: 0 | ES33: 0 | ET33: 0 | EU33: 0 | EV33: 0 | EW33: 140 | EX33: 23.17 | EY33: 0 | FQ33: 0 | FR33: 0 | FS33: 0 | FX33: 117 | FY33: 74 | GD33: 1 | GF33: -1861455940 | GG33: 2 | GH33: 1 | GI33: -2 | GJ33: 0 | GK33: 0 | GL33: =ROUND(IF(AND(BH33=3,BI33=3,FS33<>0),P33,0),2) -> 0 | GM33: =ROUND(O33+X33+Y33,2)+GX33 -> 350.47 | GN33: =IF(OR(BI33=0,BI33=1),GM33-GX33,0) -> 350.47 | GO33: =IF(BI33=2,GM33-GX33,0) -> 0 | GP33: =IF(BI33=4,GM33-GX33,0) -> 0 | GR33: 0 | GS33: 3 | GT33: 0 | GV33: =ROUND((GT33),6) -> 0 | GW33: 1 | GX33: =ROUND(HC33*I33,2) -> 0 | HA33: 0 | HB33: 0 | HC33: =GV33*GW33 -> 0 | HN33: Пр/812-018.0-1 | HO33: Пр/774-018.0 | HP33: Наружные сети водопровода, канализации, теплоснабжения, газопроводы | HQ33: Наружные сети водопровода, канализации, теплоснабжения, газопроводы | HS33: 0 | IK33: 0
A34: 18 | B34: 1 | C34: 45 | E34: 7,1 | F34: 14.4.01.15-1002 | G34: Грунтовка полимерная для повышения адгезии битумно-полимерных мастик и герметиков при герметизации деформационных швов асфальтобетонных и цементобетонных покрытий | H34: т | I34: =I33*J34 -> 0.001 | J34: 1 | K34: 1 | O34: =ROUND(CP34,2) -> 522.98 | P34: =ROUND(CQ34*I34,2) -> 522.98 | Q34: =ROUND(CR34*I34,2) -> 0 | R34: =ROUND(CS34*I34,2) -> 0 | S34: =ROUND(CT34*I34,2) -> 0 | T34: =ROUND(CU34*I34,2) -> 0 | U34: =ROUND(CV34*I34,7) -> 0 | V34: =ROUND(CW34*I34,7) -> 0 | W34: =ROUND(CX34*I34,2) -> 0 | X34: =ROUND(CY34,2) -> 0 | Y34: =ROUND(CZ34,2) -> 0 | AA34: 38182922 | AB34: =ROUND((AC34+AD34+AF34),6) -> 411791.94 | AC34: =ROUND((ES34),6) -> 411791.94 | AD34: =ROUND((((ET34)-(EU34))+AE34),6) -> 0 | AE34: =ROUND((EU34),6) -> 0 | AF34: =ROUND((EV34),6) -> 0 | AG34: =ROUND((AP34),6) -> 0 | AH34: =(EW34) -> 0 | AI34: =(EX34) -> 0 | AJ34: =(AS34) -> 0 | AK34: 411791.94 | AL34: 411791.94 | AM34: 0 | AN34: 0 | AO34: 0 | AP34: 0 | AQ34: 0 | AR34: 0 | AS34: 0 | AT34: 117 | AU34: 74 | AV34: 1 | AW34: 1 | AZ34: 1 | BA34: 1 | BB34: 1 | BC34: 1.27 | BH34: 3 | BI34: 1 | BJ34: ФСБЦ-2022, 14.4.01.15-1002, приказ Минстроя России от 18.05.2022 г. № 378/пр | BM34: 22001 | BN34: 0 | BO34: 14.4.01.15-1002 | BP34: 1 | BQ34: 2 | BR34: 0 | BS34: 1 | BT34: 1 | BU34: 1 | BV34: 1 | BW34: 1 | BX34: 1 | BZ34: 117 | CA34: 74 | CE34: 0 | CF34: 0 | CG34: 0 | CM34: 0 | CO34: 0 | CP34: =(P34+Q34+S34+R34) -> 522.98 | CQ34: =ROUND(AL34*BC34,2) -> 522975.76 | CR34: =ROUND(AM34*BB34,2) -> 0 | CS34: =ROUND(AN34*BS34,2) -> 0 | CT34: =ROUND(AO34*BA34,2) -> 0 | CU34: =AG34 -> 0 | CV34: =AH34 -> 0 | CW34: =AI34 -> 0 | CX34: =AJ34 -> 0 | CY34: =(((S34+R34)*AT34)/100) -> 0 | CZ34: =(((S34+R34)*AU34)/100) -> 0 | DN34: 0 | DO34: 0 | DP34: 1 | DQ34: 1 | DU34: 1009 | DV34: т | DW34: т | DX34: 1000 | EE34: 35227793 | EF34: 2 | EG34: Общестроительные работы | EH34: 18 | EI34: Наружные сети водопровода, канализации, теплоснабжения, газопроводы | EJ34: 1 | EK34: 22001 | EL34: Наружные сети водопровода, канализации, теплоснабжения, газопроводы | EM34: ФЕР-22 | EQ34: 0 | ER34: 411791.94 | ES34: 411791.94 | ET34: 0 | EU34: 0 | EV34: 0 | EW34: 0 | EX34: 0 | FQ34: 0 | FR34: 0 | FS34: 0 | FX34: 117 | FY34: 74 | GD34: 1 | GF34: 7353553 | GG34: 2 | GH34: 1 | GI34: 2 | GJ34: 0 | GK34: 0 | GL34: =ROUND(IF(AND(BH34=3,BI34=3,FS34<>0),P34,0),2) -> 0 | GM34: =ROUND(O34+X34+Y34,2)+GX34 -> 522.98 | GN34: =IF(OR(BI34=0,BI34=1),GM34-GX34,0) -> 522.98 | GO34: =IF(BI34=2,GM34-GX34,0) -> 0 | GP34: =IF(BI34=4,GM34-GX34,0) -> 0 | GR34: 0 | GS34: 3 | GT34: 0 | GV34: =ROUND((GT34),6) -> 0 | GW34: 1 | GX34: =ROUND(HC34*I34,2) -> 0 | HA34: 0 | HB34: 0 | HC34: =GV34*GW34 -> 0 | HN34: Пр/812-018.0-1 | HO34: Пр/774-018.0 | HP34: Наружные сети водопровода, канализации, теплоснабжения, газопроводы | HQ34: Наружные сети водопровода, канализации, теплоснабжения, газопроводы | HS34: 0 | IK34: 0
A35: 18 | B35: 1 | C35: 43 | E35: 7,2 | F35: 12.1.02.15-0041 | G35: Материал рулонный гидроизоляционный изол, резино-битумный, без полимерных добавок | H35: м2 | I35: =I33*J35 -> 0.85 | J35: 850 | K35: 850 | O35: =ROUND(CP35,2) -> 146.89 | P35: =ROUND(CQ35*I35,2) -> 146.89 | Q35: =ROUND(CR35*I35,2) -> 0 | R35: =ROUND(CS35*I35,2) -> 0 | S35: =ROUND(CT35*I35,2) -> 0 | T35: =ROUND(CU35*I35,2) -> 0 | U35: =ROUND(CV35*I35,7) -> 0 | V35: =ROUND(CW35*I35,7) -> 0 | W35: =ROUND(CX35*I35,2) -> 0 | X35: =ROUND(CY35,2) -> 0 | Y35: =ROUND(CZ35,2) -> 0 | AA35: 38182922 | AB35: =ROUND((AC35+AD35+AF35),6) -> 126.14 | AC35: =ROUND((ES35),6) -> 126.14 | AD35: =ROUND((((ET35)-(EU35))+AE35),6) -> 0 | AE35: =ROUND((EU35),6) -> 0 | AF35: =ROUND((EV35),6) -> 0 | AG35: =ROUND((AP35),6) -> 0 | AH35: =(EW35) -> 0 | AI35: =(EX35) -> 0 | AJ35: =(AS35) -> 0 | AK35: 126.14 | AL35: 126.14 | AM35: 0 | AN35: 0 | AO35: 0 | AP35: 0 | AQ35: 0 | AR35: 0 | AS35: 0 | AT35: 117 | AU35: 74 | AV35: 1 | AW35: 1 | AZ35: 1 | BA35: 1 | BB35: 1 | BC35: 1.37 | BH35: 3 | BI35: 1 | BJ35: ФСБЦ-2022, 12.1.02.15-0041, приказ Минстроя России от 18.05.2022 г. № 378/пр | BM35: 22001 | BN35: 0 | BO35: 12.1.02.15-0041 | BP35: 1 | BQ35: 2 | BR35: 0 | BS35: 1 | BT35: 1 | BU35: 1 | BV35: 1 | BW35: 1 | BX35: 1 | BZ35: 117 | CA35: 74 | CE35: 0 | CF35: 0 | CG35: 0 | CM35: 0 | CO35: 0 | CP35: =(P35+Q35+S35+R35) -> 146.89 | CQ35: =ROUND(AL35*BC35,2) -> 172.81 | CR35: =ROUND(AM35*BB35,2) -> 0 | CS35: =ROUND(AN35*BS35,2) -> 0 | CT35: =ROUND(AO35*BA35,2) -> 0 | CU35: =AG35 -> 0 | CV35: =AH35 -> 0 | CW35: =AI35 -> 0 | CX35: =AJ35 -> 0 | CY35: =(((S35+R35)*AT35)/100) -> 0 | CZ35: =(((S35+R35)*AU35)/100) -> 0 | DN35: 0 | DO35: 0 | DP35: 1 | DQ35: 1 | DU35: 1005 | DV35: м2 | DW35: м2 | DX35: 1 | EE35: 35227793 | EF35: 2 | EG35: Общестроительные работы | EH35: 18 | EI35: Наружные сети водопровода, канализации, теплоснабжения, газопроводы | EJ35: 1 | EK35: 22001 | EL35: Наружные сети водопровода, канализации, теплоснабжения, газопроводы | EM35: ФЕР-22 | EQ35: 0 | ER35: 126.14 | ES35: 126.14 | ET35: 0 | EU35: 0 | EV35: 0 | EW35: 0 | EX35: 0 | FQ35: 0 | FR35: 0 | FS35: 0 | FX35: 117 | FY35: 74 | GD35: 1 | GF35: -848550540 | GG35: 2 | GH35: 1 | GI35: 2 | GJ35: 0 | GK35: 0 | GL35: =ROUND(IF(AND(BH35=3,BI35=3,FS35<>0),P35,0),2) -> 0 | GM35: =ROUND(O35+X35+Y35,2)+GX35 -> 146.89 | GN35: =IF(OR(BI35=0,BI35=1),GM35-GX35,0) -> 146.89 | GO35: =IF(BI35=2,GM35-GX35,0) -> 0 | GP35: =IF(BI35=4,GM35-GX35,0) -> 0 | GR35: 0 | GS35: 3 | GT35: 0 | GV35: =ROUND((GT35),6) -> 0 | GW35: 1 | GX35: =ROUND(HC35*I35,2) -> 0 | HA35: 0 | HB35: 0 | HC35: =GV35*GW35 -> 0 | HN35: Пр/812-018.0-1 | HO35: Пр/774-018.0 | HP35: Наружные сети водопровода, канализации, теплоснабжения, газопроводы | HQ35: Наружные сети водопровода, канализации, теплоснабжения, газопроводы | HS35: 0 | IK35: 0
A36: 17 | B36: 1 | C36: =ROW(SmtRes!A49) -> 49 | D36: =ROW(EtalonRes!A48) -> 48 | E36: 8 | F36: 01-02-005-01 | G36: Уплотнение грунта пневматическими трамбовками, группа грунтов: 1-2 | H36: 100 м3 | I36: =ROUND(ROUND(45/100,5),7) -> 0.45 | J36: 0 | K36: =ROUND(ROUND(45/100,5),7) -> 0.45 | O36: =ROUND(CP36,2) -> 3175.26 | P36: =SUMIF(SmtRes!AQ46:'SmtRes'!AQ49,"=1",SmtRes!DF46:'SmtRes'!DF49) -> 0 | Q36: =SUMIF(SmtRes!AQ46:'SmtRes'!AQ49,"=1",SmtRes!DG46:'SmtRes'!DG49) -> 497.77 | R36: =SUMIF(SmtRes!AQ46:'SmtRes'!AQ49,"=1",SmtRes!DH46:'SmtRes'!DH49) -> 510.28 | S36: =SUMIF(SmtRes!AQ46:'SmtRes'!AQ49,"=1",SmtRes!DI46:'SmtRes'!DI49) -> 2167.21 | T36: =ROUND(CU36*I36,2) -> 0 | U36: =SUMIF(SmtRes!AQ46:'SmtRes'!AQ49,"=1",SmtRes!CV46:'SmtRes'!CV49) -> 5.6385 | V36: =SUMIF(SmtRes!AQ46:'SmtRes'!AQ49,"=1",SmtRes!CW46:'SmtRes'!CW49) -> 1.179 | W36: =ROUND(CX36*I36,2) -> 0 | X36: =ROUND(CY36,2) -> 2463.29 | Y36: =ROUND(CZ36,2) -> 1231.65 | AA36: 38182922 | AB36: =ROUND((AC36+AD36+AF36),6) -> 5919.1252 | AC36: =ROUND((0),6) -> 0 | AD36: =ROUND((((SUM(SmtRes!BR46:'SmtRes'!BR49))-(SUM(SmtRes!BS46:'SmtRes'!BS49)))+AE36),6) -> 1103.0944 | AE36: =ROUND((SUM(SmtRes!BS46:'SmtRes'!BS49)),6) -> 1133.9622 | AF36: =ROUND((SUM(SmtRes!BT46:'SmtRes'!BT49)),6) -> 4816.0308 | AG36: =ROUND((AP36),6) -> 0 | AH36: =(SUM(SmtRes!BU46:'SmtRes'!BU49)) -> 12.53 | AI36: =(SUM(SmtRes!BV46:'SmtRes'!BV49)) -> 2.62 | AJ36: =(AS36) -> 0 | AK36: 7053.0874 | AL36: 0 | AM36: 1103.0944 | AN36: 1133.9622 | AO36: 4816.0308 | AP36: 0 | AQ36: 12.53 | AR36: 2.62 | AS36: 0 | AT36: 92 | AU36: 46 | AV36: 1 | AW36: 1 | AZ36: 1 | BA36: 1 | BB36: 1 | BC36: 1 | BH36: 0 | BI36: 1 | BJ36: ГЭСН-2022 доп.4, 01-02-005-01, приказ Минстроя России от 27.12.2022 г. № 1133/пр | BM36: 1001 | BN36: 0 | BP36: 0 | BQ36: 2 | BR36: 0 | BS36: 1 | BT36: 1 | BU36: 1 | BV36: 1 | BW36: 1 | BX36: 1 | BZ36: 92 | CA36: 46 | CE36: 0 | CF36: 0 | CG36: 0 | CM36: 0 | CO36: 0 | CP36: =(P36+Q36+S36+R36) -> 3175.26 | CQ36: =SUMIF(SmtRes!AQ46:'SmtRes'!AQ49,"=1",SmtRes!AA46:'SmtRes'!AA49) -> 0 | CR36: =SUMIF(SmtRes!AQ46:'SmtRes'!AQ49,"=1",SmtRes!AB46:'SmtRes'!AB49) -> 414.07 | CS36: =SUMIF(SmtRes!AQ46:'SmtRes'!AQ49,"=1",SmtRes!AC46:'SmtRes'!AC49) -> 432.81 | CT36: =SUMIF(SmtRes!AQ46:'SmtRes'!AQ49,"=1",SmtRes!AD46:'SmtRes'!AD49) -> 384.36 | CU36: =AG36 -> 0 | CV36: =SUMIF(SmtRes!AQ46:'SmtRes'!AQ49,"=1",SmtRes!BU46:'SmtRes'!BU49) -> 12.53 | CW36: =SUMIF(SmtRes!AQ46:'SmtRes'!AQ49,"=1",SmtRes!BV46:'SmtRes'!BV49) -> 2.62 | CX36: =AJ36 -> 0 | CY36: =(((S36+R36)*AT36)/100) -> 2463.2908 | CZ36: =(((S36+R36)*AU36)/100) -> 1231.6454 | DN36: 0 | DO36: 0 | DP36: 1 | DQ36: 1 | DU36: 1007 | DV36: 100 м3 | DW36: 100 м3 | DX36: 100 | EE36: 35227734 | EF36: 2 | EG36: Общестроительные работы | EH36: 1 | EI36: Земляные работы | EJ36: 1 | EK36: 1001 | EL36: Земляные работы, выполняемые: механизированным способом | EM36: ФЕР-01 | EQ36: 0 | ER36: 0 | ES36: 0 | ET36: 0 | EU36: 0 | EV36: 0 | EW36: 12.53 | EX36: 2.62 | EY36: 0 | FQ36: 0 | FR36: 0 | FS36: 0 | FX36: 92 | FY36: 46 | GD36: 1 | GF36: -719184649 | GG36: 2 | GH36: 1 | GI36: -2 | GJ36: 0 | GK36: 0 | GL36: =ROUND(IF(AND(BH36=3,BI36=3,FS36<>0),P36,0),2) -> 0 | GM36: =ROUND(O36+X36+Y36,2)+GX36 -> 6870.2 | GN36: =IF(OR(BI36=0,BI36=1),GM36-GX36,0) -> 6870.2 | GO36: =IF(BI36=2,GM36-GX36,0) -> 0 | GP36: =IF(BI36=4,GM36-GX36,0) -> 0 | GR36: 0 | GS36: 3 | GT36: 0 | GV36: =ROUND((GT36),6) -> 0 | GW36: 1 | GX36: =ROUND(HC36*I36,2) -> 0 | HA36: 0 | HB36: 0 | HC36: =GV36*GW36 -> 0 | HN36: Пр/812-001.1-1 | HO36: Пр/774-001.1 | HP36: Земляные работы, выполняемые: механизированным способом | HQ36: Земляные работы, выполняемые: механизированным способом | HS36: 0 | IK36: 0
A37: 17 | B37: 1 | C37: =ROW(SmtRes!A55) -> 55 | D37: =ROW(EtalonRes!A53) -> 53 | E37: 9 | F37: 27-02-027-02 | G37: Устройство обратной засыпки труб ливневой канализации | H37: 10 м3 | I37: =ROUND(ROUND(45/10,5),7) -> 4.5 | J37: 0 | K37: =ROUND(ROUND(45/10,5),7) -> 4.5 | O37: =ROUND(CP37,2) -> 55891.93 | P37: =SUMIF(SmtRes!AQ50:'SmtRes'!AQ55,"=1",SmtRes!DF50:'SmtRes'!DF55) -> 43419.45 | Q37: =SUMIF(SmtRes!AQ50:'SmtRes'!AQ55,"=1",SmtRes!DG50:'SmtRes'!DG55) -> 7134.51 | R37: =SUMIF(SmtRes!AQ50:'SmtRes'!AQ55,"=1",SmtRes!DH50:'SmtRes'!DH55) -> 2120.88 | S37: =SUMIF(SmtRes!AQ50:'SmtRes'!AQ55,"=1",SmtRes!DI50:'SmtRes'!DI55) -> 3217.09 | T37: =ROUND(CU37*I37,2) -> 0 | U37: =SUMIF(SmtRes!AQ50:'SmtRes'!AQ55,"=1",SmtRes!CV50:'SmtRes'!CV55) -> 8.37 | V37: =SUMIF(SmtRes!AQ50:'SmtRes'!AQ55,"=1",SmtRes!CW50:'SmtRes'!CW55) -> 3.42 | W37: =ROUND(CX37*I37,2) -> 0 | X37: =ROUND(CY37,2) -> 7846.82 | Y37: =ROUND(CZ37,2) -> 7152.88 | AA37: 38182922 | AB37: =ROUND((AC37+AD37+AF37),6) -> 11578.313 | AC37: =ROUND((SUM(SmtRes!BQ50:'SmtRes'!BQ55)),6) -> 9648.7664 | AD37: =ROUND((((SUM(SmtRes!BR50:'SmtRes'!BR55))-(SUM(SmtRes!BS50:'SmtRes'!BS55)))+AE37),6) -> 1214.6367 | AE37: =ROUND((SUM(SmtRes!BS50:'SmtRes'!BS55)),6) -> 471.3064 | AF37: =ROUND((SUM(SmtRes!BT50:'SmtRes'!BT55)),6) -> 714.9096 | AG37: =ROUND((AP37),6) -> 0 | AH37: =(SUM(SmtRes!BU50:'SmtRes'!BU55)) -> 1.86 | AI37: =(SUM(SmtRes!BV50:'SmtRes'!BV55)) -> 0.76 | AJ37: =(AS37) -> 0 | AK37: 12049.619 | AL37: 9648.7664 | AM37: 1214.6367 | AN37: 471.3064 | AO37: 714.9096 | AP37: 0 | AQ37: 1.86 | AR37: 0.76 | AS37: 0 | AT37: 147 | AU37: 134 | AV37: 1 | AW37: 1 | AZ37: 1 | BA37: 1 | BB37: 1 | BC37: 1 | BH37: 0 | BI37: 1 | BJ37: ГЭСН-2022 доп.15, 27-02-027-02, приказ Минстроя России от 14.08.2025 г. № 490/пр | BM37: 27001 | BN37: 0 | BP37: 0 | BQ37: 2 | BR37: 0 | BS37: 1 | BT37: 1 | BU37: 1 | BV37: 1 | BW37: 1 | BX37: 1 | BZ37: 147 | CA37: 134 | CE37: 0 | CF37: 0 | CG37: 0 | CM37: 0 | CO37: 0 | CP37: =(P37+Q37+S37+R37) -> 55891.93 | CQ37: =SUMIF(SmtRes!AQ50:'SmtRes'!AQ55,"=1",SmtRes!AA50:'SmtRes'!AA55) -> 757.36 | CR37: =SUMIF(SmtRes!AQ50:'SmtRes'!AQ55,"=1",SmtRes!AB50:'SmtRes'!AB55) -> 2065.82 | CS37: =SUMIF(SmtRes!AQ50:'SmtRes'!AQ55,"=1",SmtRes!AC50:'SmtRes'!AC55) -> 620.14 | CT37: =SUMIF(SmtRes!AQ50:'SmtRes'!AQ55,"=1",SmtRes!AD50:'SmtRes'!AD55) -> 384.36 | CU37: =AG37 -> 0 | CV37: =SUMIF(SmtRes!AQ50:'SmtRes'!AQ55,"=1",SmtRes!BU50:'SmtRes'!BU55) -> 1.86 | CW37: =SUMIF(SmtRes!AQ50:'SmtRes'!AQ55,"=1",SmtRes!BV50:'SmtRes'!BV55) -> 0.76 | CX37: =AJ37 -> 0 | CY37: =(((S37+R37)*AT37)/100) -> 7846.8159 | CZ37: =(((S37+R37)*AU37)/100) -> 7152.8798 | DN37: 0 | DO37: 0 | DP37: 1 | DQ37: 1 | DU37: 1007 | DV37: 10 м3 | DW37: 10 м3 | DX37: 10 | EE37: 35227801 | EF37: 2 | EG37: Общестроительные работы | EH37: 21 | EI37: Автомобильные дороги | EJ37: 1 | EK37: 27001 | EL37: Автомобильные дороги | EM37: ФЕР-27 | EQ37: 0 | ER37: 0 | ES37: 0 | ET37: 0 | EU37: 0 | EV37: 0 | EW37: 1.86 | EX37: 0.76 | EY37: 0 | FQ37: 0 | FR37: 0 | FS37: 0 | FX37: 147 | FY37: 134 | GD37: 1 | GF37: 1906472589 | GG37: 2 | GH37: 1 | GI37: -2 | GJ37: 0 | GK37: 0 | GL37: =ROUND(IF(AND(BH37=3,BI37=3,FS37<>0),P37,0),2) -> 0 | GM37: =ROUND(O37+X37+Y37,2)+GX37 -> 70891.63 | GN37: =IF(OR(BI37=0,BI37=1),GM37-GX37,0) -> 70891.63 | GO37: =IF(BI37=2,GM37-GX37,0) -> 0 | GP37: =IF(BI37=4,GM37-GX37,0) -> 0 | GR37: 0 | GS37: 3 | GT37: 0 | GV37: =ROUND((GT37),6) -> 0 | GW37: 1 | GX37: =ROUND(HC37*I37,2) -> 0 | HA37: 0 | HB37: 0 | HC37: =GV37*GW37 -> 0 | HN37: Пр/812-021.0-1 | HO37: Пр/774-021.0 | HP37: Автомобильные дороги | HQ37: Автомобильные дороги | HS37: 0 | IK37: 0
A38: 18 | B38: 1 | C38: 53 | E38: 9,1 | F38: 91.01.05-104 | G38: Экскаваторы одноковшовые дизельные на пневмоколесном ходу, объем ковша 0,4 м3 | H38: маш.-ч | I38: =I37*J38 -> 3.42 | J38: 0.76 | K38: 0.76 | O38: =ROUND(CP38,2) -> 6672.11 | P38: =ROUND(CQ38*I38,2) -> 0 | Q38: =ROUND(CR38*I38,2) -> 4971 | R38: =ROUND(CS38*I38,2) -> 1701.11 | S38: =ROUND(CT38*I38,2) -> 0 | T38: =ROUND(CU38*I38,2) -> 0 | U38: =ROUND(CV38*I38,7) -> 0 | V38: =ROUND(CW38*I38,7) -> 3.42 | W38: =ROUND(CX38*I38,2) -> 0 | X38: =ROUND(CY38,2) -> 2500.63 | Y38: =ROUND(CZ38,2) -> 2279.49 | AA38: 38182922 | AB38: =ROUND((AC38+AD38+AF38),6) -> 1162.81 | AC38: =ROUND((ES38),6) -> 0 | AD38: =ROUND((((ET38)-(EU38))+AE38),6) -> 1162.81 | AE38: =ROUND((EU38),6) -> 497.4 | AF38: =ROUND((EV38),6) -> 0 | AG38: =ROUND((AP38),6) -> 0 | AH38: =(EW38) -> 0 | AI38: =(EX38) -> 1 | AJ38: =(AS38) -> 0 | AK38: 1162.81 | AL38: 0 | AM38: 1162.81 | AN38: 497.4 | AO38: 0 | AP38: 0 | AQ38: 0 | AR38: 1 | AS38: 0 | AT38: 147 | AU38: 134 | AV38: 1 | AW38: 1 | AZ38: 1 | BA38: 1 | BB38: 1.25 | BC38: 1 | BH38: 2 | BI38: 1 | BJ38: ФСЭМ-2022, 91.01.05-104, приказ Минстроя России от 18.05.2022 г. № 378/пр | BM38: 27001 | BN38: 0 | BO38: 91.01.05-104 | BP38: 1 | BQ38: 2 | BR38: 0 | BS38: 1 | BT38: 1 | BU38: 1 | BV38: 1 | BW38: 1 | BX38: 1 | BZ38: 147 | CA38: 134 | CE38: 0 | CF38: 0 | CG38: 0 | CM38: 0 | CO38: 0 | CP38: =(P38+Q38+S38+R38) -> 6672.11 | CQ38: =ROUND(AL38*BC38,2) -> 0 | CR38: =ROUND(AM38*BB38,2) -> 1453.51 | CS38: =ROUND(AN38*BS38,2) -> 497.4 | CT38: =ROUND(AO38*BA38,2) -> 0 | CU38: =AG38 -> 0 | CV38: =AH38 -> 0 | CW38: =AI38 -> 1 | CX38: =AJ38 -> 0 | CY38: =(((S38+R38)*AT38)/100) -> 2500.6317 | CZ38: =(((S38+R38)*AU38)/100) -> 2279.4874 | DN38: 0 | DO38: 0 | DP38: 1 | DQ38: 1 | DU38: 1011 | DV38: маш.-ч | DW38: маш.-ч | DX38: 1 | EE38: 35227801 | EF38: 2 | EG38: Общестроительные работы | EH38: 21 | EI38: Автомобильные дороги | EJ38: 1 | EK38: 27001 | EL38: Автомобильные дороги | EM38: ФЕР-27 | EQ38: 0 | ER38: 1162.81 | ES38: 0 | ET38: 1162.81 | EU38: 497.4 | EV38: 0 | EW38: 0 | EX38: 1 | FQ38: 0 | FR38: 0 | FS38: 1 | FX38: 147 | FY38: 134 | GD38: 1 | GF38: -598721075 | GG38: 2 | GH38: 1 | GI38: 2 | GJ38: 0 | GK38: 0 | GL38: =ROUND(IF(AND(BH38=3,BI38=3,FS38<>0),P38,0),2) -> 0 | GM38: =ROUND(O38+X38+Y38,2)+GX38 -> 11452.23 | GN38: =IF(OR(BI38=0,BI38=1),GM38-GX38,0) -> 11452.23 | GO38: =IF(BI38=2,GM38-GX38,0) -> 0 | GP38: =IF(BI38=4,GM38-GX38,0) -> 0 | GR38: 0 | GS38: 3 | GT38: 0 | GV38: =ROUND((GT38),6) -> 0 | GW38: 1 | GX38: =ROUND(HC38*I38,2) -> 0 | HA38: 0 | HB38: 0 | HC38: =GV38*GW38 -> 0 | HN38: Пр/812-021.0-1 | HO38: Пр/774-021.0 | HP38: Автомобильные дороги | HQ38: Автомобильные дороги | HS38: 0 | IK38: 0
A39: 17 | B39: 1 | C39: =ROW(SmtRes!A56) -> 56 | D39: =ROW(EtalonRes!A54) -> 54 | E39: 10 | F39: 91.01.05-089 | G39: Экскаваторы одноковшовые дизельные на гусеничном ходу, объем ковша 1,25 м3 | H39: маш.-ч | I39: =ROUND(ROUND(-3.42,5),7) -> -3.42 | J39: 0 | K39: =ROUND(ROUND(-3.42,5),7) -> -3.42 | O39: =ROUND(CP39,2) -> -9004.07 | P39: =ROUND(CQ39*I39,2) -> 0 | Q39: =ROUND(CR39*I39,2) -> -6883.19 | R39: =ROUND(CS39*I39,2) -> -2120.88 | S39: =ROUND(CT39*I39,2) -> 0 | T39: =ROUND(CU39*I39,2) -> 0 | U39: =ROUND(CV39*I39,7) -> 0 | V39: =ROUND(CW39*I39,7) -> 0 | W39: =ROUND(CX39*I39,2) -> 0 | X39: =ROUND(CY39,2) -> 0 | Y39: =ROUND(CZ39,2) -> 0 | AA39: 38182922 | AB39: =ROUND((AC39+AD39+AF39),6) -> 1524.72 | AC39: =ROUND((ES39),6) -> 0 | AD39: =ROUND((((ET39)-(EU39))+AE39),6) -> 1524.72 | AE39: =ROUND((EU39),6) -> 620.14 | AF39: =ROUND((EV39),6) -> 0 | AG39: =ROUND((AP39),6) -> 0 | AH39: =(EW39) -> 0 | AI39: =(EX39) -> 0 | AJ39: =(AS39) -> 0 | AK39: 1524.72 | AL39: 0 | AM39: 1524.72 | AN39: 620.14 | AO39: 0 | AP39: 0 | AQ39: 0 | AR39: 0 | AS39: 0 | AT39: 0 | AU39: 0 | AV39: 1 | AW39: 1 | AZ39: 1 | BA39: 1 | BB39: 1.32 | BC39: 1 | BH39: 2 | BI39: 1 | BJ39: ФСЭМ-2022, 91.01.05-089, приказ Минстроя России от 18.05.2022 г. № 378/пр | BM39: 400001 | BN39: 0 | BO39: 91.01.05-089 | BP39: 1 | BQ39: 7 | BR39: 0 | BS39: 1 | BT39: 1 | BU39: 1 | BV39: 1 | BW39: 1 | BX39: 1 | BZ39: 0 | CA39: 0 | CE39: 0 | CF39: 0 | CG39: 0 | CM39: 0 | CO39: 0 | CP39: =(P39+Q39+S39+R39) -> -9004.07 | CQ39: =ROUND(AL39*BC39,2) -> 0 | CR39: =ROUND(AM39*BB39,2) -> 2012.63 | CS39: =ROUND(AN39*BS39,2) -> 620.14 | CT39: =ROUND(AO39*BA39,2) -> 0 | CU39: =AG39 -> 0 | CV39: =AH39 -> 0 | CW39: =AI39 -> 0 | CX39: =AJ39 -> 0 | CY39: =(((S39+R39)*AT39)/100) -> 0 | CZ39: =(((S39+R39)*AU39)/100) -> 0 | DN39: 0 | DO39: 0 | DP39: 1 | DQ39: 1 | DU39: 1011 | DV39: маш.-ч | DW39: маш.-ч | DX39: 1 | EE39: 35227692 | EF39: 7 | EG39: Машины и механизмы | EH39: 0 | EJ39: 1 | EK39: 400001 | EL39: Эксплуатация машин и механизмов ( ценники на ЭММ ) | EM39: ЭММ | EQ39: 0 | ER39: 1524.72 | ES39: 0 | ET39: 1524.72 | EU39: 620.14 | EV39: 0 | EW39: 0 | EX39: 0 | EY39: 0 | FQ39: 0 | FR39: 0 | FS39: 1 | FX39: 0 | FY39: 0 | GD39: 1 | GF39: -972071566 | GG39: 2 | GH39: 1 | GI39: 2 | GJ39: 0 | GK39: 0 | GL39: =ROUND(IF(AND(BH39=3,BI39=3,FS39<>0),P39,0),2) -> 0 | GM39: =ROUND(O39+X39+Y39,2)+GX39 -> -9004.07 | GN39: =IF(OR(BI39=0,BI39=1),GM39-GX39,0) -> -9004.07 | GO39: =IF(BI39=2,GM39-GX39,0) -> 0 | GP39: =IF(BI39=4,GM39-GX39,0) -> 0 | GR39: 0 | GS39: 7 | GT39: 0 | GV39: =ROUND((GT39),6) -> 0 | GW39: 1 | GX39: =ROUND(HC39*I39,2) -> 0 | HA39: 0 | HB39: 0 | HC39: =GV39*GW39 -> 0 | HS39: 0 | IK39: 0
A40: 17 | B40: 1 | E40: 11 | F40: 02.3.01.02-1104 | G40: Песок природный для строительных работ I класс, средний | H40: м3 | I40: =ROUND(ROUND(-57.33,5),7) -> -57.33 | J40: 0 | K40: =ROUND(ROUND(-57.33,5),7) -> -57.33 | O40: =ROUND(CP40,2) -> -43419.45 | P40: =ROUND(CQ40*I40,2) -> -43419.45 | Q40: =ROUND(CR40*I40,2) -> 0 | R40: =ROUND(CS40*I40,2) -> 0 | S40: =ROUND(CT40*I40,2) -> 0 | T40: =ROUND(CU40*I40,2) -> 0 | U40: =ROUND(CV40*I40,7) -> 0 | V40: =ROUND(CW40*I40,7) -> 0 | W40: =ROUND(CX40*I40,2) -> 0 | X40: =ROUND(CY40,2) -> 0 | Y40: =ROUND(CZ40,2) -> 0 | AA40: 38182922 | AB40: =ROUND((AC40+AD40+AF40),6) -> 757.36 | AC40: =ROUND((ES40),6) -> 757.36 | AD40: =ROUND((((ET40)-(EU40))+AE40),6) -> 0 | AE40: =ROUND((EU40),6) -> 0 | AF40: =ROUND((EV40),6) -> 0 | AG40: =ROUND((AP40),6) -> 0 | AH40: =(EW40) -> 0 | AI40: =(EX40) -> 0 | AJ40: =(AS40) -> 0 | AK40: 757.36 | AL40: 757.36 | AM40: 0 | AN40: 0 | AO40: 0 | AP40: 0 | AQ40: 0 | AR40: 0 | AS40: 0 | AT40: 0 | AU40: 0 | AV40: 1 | AW40: 1 | AZ40: 1 | BA40: 1 | BB40: 1 | BC40: 1 | BH40: 3 | BI40: 1 | BJ40: ФСБЦ-2022, 02.3.01.02-1104, приказ Минстроя России от 18.05.2022 г. № 378/пр | BM40: 500001 | BN40: 0 | BP40: 0 | BQ40: 8 | BR40: 0 | BS40: 1 | BT40: 1 | BU40: 1 | BV40: 1 | BW40: 1 | BX40: 1 | BZ40: 0 | CA40: 0 | CE40: 0 | CF40: 0 | CG40: 0 | CM40: 0 | CO40: 0 | CP40: =(P40+Q40+S40+R40) -> -43419.45 | CQ40: =ROUND(AL40*BC40,2) -> 757.36 | CR40: =ROUND(AM40*BB40,2) -> 0 | CS40: =ROUND(AN40*BS40,2) -> 0 | CT40: =ROUND(AO40*BA40,2) -> 0 | CU40: =AG40 -> 0 | CV40: =AH40 -> 0 | CW40: =AI40 -> 0 | CX40: =AJ40 -> 0 | CY40: =0 -> 0 | CZ40: =0 -> 0 | DN40: 0 | DO40: 0 | DP40: 1 | DQ40: 1 | DU40: 1007 | DV40: м3 | DW40: м3 | DX40: 1 | EE40: 35227693 | EF40: 8 | EG40: Материалы строительные | EH40: 0 | EJ40: 1 | EK40: 500001 | EL40: Материалы и конструкции ( строительные ) по ценникам и каталогом | EM40: ФССЦст | EQ40: 0 | ER40: 757.36 | ES40: 757.36 | ET40: 0 | EU40: 0 | EV40: 0 | EW40: 0 | EX40: 0 | EY40: 0 | FQ40: 0 | FR40: 0 | FS40: 0 | FX40: 0 | FY40: 0 | GD40: 1 | GE40: 573.7 | GF40: 318135557 | GG40: 2 | GH40: 1 | GI40: -2 | GJ40: 0 | GK40: 0 | GL40: =ROUND(IF(AND(BH40=3,BI40=3,FS40<>0),P40,0),2) -> 0 | GM40: =ROUND(O40+X40+Y40,2)+GX40 -> -43419.45 | GN40: =IF(OR(BI40=0,BI40=1),GM40-GX40,0) -> -43419.45 | GO40: =IF(BI40=2,GM40-GX40,0) -> 0 | GP40: =IF(BI40=4,GM40-GX40,0) -> 0 | GR40: 3 | GS40: 3 | GT40: 0 | GV40: =ROUND((GT40),6) -> 0 | GW40: 1 | GX40: =ROUND(HC40*I40,2) -> 0 | HA40: 0 | HB40: 0 | HC40: =GV40*GW40 -> 0 | HS40: 0 | IK40: 0
A42: 51 | B42: =B20 -> 1 | C42: =A20 -> 3 | D42: =ROW(A20) -> 20 | F42: =IF(F20<>"",F20,"") -> Новая локальная смета | G42: =IF(G20<>"",G20,"") -> ремонт трубы | H42: 0 | O42: =ROUND(AB42,2) -> 52656.07 | P42: =ROUND(AC42,2) -> 4333.36 | Q42: =ROUND(AD42,2) -> 22333.26 | R42: =ROUND(AE42,2) -> 5074.08 | S42: =ROUND(AF42,2) -> 20915.37 | T42: =ROUND(AG42,2) -> 0 | U42: =AH42 -> 49.772 | V42: =AI42 -> 12.61312 | W42: =ROUND(AJ42,2) -> 0 | X42: =ROUND(AK42,2) -> 34113.56 | Y42: =ROUND(AL42,2) -> 23901.1 | AB42: =ROUND(SUMIF(AA24:AA40,"=38182922",O24:O40),2) -> 52656.07 | AC42: =ROUND(SUMIF(AA24:AA40,"=38182922",P24:P40),2) -> 4333.36 | AD42: =ROUND(SUMIF(AA24:AA40,"=38182922",Q24:Q40),2) -> 22333.26 | AE42: =ROUND(SUMIF(AA24:AA40,"=38182922",R24:R40),2) -> 5074.08 | AF42: =ROUND(SUMIF(AA24:AA40,"=38182922",S24:S40),2) -> 20915.37 | AG42: =ROUND(SUMIF(AA24:AA40,"=38182922",T24:T40),2) -> 0 | AH42: =SUMIF(AA24:AA40,"=38182922",U24:U40) -> 49.772 | AI42: =SUMIF(AA24:AA40,"=38182922",V24:V40) -> 12.61312 | AJ42: =ROUND(SUMIF(AA24:AA40,"=38182922",W24:W40),2) -> 0 | AK42: =ROUND(SUMIF(AA24:AA40,"=38182922",X24:X40),2) -> 34113.56 | AL42: =ROUND(SUMIF(AA24:AA40,"=38182922",Y24:Y40),2) -> 23901.1 | AO42: =ROUND(BX42,2) -> 0 | AP42: =ROUND(BY42,2) -> 0 | AQ42: =ROUND(BZ42,2) -> 0 | AR42: =ROUND(CA42,2) -> 110670.73 | AS42: =ROUND(CB42,2) -> 110670.73 | AT42: =ROUND(CC42,2) -> 0 | AU42: =ROUND(CD42,2) -> 0 | AV42: =ROUND(CE42,2) -> 4333.36 | ... BD42: =ROUND(CM42,2) -> 0 | BX42: =ROUND(SUMIF(AA24:AA40,"=38182922",FQ24:FQ40),2) -> 0 | BY42: =ROUND(SUMIF(AA24:AA40,"=38182922",FR24:FR40),2) -> 0 | BZ42: =ROUND(SUMIF(AA24:AA40,"=38182922",GL24:GL40),2) -> 0 | CA42: =ROUND(SUMIF(AA24:AA40,"=38182922",GM24:GM40),2) -> 110670.73 | CB42: =ROUND(SUMIF(AA24:AA40,"=38182922",GN24:GN40),2) -> 110670.73 | CC42: =ROUND(SUMIF(AA24:AA40,"=38182922",GO24:GO40),2) -> 0 | CD42: =ROUND(SUMIF(AA24:AA40,"=38182922",GP24:GP40),2) -> 0 | CE42: =AC42-BX42 -> 4333.36 | CF42: =AC42-BY42 -> 4333.36 | CG42: =BX42-BZ42 -> 0 | CH42: =AC42-BX42-BY42+BZ42 -> 4333.36 | CI42: =BY42-BZ42 -> 0 | CJ42: =ROUND(SUMIF(AA24:AA40,"=38182922",GX24:GX40),2) -> 0 | CK42: =ROUND(SUMIF(AA24:AA40,"=38182922",GY24:GY40),2) -> 0 | CL42: =ROUND(SUMIF(AA24:AA40,"=38182922",GZ24:GZ40),2) -> 0 | CM42: =ROUND(SUMIF(AA24:AA40,"=38182922",HD24:HD40),2) -> 0 | GX42: 0
A44: 50 | B44: 0 | C44: 0 | D44: 1 | E44: 201 | F44: =ROUND(Source!O42,O44) -> 52656.07 | G44: ПЗ | H44: Прямые затраты | K44: 201 | L44: 1 | M44: 3 | O44: 2 | W44: 52656.07 | X44: 1 | Y44: 52656.07
A45: 50 | B45: 0 | C45: 0 | D45: 1 | E45: 202 | F45: =ROUND(Source!P42,O45) -> 4333.36 | G45: СтМатОб | H45: Стоимость материальных ресурсов (всего) | K45: 202 | L45: 2 | M45: 3 | O45: 2 | W45: 4333.36 | X45: 1 | Y45: 4333.36
A46: 50 | B46: 0 | C46: 0 | D46: 1 | E46: 222 | F46: =ROUND(Source!AO42,O46) -> 0 | G46: СтМатОбЗак | H46: Стоимость материалов и оборудования заказчика | K46: 222 | L46: 3 | M46: 3 | O46: 2 | W46: 0 | X46: 1 | Y46: 0
A47: 50 | B47: 0 | C47: 0 | D47: 1 | E47: 225 | F47: =ROUND(Source!AV42,O47) -> 4333.36 | G47: СтМатОбПод | H47: Стоимость материалов и оборудования подрядчика | K47: 225 | L47: 4 | M47: 3 | O47: 2 | W47: 4333.36 | X47: 1 | Y47: 4333.36
A48: 50 | B48: 0 | C48: 0 | D48: 1 | E48: 226 | F48: =ROUND(Source!AW42,O48) -> 4333.36 | G48: СтМат | H48: Стоимость материалов (всего) | K48: 226 | L48: 5 | M48: 3 | O48: 2 | W48: 4333.36 | X48: 1 | Y48: 4333.36
A49: 50 | B49: 0 | C49: 0 | D49: 1 | E49: 227 | F49: =ROUND(Source!AX42,O49) -> 0 | G49: СтМатЗак | H49: Стоимость материалов заказчика | K49: 227 | L49: 6 | M49: 3 | O49: 2 | W49: 0 | X49: 1 | Y49: 0
A50: 50 | B50: 0 | C50: 0 | D50: 1 | E50: 228 | F50: =ROUND(Source!AY42,O50) -> 4333.36 | G50: СтМатПод | H50: Стоимость материалов подрядчика | K50: 228 | L50: 7 | M50: 3 | O50: 2 | W50: 4333.36 | X50: 1 | Y50: 4333.36
A51: 50 | B51: 0 | C51: 0 | D51: 1 | E51: 216 | F51: =ROUND(Source!AP42,O51) -> 0 | G51: Оборуд | H51: Стоимость оборудования (всего) | K51: 216 | L51: 8 | M51: 3 | O51: 2 | W51: 0 | X51: 1 | Y51: 0
A52: 50 | B52: 0 | C52: 0 | D52: 1 | E52: 223 | F52: =ROUND(Source!AQ42,O52) -> 0 | G52: ОборудЗак | H52: Стоимость оборудования заказчика | K52: 223 | L52: 9 | M52: 3 | O52: 2 | W52: 0 | X52: 1 | Y52: 0
A53: 50 | B53: 0 | C53: 0 | D53: 1 | E53: 229 | F53: =ROUND(Source!AZ42,O53) -> 0 | G53: ОборудПод | H53: Стоимость оборудования подрядчика | K53: 229 | L53: 10 | M53: 3 | O53: 2 | W53: 0 | X53: 1 | Y53: 0
A54: 50 | B54: 0 | C54: 0 | D54: 1 | E54: 203 | F54: =ROUND(Source!Q42,O54) -> 22333.26 | G54: ЭММ | H54: Эксплуатация машин | K54: 203 | L54: 11 | M54: 3 | O54: 2 | W54: 22333.26 | X54: 1 | Y54: 22333.26
A55: 50 | B55: 0 | C55: 0 | D55: 1 | E55: 231 | F55: =ROUND(Source!BB42,O55) -> 0 | G55: ЭММсНРиСП | H55: Эксплуатация машин по ТСН-2001.16 | K55: 231 | L55: 12 | M55: 3 | O55: 2 | W55: 0 | X55: 1 | Y55: 0
A56: 50 | B56: 0 | C56: 0 | D56: 1 | E56: 204 | F56: =ROUND(Source!R42,O56) -> 5074.08 | G56: ЗПМ | H56: ЗП машинистов | K56: 204 | L56: 13 | M56: 3 | O56: 2 | W56: 5074.08 | X56: 1 | Y56: 5074.08
A57: 50 | B57: 0 | C57: 0 | D57: 1 | E57: 205 | F57: =ROUND(Source!S42,O57) -> 20915.37 | G57: ОЗП | H57: Основная ЗП рабочих | K57: 205 | L57: 14 | M57: 3 | O57: 2 | W57: 20915.37 | X57: 1 | Y57: 20915.37
A58: 50 | B58: 0 | C58: 0 | D58: 1 | E58: 232 | F58: =ROUND(Source!BC42,O58) -> 0 | G58: ОЗПсНРиСП | H58: Основная ЗП рабочих по ТСН-2001.16 | K58: 232 | L58: 15 | M58: 3 | O58: 2 | W58: 0 | X58: 1 | Y58: 0
A59: 50 | B59: 0 | C59: 0 | D59: 1 | E59: 214 | F59: =ROUND(Source!AS42,O59) -> 110670.73 | G59: Строит | H59: Строительные работы с НР и СП | K59: 214 | L59: 16 | M59: 3 | O59: 2 | W59: 110670.73 | X59: 1 | Y59: 110670.73
A60: 50 | B60: 0 | C60: 0 | D60: 1 | E60: 215 | F60: =ROUND(Source!AT42,O60) -> 0 | G60: Монтаж | H60: Монтажные работы с НР и СП | K60: 215 | L60: 17 | M60: 3 | O60: 2 | W60: 0 | X60: 1 | Y60: 0
A61: 50 | B61: 0 | C61: 0 | D61: 1 | E61: 217 | F61: =ROUND(Source!AU42,O61) -> 0 | G61: Прочие | H61: Прочие работы с НР и СП | K61: 217 | L61: 18 | M61: 3 | O61: 2 | W61: 0 | X61: 1 | Y61: 0
A62: 50 | B62: 0 | C62: 0 | D62: 1 | E62: 230 | F62: =ROUND(Source!BA42,O62) -> 0 | G62: ПрочиеЗатр | H62: Прочие затраты по ТСН-2001.16 | K62: 230 | L62: 19 | M62: 3 | O62: 2 | W62: 0 | X62: 1 | Y62: 0
A63: 50 | B63: 0 | C63: 0 | D63: 1 | E63: 206 | F63: =ROUND(Source!T42,O63) -> 0 | G63: ВозврМат | H63: Возврат материалов | K63: 206 | L63: 20 | M63: 3 | O63: 2 | W63: 0 | X63: 1 | Y63: 0
A64: 50 | B64: 0 | C64: 0 | D64: 1 | E64: 207 | F64: =ROUND(Source!U42,O64) -> 49.772 | G64: ТрудСтр | H64: Трудозатраты строителей | K64: 207 | L64: 21 | M64: 3 | O64: 7 | W64: 49.772 | X64: 1 | Y64: 49.772
A65: 50 | B65: 0 | C65: 0 | D65: 1 | E65: 208 | F65: =ROUND(Source!V42,O65) -> 12.61312 | G65: ТрудМаш | H65: Трудозатраты машинистов | K65: 208 | L65: 22 | M65: 3 | O65: 7 | W65: 12.61312 | X65: 1 | Y65: 12.61312
A66: 50 | B66: 0 | C66: 0 | D66: 1 | E66: 209 | F66: =ROUND(Source!W42,O66) -> 0 | G66: ТранспМат | H66: Транспорт материалов | K66: 209 | L66: 23 | M66: 3 | O66: 2 | W66: 0 | X66: 1 | Y66: 0
A67: 50 | B67: 0 | C67: 0 | D67: 1 | E67: 233 | F67: =ROUND(Source!BD42,O67) -> 0 | G67: Перевозка | H67: Перевозка грузов | K67: 233 | L67: 24 | M67: 3 | O67: 2 | W67: 0 | X67: 1 | Y67: 0
A68: 50 | B68: 0 | C68: 0 | D68: 1 | E68: 210 | F68: =ROUND(Source!X42,O68) -> 34113.56 | G68: НР | H68: Накладные расходы | K68: 210 | L68: 25 | M68: 3 | O68: 2 | W68: 34113.56 | X68: 1 | Y68: 34113.56
A69: 50 | B69: 0 | C69: 0 | D69: 1 | E69: 211 | F69: =ROUND(Source!Y42,O69) -> 23901.1 | G69: СмПриб | H69: Сметная прибыль | K69: 211 | L69: 26 | M69: 3 | O69: 2 | W69: 23901.1 | X69: 1 | Y69: 23901.1
A70: 50 | B70: 0 | C70: 0 | D70: 1 | E70: 224 | F70: =ROUND(Source!AR42,O70) -> 110670.73 | G70: Всего | H70: Всего с НР и СП | K70: 224 | L70: 27 | M70: 3 | O70: 2 | W70: 110670.73 | X70: 1 | Y70: 110670.73
A71: 50 | B71: 1 | C71: 0 | D71: 2 | E71: 0 | F71: =ROUND(F70,O71) -> 110670.73 | G71: Итого | H71: Итого по смете | K71: 212 | L71: 28 | M71: 0 | O71: 2 | W71: 110670.73 | X71: 1 | Y71: 110670.73
A72: 50 | B72: 1 | C72: 0 | D72: 2 | E72: 0 | F72: =ROUND(F71*6.2/100,O72) -> 6861.59 | G72: ВЗиС | H72: Временные здания и сооружения | K72: 212 | L72: 29 | M72: 0 | O72: 2 | W72: 6861.59 | X72: 1 | Y72: 6861.59
A73: 50 | B73: 1 | C73: 0 | D73: 2 | E73: 38177147 | F73: =ROUND(F71+F72,O73) -> 117532.32 | G73: Итого с ВЗиС | H73: Итого с временными зданиями и сооружениями | K73: 212 | L73: 30 | M73: 0 | O73: 2 | W73: 117532.32 | X73: 1 | Y73: 117532.32
A74: 50 | B74: 1 | C74: 0 | D74: 2 | E74: 0 | F74: =ROUND(F73*0.22,O74) -> 25857.11 | G74: НДС 22% | H74: НДС 22% | K74: 212 | L74: 31 | M74: 0 | O74: 2 | W74: 25857.11 | X74: 1 | Y74: 25857.11
A75: 50 | B75: 1 | C75: 0 | D75: 2 | E75: 213 | F75: =ROUND(F73+F74,O75) -> 143389.43 | G75: Всего с НДС | H75: Всего с НДС | K75: 212 | L75: 32 | M75: 0 | O75: 2 | W75: 143389.43 | X75: 1 | Y75: 143389.43
A77: 51 | B77: =B12 -> 134 | C77: =A12 -> 1 | D77: =ROW(A12) -> 12 | F77: =IF(F12<>"",F12,"") -> Новый объект строительства | G77: =IF(G12<>"",G12,"") -> ремонт трубы | H77: 0 | O77: =ROUND(O42,2) -> 52656.07 | P77: =ROUND(P42,2) -> 4333.36 | Q77: =ROUND(Q42,2) -> 22333.26 | R77: =ROUND(R42,2) -> 5074.08 | S77: =ROUND(S42,2) -> 20915.37 | T77: =ROUND(T42,2) -> 0 | U77: =U42 -> 49.772 | V77: =V42 -> 12.61312 | W77: =ROUND(W42,2) -> 0 | X77: =ROUND(X42,2) -> 34113.56 | Y77: =ROUND(Y42,2) -> 23901.1 | AO77: =ROUND(AO42,2) -> 0 | AP77: =ROUND(AP42,2) -> 0 | AQ77: =ROUND(AQ42,2) -> 0 | AR77: =ROUND(AR42,2) -> 110670.73 | AS77: =ROUND(AS42,2) -> 110670.73 | AT77: =ROUND(AT42,2) -> 0 | AU77: =ROUND(AU42,2) -> 0 | AV77: =ROUND(AV42,2) -> 4333.36 | ... BD77: =ROUND(BD42,2) -> 0 | GX77: 0
A79: 50 | B79: 0 | C79: 0 | D79: 1 | E79: 201 | F79: =ROUND(Source!O77,O79) -> 52656.07 | G79: ПЗ | H79: Прямые затраты | K79: 201 | L79: 1 | M79: 3 | O79: 2 | W79: 52656.07 | X79: 1 | Y79: 52656.07
A80: 50 | B80: 0 | C80: 0 | D80: 1 | E80: 202 | F80: =ROUND(Source!P77,O80) -> 4333.36 | G80: СтМатОб | H80: Стоимость материальных ресурсов (всего) | K80: 202 | L80: 2 | M80: 3 | O80: 2 | W80: 4333.36 | X80: 1 | Y80: 4333.36
A81: 50 | B81: 0 | C81: 0 | D81: 1 | E81: 222 | F81: =ROUND(Source!AO77,O81) -> 0 | G81: СтМатОбЗак | H81: Стоимость материалов и оборудования заказчика | K81: 222 | L81: 3 | M81: 3 | O81: 2 | W81: 0 | X81: 1 | Y81: 0
A82: 50 | B82: 0 | C82: 0 | D82: 1 | E82: 225 | F82: =ROUND(Source!AV77,O82) -> 4333.36 | G82: СтМатОбПод | H82: Стоимость материалов и оборудования подрядчика | K82: 225 | L82: 4 | M82: 3 | O82: 2 | W82: 4333.36 | X82: 1 | Y82: 4333.36
A83: 50 | B83: 0 | C83: 0 | D83: 1 | E83: 226 | F83: =ROUND(Source!AW77,O83) -> 4333.36 | G83: СтМат | H83: Стоимость материалов (всего) | K83: 226 | L83: 5 | M83: 3 | O83: 2 | W83: 4333.36 | X83: 1 | Y83: 4333.36
A84: 50 | B84: 0 | C84: 0 | D84: 1 | E84: 227 | F84: =ROUND(Source!AX77,O84) -> 0 | G84: СтМатЗак | H84: Стоимость материалов заказчика | K84: 227 | L84: 6 | M84: 3 | O84: 2 | W84: 0 | X84: 1 | Y84: 0
A85: 50 | B85: 0 | C85: 0 | D85: 1 | E85: 228 | F85: =ROUND(Source!AY77,O85) -> 4333.36 | G85: СтМатПод | H85: Стоимость материалов подрядчика | K85: 228 | L85: 7 | M85: 3 | O85: 2 | W85: 4333.36 | X85: 1 | Y85: 4333.36
A86: 50 | B86: 0 | C86: 0 | D86: 1 | E86: 216 | F86: =ROUND(Source!AP77,O86) -> 0 | G86: Оборуд | H86: Стоимость оборудования (всего) | K86: 216 | L86: 8 | M86: 3 | O86: 2 | W86: 0 | X86: 1 | Y86: 0
A87: 50 | B87: 0 | C87: 0 | D87: 1 | E87: 223 | F87: =ROUND(Source!AQ77,O87) -> 0 | G87: ОборудЗак | H87: Стоимость оборудования заказчика | K87: 223 | L87: 9 | M87: 3 | O87: 2 | W87: 0 | X87: 1 | Y87: 0
A88: 50 | B88: 0 | C88: 0 | D88: 1 | E88: 229 | F88: =ROUND(Source!AZ77,O88) -> 0 | G88: ОборудПод | H88: Стоимость оборудования подрядчика | K88: 229 | L88: 10 | M88: 3 | O88: 2 | W88: 0 | X88: 1 | Y88: 0
A89: 50 | B89: 0 | C89: 0 | D89: 1 | E89: 203 | F89: =ROUND(Source!Q77,O89) -> 22333.26 | G89: ЭММ | H89: Эксплуатация машин | K89: 203 | L89: 11 | M89: 3 | O89: 2 | W89: 22333.26 | X89: 1 | Y89: 22333.26
A90: 50 | B90: 0 | C90: 0 | D90: 1 | E90: 231 | F90: =ROUND(Source!BB77,O90) -> 0 | G90: ЭММсНРиСП | H90: Эксплуатация машин по ТСН-2001.16 | K90: 231 | L90: 12 | M90: 3 | O90: 2 | W90: 0 | X90: 1 | Y90: 0
A91: 50 | B91: 0 | C91: 0 | D91: 1 | E91: 204 | F91: =ROUND(Source!R77,O91) -> 5074.08 | G91: ЗПМ | H91: ЗП машинистов | K91: 204 | L91: 13 | M91: 3 | O91: 2 | W91: 5074.08 | X91: 1 | Y91: 5074.08
A92: 50 | B92: 0 | C92: 0 | D92: 1 | E92: 205 | F92: =ROUND(Source!S77,O92) -> 20915.37 | G92: ОЗП | H92: Основная ЗП рабочих | K92: 205 | L92: 14 | M92: 3 | O92: 2 | W92: 20915.37 | X92: 1 | Y92: 20915.37
A93: 50 | B93: 0 | C93: 0 | D93: 1 | E93: 232 | F93: =ROUND(Source!BC77,O93) -> 0 | G93: ОЗПсНРиСП | H93: Основная ЗП рабочих по ТСН-2001.16 | K93: 232 | L93: 15 | M93: 3 | O93: 2 | W93: 0 | X93: 1 | Y93: 0
A94: 50 | B94: 0 | C94: 0 | D94: 1 | E94: 214 | F94: =ROUND(Source!AS77,O94) -> 110670.73 | G94: Строит | H94: Строительные работы с НР и СП | K94: 214 | L94: 16 | M94: 3 | O94: 2 | W94: 110670.73 | X94: 1 | Y94: 110670.73
A95: 50 | B95: 0 | C95: 0 | D95: 1 | E95: 215 | F95: =ROUND(Source!AT77,O95) -> 0 | G95: Монтаж | H95: Монтажные работы с НР и СП | K95: 215 | L95: 17 | M95: 3 | O95: 2 | W95: 0 | X95: 1 | Y95: 0
A96: 50 | B96: 0 | C96: 0 | D96: 1 | E96: 217 | F96: =ROUND(Source!AU77,O96) -> 0 | G96: Прочие | H96: Прочие работы с НР и СП | K96: 217 | L96: 18 | M96: 3 | O96: 2 | W96: 0 | X96: 1 | Y96: 0
A97: 50 | B97: 0 | C97: 0 | D97: 1 | E97: 230 | F97: =ROUND(Source!BA77,O97) -> 0 | G97: ПрочиеЗатр | H97: Прочие затраты по ТСН-2001.16 | K97: 230 | L97: 19 | M97: 3 | O97: 2 | W97: 0 | X97: 1 | Y97: 0
A98: 50 | B98: 0 | C98: 0 | D98: 1 | E98: 206 | F98: =ROUND(Source!T77,O98) -> 0 | G98: ВозврМат | H98: Возврат материалов | K98: 206 | L98: 20 | M98: 3 | O98: 2 | W98: 0 | X98: 1 | Y98: 0
A99: 50 | B99: 0 | C99: 0 | D99: 1 | E99: 207 | F99: =ROUND(Source!U77,O99) -> 49.772 | G99: ТрудСтр | H99: Трудозатраты строителей | K99: 207 | L99: 21 | M99: 3 | O99: 7 | W99: 49.772 | X99: 1 | Y99: 49.772
A100: 50 | B100: 0 | C100: 0 | D100: 1 | E100: 208 | F100: =ROUND(Source!V77,O100) -> 12.61312 | G100: ТрудМаш | H100: Трудозатраты машинистов | K100: 208 | L100: 22 | M100: 3 | O100: 7 | W100: 12.61312 | X100: 1 | Y100: 12.61312
A101: 50 | B101: 0 | C101: 0 | D101: 1 | E101: 209 | F101: =ROUND(Source!W77,O101) -> 0 | G101: ТранспМат | H101: Транспорт материалов | K101: 209 | L101: 23 | M101: 3 | O101: 2 | W101: 0 | X101: 1 | Y101: 0
A102: 50 | B102: 0 | C102: 0 | D102: 1 | E102: 233 | F102: =ROUND(Source!BD77,O102) -> 0 | G102: Перевозка | H102: Перевозка грузов | K102: 233 | L102: 24 | M102: 3 | O102: 2 | W102: 0 | X102: 1 | Y102: 0
A103: 50 | B103: 0 | C103: 0 | D103: 1 | E103: 210 | F103: =ROUND(Source!X77,O103) -> 34113.56 | G103: НР | H103: Накладные расходы | K103: 210 | L103: 25 | M103: 3 | O103: 2 | W103: 34113.56 | X103: 1 | Y103: 34113.56
A104: 50 | B104: 0 | C104: 0 | D104: 1 | E104: 211 | F104: =ROUND(Source!Y77,O104) -> 23901.1 | G104: СмПриб | H104: Сметная прибыль | K104: 211 | L104: 26 | M104: 3 | O104: 2 | W104: 23901.1 | X104: 1 | Y104: 23901.1
A105: 50 | B105: 0 | C105: 0 | D105: 1 | E105: 224 | F105: =ROUND(Source!AR77,O105) -> 110670.73 | G105: Всего | H105: Всего с НР и СП | K105: 224 | L105: 27 | M105: 3 | O105: 2 | W105: 110670.73 | X105: 1 | Y105: 110670.73
A108: 70 | B108: 1 | D108: 1 | E108: СТР_РЕК | F108: СТРОИТЕЛЬСТВО и РЕКОНСТРУКЦИЯ зданий и сооружений всех назначений | G108: 0 | H108: 0 | J108: 1 | K108: 0 | N108: 0 | P108: Строительство и реконструкция
A109: 70 | B109: 1 | D109: 2 | E109: РЕМ_ЖИЛ | F109: КАП. РЕМ. ЖИЛЫХ И ОБЩЕСТВЕННЫХ ЗДАНИЙ | G109: 0 | H109: 0 | J109: 1 | K109: 0 | N109: 0 | P109: Капитальный ремонт жилых и общественных зданий
A110: 70 | B110: 1 | D110: 3 | E110: РЕМ_ПР | F110: КАП. РЕМ. ПРОИЗВОДСТВЕННЫХ ЗД. и СООРУЖЕНИЙ, НАРУЖНЫХ ИНЖЕНЕРНЫХ СЕТЕЙ, УЛИЦ И ДОРОГ МЕСТНОГО ЗНАЧЕНИЯ, ИНЖ,СООРУЖЕНИЙ ( ГИДРОТЕХ,СООРУЖ, МОСТОВ И ПУТЕПРОВОДОВ И Т.П.) | G110: 1 | H110: 0 | J110: 1 | K110: 0 | N110: 0 | P110: Капитальный ремонт прозводственных зданий
A111: 70 | B111: 1 | D111: 4 | E111: Территория | F111: для территории Российской Федерации, не относящейся к районам Крайнего Севера и приравненным к ним местностям | G111: 1 | H111: 0 | J111: 2 | K111: 0 | N111: 0
A112: 70 | B112: 1 | D112: 5 | E112: МПРКС | F112: для территории Российской Федерации, относящейся к местностям, приравненным к районам Крайнего Севера | G112: 0 | H112: 0 | J112: 2 | K112: 0 | N112: 0
A113: 70 | B113: 1 | D113: 6 | E113: РКС | F113: для территории Российской Федерации, относящейся к районам Крайнего Севера | G113: 0 | H113: 0 | J113: 2 | K113: 0 | N113: 0
A114: 70 | B114: 1 | D114: 7 | E114: СЛЖ | F114: При определении сметной стоимости строительства объектов капитального строительства, относящихся к особо опасным и технически сложным. За исключением АЭС. | G114: 0 | H114: 0 | I114: Для сборников ФЕР ( при производстве работ на технически сложных объектах ): · { СЛЖ } - (вкл.) - работа на сложных объектах (к=1,2 к НР) · { СЛЖ } - (выкл.) - работа на обычных объектах | J114: 0 | K114: 0 | N114: 0 | P114: Сложные объекты
A115: 70 | B115: 1 | D115: 8 | E115: СТНДРТ | F115: При определении сметной стоимости строительства объектов капитального строительства (за исключением АЭС). | G115: 1 | H115: 0 | J115: 5 | K115: 0 | N115: 0
A116: 70 | B116: 1 | D116: 9 | E116: АЭС_ПНР | F116: При определении сметной стоимости строительства объектов капитального строительства АЭС. Пусконаладочные работы (за исключением технологического оборудования АЭС). | G116: 0 | H116: 0 | J116: 5 | K116: 0 | N116: 0 | P116: АЭС
A117: 70 | B117: 1 | D117: 10 | E117: АЭС_ПНР_ТЕХ | F117: При определении сметной стоимости строительства объектов капитального строительства АЭС. Пусконаладочные работы технологического оборудования АЭС. | G117: 0 | H117: 0 | I117: Для сборника ФЕРм -39 и ФЕРМ-08 ( при работах по контролю сварных соединений) : {мАЭС} - ( вкл.) - при выполнении работ по на АЭС (HР=101%; СП= 68%; {мАЭС} - (выкл.) - при выполнении работ на обычных объектах | J117: 5 | K117: 0 | N117: 0 | P117: АЭС, ПНР технологического оборудования АЭС.
A118: 70 | B118: 1 | D118: 11 | E118: ОПТ/В | F118: {вкл} - Прокладка МЕЖДУГОРОДНЫХ ВОЛОКОННО-ОПТИЧЕСКИХ ЛИНИЙ (для ФЕРм10, отд. 6 разд.3) {выкл} - Прокладка ГОРОДСКИХ ВОЛОКОННО-ОПТИЧЕСКИХ ЛИНИЙ (для ФЕРм10, отд. 6 разд.3) | G118: 0 | H118: 0 | I118: Для сборников ФЕРм-10 ( волоконно-оптические линии связи ): · {М_ГОР_опт} - ( вкл.) - междугородные сети связи ( НР=120% , СП=70% ) · {М_ГОР_опт} - ( выкл.) - городские сети связи ( НР=100%; СП=65%) | J118: 0 | K118: 0 | N118: 0 | P118: Прокладка междугородных в/опт. кабелей
A119: 70 | B119: 1 | D119: 12 | E119: АВИ | F119: (вкл) - При работах по ДИСПЕТЧЕРИЗАЦИИ управления движением АВИАТРАНСПОРТОМ {вкл} (монтажные работы ) | G119: 0 | H119: 0 | I119: Для сборников ФЕРм 08;10;11 : · {мАВИА} - (вкл.) - производство монтажных работы по диспетчеризации управления движением авиатранспортном (НР=95%, СП=55%) ; · {мАВИА} - (выкл. ) - при производстве работ на прочих объектах , кром | J119: 0 | K119: 0 | N119: 0 | P119: Диспетчеризация авиатранспорта
A120: 70 | B120: 1 | D120: 13 | E120: ЗАКР | F120: {вкл} - Обслуживающие и сопутствующие работы в тоннелях при производстве работ ЗАКРЫТЫМ СПОСОБОМ {выкл} - Обслуживающие и сопутствующие работы в тоннелях при производстве работ ОТКРЫТЫМ | G120: 0 | H120: 0 | I120: Для сборника ФЕР -29 ( сопутствующие работы в тоннелях и метро. ): · {ЗАКР} - (вкл.) - при выполнении работ в тоннелях и метро закрытым способом (НР=145% , СП=75%); · {ЗАКР} - (выкл.) - при выполнении работ в тоннелях и метро отк | J120: 0 | K120: 0 | N120: 0 | P120: Производство работ закрытым способом (обслуживающие процессы)
A121: 70 | B121: 1 | D121: 14 | E121: АВТО_ДРГ | F121: {вкл} - НР и СП по п.021.0 "Автомобильные дороги" (раздел 2 нормы 27-02-010-01:07) {выкл} - НР и СП по п.021.1 Устройство покрытий дорожек, тротуаров, мостовых и площадок и прочее (раздел 2 нормы 27-02-010-01:07) | G121: 1 | H121: 0 | J121: 0 | K121: 0 | N121: 0
A122: 70 | B122: 1 | D122: 15 | E122: ГОР | F122: (вкл) - ФЕРм-08, выполнение работ на горнорудных объектах (выкл) - ФЕРм-08, выполнение работ на других объектах | G122: 0 | H122: 0 | J122: 0 | K122: 0 | N122: 0 | P122: Выполнение работ на горнорудных объектах
...

Sheet SourceObSm
A1: 0 | B1: Smeta.RU (495) 974-1589 | D1: _OBSM_ | F1: 0 | G1: 0 | H1: 0 | I1: Smeta.RU | K1: 1 | L1: 28227 | M1: 38175928 | N1: 12 | O1: 1 | P1: 0 | Q1: 5
A4: 8 | B4: 1 | C4: -1 | F4: Новый проект 4 | G4: ремонт трубы | EC4: 0
A12: 1 | B12: 51 | C12: 0 | E12: 0 | F12: Новый объект строительства | G12: ремонт трубы | I12: 0 | K12: 0 | L12: 0 | M12: 523 | O12: 0 | P12: 0 | Q12: 7 | R12: 0 | T12: 4 | V12: 0 | BB12: 0 | BH12: Сметные нормы списания | BI12: Коды ценников | BJ12: 1 | BK12: 1 | BL12: 0 | BM12: 1 | BN12: 1 | BO12: 0 | BP12: 6 | BQ12: 2 | BR12: 1 | BS12: 1 | BT12: 0 | BU12: 0 | BV12: 1 | BW12: 0 | BX12: 0 | BY12: ФСНБ-2022_И17 | BZ12: Версия 1.17.0 для ФСНБ-2022 И17 | CA12: ФСНБ-2022 - Изменения И17 | CB12: ФСНБ-2022 - Изменения И17 | CC12: ФСНБ-2022 - Изменения И17 | CD12: ФСНБ-2022 - Изменения И17 | CE12: Поправки для ФСНБ-2022 от 25.02.2026 г И17 (55/пр) Капитальный ремонт производственных зданий | CF12: 0 | CG12: 0 | CH12: 487489544 | CK12: 18 | CQ12: Приказ Минстроя России от 30.12.2021 г. № 1046/пр; Приказ Минстроя России от 04.08.2020 г. № 421/пр; Приказ Минстроя России от 21.12.2020 г. № 812/пр; Приказ Минстроя России от 11.12.2020 г. № 774/пр | CR12: ГСН | CS12: 46073 | CT12: 540 | CU12: 17 | CV12: Приказ Минстроя России от 18.05.2022 г. № 378/пр; Приказ Минстроя России от 26.08.2022 г. № 703/пр; Приказ Минстроя России от 26.10.2022 г. № 905/пр; Приказ Минстроя России от 27.12.2022 г. № 1133/пр; Приказ Минстроя России от 10.02.2023 г. № 84/пр; Приказ Минстроя России от 11.05.2023 г. № 335/пр; Приказ Минстроя России от 02.08.2023 г. № 551/пр; Приказ Минстроя России от 14.11.2023 г. № 817/пр; Приказ Минстроя России от 16.02.2024 г. № 102/пр; Приказ Минстроя России от 13.05.2024 г. № 323/пр; Приказ Минстроя России от 09.08.2024 г. № 524/пр; Приказ Минстроя России от 07.11.2024 г. № 747/пр; Приказ Минстроя России от 07.02.2025 г. № 69/пр; Приказ Минстроя России от 19.05.2025 г. № 299/пр; Приказ Минстроя России от 14.08.2025 г. № 490/пр; Приказ Минстроя России от 12.11.2025 г. № 696/пр; Приказ Минстроя России от 17.02.2026 г. № 91/пр; Приказ Минстроя России от 07.07.2022 г. № 557/пр; Приказ Минстроя России от 30.01.2024 г. № 55/пр; Приказ Минстроя России от 23.01.2025 г. № 30/пр; Приказ Минстроя России от 02.09.2021 г. № 636/пр; Приказ Минстроя России от 26.07.2022 г. № 611/пр; Приказ Минстроя России от 22.04.2022 г. № 317/пр | CY12: 0 | EC12: 0
A14: 22 | B14: 1 | C14: 0 | D14: 38182922 | E14: 0 | F14: 2 | G14: 1
A16: 3 | B16: 1 | C16: Новая локальная смета | D16: ремонт трубы | E16: =ROUND((Source!F59)/1000,2) -> 110.67 | F16: =ROUND((Source!F60)/1000,2) -> 0 | G16: =ROUND((Source!F51)/1000,2) -> 0 | H16: =ROUND((Source!F61)/1000+(Source!F62)/1000,2) -> 0 | I16: =E16+F16+G16+H16 -> 110.67 | J16: =ROUND((Source!F57+Source!F56)/1000,2) -> 25.99 | K16: 56.99 | L16: 0 | M16: 0 | N16: =I16+L16+M16 -> 110.67 | AI16: 0 | AJ16: 0 | AN16: 0 | AT16: 52656.07 | AU16: 4333.36 | AV16: 0 | AW16: 0 | AX16: 0 | AY16: 22333.26 | AZ16: 5074.08 | BA16: 20915.37 | BB16: 110670.73 | BC16: 0 | BD16: 0 | BE16: 0 | BF16: 49.772 | BG16: 12.61312 | BH16: 0 | BI16: 34113.56 | BJ16: 23901.1 | BK16: 110670.73
A18: 51 | E18: 110.67 | F18: 0 | G18: 0 | H18: 0 | I18: 110.67 | J18: 25.99 | K18: 56.99 | L18: 0 | M18: 0 | N18: 110.67
A20: 50 | B20: 0 | C20: 0 | D20: 1 | E20: 201 | F20: 52656.07 | G20: ПЗ | H20: Прямые затраты | K20: 201 | L20: 1 | M20: 3 | O20: 2
A21: 50 | B21: 0 | C21: 0 | D21: 1 | E21: 202 | F21: 4333.36 | G21: СтМатОб | H21: Стоимость материальных ресурсов (всего) | K21: 202 | L21: 2 | M21: 3 | O21: 2
A22: 50 | B22: 0 | C22: 0 | D22: 1 | E22: 222 | F22: 0 | G22: СтМатОбЗак | H22: Стоимость материалов и оборудования заказчика | K22: 222 | L22: 3 | M22: 3 | O22: 2
A23: 50 | B23: 0 | C23: 0 | D23: 1 | E23: 225 | F23: 4333.36 | G23: СтМатОбПод | H23: Стоимость материалов и оборудования подрядчика | K23: 225 | L23: 4 | M23: 3 | O23: 2
A24: 50 | B24: 0 | C24: 0 | D24: 1 | E24: 226 | F24: 4333.36 | G24: СтМат | H24: Стоимость материалов (всего) | K24: 226 | L24: 5 | M24: 3 | O24: 2
A25: 50 | B25: 0 | C25: 0 | D25: 1 | E25: 227 | F25: 0 | G25: СтМатЗак | H25: Стоимость материалов заказчика | K25: 227 | L25: 6 | M25: 3 | O25: 2
A26: 50 | B26: 0 | C26: 0 | D26: 1 | E26: 228 | F26: 4333.36 | G26: СтМатПод | H26: Стоимость материалов подрядчика | K26: 228 | L26: 7 | M26: 3 | O26: 2
A27: 50 | B27: 0 | C27: 0 | D27: 1 | E27: 216 | F27: 0 | G27: Оборуд | H27: Стоимость оборудования (всего) | K27: 216 | L27: 8 | M27: 3 | O27: 2
A28: 50 | B28: 0 | C28: 0 | D28: 1 | E28: 223 | F28: 0 | G28: ОборудЗак | H28: Стоимость оборудования заказчика | K28: 223 | L28: 9 | M28: 3 | O28: 2
A29: 50 | B29: 0 | C29: 0 | D29: 1 | E29: 229 | F29: 0 | G29: ОборудПод | H29: Стоимость оборудования подрядчика | K29: 229 | L29: 10 | M29: 3 | O29: 2
A30: 50 | B30: 0 | C30: 0 | D30: 1 | E30: 203 | F30: 22333.26 | G30: ЭММ | H30: Эксплуатация машин | K30: 203 | L30: 11 | M30: 3 | O30: 2
A31: 50 | B31: 0 | C31: 0 | D31: 1 | E31: 231 | F31: 0 | G31: ЭММсНРиСП | H31: Эксплуатация машин по ТСН-2001.16 | K31: 231 | L31: 12 | M31: 3 | O31: 2
... A46: 50 | B46: 0 | C46: 0 | D46: 1 | E46: 224 | F46: 110670.73 | G46: Всего | H46: Всего с НР и СП | K46: 224 | L46: 27 | M46: 3 | O46: 2
A48: -1
A51: 75 | B51: Уровень цен | C51: 2026 | D51: 1 | E51: 0 | F51: 1 | G51: 0 | H51: 1 | I51: 0 | J51: 3 | K51: 0 | L51: 0 | M51: 0 | N51: 38182922 | O51: 1
A52: 2 | B52: Вид цен | C52: Тверская область, КТЦ к ФСНБ-2022, 1 квартал 2026 г | D52: 0 | E52: 0 | F52: 0 | AN52: 38182923
A53: 1 | B53: Сборник индексов | C53: Тверская область к ФСНБ-2022 ФГИС ЦС | D53: 2026 | E53: 3 | F53: 1 | G53: 1 | H53: 0 | I53: 2 | J53: 1 | K53: 1 | L53: 1 | M53: 1 | N53: 1 | O53: 1 | P53: 1 | Q53: 1 | AN53: 38182924 | AO53: Письмо Минстроя России «О размещении индексов изменения сметной стоимости строительства по группам однородных строительных ресурсов на I квартал 2026 года» | AP53: Справочная информация | AQ53: 46078 | AR53: 409 | AS53: Письмо Минстроя России от 25.02.2026 № 9859-ИФ/09 | AT53: Постановление Правительства Тверской области | AU53: Справочная информация | AV53: 45772 | AW53: 229 | AX53: Постановление Правительства Тверской области от 25.04.2025 г. № 229-пп

Sheet SmtRes
A1: =ROW(Source!A24) -> 24 | B1: 38182922 | C1: 38182940 | D1: 35338390 | E1: 117 | F1: 1 | G1: 1 | H1: 1 | I1: 1-100-20 | K1: Средний разряд работы 2,0 | L1: 1191 | N1: 1013 | O1: чел.-ч. | P1: чел.-ч. | Q1: 1 | W1: 0 | X1: 370475345 | Y1: =AT1 -> 5.9 | AA1: 0 | AB1: 0 | AC1: 0 | AD1: 352.06 | AE1: 0 | AF1: 0 | AG1: 0 | AH1: 352.06 | AI1: 1 | AJ1: 1 | AK1: 1 | AL1: 1 | AM1: -2 | AN1: 0 | AO1: 0 | AP1: 0 | AQ1: 1 | AR1: 0 | AT1: 5.9 | AV1: 1 | AW1: 2 | AX1: 38182941 | AY1: 1 | AZ1: 0 | BA1: 1 | BB1: 1 | BC1: 0 | BD1: 0 | BE1: 0 | BF1: 0 | BG1: 0 | BH1: 0 | BI1: 0 | BJ1: 0 | BK1: 0 | BL1: 0 | BM1: 2077.154 | BN1: 5.9 | BO1: 0 | BP1: 1 | BQ1: 0 | BR1: 0 | BS1: 0 | BT1: 2077.154 | BU1: 5.9 | BV1: 0 | BW1: 1 | CU1: =ROUND(AT1*Source!I24*AH1*AL1,2) -> 93.47 | CV1: =ROUND(Y1*Source!I24,7) -> 0.2655 | CW1: 0 | CX1: =ROUND(Y1*Source!I24,7) -> 0.2655 | CY1: =AD1 -> 352.06 | CZ1: =AH1 -> 352.06 | DA1: =AL1 -> 1 | DB1: =ROUND(ROUND(AT1*CZ1,2),6) -> 2077.15 | DC1: =ROUND(ROUND(AT1*AG1,2),6) -> 0 | DF1: =ROUND(ROUND(AE1,2)*CX1,2) -> 0 | DG1: =ROUND(ROUND(AF1,2)*CX1,2) -> 0 | DH1: =ROUND(ROUND(AG1,2)*CX1,2) -> 0 | DI1: =ROUND(ROUND(AH1,2)*CX1,2) -> 93.47 | DJ1: =DI1 -> 93.47 | DK1: 1 | DM1: 0 | DO1: 0
A2: =ROW(Source!A24) -> 24 | B2: 38182922 | C2: 38182940 | D2: 35338624 | E2: 117 | F2: 1 | G2: 1 | H2: 1 | I2: 4-100-00 | K2: Затраты труда машинистов | L2: 1191 | N2: 1013 | O2: чел.-ч. | P2: чел.-ч. | Q2: 1 | W2: 0 | X2: -1417349443 | Y2: =AT2 -> 29.39 | AA2: 0 | AB2: 0 | AC2: 0 | AD2: 0 | AE2: 0 | AF2: 0 | AG2: 0 | AH2: 0 | AI2: 1 | AJ2: 1 | AK2: 1 | AL2: 1 | AM2: -2 | AN2: 0 | AO2: 0 | AP2: 0 | AQ2: 1 | AR2: 0 | AT2: 29.39 | AV2: 2 | AW2: 2 | AX2: 38182942 | AY2: 1 | AZ2: 0 | BA2: 2 | BB2: 1 | BC2: 0 | BD2: 0 | BE2: 0 | BF2: 0 | BG2: 0 | BH2: 0 | BI2: 0 | BJ2: 0 | BK2: 0 | BL2: 0 | BM2: 0 | BN2: 0 | BO2: 0 | BP2: 0 | BQ2: 0 | BR2: 0 | BS2: 0 | BT2: 0 | BU2: 0 | BV2: 0 | BW2: 0 | CV2: 0 | CW2: 0 | CX2: =ROUND(Y2*Source!I24,7) -> 1.32255 | CY2: =AD2 -> 0 | CZ2: =AH2 -> 0 | DA2: =AL2 -> 1 | DB2: =ROUND(ROUND(AT2*CZ2,2),6) -> 0 | DC2: =ROUND(ROUND(AT2*AG2,2),6) -> 0 | DF2: =ROUND(ROUND(AE2,2)*CX2,2) -> 0 | DG2: =ROUND(ROUND(AF2,2)*CX2,2) -> 0 | DH2: =ROUND(ROUND(AG2,2)*CX2,2) -> 0 | DI2: =ROUND(ROUND(AH2,2)*CX2,2) -> 0 | DJ2: =DI2 -> 0 | DK2: 0 | DM2: 0 | DO2: 0
A3: =ROW(Source!A24) -> 24 | B3: 38182922 | C3: 38182940 | D3: 35344726 | E3: 1 | F3: 1 | G3: 1 | H3: 2 | I3: 91.01.05-084 | J3: ФСЭМ-2022, 91.01.05-084, приказ Минстроя России от 18.05.2022 г. № 378/пр | K3: Экскаваторы одноковшовые дизельные на гусеничном ходу, объем ковша 0,4 м3 | L3: 1368 | N3: 1011 | O3: маш.-ч | P3: маш.-ч | Q3: 1 | W3: 0 | X3: 1473885390 | Y3: =AT3 -> 29.39 | AA3: 0 | AB3: 1250.88 | AC3: 497.4 | AD3: 0 | AE3: 0 | AF3: 947.64 | AG3: 497.4 | AH3: 0 | AI3: 1 | AJ3: 1.32 | AK3: 1 | AL3: 1 | AM3: 2 | AN3: 0 | AO3: 0 | AP3: 0 | AQ3: 1 | AR3: 0 | AT3: 29.39 | AV3: 1 | AW3: 2 | AX3: 38182943 | AY3: 1 | AZ3: 0 | BA3: 3 | BB3: 1 | BC3: 0 | BD3: 0 | BE3: 0 | BF3: 0 | BG3: 0 | BH3: 0 | BI3: 0 | BJ3: 0 | BK3: 27851.14 | BL3: 14618.586 | BM3: 0 | BN3: 0 | BO3: 29.39 | BP3: 1 | BQ3: 0 | BR3: 27851.14 | BS3: 14618.586 | BT3: 0 | BU3: 0 | BV3: 29.39 | BW3: 1 | CV3: 0 | CW3: =ROUND(Y3*Source!I24*DO3,7) -> 1.32255 | CX3: =ROUND(Y3*Source!I24,7) -> 1.32255 | CY3: =AB3 -> 1250.88 | CZ3: =AF3 -> 947.64 | DA3: =AJ3 -> 1.32 | DB3: =ROUND(ROUND(AT3*CZ3,2),6) -> 27851.14 | DC3: =ROUND(ROUND(AT3*AG3,2),6) -> 14618.59 | DF3: =ROUND(ROUND(AE3,2)*CX3,2) -> 0 | DG3: =ROUND(ROUND(AF3*AJ3,2)*CX3,2) -> 1654.35 | DH3: =ROUND(ROUND(AG3,2)*CX3,2) -> 657.84 | DI3: =ROUND(ROUND(AH3,2)*CX3,2) -> 0 | DJ3: =DG3+DH3 -> 2312.19 | DK3: 0 | DL3: 4-100-050 | DM3: 5 | DN3: чел.-ч. | DO3: 1
A4: =ROW(Source!A25) -> 25 | B4: 38182922 | C4: 38182946 | D4: 35338454 | E4: 117 | F4: 1 | G4: 1 | H4: 1 | I4: 1-100-40 | K4: Средний разряд работы 4,0 | L4: 1191 | N4: 1013 | O4: чел.-ч. | P4: чел.-ч. | Q4: 1 | W4: 0 | X4: 888410196 | Y4: =(AT4*ROUND(0.8,7)) -> 150.08 | AA4: 0 | AB4: 0 | AC4: 0 | AD4: 432.81 | AE4: 0 | AF4: 0 | AG4: 0 | AH4: 432.81 | AI4: 1 | AJ4: 1 | AK4: 1 | AL4: 1 | AM4: -2 | AN4: 0 | AO4: 0 | AP4: 1 | AQ4: 1 | AR4: 0 | AT4: 187.6 | AU4: *0,8 | AV4: 1 | AW4: 2 | AX4: 38182947 | AY4: 1 | AZ4: 0 | BA4: 4 | BB4: 1 | BC4: 0 | BD4: 0 | BE4: 0 | BF4: 0 | BG4: 0 | BH4: 0 | BI4: 0 | BJ4: 0 | BK4: 0 | BL4: 0 | BM4: 81195.156 | BN4: 187.6 | BO4: 0 | BP4: 1 | BQ4: 0 | BR4: 0 | BS4: 0 | BT4: 64956.125 | BU4: 150.08 | BV4: 0 | BW4: 1 | CU4: =ROUND(AT4*Source!I25*AH4*AL4,2) -> 8119.52 | CV4: =ROUND(Y4*Source!I25,7) -> 15.008 | CW4: 0 | CX4: =ROUND(Y4*Source!I25,7) -> 15.008 | CY4: =AD4 -> 432.81 | CZ4: =AH4 -> 432.81 | DA4: =AL4 -> 1 | DB4: =ROUND((ROUND(AT4*CZ4,2)*ROUND(0.8,7)),6) -> 64956.128 | DC4: =ROUND((ROUND(AT4*AG4,2)*ROUND(0.8,7)),6) -> 0 | DF4: =ROUND(ROUND(AE4,2)*CX4,2) -> 0 | DG4: =ROUND(ROUND(AF4,2)*CX4,2) -> 0 | DH4: =ROUND(ROUND(AG4,2)*CX4,2) -> 0 | DI4: =ROUND(ROUND(AH4,2)*CX4,2) -> 6495.61 | DJ4: =DI4 -> 6495.61 | DK4: 1 | DM4: 0 | DO4: 0
A5: =ROW(Source!A25) -> 25 | B5: 38182922 | C5: 38182946 | D5: 35338624 | E5: 117 | F5: 1 | G5: 1 | H5: 1 | I5: 4-100-00 | K5: Затраты труда машинистов | L5: 1191 | N5: 1013 | O5: чел.-ч. | P5: чел.-ч. | Q5: 1 | W5: 0 | X5: -1417349443 | Y5: =(AT5*ROUND(0.8,7)) -> 10.304 | AA5: 0 | AB5: 0 | AC5: 0 | AD5: 0 | AE5: 0 | AF5: 0 | AG5: 0 | AH5: 0 | AI5: 1 | AJ5: 1 | AK5: 1 | AL5: 1 | AM5: -2 | AN5: 0 | AO5: 0 | AP5: 1 | AQ5: 1 | AR5: 0 | AT5: 12.88 | AU5: *0,8 | AV5: 2 | AW5: 2 | AX5: 38182948 | AY5: 1 | AZ5: 0 | BA5: 5 | BB5: 1 | BC5: 0 | BD5: 0 | BE5: 0 | BF5: 0 | BG5: 0 | BH5: 0 | BI5: 0 | BJ5: 0 | BK5: 0 | BL5: 0 | BM5: 0 | BN5: 0 | BO5: 0 | BP5: 0 | BQ5: 0 | BR5: 0 | BS5: 0 | BT5: 0 | BU5: 0 | BV5: 0 | BW5: 0 | CV5: 0 | CW5: 0 | CX5: =ROUND(Y5*Source!I25,7) -> 1.0304 | CY5: =AD5 -> 0 | CZ5: =AH5 -> 0 | DA5: =AL5 -> 1 | DB5: =ROUND((ROUND(AT5*CZ5,2)*ROUND(0.8,7)),6) -> 0 | DC5: =ROUND((ROUND(AT5*AG5,2)*ROUND(0.8,7)),6) -> 0 | DF5: =ROUND(ROUND(AE5,2)*CX5,2) -> 0 | DG5: =ROUND(ROUND(AF5,2)*CX5,2) -> 0 | DH5: =ROUND(ROUND(AG5,2)*CX5,2) -> 0 | DI5: =ROUND(ROUND(AH5,2)*CX5,2) -> 0 | DJ5: =DI5 -> 0 | DK5: 0 | DM5: 0 | DO5: 0
A6: =ROW(Source!A25) -> 25 | B6: 38182922 | C6: 38182946 | D6: 35345762 | E6: 1 | F6: 1 | G6: 1 | H6: 2 | I6: 91.10.05-009 | J6: ФСЭМ-2022, 91.10.05-009, приказ Минстроя России от 18.05.2022 г. № 378/пр | K6: Трубоукладчики, номинальная грузоподъемность 35 т | L6: 1368 | N6: 1011 | O6: маш.-ч | P6: маш.-ч | Q6: 1 | W6: 0 | X6: -1505731505 | Y6: =(AT6*ROUND(0.8,7)) -> 9.92 | AA6: 0 | AB6: 4931.99 | AC6: 707.35 | AD6: 0 | AE6: 0 | AF6: 4403.56 | AG6: 707.35 | AH6: 0 | AI6: 1 | AJ6: 1.12 | AK6: 1 | AL6: 1 | AM6: 2 | AN6: 0 | AO6: 0 | AP6: 1 | AQ6: 1 | AR6: 0 | AT6: 12.4 | AU6: *0,8 | AV6: 1 | AW6: 2 | AX6: 38182949 | AY6: 1 | AZ6: 0 | BA6: 6 | BB6: 1 | BC6: 0 | BD6: 0 | BE6: 0 | BF6: 0 | BG6: 0 | BH6: 0 | BI6: 0 | BJ6: 0 | BK6: 54604.144 | BL6: 8771.14 | BM6: 0 | BN6: 0 | BO6: 12.4 | BP6: 1 | BQ6: 0 | BR6: 43683.315 | BS6: 7016.912 | BT6: 0 | BU6: 0 | BV6: 9.92 | BW6: 1 | CV6: 0 | CW6: =ROUND(Y6*Source!I25*DO6,7) -> 0.992 | CX6: =ROUND(Y6*Source!I25,7) -> 0.992 | CY6: =AB6 -> 4931.99 | CZ6: =AF6 -> 4403.56 | DA6: =AJ6 -> 1.12 | DB6: =ROUND((ROUND(AT6*CZ6,2)*ROUND(0.8,7)),6) -> 43683.312 | DC6: =ROUND((ROUND(AT6*AG6,2)*ROUND(0.8,7)),6) -> 7016.912 | DF6: =ROUND(ROUND(AE6,2)*CX6,2) -> 0 | DG6: =ROUND(ROUND(AF6*AJ6,2)*CX6,2) -> 4892.53 | DH6: =ROUND(ROUND(AG6,2)*CX6,2) -> 701.69 | DI6: =ROUND(ROUND(AH6,2)*CX6,2) -> 0 | DJ6: =DG6+DH6 -> 5594.22 | DK6: 0 | DL6: 4-100-090 | DM6: 9 | DN6: чел.-ч. | DO6: 1
A7: =ROW(Source!A25) -> 25 | B7: 38182922 | C7: 38182946 | D7: 35346009 | E7: 1 | F7: 1 | G7: 1 | H7: 2 | I7: 91.14.02-001 | J7: ФСЭМ-2022 доп.7, 91.14.02-001, приказ Минстроя России от 02.08.2023 г. № 551/пр | K7: Автомобили бортовые, грузоподъемность до 5 т | L7: 1368 | N7: 1011 | O7: маш.-ч | P7: маш.-ч | Q7: 1 | W7: 0 | X7: -849950259 | Y7: =(AT7*ROUND(0.8,7)) -> 0.384 | AA7: 0 | AB7: 652.84 | AC7: 432.81 | AD7: 0 | AE7: 0 | AF7: 652.84 | AG7: 432.81 | AH7: 0 | AI7: 1 | AJ7: 1 | AK7: 1 | AL7: 1 | AM7: -2 | AN7: 0 | AO7: 0 | AP7: 1 | AQ7: 1 | AR7: 0 | AT7: 0.48 | AU7: *0,8 | AV7: 1 | AW7: 2 | AX7: 38182950 | AY7: 1 | AZ7: 0 | BA7: 7 | BB7: 1 | BC7: 0 | BD7: 0 | BE7: 0 | BF7: 0 | BG7: 0 | BH7: 0 | BI7: 0 | BJ7: 0 | BK7: 313.3632 | BL7: 207.7488 | BM7: 0 | BN7: 0 | BO7: 0.48 | BP7: 1 | BQ7: 0 | BR7: 250.69056 | BS7: 166.19904 | BT7: 0 | BU7: 0 | BV7: 0.384 | BW7: 1 | CV7: 0 | CW7: =ROUND(Y7*Source!I25*DO7,7) -> 0.0384 | CX7: =ROUND(Y7*Source!I25,7) -> 0.0384 | CY7: =AB7 -> 652.84 | CZ7: =AF7 -> 652.84 | DA7: =AJ7 -> 1 | DB7: =ROUND((ROUND(AT7*CZ7,2)*ROUND(0.8,7)),6) -> 250.688 | DC7: =ROUND((ROUND(AT7*AG7,2)*ROUND(0.8,7)),6) -> 166.2 | DF7: =ROUND(ROUND(AE7,2)*CX7,2) -> 0 | DG7: =ROUND(ROUND(AF7,2)*CX7,2) -> 25.07 | DH7: =ROUND(ROUND(AG7,2)*CX7,2) -> 16.62 | DI7: =ROUND(ROUND(AH7,2)*CX7,2) -> 0 | DJ7: =DG7+DH7 -> 41.69 | DK7: 1 | DL7: 4-100-040 | DM7: 4 | DN7: чел.-ч. | DO7: 1
A8: =ROW(Source!A25) -> 25 | B8: 38182922 | C8: 38182946 | D8: 35410630 | E8: 1 | F8: 1 | G8: 1 | H8: 3 | I8: 01.1.02.10-1022 | J8: ФСБЦ-2022, 01.1.02.10-1022, приказ Минстроя России от 18.05.2022 г. № 378/пр | K8: Хризотил (асбест хризотиловый), группа 6К, марки 6К-45, 6К-30, 6К-20, 6К-5 | L8: 1348 | N8: 1009 | O8: т | P8: т | Q8: 1000 | W8: 0 | X8: 192185020 | Y8: =(AT8*ROUND(0,7)) -> 0 | AA8: 25474.25 | AB8: 0 | AC8: 0 | AD8: 0 | AE8: 21588.35 | AF8: 0 | AG8: 0 | AH8: 0 | AI8: 1.18 | AJ8: 1 | AK8: 1 | AL8: 1 | AM8: 2 | AN8: 0 | AO8: 0 | AP8: 1 | AQ8: 1 | AR8: 0 | AT8: 0.114 | AU8: *0 | AV8: 0 | AW8: 2 | AX8: 38182951 | AY8: 1 | AZ8: 0 | BA8: 8 | BB8: 1 | BC8: 0 | BD8: 0 | BE8: 0 | BF8: 0 | BG8: 0 | BH8: 0 | BI8: 0 | BJ8: 2461.0719 | BK8: 0 | BL8: 0 | BM8: 0 | BN8: 0 | BO8: 0 | BP8: 1 | BQ8: 0 | BR8: 0 | BS8: 0 | BT8: 0 | BU8: 0 | BV8: 0 | BW8: 0 | CV8: 0 | CW8: 0 | CX8: =ROUND(Y8*Source!I25,7) -> 0 | CY8: =AA8 -> 25474.25 | CZ8: =AE8 -> 21588.35 | DA8: =AI8 -> 1.18 | DB8: =ROUND((ROUND(AT8*CZ8,2)*ROUND(0,7)),6) -> 0 | DC8: =ROUND((ROUND(AT8*AG8,2)*ROUND(0,7)),6) -> 0 | DF8: =ROUND(ROUND(AE8*AI8,2)*CX8,2) -> 0 | DG8: =ROUND(ROUND(AF8,2)*CX8,2) -> 0 | DH8: =ROUND(ROUND(AG8,2)*CX8,2) -> 0 | DI8: =ROUND(ROUND(AH8,2)*CX8,2) -> 0 | DJ8: =DF8 -> 0 | DK8: 0 | DM8: 0 | DO8: 0
A9: =ROW(Source!A25) -> 25 | B9: 38182922 | C9: 38182946 | D9: 35412767 | E9: 1 | F9: 1 | G9: 1 | H9: 3 | I9: 01.7.03.01-0001 | J9: ФСБЦ-2022, 01.7.03.01-0001, приказ Минстроя России от 18.05.2022 г. № 378/пр | K9: Вода | L9: 1339 | N9: 1007 | O9: м3 | P9: м3 | Q9: 1 | W9: 0 | X9: 1964556667 | Y9: =(AT9*ROUND(0,7)) -> 0 | AA9: 26.07 | AB9: 0 | AC9: 0 | AD9: 0 | AE9: 35.71 | AF9: 0 | AG9: 0 | AH9: 0 | AI9: 0.73 | AJ9: 1 | AK9: 1 | AL9: 1 | AM9: 2 | AN9: 0 | AO9: 0 | AP9: 1 | AQ9: 1 | AR9: 0 | AT9: 78.5 | AU9: *0 | AV9: 0 | AW9: 2 | AX9: 38182952 | AY9: 1 | AZ9: 0 | BA9: 9 | BB9: 1 | BC9: 0 | BD9: 0 | BE9: 0 | BF9: 0 | BG9: 0 | BH9: 0 | BI9: 0 | BJ9: 2803.235 | BK9: 0 | BL9: 0 | BM9: 0 | BN9: 0 | BO9: 0 | BP9: 1 | BQ9: 0 | BR9: 0 | BS9: 0 | BT9: 0 | BU9: 0 | BV9: 0 | BW9: 0 | CV9: 0 | CW9: 0 | CX9: =ROUND(Y9*Source!I25,7) -> 0 | CY9: =AA9 -> 26.07 | CZ9: =AE9 -> 35.71 | DA9: =AI9 -> 0.73 | DB9: =ROUND((ROUND(AT9*CZ9,2)*ROUND(0,7)),6) -> 0 | DC9: =ROUND((ROUND(AT9*AG9,2)*ROUND(0,7)),6) -> 0 | DF9: =ROUND(ROUND(AE9*AI9,2)*CX9,2) -> 0 | DG9: =ROUND(ROUND(AF9,2)*CX9,2) -> 0 | DH9: =ROUND(ROUND(AG9,2)*CX9,2) -> 0 | DI9: =ROUND(ROUND(AH9,2)*CX9,2) -> 0 | DJ9: =DF9 -> 0 | DK9: 0 | DM9: 0 | DO9: 0
A10: =ROW(Source!A25) -> 25 | B10: 38182922 | C10: 38182946 | D10: 35413250 | E10: 1 | F10: 1 | G10: 1 | H10: 3 | I10: 01.7.07.29-0322 | J10: ФСБЦ-2022 доп.16, 01.7.07.29-0322, приказ Минстроя России от 12.11.2025 г. № 696/пр | K10: Канат пропитанный (каболка) из льняного и джутового волокна, канализационный и водопроводный, отжатый, диаметр 10-100 мм | L10: 1346 | N10: 1009 | O10: кг | P10: кг | Q10: 1 | W10: 0 | X10: 219322737 | Y10: =(AT10*ROUND(0,7)) -> 0 | AA10: 207.78 | AB10: 0 | AC10: 0 | AD10: 0 | AE10: 152.78 | AF10: 0 | AG10: 0 | AH10: 0 | AI10: 1.36 | AJ10: 1 | AK10: 1 | AL10: 1 | AM10: 2 | AN10: 0 | AO10: 0 | AP10: 1 | AQ10: 1 | AR10: 0 | AT10: 84 | AU10: *0 | AV10: 0 | AW10: 2 | AX10: 38182953 | AY10: 1 | AZ10: 0 | BA10: 10 | BB10: 1 | BC10: 0 | BD10: 0 | BE10: 0 | BF10: 0 | BG10: 0 | BH10: 0 | BI10: 0 | BJ10: 12833.52 | BK10: 0 | BL10: 0 | BM10: 0 | BN10: 0 | BO10: 0 | BP10: 1 | BQ10: 0 | BR10: 0 | BS10: 0 | BT10: 0 | BU10: 0 | BV10: 0 | BW10: 0 | CV10: 0 | CW10: 0 | CX10: =ROUND(Y10*Source!I25,7) -> 0 | CY10: =AA10 -> 207.78 | CZ10: =AE10 -> 152.78 | DA10: =AI10 -> 1.36 | DB10: =ROUND((ROUND(AT10*CZ10,2)*ROUND(0,7)),6) -> 0 | DC10: =ROUND((ROUND(AT10*AG10,2)*ROUND(0,7)),6) -> 0 | DF10: =ROUND(ROUND(AE10*AI10,2)*CX10,2) -> 0 | DG10: =ROUND(ROUND(AF10,2)*CX10,2) -> 0 | DH10: =ROUND(ROUND(AG10,2)*CX10,2) -> 0 | DI10: =ROUND(ROUND(AH10,2)*CX10,2) -> 0 | DJ10: =DF10 -> 0 | DK10: 0 | DM10: 0 | DO10: 0
A11: =ROW(Source!A25) -> 25 | B11: 38182922 | C11: 38182946 | D11: 35416145 | E11: 1 | F11: 1 | G11: 1 | H11: 3 | I11: 03.2.01.01-0001 | J11: ФСБЦ-2022 доп.14, 03.2.01.01-0001, приказ Минстроя России от 19.05.2025 г. № 299/пр | K11: Портландцемент бездобавочный общестроительный ЦЕМ 0 32,5Н | L11: 1348 | N11: 1009 | O11: т | P11: т | Q11: 1000 | W11: 0 | X11: 269049756 | Y11: =(AT11*ROUND(0,7)) -> 0 | AA11: 9073.61 | AB11: 0 | AC11: 0 | AD11: 0 | AE11: 4800.85 | AF11: 0 | AG11: 0 | AH11: 0 | AI11: 1.89 | AJ11: 1 | AK11: 1 | AL11: 1 | AM11: 2 | AN11: 0 | AO11: 0 | AP11: 1 | AQ11: 1 | AR11: 0 | AT11: 0.2656 | AU11: *0 | AV11: 0 | AW11: 2 | AX11: 38182954 | AY11: 1 | AZ11: 0 | BA11: 11 | BB11: 1 | BC11: 0 | BD11: 0 | BE11: 0 | BF11: 0 | BG11: 0 | BH11: 0 | BI11: 0 | BJ11: 1275.1058 | BK11: 0 | BL11: 0 | BM11: 0 | BN11: 0 | BO11: 0 | BP11: 1 | BQ11: 0 | BR11: 0 | BS11: 0 | BT11: 0 | BU11: 0 | BV11: 0 | BW11: 0 | CV11: 0 | CW11: 0 | CX11: =ROUND(Y11*Source!I25,7) -> 0 | CY11: =AA11 -> 9073.61 | CZ11: =AE11 -> 4800.85 | DA11: =AI11 -> 1.89 | DB11: =ROUND((ROUND(AT11*CZ11,2)*ROUND(0,7)),6) -> 0 | DC11: =ROUND((ROUND(AT11*AG11,2)*ROUND(0,7)),6) -> 0 | DF11: =ROUND(ROUND(AE11*AI11,2)*CX11,2) -> 0 | DG11: =ROUND(ROUND(AF11,2)*CX11,2) -> 0 | DH11: =ROUND(ROUND(AG11,2)*CX11,2) -> 0 | DI11: =ROUND(ROUND(AH11,2)*CX11,2) -> 0 | DJ11: =DF11 -> 0 | DK11: 0 | DM11: 0 | DO11: 0
A12: =ROW(Source!A25) -> 25 | B12: 38182922 | C12: 38182946 | D12: 35416737 | E12: 1 | F12: 1 | G12: 1 | H12: 3 | I12: 04.3.01.09-0014 | J12: ФСБЦ-2022, 04.3.01.09-0014, приказ Минстроя России от 18.05.2022 г. № 378/пр | K12: Раствор готовый кладочный, цементный, М100 | L12: 1339 | N12: 1007 | O12: м3 | P12: м3 | Q12: 1 | W12: 0 | X12: -2089581116 | Y12: =(AT12*ROUND(0,7)) -> 0 | AA12: 5769.31 | AB12: 0 | AC12: 0 | AD12: 0 | AE12: 5769.31 | AF12: 0 | AG12: 0 | AH12: 0 | AI12: 1 | AJ12: 1 | AK12: 1 | AL12: 1 | AM12: -2 | AN12: 0 | AO12: 0 | AP12: 1 | AQ12: 1 | AR12: 0 | AT12: 0.66 | AU12: *0 | AV12: 0 | AW12: 2 | AX12: 38182955 | AY12: 1 | AZ12: 0 | BA12: 12 | BB12: 1 | BC12: 0 | BD12: 0 | BE12: 0 | BF12: 0 | BG12: 0 | BH12: 0 | BI12: 0 | BJ12: 3807.7446 | BK12: 0 | BL12: 0 | BM12: 0 | BN12: 0 | BO12: 0 | BP12: 1 | BQ12: 0 | BR12: 0 | BS12: 0 | BT12: 0 | BU12: 0 | BV12: 0 | BW12: 0 | CV12: 0 | CW12: 0 | CX12: =ROUND(Y12*Source!I25,7) -> 0 | CY12: =AA12 -> 5769.31 | CZ12: =AE12 -> 5769.31 | DA12: =AI12 -> 1 | DB12: =ROUND((ROUND(AT12*CZ12,2)*ROUND(0,7)),6) -> 0 | DC12: =ROUND((ROUND(AT12*AG12,2)*ROUND(0,7)),6) -> 0 | DF12: =ROUND(ROUND(AE12,2)*CX12,2) -> 0 | DG12: =ROUND(ROUND(AF12,2)*CX12,2) -> 0 | DH12: =ROUND(ROUND(AG12,2)*CX12,2) -> 0 | DI12: =ROUND(ROUND(AH12,2)*CX12,2) -> 0 | DJ12: =DF12 -> 0 | DK12: 1 | DM12: 0 | DO12: 0
A13: =ROW(Source!A25) -> 25 | B13: 38182922 | C13: 38182946 | D13: 35340034 | E13: 117 | F13: 1 | G13: 1 | H13: 3 | I13: 05.1.02.08 | K13: Трубы железобетонные безнапорные раструбные | L13: 1301 | N13: 1003 | O13: м | P13: м | Q13: 1 | W13: 0 | X13: 1219364707 | Y13: =(AT13*ROUND(0,7)) -> 0 | AA13: 0 | AB13: 0 | AC13: 0 | AD13: 0 | AE13: 0 | AF13: 0 | AG13: 0 | AH13: 0 | AI13: 1 | AJ13: 1 | AK13: 1 | AL13: 1 | AM13: 0 | AN13: 0 | AO13: 0 | AP13: 1 | AQ13: 0 | AR13: 0 | AT13: 99.7 | AU13: *0 | AV13: 0 | AW13: 2 | AX13: 38182956 | AY13: 1 | AZ13: 0 | BA13: 13 | BB13: 0 | BC13: 0 | BD13: 0 | BE13: 0 | BF13: 0 | BG13: 0 | BH13: 0 | BI13: 0 | BJ13: 0 | BK13: 0 | BL13: 0 | BM13: 0 | BN13: 0 | BO13: 0 | BP13: 0 | BQ13: 0 | BR13: 0 | BS13: 0 | BT13: 0 | BU13: 0 | BV13: 0 | BW13: 0 | CV13: 0 | CW13: 0 | CX13: =ROUND(Y13*Source!I25,7) -> 0 | CY13: =AA13 -> 0 | CZ13: =AE13 -> 0 | DA13: =AI13 -> 1 | DB13: =ROUND((ROUND(AT13*CZ13,2)*ROUND(0,7)),6) -> 0 | DC13: =ROUND((ROUND(AT13*AG13,2)*ROUND(0,7)),6) -> 0 | DF13: =ROUND(ROUND(AE13,2)*CX13,2) -> 0 | DG13: =ROUND(ROUND(AF13,2)*CX13,2) -> 0 | DH13: =ROUND(ROUND(AG13,2)*CX13,2) -> 0 | DI13: =ROUND(ROUND(AH13,2)*CX13,2) -> 0 | DJ13: =DF13 -> 0 | DK13: 0 | DM13: 0 | DO13: 0
A14: =ROW(Source!A27) -> 27 | B14: 38182922 | C14: 38183869 | D14: 35338476 | E14: 117 | F14: 1 | G14: 1 | H14: 1 | I14: 1-100-47 | K14: Средний разряд работы 4,7 | L14: 1191 | N14: 1013 | O14: чел.-ч. | P14: чел.-ч. | Q14: 1 | W14: 0 | X14: 1521243167 | Y14: =AT14 -> 1.59 | AA14: 0 | AB14: 0 | AC14: 0 | AD14: 478.03 | AE14: 0 | AF14: 0 | AG14: 0 | AH14: 478.03 | AI14: 1 | AJ14: 1 | AK14: 1 | AL14: 1 | AM14: -2 | AN14: 0 | AO14: 0 | AP14: 1 | AQ14: 1 | AR14: 0 | AT14: 1.59 | AV14: 1 | AW14: 2 | AX14: 38183870 | AY14: 1 | AZ14: 0 | BA14: 14 | BB14: 1 | BC14: 0 | BD14: 0 | BE14: 0 | BF14: 0 | BG14: 0 | BH14: 0 | BI14: 0 | BJ14: 0 | BK14: 0 | BL14: 0 | BM14: 760.0677 | BN14: 1.59 | BO14: 0 | BP14: 1 | BQ14: 0 | BR14: 0 | BS14: 0 | BT14: 760.0677 | BU14: 1.59 | BV14: 0 | BW14: 1 | CU14: =ROUND(AT14*Source!I27*AH14*AL14,2) -> 760.07 | CV14: =ROUND(Y14*Source!I27,7) -> 1.59 | CW14: 0 | CX14: =ROUND(Y14*Source!I27,7) -> 1.59 | CY14: =AD14 -> 478.03 | CZ14: =AH14 -> 478.03 | DA14: =AL14 -> 1 | DB14: =ROUND(ROUND(AT14*CZ14,2),6) -> 760.07 | DC14: =ROUND(ROUND(AT14*AG14,2),6) -> 0 | DF14: =ROUND(ROUND(AE14,2)*CX14,2) -> 0 | DG14: =ROUND(ROUND(AF14,2)*CX14,2) -> 0 | DH14: =ROUND(ROUND(AG14,2)*CX14,2) -> 0 | DI14: =ROUND(ROUND(AH14,2)*CX14,2) -> 760.07 | DJ14: =DI14 -> 760.07 | DK14: 1 | DM14: 0 | DO14: 0
A15: =ROW(Source!A27) -> 27 | B15: 38182922 | C15: 38183869 | D15: 35338624 | E15: 117 | F15: 1 | G15: 1 | H15: 1 | I15: 4-100-00 | K15: Затраты труда машинистов | L15: 1191 | N15: 1013 | O15: чел.-ч. | P15: чел.-ч. | Q15: 1 | W15: 0 | X15: -1417349443 | Y15: =AT15 -> 0.75 | AA15: 0 | AB15: 0 | AC15: 0 | AD15: 0 | AE15: 0 | AF15: 0 | AG15: 0 | AH15: 0 | AI15: 1 | AJ15: 1 | AK15: 1 | AL15: 1 | AM15: -2 | AN15: 0 | AO15: 0 | AP15: 1 | AQ15: 1 | AR15: 0 | AT15: 0.75 | AV15: 2 | AW15: 2 | AX15: 38183871 | AY15: 1 | AZ15: 0 | BA15: 15 | BB15: 1 | BC15: 0 | BD15: 0 | BE15: 0 | BF15: 0 | BG15: 0 | BH15: 0 | BI15: 0 | BJ15: 0 | BK15: 0 | BL15: 0 | BM15: 0 | BN15: 0 | BO15: 0 | BP15: 0 | BQ15: 0 | BR15: 0 | BS15: 0 | BT15: 0 | BU15: 0 | BV15: 0 | BW15: 0 | CV15: 0 | CW15: 0 | CX15: =ROUND(Y15*Source!I27,7) -> 0.75 | CY15: =AD15 -> 0 | CZ15: =AH15 -> 0 | DA15: =AL15 -> 1 | DB15: =ROUND(ROUND(AT15*CZ15,2),6) -> 0 | DC15: =ROUND(ROUND(AT15*AG15,2),6) -> 0 | DF15: =ROUND(ROUND(AE15,2)*CX15,2) -> 0 | DG15: =ROUND(ROUND(AF15,2)*CX15,2) -> 0 | DH15: =ROUND(ROUND(AG15,2)*CX15,2) -> 0 | DI15: =ROUND(ROUND(AH15,2)*CX15,2) -> 0 | DJ15: =DI15 -> 0 | DK15: 0 | DM15: 0 | DO15: 0
A16: =ROW(Source!A27) -> 27 | B16: 38182922 | C16: 38183869 | D16: 35345762 | E16: 1 | F16: 1 | G16: 1 | H16: 2 | I16: 91.10.05-009 | J16: ФСЭМ-2022, 91.10.05-009, приказ Минстроя России от 18.05.2022 г. № 378/пр | K16: Трубоукладчики, номинальная грузоподъемность 35 т | L16: 1368 | N16: 1011 | O16: маш.-ч | P16: маш.-ч | Q16: 1 | W16: 0 | X16: -1505731505 | Y16: =AT16 -> 0.75 | AA16: 0 | AB16: 4931.99 | AC16: 707.35 | AD16: 0 | AE16: 0 | AF16: 4403.56 | AG16: 707.35 | AH16: 0 | AI16: 1 | AJ16: 1.12 | AK16: 1 | AL16: 1 | AM16: 2 | AN16: 0 | AO16: 0 | AP16: 1 | AQ16: 1 | AR16: 0 | AT16: 0.75 | AV16: 1 | AW16: 2 | AX16: 38183872 | AY16: 1 | AZ16: 0 | BA16: 16 | BB16: 1 | BC16: 0 | BD16: 0 | BE16: 0 | BF16: 0 | BG16: 0 | BH16: 0 | BI16: 0 | BJ16: 0 | BK16: 3302.67 | BL16: 530.5125 | BM16: 0 | BN16: 0 | BO16: 0.75 | BP16: 1 | BQ16: 0 | BR16: 3302.67 | BS16: 530.5125 | BT16: 0 | BU16: 0 | BV16: 0.75 | BW16: 1 | CV16: 0 | CW16: =ROUND(Y16*Source!I27*DO16,7) -> 0.75 | CX16: =ROUND(Y16*Source!I27,7) -> 0.75 | CY16: =AB16 -> 4931.99 | CZ16: =AF16 -> 4403.56 | DA16: =AJ16 -> 1.12 | DB16: =ROUND(ROUND(AT16*CZ16,2),6) -> 3302.67 | DC16: =ROUND(ROUND(AT16*AG16,2),6) -> 530.51 | DF16: =ROUND(ROUND(AE16,2)*CX16,2) -> 0 | DG16: =ROUND(ROUND(AF16*AJ16,2)*CX16,2) -> 3698.99 | DH16: =ROUND(ROUND(AG16,2)*CX16,2) -> 530.51 | DI16: =ROUND(ROUND(AH16,2)*CX16,2) -> 0 | DJ16: =DG16+DH16 -> 4229.5 | DK16: 0 | DL16: 4-100-090 | DM16: 9 | DN16: чел.-ч. | DO16: 1
A17: =ROW(Source!A27) -> 27 | B17: 38182922 | C17: 38183869 | D17: 35346167 | E17: 1 | F17: 1 | G17: 1 | H17: 2 | I17: 91.17.04-042 | J17: ФСЭМ-2022, 91.17.04-042, приказ Минстроя России от 18.05.2022 г. № 378/пр | K17: Аппараты для газовой сварки и резки | L17: 1368 | N17: 1011 | O17: маш.-ч | P17: маш.-ч | Q17: 1 | W17: 0 | X17: -880363394 | Y17: =AT17 -> 0.44 | AA17: 0 | AB17: 5.35 | AC17: 0 | AD17: 0 | AE17: 0 | AF17: 4.35 | AG17: 0 | AH17: 0 | AI17: 1 | AJ17: 1.23 | AK17: 1 | AL17: 1 | AM17: 2 | AN17: 0 | AO17: 0 | AP17: 1 | AQ17: 1 | AR17: 0 | AT17: 0.44 | AV17: 1 | AW17: 2 | AX17: 38183873 | AY17: 1 | AZ17: 0 | BA17: 17 | BB17: 1 | BC17: 0 | BD17: 0 | BE17: 0 | BF17: 0 | BG17: 0 | BH17: 0 | BI17: 0 | BJ17: 0 | BK17: 1.914 | BL17: 0 | BM17: 0 | BN17: 0 | BO17: 0 | BP17: 1 | BQ17: 0 | BR17: 1.914 | BS17: 0 | BT17: 0 | BU17: 0 | BV17: 0 | BW17: 1 | CV17: 0 | CW17: =ROUND(Y17*Source!I27*DO17,7) -> 0 | CX17: =ROUND(Y17*Source!I27,7) -> 0.44 | CY17: =AB17 -> 5.35 | CZ17: =AF17 -> 4.35 | DA17: =AJ17 -> 1.23 | DB17: =ROUND(ROUND(AT17*CZ17,2),6) -> 1.91 | DC17: =ROUND(ROUND(AT17*AG17,2),6) -> 0 | DF17: =ROUND(ROUND(AE17,2)*CX17,2) -> 0 | DG17: =ROUND(ROUND(AF17*AJ17,2)*CX17,2) -> 2.35 | DH17: =ROUND(ROUND(AG17,2)*CX17,2) -> 0 | DI17: =ROUND(ROUND(AH17,2)*CX17,2) -> 0 | DJ17: =DG17+DH17 -> 2.35 | DK17: 0 | DM17: 0 | DO17: 0
A18: =ROW(Source!A27) -> 27 | B18: 38182922 | C18: 38183869 | D18: 35410783 | E18: 1 | F18: 1 | G18: 1 | H18: 3 | I18: 01.3.02.08-0001 | J18: ФСБЦ-2022 доп.3, 01.3.02.08-0001, приказ Минстроя России от 26.10.2022 г. № 905/пр | K18: Кислород газообразный технический | L18: 1339 | N18: 1007 | O18: м3 | P18: м3 | Q18: 1 | W18: 0 | X18: -2058989610 | Y18: =AT18 -> 1.59 | AA18: 89 | AB18: 0 | AC18: 0 | AD18: 0 | AE18: 89 | AF18: 0 | AG18: 0 | AH18: 0 | AI18: 1 | AJ18: 1 | AK18: 1 | AL18: 1 | AM18: -2 | AN18: 0 | AO18: 0 | AP18: 1 | AQ18: 1 | AR18: 0 | AT18: 1.59 | AV18: 0 | AW18: 2 | AX18: 38183874 | AY18: 1 | AZ18: 0 | BA18: 18 | BB18: 1 | BC18: 0 | BD18: 0 | BE18: 0 | BF18: 0 | BG18: 0 | BH18: 0 | BI18: 0 | BJ18: 141.51 | BK18: 0 | BL18: 0 | BM18: 0 | BN18: 0 | BO18: 0 | BP18: 1 | BQ18: 141.51 | BR18: 0 | BS18: 0 | BT18: 0 | BU18: 0 | BV18: 0 | BW18: 1 | CV18: 0 | CW18: 0 | CX18: =ROUND(Y18*Source!I27,7) -> 1.59 | CY18: =AA18 -> 89 | CZ18: =AE18 -> 89 | DA18: =AI18 -> 1 | DB18: =ROUND(ROUND(AT18*CZ18,2),6) -> 141.51 | DC18: =ROUND(ROUND(AT18*AG18,2),6) -> 0 | DF18: =ROUND(ROUND(AE18,2)*CX18,2) -> 141.51 | DG18: =ROUND(ROUND(AF18,2)*CX18,2) -> 0 | DH18: =ROUND(ROUND(AG18,2)*CX18,2) -> 0 | DI18: =ROUND(ROUND(AH18,2)*CX18,2) -> 0 | DJ18: =DF18 -> 141.51 | DK18: 1 | DM18: 0 | DO18: 0
A19: =ROW(Source!A27) -> 27 | B19: 38182922 | C19: 38183869 | D19: 35410787 | E19: 1 | F19: 1 | G19: 1 | H19: 3 | I19: 01.3.02.09-0022 | J19: ФСБЦ-2022 доп.3, 01.3.02.09-0022, приказ Минстроя России от 26.10.2022 г. № 905/пр | K19: Пропан-бутан смесь техническая | L19: 1346 | N19: 1009 | O19: кг | P19: кг | Q19: 1 | W19: 0 | X19: -1568219933 | Y19: =AT19 -> 4.0656 | AA19: 57.1 | AB19: 0 | AC19: 0 | AD19: 0 | AE19: 41.38 | AF19: 0 | AG19: 0 | AH19: 0 | AI19: 1.38 | AJ19: 1 | AK19: 1 | AL19: 1 | AM19: 2 | AN19: 0 | AO19: 0 | AP19: 1 | AQ19: 1 | AR19: 0 | AT19: 4.0656 | AV19: 0 | AW19: 2 | AX19: 38183875 | AY19: 1 | AZ19: 0 | BA19: 19 | BB19: 1 | BC19: 0 | BD19: 0 | BE19: 0 | BF19: 0 | BG19: 0 | BH19: 0 | BI19: 0 | BJ19: 168.23453 | BK19: 0 | BL19: 0 | BM19: 0 | BN19: 0 | BO19: 0 | BP19: 1 | BQ19: 168.23453 | BR19: 0 | BS19: 0 | BT19: 0 | BU19: 0 | BV19: 0 | BW19: 1 | CV19: 0 | CW19: 0 | CX19: =ROUND(Y19*Source!I27,7) -> 4.0656 | CY19: =AA19 -> 57.1 | CZ19: =AE19 -> 41.38 | DA19: =AI19 -> 1.38 | DB19: =ROUND(ROUND(AT19*CZ19,2),6) -> 168.23 | DC19: =ROUND(ROUND(AT19*AG19,2),6) -> 0 | DF19: =ROUND(ROUND(AE19*AI19,2)*CX19,2) -> 232.15 | DG19: =ROUND(ROUND(AF19,2)*CX19,2) -> 0 | DH19: =ROUND(ROUND(AG19,2)*CX19,2) -> 0 | DI19: =ROUND(ROUND(AH19,2)*CX19,2) -> 0 | DJ19: =DF19 -> 232.15 | DK19: 0 | DM19: 0 | DO19: 0
A20: =ROW(Source!A27) -> 27 | B20: 38182922 | C20: 38183869 | D20: 35423680 | E20: 1 | F20: 1 | G20: 1 | H20: 3 | I20: 11.1.03.01-0067 | J20: ФСБЦ-2022, 11.1.03.01-0067, приказ Минстроя России от 18.05.2022 г. № 378/пр | K20: Брус обрезной хвойных пород (ель, сосна), естественной влажности, длина 2-6,5 м, ширина 100 и более мм, толщина 100 и более мм, сорт III | L20: 1339 | N20: 1007 | O20: м3 | P20: м3 | Q20: 1 | W20: 0 | X20: -831399682 | Y20: =AT20 -> 0.027 | AA20: 13324 | AB20: 0 | AC20: 0 | AD20: 0 | AE20: 16655 | AF20: 0 | AG20: 0 | AH20: 0 | AI20: 0.8 | AJ20: 1 | AK20: 1 | AL20: 1 | AM20: 2 | AN20: 0 | AO20: 0 | AP20: 1 | AQ20: 1 | AR20: 0 | AT20: 0.027 | AV20: 0 | AW20: 2 | AX20: 38183876 | AY20: 1 | AZ20: 0 | BA20: 20 | BB20: 1 | BC20: 0 | BD20: 0 | BE20: 0 | BF20: 0 | BG20: 0 | BH20: 0 | BI20: 0 | BJ20: 449.685 | BK20: 0 | BL20: 0 | BM20: 0 | BN20: 0 | BO20: 0 | BP20: 1 | BQ20: 449.685 | BR20: 0 | BS20: 0 | BT20: 0 | BU20: 0 | BV20: 0 | BW20: 1 | CV20: 0 | CW20: 0 | CX20: =ROUND(Y20*Source!I27,7) -> 0.027 | CY20: =AA20 -> 13324 | CZ20: =AE20 -> 16655 | DA20: =AI20 -> 0.8 | DB20: =ROUND(ROUND(AT20*CZ20,2),6) -> 449.69 | DC20: =ROUND(ROUND(AT20*AG20,2),6) -> 0 | DF20: =ROUND(ROUND(AE20*AI20,2)*CX20,2) -> 359.75 | DG20: =ROUND(ROUND(AF20,2)*CX20,2) -> 0 | DH20: =ROUND(ROUND(AG20,2)*CX20,2) -> 0 | DI20: =ROUND(ROUND(AH20,2)*CX20,2) -> 0 | DJ20: =DF20 -> 359.75 | DK20: 0 | DM20: 0 | DO20: 0
A21: =ROW(Source!A28) -> 28 | B21: 38182922 | C21: 38182974 | D21: 20031442 | E21: 117 | F21: 1 | G21: 1 | H21: 1 | I21: 1-100-40 | K21: Средний разряд работы 4,0 | L21: 1191 | N21: 1013 | O21: чел.-ч. | P21: чел.-ч. | Q21: 1 | W21: 0 | X21: 888410196 | Y21: =AT21 -> 187.6 | AA21: 0 | AB21: 0 | AC21: 0 | AD21: 432.81 | AE21: 0 | AF21: 0 | AG21: 0 | AH21: 432.81 | AI21: 1 | AJ21: 1 | AK21: 1 | AL21: 1 | AM21: -2 | AN21: 0 | AO21: 0 | AP21: 1 | AQ21: 1 | AR21: 0 | AT21: 187.6 | AV21: 1 | AW21: 2 | AX21: 38182985 | AY21: 1 | AZ21: 0 | BA21: 21 | BB21: 1 | BC21: 0 | BD21: 0 | BE21: 0 | BF21: 0 | BG21: 0 | BH21: 0 | BI21: 0 | BJ21: 0 | BK21: 0 | BL21: 0 | BM21: 81195.156 | BN21: 187.6 | BO21: 0 | BP21: 1 | BQ21: 0 | BR21: 0 | BS21: 0 | BT21: 81195.156 | BU21: 187.6 | BV21: 0 | BW21: 1 | CU21: =ROUND(AT21*Source!I28*AH21*AL21,2) -> 8119.52 | CV21: =ROUND(Y21*Source!I28,7) -> 18.76 | CW21: 0 | CX21: =ROUND(Y21*Source!I28,7) -> 18.76 | CY21: =AD21 -> 432.81 | CZ21: =AH21 -> 432.81 | DA21: =AL21 -> 1 | DB21: =ROUND(ROUND(AT21*CZ21,2),6) -> 81195.16 | DC21: =ROUND(ROUND(AT21*AG21,2),6) -> 0 | DF21: =ROUND(ROUND(AE21,2)*CX21,2) -> 0 | DG21: =ROUND(ROUND(AF21,2)*CX21,2) -> 0 | DH21: =ROUND(ROUND(AG21,2)*CX21,2) -> 0 | DI21: =ROUND(ROUND(AH21,2)*CX21,2) -> 8119.52 | DJ21: =DI21 -> 8119.52 | DK21: 1 | DM21: 0 | DO21: 0
A22: =ROW(Source!A28) -> 28 | B22: 38182922 | C22: 38182974 | D22: 20031379 | E22: 117 | F22: 1 | G22: 1 | H22: 1 | I22: 4-100-00 | K22: Затраты труда машинистов | L22: 1191 | N22: 1013 | O22: чел.-ч. | P22: чел.-ч. | Q22: 1 | W22: 0 | X22: -1417349443 | Y22: =AT22 -> 12.88 | AA22: 0 | AB22: 0 | AC22: 0 | AD22: 0 | AE22: 0 | AF22: 0 | AG22: 0 | AH22: 0 | AI22: 1 | AJ22: 1 | AK22: 1 | AL22: 1 | AM22: -2 | AN22: 0 | AO22: 0 | AP22: 1 | AQ22: 1 | AR22: 0 | AT22: 12.88 | AV22: 2 | AW22: 2 | AX22: 38182986 | AY22: 1 | AZ22: 0 | BA22: 22 | BB22: 1 | BC22: 0 | BD22: 0 | BE22: 0 | BF22: 0 | BG22: 0 | BH22: 0 | BI22: 0 | BJ22: 0 | BK22: 0 | BL22: 0 | BM22: 0 | BN22: 0 | BO22: 0 | BP22: 0 | BQ22: 0 | BR22: 0 | BS22: 0 | BT22: 0 | BU22: 0 | BV22: 0 | BW22: 0 | CV22: 0 | CW22: 0 | CX22: =ROUND(Y22*Source!I28,7) -> 1.288 | CY22: =AD22 -> 0 | CZ22: =AH22 -> 0 | DA22: =AL22 -> 1 | DB22: =ROUND(ROUND(AT22*CZ22,2),6) -> 0 | DC22: =ROUND(ROUND(AT22*AG22,2),6) -> 0 | DF22: =ROUND(ROUND(AE22,2)*CX22,2) -> 0 | DG22: =ROUND(ROUND(AF22,2)*CX22,2) -> 0 | DH22: =ROUND(ROUND(AG22,2)*CX22,2) -> 0 | DI22: =ROUND(ROUND(AH22,2)*CX22,2) -> 0 | DJ22: =DI22 -> 0 | DK22: 0 | DM22: 0 | DO22: 0
A23: =ROW(Source!A28) -> 28 | B23: 38182922 | C23: 38182974 | D23: 35345762 | E23: 1 | F23: 1 | G23: 1 | H23: 2 | I23: 91.10.05-009 | J23: ФСЭМ-2022, 91.10.05-009, приказ Минстроя России от 18.05.2022 г. № 378/пр | K23: Трубоукладчики, номинальная грузоподъемность 35 т | L23: 1368 | N23: 1011 | O23: маш.-ч | P23: маш.-ч | Q23: 1 | W23: 0 | X23: -1505731505 | Y23: =AT23 -> 12.4 | AA23: 0 | AB23: 4931.99 | AC23: 707.35 | AD23: 0 | AE23: 0 | AF23: 4403.56 | AG23: 707.35 | AH23: 0 | AI23: 1 | AJ23: 1.12 | AK23: 1 | AL23: 1 | AM23: 2 | AN23: 0 | AO23: 0 | AP23: 1 | AQ23: 1 | AR23: 0 | AT23: 12.4 | AV23: 1 | AW23: 2 | AX23: 38182987 | AY23: 1 | AZ23: 0 | BA23: 23 | BB23: 1 | BC23: 0 | BD23: 0 | BE23: 0 | BF23: 0 | BG23: 0 | BH23: 0 | BI23: 0 | BJ23: 0 | BK23: 54604.144 | BL23: 8771.14 | BM23: 0 | BN23: 0 | BO23: 12.4 | BP23: 1 | BQ23: 0 | BR23: 54604.144 | BS23: 8771.14 | BT23: 0 | BU23: 0 | BV23: 12.4 | BW23: 1 | CV23: 0 | CW23: =ROUND(Y23*Source!I28*DO23,7) -> 1.24 | CX23: =ROUND(Y23*Source!I28,7) -> 1.24 | CY23: =AB23 -> 4931.99 | CZ23: =AF23 -> 4403.56 | DA23: =AJ23 -> 1.12 | DB23: =ROUND(ROUND(AT23*CZ23,2),6) -> 54604.14 | DC23: =ROUND(ROUND(AT23*AG23,2),6) -> 8771.14 | DF23: =ROUND(ROUND(AE23,2)*CX23,2) -> 0 | DG23: =ROUND(ROUND(AF23*AJ23,2)*CX23,2) -> 6115.67 | DH23: =ROUND(ROUND(AG23,2)*CX23,2) -> 877.11 | DI23: =ROUND(ROUND(AH23,2)*CX23,2) -> 0 | DJ23: =DG23+DH23 -> 6992.78 | DK23: 0 | DL23: 4-100-090 | DM23: 9 | DN23: чел.-ч. | DO23: 1
A24: =ROW(Source!A28) -> 28 | B24: 38182922 | C24: 38182974 | D24: 35346009 | E24: 1 | F24: 1 | G24: 1 | H24: 2 | I24: 91.14.02-001 | J24: ФСЭМ-2022 доп.7, 91.14.02-001, приказ Минстроя России от 02.08.2023 г. № 551/пр | K24: Автомобили бортовые, грузоподъемность до 5 т | L24: 1368 | N24: 1011 | O24: маш.-ч | P24: маш.-ч | Q24: 1 | W24: 0 | X24: -849950259 | Y24: =AT24 -> 0.48 | AA24: 0 | AB24: 652.84 | AC24: 432.81 | AD24: 0 | AE24: 0 | AF24: 652.84 | AG24: 432.81 | AH24: 0 | AI24: 1 | AJ24: 1 | AK24: 1 | AL24: 1 | AM24: -2 | AN24: 0 | AO24: 0 | AP24: 1 | AQ24: 1 | AR24: 0 | AT24: 0.48 | AV24: 1 | AW24: 2 | AX24: 38182988 | AY24: 1 | AZ24: 0 | BA24: 24 | BB24: 1 | BC24: 0 | BD24: 0 | BE24: 0 | BF24: 0 | BG24: 0 | BH24: 0 | BI24: 0 | BJ24: 0 | BK24: 313.3632 | BL24: 207.7488 | BM24: 0 | BN24: 0 | BO24: 0.48 | BP24: 1 | BQ24: 0 | BR24: 313.3632 | BS24: 207.7488 | BT24: 0 | BU24: 0 | BV24: 0.48 | BW24: 1 | CV24: 0 | CW24: =ROUND(Y24*Source!I28*DO24,7) -> 0.048 | CX24: =ROUND(Y24*Source!I28,7) -> 0.048 | CY24: =AB24 -> 652.84 | CZ24: =AF24 -> 652.84 | DA24: =AJ24 -> 1 | DB24: =ROUND(ROUND(AT24*CZ24,2),6) -> 313.36 | DC24: =ROUND(ROUND(AT24*AG24,2),6) -> 207.75 | DF24: =ROUND(ROUND(AE24,2)*CX24,2) -> 0 | DG24: =ROUND(ROUND(AF24,2)*CX24,2) -> 31.34 | DH24: =ROUND(ROUND(AG24,2)*CX24,2) -> 20.77 | DI24: =ROUND(ROUND(AH24,2)*CX24,2) -> 0 | DJ24: =DG24+DH24 -> 52.11 | DK24: 1 | DL24: 4-100-040 | DM24: 4 | DN24: чел.-ч. | DO24: 1
A25: =ROW(Source!A28) -> 28 | B25: 38182922 | C25: 38182974 | D25: 35410630 | E25: 1 | F25: 1 | G25: 1 | H25: 3 | I25: 01.1.02.10-1022 | J25: ФСБЦ-2022, 01.1.02.10-1022, приказ Минстроя России от 18.05.2022 г. № 378/пр | K25: Хризотил (асбест хризотиловый), группа 6К, марки 6К-45, 6К-30, 6К-20, 6К-5 | L25: 1348 | N25: 1009 | O25: т | P25: т | Q25: 1000 | W25: 0 | X25: 192185020 | Y25: =AT25 -> 0.114 | AA25: 25474.25 | AB25: 0 | AC25: 0 | AD25: 0 | AE25: 21588.35 | AF25: 0 | AG25: 0 | AH25: 0 | AI25: 1.18 | AJ25: 1 | AK25: 1 | AL25: 1 | AM25: 2 | AN25: 0 | AO25: 0 | AP25: 1 | AQ25: 1 | AR25: 0 | AT25: 0.114 | AV25: 0 | AW25: 2 | AX25: 38182989 | AY25: 1 | AZ25: 0 | BA25: 25 | BB25: 1 | BC25: 0 | BD25: 0 | BE25: 0 | BF25: 0 | BG25: 0 | BH25: 0 | BI25: 0 | BJ25: 2461.0719 | BK25: 0 | BL25: 0 | BM25: 0 | BN25: 0 | BO25: 0 | BP25: 1 | BQ25: 2461.0719 | BR25: 0 | BS25: 0 | BT25: 0 | BU25: 0 | BV25: 0 | BW25: 1 | CV25: 0 | CW25: 0 | CX25: =ROUND(Y25*Source!I28,7) -> 0.0114 | CY25: =AA25 -> 25474.25 | CZ25: =AE25 -> 21588.35 | DA25: =AI25 -> 1.18 | DB25: =ROUND(ROUND(AT25*CZ25,2),6) -> 2461.07 | DC25: =ROUND(ROUND(AT25*AG25,2),6) -> 0 | DF25: =ROUND(ROUND(AE25*AI25,2)*CX25,2) -> 290.41 | DG25: =ROUND(ROUND(AF25,2)*CX25,2) -> 0 | DH25: =ROUND(ROUND(AG25,2)*CX25,2) -> 0 | DI25: =ROUND(ROUND(AH25,2)*CX25,2) -> 0 | DJ25: =DF25 -> 290.41 | DK25: 0 | DM25: 0 | DO25: 0
A26: =ROW(Source!A28) -> 28 | B26: 38182922 | C26: 38182974 | D26: 35412767 | E26: 1 | F26: 1 | G26: 1 | H26: 3 | I26: 01.7.03.01-0001 | J26: ФСБЦ-2022, 01.7.03.01-0001, приказ Минстроя России от 18.05.2022 г. № 378/пр | K26: Вода | L26: 1339 | N26: 1007 | O26: м3 | P26: м3 | Q26: 1 | W26: 0 | X26: 1964556667 | Y26: =AT26 -> 78.5 | AA26: 26.07 | AB26: 0 | AC26: 0 | AD26: 0 | AE26: 35.71 | AF26: 0 | AG26: 0 | AH26: 0 | AI26: 0.73 | AJ26: 1 | AK26: 1 | AL26: 1 | AM26: 2 | AN26: 0 | AO26: 0 | AP26: 1 | AQ26: 1 | AR26: 0 | AT26: 78.5 | AV26: 0 | AW26: 2 | AX26: 38182990 | AY26: 1 | AZ26: 0 | BA26: 26 | BB26: 1 | BC26: 0 | BD26: 0 | BE26: 0 | BF26: 0 | BG26: 0 | BH26: 0 | BI26: 0 | BJ26: 2803.235 | BK26: 0 | BL26: 0 | BM26: 0 | BN26: 0 | BO26: 0 | BP26: 1 | BQ26: 2803.235 | BR26: 0 | BS26: 0 | BT26: 0 | BU26: 0 | BV26: 0 | BW26: 1 | CV26: 0 | CW26: 0 | CX26: =ROUND(Y26*Source!I28,7) -> 7.85 | CY26: =AA26 -> 26.07 | CZ26: =AE26 -> 35.71 | DA26: =AI26 -> 0.73 | DB26: =ROUND(ROUND(AT26*CZ26,2),6) -> 2803.24 | DC26: =ROUND(ROUND(AT26*AG26,2),6) -> 0 | DF26: =ROUND(ROUND(AE26*AI26,2)*CX26,2) -> 204.65 | DG26: =ROUND(ROUND(AF26,2)*CX26,2) -> 0 | DH26: =ROUND(ROUND(AG26,2)*CX26,2) -> 0 | DI26: =ROUND(ROUND(AH26,2)*CX26,2) -> 0 | DJ26: =DF26 -> 204.65 | DK26: 0 | DM26: 0 | DO26: 0
A27: =ROW(Source!A28) -> 28 | B27: 38182922 | C27: 38182974 | D27: 35413250 | E27: 1 | F27: 1 | G27: 1 | H27: 3 | I27: 01.7.07.29-0322 | J27: ФСБЦ-2022 доп.16, 01.7.07.29-0322, приказ Минстроя России от 12.11.2025 г. № 696/пр | K27: Канат пропитанный (каболка) из льняного и джутового волокна, канализационный и водопроводный, отжатый, диаметр 10-100 мм | L27: 1346 | N27: 1009 | O27: кг | P27: кг | Q27: 1 | W27: 0 | X27: 219322737 | Y27: =AT27 -> 84 | AA27: 207.78 | AB27: 0 | AC27: 0 | AD27: 0 | AE27: 152.78 | AF27: 0 | AG27: 0 | AH27: 0 | AI27: 1.36 | AJ27: 1 | AK27: 1 | AL27: 1 | AM27: 2 | AN27: 0 | AO27: 0 | AP27: 1 | AQ27: 1 | AR27: 0 | AT27: 84 | AV27: 0 | AW27: 2 | AX27: 38182991 | AY27: 1 | AZ27: 0 | BA27: 27 | BB27: 1 | BC27: 0 | BD27: 0 | BE27: 0 | BF27: 0 | BG27: 0 | BH27: 0 | BI27: 0 | BJ27: 12833.52 | BK27: 0 | BL27: 0 | BM27: 0 | BN27: 0 | BO27: 0 | BP27: 1 | BQ27: 12833.52 | BR27: 0 | BS27: 0 | BT27: 0 | BU27: 0 | BV27: 0 | BW27: 1 | CV27: 0 | CW27: 0 | CX27: =ROUND(Y27*Source!I28,7) -> 8.4 | CY27: =AA27 -> 207.78 | CZ27: =AE27 -> 152.78 | DA27: =AI27 -> 1.36 | DB27: =ROUND(ROUND(AT27*CZ27,2),6) -> 12833.52 | DC27: =ROUND(ROUND(AT27*AG27,2),6) -> 0 | DF27: =ROUND(ROUND(AE27*AI27,2)*CX27,2) -> 1745.35 | DG27: =ROUND(ROUND(AF27,2)*CX27,2) -> 0 | DH27: =ROUND(ROUND(AG27,2)*CX27,2) -> 0 | DI27: =ROUND(ROUND(AH27,2)*CX27,2) -> 0 | DJ27: =DF27 -> 1745.35 | DK27: 0 | DM27: 0 | DO27: 0
A28: =ROW(Source!A28) -> 28 | B28: 38182922 | C28: 38182974 | D28: 35416145 | E28: 1 | F28: 1 | G28: 1 | H28: 3 | I28: 03.2.01.01-0001 | J28: ФСБЦ-2022 доп.14, 03.2.01.01-0001, приказ Минстроя России от 19.05.2025 г. № 299/пр | K28: Портландцемент бездобавочный общестроительный ЦЕМ 0 32,5Н | L28: 1348 | N28: 1009 | O28: т | P28: т | Q28: 1000 | W28: 0 | X28: 269049756 | Y28: =AT28 -> 0.2656 | AA28: 9073.61 | AB28: 0 | AC28: 0 | AD28: 0 | AE28: 4800.85 | AF28: 0 | AG28: 0 | AH28: 0 | AI28: 1.89 | AJ28: 1 | AK28: 1 | AL28: 1 | AM28: 2 | AN28: 0 | AO28: 0 | AP28: 1 | AQ28: 1 | AR28: 0 | AT28: 0.2656 | AV28: 0 | AW28: 2 | AX28: 38182992 | AY28: 1 | AZ28: 0 | BA28: 28 | BB28: 1 | BC28: 0 | BD28: 0 | BE28: 0 | BF28: 0 | BG28: 0 | BH28: 0 | BI28: 0 | BJ28: 1275.1058 | BK28: 0 | BL28: 0 | BM28: 0 | BN28: 0 | BO28: 0 | BP28: 1 | BQ28: 1275.1058 | BR28: 0 | BS28: 0 | BT28: 0 | BU28: 0 | BV28: 0 | BW28: 1 | CV28: 0 | CW28: 0 | CX28: =ROUND(Y28*Source!I28,7) -> 0.02656 | CY28: =AA28 -> 9073.61 | CZ28: =AE28 -> 4800.85 | DA28: =AI28 -> 1.89 | DB28: =ROUND(ROUND(AT28*CZ28,2),6) -> 1275.11 | DC28: =ROUND(ROUND(AT28*AG28,2),6) -> 0 | DF28: =ROUND(ROUND(AE28*AI28,2)*CX28,2) -> 241 | DG28: =ROUND(ROUND(AF28,2)*CX28,2) -> 0 | DH28: =ROUND(ROUND(AG28,2)*CX28,2) -> 0 | DI28: =ROUND(ROUND(AH28,2)*CX28,2) -> 0 | DJ28: =DF28 -> 241 | DK28: 0 | DM28: 0 | DO28: 0
A29: =ROW(Source!A28) -> 28 | B29: 38182922 | C29: 38182974 | D29: 35416737 | E29: 1 | F29: 1 | G29: 1 | H29: 3 | I29: 04.3.01.09-0014 | J29: ФСБЦ-2022, 04.3.01.09-0014, приказ Минстроя России от 18.05.2022 г. № 378/пр | K29: Раствор готовый кладочный, цементный, М100 | L29: 1339 | N29: 1007 | O29: м3 | P29: м3 | Q29: 1 | W29: 0 | X29: -2089581116 | Y29: =AT29 -> 0.66 | AA29: 5769.31 | AB29: 0 | AC29: 0 | AD29: 0 | AE29: 5769.31 | AF29: 0 | AG29: 0 | AH29: 0 | AI29: 1 | AJ29: 1 | AK29: 1 | AL29: 1 | AM29: -2 | AN29: 0 | AO29: 0 | AP29: 1 | AQ29: 1 | AR29: 0 | AT29: 0.66 | AV29: 0 | AW29: 2 | AX29: 38182993 | AY29: 1 | AZ29: 0 | BA29: 29 | BB29: 1 | BC29: 0 | BD29: 0 | BE29: 0 | BF29: 0 | BG29: 0 | BH29: 0 | BI29: 0 | BJ29: 3807.7446 | BK29: 0 | BL29: 0 | BM29: 0 | BN29: 0 | BO29: 0 | BP29: 1 | BQ29: 3807.7446 | BR29: 0 | BS29: 0 | BT29: 0 | BU29: 0 | BV29: 0 | BW29: 1 | CV29: 0 | CW29: 0 | CX29: =ROUND(Y29*Source!I28,7) -> 0.066 | CY29: =AA29 -> 5769.31 | CZ29: =AE29 -> 5769.31 | DA29: =AI29 -> 1 | DB29: =ROUND(ROUND(AT29*CZ29,2),6) -> 3807.74 | DC29: =ROUND(ROUND(AT29*AG29,2),6) -> 0 | DF29: =ROUND(ROUND(AE29,2)*CX29,2) -> 380.77 | DG29: =ROUND(ROUND(AF29,2)*CX29,2) -> 0 | DH29: =ROUND(ROUND(AG29,2)*CX29,2) -> 0 | DI29: =ROUND(ROUND(AH29,2)*CX29,2) -> 0 | DJ29: =DF29 -> 380.77 | DK29: 1 | DM29: 0 | DO29: 0
A30: =ROW(Source!A28) -> 28 | B30: 38182922 | C30: 38182974 | D30: 35340023 | E30: 117 | F30: 1 | G30: 1 | H30: 3 | I30: 05.1.02.08 | K30: Трубы железобетонные безнапорные раструбные | L30: 1301 | N30: 1003 | O30: м | P30: м | Q30: 1 | W30: 0 | X30: 1219364707 | Y30: =AT30 -> 99.7 | AA30: 0 | AB30: 0 | AC30: 0 | AD30: 0 | AE30: 0 | AF30: 0 | AG30: 0 | AH30: 0 | AI30: 1 | AJ30: 1 | AK30: 1 | AL30: 1 | AM30: 0 | AN30: 0 | AO30: 0 | AP30: 1 | AQ30: 0 | AR30: 0 | AT30: 99.7 | AV30: 0 | AW30: 2 | AX30: 38182994 | AY30: 1 | AZ30: 0 | BA30: 30 | BB30: 0 | BC30: 0 | BD30: 0 | BE30: 0 | BF30: 0 | BG30: 0 | BH30: 0 | BI30: 0 | BJ30: 0 | BK30: 0 | BL30: 0 | BM30: 0 | BN30: 0 | BO30: 0 | BP30: 0 | BQ30: 0 | BR30: 0 | BS30: 0 | BT30: 0 | BU30: 0 | BV30: 0 | BW30: 0 | CV30: 0 | CW30: 0 | CX30: =ROUND(Y30*Source!I28,7) -> 9.97 | CY30: =AA30 -> 0 | CZ30: =AE30 -> 0 | DA30: =AI30 -> 1 | DB30: =ROUND(ROUND(AT30*CZ30,2),6) -> 0 | DC30: =ROUND(ROUND(AT30*AG30,2),6) -> 0 | DF30: =ROUND(ROUND(AE30,2)*CX30,2) -> 0 | DG30: =ROUND(ROUND(AF30,2)*CX30,2) -> 0 | DH30: =ROUND(ROUND(AG30,2)*CX30,2) -> 0 | DI30: =ROUND(ROUND(AH30,2)*CX30,2) -> 0 | DJ30: =DF30 -> 0 | DK30: 0 | DM30: 0 | DO30: 0
A31: =ROW(Source!A30) -> 30 | B31: 38182922 | C31: 38183701 | D31: 35338624 | E31: 117 | F31: 1 | G31: 1 | H31: 1 | I31: 4-100-00 | K31: Затраты труда машинистов | L31: 1191 | N31: 1013 | O31: чел.-ч. | P31: чел.-ч. | Q31: 1 | W31: 0 | X31: -1417349443 | Y31: =AT31 -> 0.9 | AA31: 0 | AB31: 0 | AC31: 0 | AD31: 0 | AE31: 0 | AF31: 0 | AG31: 0 | AH31: 0 | AI31: 1 | AJ31: 1 | AK31: 1 | AL31: 1 | AM31: -2 | AN31: 0 | AO31: 0 | AP31: 0 | AQ31: 1 | AR31: 0 | AT31: 0.9 | AV31: 2 | AW31: 2 | AX31: 38183702 | AY31: 1 | AZ31: 0 | BA31: 31 | BB31: 1 | BC31: 0 | BD31: 0 | BE31: 0 | BF31: 0 | BG31: 0 | BH31: 0 | BI31: 0 | BJ31: 0 | BK31: 0 | BL31: 0 | BM31: 0 | BN31: 0 | BO31: 0 | BP31: 0 | BQ31: 0 | BR31: 0 | BS31: 0 | BT31: 0 | BU31: 0 | BV31: 0 | BW31: 0 | CV31: 0 | CW31: 0 | CX31: =ROUND(Y31*Source!I30,7) -> 0.09 | CY31: =AD31 -> 0 | CZ31: =AH31 -> 0 | DA31: =AL31 -> 1 | DB31: =ROUND(ROUND(AT31*CZ31,2),6) -> 0 | DC31: =ROUND(ROUND(AT31*AG31,2),6) -> 0 | DF31: =ROUND(ROUND(AE31,2)*CX31,2) -> 0 | DG31: =ROUND(ROUND(AF31,2)*CX31,2) -> 0 | DH31: =ROUND(ROUND(AG31,2)*CX31,2) -> 0 | DI31: =ROUND(ROUND(AH31,2)*CX31,2) -> 0 | DJ31: =DI31 -> 0 | DK31: 0 | DM31: 0 | DO31: 0
A32: =ROW(Source!A30) -> 30 | B32: 38182922 | C32: 38183701 | D32: 35344687 | E32: 1 | F32: 1 | G32: 1 | H32: 2 | I32: 91.01.01-046 | J32: ФСЭМ-2022, 91.01.01-046, приказ Минстроя России от 18.05.2022 г. № 378/пр | K32: Бульдозеры, мощность 303 кВт (410 л.с.) | L32: 1368 | N32: 1011 | O32: маш.-ч | P32: маш.-ч | Q32: 1 | W32: 0 | X32: 626856282 | Y32: =AT32 -> 0.9 | AA32: 0 | AB32: 5605.48 | AC32: 707.35 | AD32: 0 | AE32: 0 | AF32: 5605.48 | AG32: 707.35 | AH32: 0 | AI32: 1 | AJ32: 1 | AK32: 1 | AL32: 1 | AM32: -2 | AN32: 0 | AO32: 0 | AP32: 0 | AQ32: 1 | AR32: 0 | AT32: 0.9 | AV32: 1 | AW32: 2 | AX32: 38183717 | AY32: 1 | AZ32: 0 | BA32: 32 | BB32: 1 | BC32: 0 | BD32: 0 | BE32: 0 | BF32: 0 | BG32: 0 | BH32: 0 | BI32: 0 | BJ32: 0 | BK32: 5044.932 | BL32: 636.615 | BM32: 0 | BN32: 0 | BO32: 0.9 | BP32: 1 | BQ32: 0 | BR32: 5044.932 | BS32: 636.615 | BT32: 0 | BU32: 0 | BV32: 0.9 | BW32: 1 | CV32: 0 | CW32: =ROUND(Y32*Source!I30*DO32,7) -> 0.09 | CX32: =ROUND(Y32*Source!I30,7) -> 0.09 | CY32: =AB32 -> 5605.48 | CZ32: =AF32 -> 5605.48 | DA32: =AJ32 -> 1 | DB32: =ROUND(ROUND(AT32*CZ32,2),6) -> 5044.93 | DC32: =ROUND(ROUND(AT32*AG32,2),6) -> 636.62 | DF32: =ROUND(ROUND(AE32,2)*CX32,2) -> 0 | DG32: =ROUND(ROUND(AF32,2)*CX32,2) -> 504.49 | DH32: =ROUND(ROUND(AG32,2)*CX32,2) -> 63.66 | DI32: =ROUND(ROUND(AH32,2)*CX32,2) -> 0 | DJ32: =DG32+DH32 -> 568.15 | DK32: 1 | DL32: 4-100-090 | DM32: 9 | DN32: чел.-ч. | DO32: 1
A33: =ROW(Source!A30) -> 30 | B33: 38182922 | C33: 38183701 | D33: 35344734 | E33: 1 | F33: 1 | G33: 1 | H33: 2 | I33: 91.01.05-104 | J33: ФСЭМ-2022, 91.01.05-104, приказ Минстроя России от 18.05.2022 г. № 378/пр | K33: Экскаваторы одноковшовые дизельные на пневмоколесном ходу, объем ковша 0,4 м3 | L33: 1368 | N33: 1011 | O33: маш.-ч | P33: маш.-ч | Q33: 1 | W33: 0 | X33: -598721075 | Y33: =AT33 -> 0.9 | AA33: 0 | AB33: 1453.51 | AC33: 497.4 | AD33: 0 | AE33: 0 | AF33: 1162.81 | AG33: 497.4 | AH33: 0 | AI33: 1 | AJ33: 1.25 | AK33: 1 | AL33: 1 | AM33: 0 | AN33: 0 | AO33: 0 | AP33: 0 | AQ33: 0 | AR33: 0 | AT33: 0.9 | AV33: 1 | AW33: 1 | AX33: -1 | AY33: 0 | AZ33: 0 | BB33: 0 | BC33: 0 | BD33: 0 | BE33: 0 | BF33: 0 | BG33: 0 | BH33: 0 | BI33: 0 | BJ33: 0 | BK33: 0 | BL33: 0 | BM33: 0 | BN33: 0 | BO33: 0 | BP33: 0 | BQ33: 0 | BR33: 0 | BS33: 0 | BT33: 0 | BU33: 0 | BV33: 0 | BW33: 0 | CV33: 0 | CW33: =ROUND(Y33*Source!I30*DO33,7) -> 0.09 | CX33: =ROUND(Y33*Source!I30,7) -> 0.09 | CY33: =AB33 -> 1453.51 | CZ33: =AF33 -> 1162.81 | DA33: =AJ33 -> 1.25 | DB33: =ROUND(ROUND(AT33*CZ33,2),6) -> 1046.53 | DC33: =ROUND(ROUND(AT33*AG33,2),6) -> 447.66 | DF33: =ROUND(ROUND(AE33,2)*CX33,2) -> 0 | DG33: =ROUND(ROUND(AF33*AJ33,2)*CX33,2) -> 130.82 | DH33: =ROUND(ROUND(AG33,2)*CX33,2) -> 44.77 | DI33: =ROUND(ROUND(AH33,2)*CX33,2) -> 0 | DJ33: =DG33+DH33 -> 175.59 | DK33: 0 | DL33: 4-100-050 | DM33: 5 | DN33: чел.-ч. | DO33: 1
A34: =ROW(Source!A32) -> 32 | B34: 38182922 | C34: 38183714 | D34: 35338838 | E34: 117 | F34: 1 | G34: 1 | H34: 1 | I34: 4-100-090 | K34: Машинист 9 разряда | L34: 1191 | N34: 1013 | O34: чел.-ч. | P34: чел.-ч. | Q34: 1 | W34: 0 | X34: -45074197 | Y34: =AT34 -> 1 | AA34: 0 | AB34: 0 | AC34: 0 | AD34: 707.35 | AE34: 0 | AF34: 0 | AG34: 0 | AH34: 707.35 | AI34: 1 | AJ34: 1 | AK34: 1 | AL34: 1 | AM34: -2 | AN34: 0 | AO34: 0 | AP34: 0 | AQ34: 1 | AR34: 0 | AT34: 1 | AV34: 2 | AW34: 2 | AX34: 38183716 | AY34: 1 | AZ34: 0 | BA34: 33 | BB34: 1 | BC34: 0 | BD34: 0 | BE34: 0 | BF34: 0 | BG34: 0 | BH34: 0 | BI34: 0 | BJ34: 0 | BK34: 0 | BL34: 0 | BM34: 0 | BN34: 0 | BO34: 0 | BP34: 0 | BQ34: 0 | BR34: 0 | BS34: 0 | BT34: 0 | BU34: 0 | BV34: 0 | BW34: 0 | CV34: 0 | CW34: 0 | CX34: =ROUND(Y34*Source!I32,7) -> -0.09 | CY34: =AD34 -> 707.35 | CZ34: =AH34 -> 707.35 | DA34: =AL34 -> 1 | DB34: =ROUND(ROUND(AT34*CZ34,2),6) -> 707.35 | DC34: =ROUND(ROUND(AT34*AG34,2),6) -> 0 | DF34: =ROUND(ROUND(AE34,2)*CX34,2) -> 0 | DG34: =ROUND(ROUND(AF34,2)*CX34,2) -> 0 | DH34: =ROUND(ROUND(AG34,2)*CX34,2) -> 0 | DI34: =ROUND(ROUND(AH34,2)*CX34,2) -> -63.66 | DJ34: =DI34 -> -63.66 | DK34: 1 | DM34: 0 | DO34: 0
A35: =ROW(Source!A33) -> 33 | B35: 38182922 | C35: 38183769 | D35: 35338460 | E35: 117 | F35: 1 | G35: 1 | H35: 1 | I35: 1-100-42 | K35: Средний разряд работы 4,2 | L35: 1191 | N35: 1013 | O35: чел.-ч. | P35: чел.-ч. | Q35: 1 | W35: 0 | X35: 1522950421 | Y35: =AT35 -> 140 | AA35: 0 | AB35: 0 | AC35: 0 | AD35: 445.73 | AE35: 0 | AF35: 0 | AG35: 0 | AH35: 445.73 | AI35: 1 | AJ35: 1 | AK35: 1 | AL35: 1 | AM35: -2 | AN35: 0 | AO35: 0 | AP35: 0 | AQ35: 1 | AR35: 0 | AT35: 140 | AV35: 1 | AW35: 2 | AX35: 38183770 | AY35: 1 | AZ35: 0 | BA35: 34 | BB35: 1 | BC35: 0 | BD35: 0 | BE35: 0 | BF35: 0 | BG35: 0 | BH35: 0 | BI35: 0 | BJ35: 0 | BK35: 0 | BL35: 0 | BM35: 62402.2 | BN35: 140 | BO35: 0 | BP35: 1 | BQ35: 0 | BR35: 0 | BS35: 0 | BT35: 62402.2 | BU35: 140 | BV35: 0 | BW35: 1 | CU35: =ROUND(AT35*Source!I33*AH35*AL35,2) -> 62.4 | CV35: =ROUND(Y35*Source!I33,7) -> 0.14 | CW35: 0 | CX35: =ROUND(Y35*Source!I33,7) -> 0.14 | CY35: =AD35 -> 445.73 | CZ35: =AH35 -> 445.73 | DA35: =AL35 -> 1 | DB35: =ROUND(ROUND(AT35*CZ35,2),6) -> 62402.2 | DC35: =ROUND(ROUND(AT35*AG35,2),6) -> 0 | DF35: =ROUND(ROUND(AE35,2)*CX35,2) -> 0 | DG35: =ROUND(ROUND(AF35,2)*CX35,2) -> 0 | DH35: =ROUND(ROUND(AG35,2)*CX35,2) -> 0 | DI35: =ROUND(ROUND(AH35,2)*CX35,2) -> 62.4 | DJ35: =DI35 -> 62.4 | DK35: 1 | DM35: 0 | DO35: 0
A36: =ROW(Source!A33) -> 33 | B36: 38182922 | C36: 38183769 | D36: 35338624 | E36: 117 | F36: 1 | G36: 1 | H36: 1 | I36: 4-100-00 | K36: Затраты труда машинистов | L36: 1191 | N36: 1013 | O36: чел.-ч. | P36: чел.-ч. | Q36: 1 | W36: 0 | X36: -1417349443 | Y36: =AT36 -> 23.17 | AA36: 0 | AB36: 0 | AC36: 0 | AD36: 0 | AE36: 0 | AF36: 0 | AG36: 0 | AH36: 0 | AI36: 1 | AJ36: 1 | AK36: 1 | AL36: 1 | AM36: -2 | AN36: 0 | AO36: 0 | AP36: 0 | AQ36: 1 | AR36: 0 | AT36: 23.17 | AV36: 2 | AW36: 2 | AX36: 38183771 | AY36: 1 | AZ36: 0 | BA36: 35 | BB36: 1 | BC36: 0 | BD36: 0 | BE36: 0 | BF36: 0 | BG36: 0 | BH36: 0 | BI36: 0 | BJ36: 0 | BK36: 0 | BL36: 0 | BM36: 0 | BN36: 0 | BO36: 0 | BP36: 0 | BQ36: 0 | BR36: 0 | BS36: 0 | BT36: 0 | BU36: 0 | BV36: 0 | BW36: 0 | CV36: 0 | CW36: 0 | CX36: =ROUND(Y36*Source!I33,7) -> 0.02317 | CY36: =AD36 -> 0 | CZ36: =AH36 -> 0 | DA36: =AL36 -> 1 | DB36: =ROUND(ROUND(AT36*CZ36,2),6) -> 0 | DC36: =ROUND(ROUND(AT36*AG36,2),6) -> 0 | DF36: =ROUND(ROUND(AE36,2)*CX36,2) -> 0 | DG36: =ROUND(ROUND(AF36,2)*CX36,2) -> 0 | DH36: =ROUND(ROUND(AG36,2)*CX36,2) -> 0 | DI36: =ROUND(ROUND(AH36,2)*CX36,2) -> 0 | DJ36: =DI36 -> 0 | DK36: 0 | DM36: 0 | DO36: 0
A37: =ROW(Source!A33) -> 33 | B37: 38182922 | C37: 38183769 | D37: 35345762 | E37: 1 | F37: 1 | G37: 1 | H37: 2 | I37: 91.10.05-009 | J37: ФСЭМ-2022, 91.10.05-009, приказ Минстроя России от 18.05.2022 г. № 378/пр | K37: Трубоукладчики, номинальная грузоподъемность 35 т | L37: 1368 | N37: 1011 | O37: маш.-ч | P37: маш.-ч | Q37: 1 | W37: 0 | X37: -1505731505 | Y37: =AT37 -> 12.18 | AA37: 0 | AB37: 4931.99 | AC37: 707.35 | AD37: 0 | AE37: 0 | AF37: 4403.56 | AG37: 707.35 | AH37: 0 | AI37: 1 | AJ37: 1.12 | AK37: 1 | AL37: 1 | AM37: 2 | AN37: 0 | AO37: 0 | AP37: 0 | AQ37: 1 | AR37: 0 | AT37: 12.18 | AV37: 1 | AW37: 2 | AX37: 38183772 | AY37: 1 | AZ37: 0 | BA37: 36 | BB37: 1 | BC37: 0 | BD37: 0 | BE37: 0 | BF37: 0 | BG37: 0 | BH37: 0 | BI37: 0 | BJ37: 0 | BK37: 53635.361 | BL37: 8615.523 | BM37: 0 | BN37: 0 | BO37: 12.18 | BP37: 1 | BQ37: 0 | BR37: 53635.361 | BS37: 8615.523 | BT37: 0 | BU37: 0 | BV37: 12.18 | BW37: 1 | CV37: 0 | CW37: =ROUND(Y37*Source!I33*DO37,7) -> 0.01218 | CX37: =ROUND(Y37*Source!I33,7) -> 0.01218 | CY37: =AB37 -> 4931.99 | CZ37: =AF37 -> 4403.56 | DA37: =AJ37 -> 1.12 | DB37: =ROUND(ROUND(AT37*CZ37,2),6) -> 53635.36 | DC37: =ROUND(ROUND(AT37*AG37,2),6) -> 8615.52 | DF37: =ROUND(ROUND(AE37,2)*CX37,2) -> 0 | DG37: =ROUND(ROUND(AF37*AJ37,2)*CX37,2) -> 60.07 | DH37: =ROUND(ROUND(AG37,2)*CX37,2) -> 8.62 | DI37: =ROUND(ROUND(AH37,2)*CX37,2) -> 0 | DJ37: =DG37+DH37 -> 68.69 | DK37: 0 | DL37: 4-100-090 | DM37: 9 | DN37: чел.-ч. | DO37: 1
A38: =ROW(Source!A33) -> 33 | B38: 38182922 | C38: 38183769 | D38: 35346009 | E38: 1 | F38: 1 | G38: 1 | H38: 2 | I38: 91.14.02-001 | J38: ФСЭМ-2022 доп.7, 91.14.02-001, приказ Минстроя России от 02.08.2023 г. № 551/пр | K38: Автомобили бортовые, грузоподъемность до 5 т | L38: 1368 | N38: 1011 | O38: маш.-ч | P38: маш.-ч | Q38: 1 | W38: 0 | X38: -849950259 | Y38: =AT38 -> 1.06 | AA38: 0 | AB38: 652.84 | AC38: 432.81 | AD38: 0 | AE38: 0 | AF38: 652.84 | AG38: 432.81 | AH38: 0 | AI38: 1 | AJ38: 1 | AK38: 1 | AL38: 1 | AM38: -2 | AN38: 0 | AO38: 0 | AP38: 0 | AQ38: 1 | AR38: 0 | AT38: 1.06 | AV38: 1 | AW38: 2 | AX38: 38183773 | AY38: 1 | AZ38: 0 | BA38: 37 | BB38: 1 | BC38: 0 | BD38: 0 | BE38: 0 | BF38: 0 | BG38: 0 | BH38: 0 | BI38: 0 | BJ38: 0 | BK38: 692.0104 | BL38: 458.7786 | BM38: 0 | BN38: 0 | BO38: 1.06 | BP38: 1 | BQ38: 0 | BR38: 692.0104 | BS38: 458.7786 | BT38: 0 | BU38: 0 | BV38: 1.06 | BW38: 1 | CV38: 0 | CW38: =ROUND(Y38*Source!I33*DO38,7) -> 0.00106 | CX38: =ROUND(Y38*Source!I33,7) -> 0.00106 | CY38: =AB38 -> 652.84 | CZ38: =AF38 -> 652.84 | DA38: =AJ38 -> 1 | DB38: =ROUND(ROUND(AT38*CZ38,2),6) -> 692.01 | DC38: =ROUND(ROUND(AT38*AG38,2),6) -> 458.78 | DF38: =ROUND(ROUND(AE38,2)*CX38,2) -> 0 | DG38: =ROUND(ROUND(AF38,2)*CX38,2) -> 0.69 | DH38: =ROUND(ROUND(AG38,2)*CX38,2) -> 0.46 | DI38: =ROUND(ROUND(AH38,2)*CX38,2) -> 0 | DJ38: =DG38+DH38 -> 1.15 | DK38: 1 | DL38: 4-100-040 | DM38: 4 | DN38: чел.-ч. | DO38: 1
A39: =ROW(Source!A33) -> 33 | B39: 38182922 | C39: 38183769 | D39: 35346101 | E39: 1 | F39: 1 | G39: 1 | H39: 2 | I39: 91.16.01-002 | J39: ФСЭМ-2022, 91.16.01-002, приказ Минстроя России от 18.05.2022 г. № 378/пр | K39: Электростанции передвижные, мощность 4 кВт | L39: 1368 | N39: 1011 | O39: маш.-ч | P39: маш.-ч | Q39: 1 | W39: 0 | X39: -245244677 | Y39: =AT39 -> 9.93 | AA39: 0 | AB39: 130.39 | AC39: 432.81 | AD39: 0 | AE39: 0 | AF39: 130.39 | AG39: 432.81 | AH39: 0 | AI39: 1 | AJ39: 1 | AK39: 1 | AL39: 1 | AM39: -2 | AN39: 0 | AO39: 0 | AP39: 0 | AQ39: 1 | AR39: 0 | AT39: 9.93 | AV39: 1 | AW39: 2 | AX39: 38183774 | AY39: 1 | AZ39: 0 | BA39: 38 | BB39: 1 | BC39: 0 | BD39: 0 | BE39: 0 | BF39: 0 | BG39: 0 | BH39: 0 | BI39: 0 | BJ39: 0 | BK39: 1294.7727 | BL39: 4297.8033 | BM39: 0 | BN39: 0 | BO39: 9.93 | BP39: 1 | BQ39: 0 | BR39: 1294.7727 | BS39: 4297.8033 | BT39: 0 | BU39: 0 | BV39: 9.93 | BW39: 1 | CV39: 0 | CW39: =ROUND(Y39*Source!I33*DO39,7) -> 0.00993 | CX39: =ROUND(Y39*Source!I33,7) -> 0.00993 | CY39: =AB39 -> 130.39 | CZ39: =AF39 -> 130.39 | DA39: =AJ39 -> 1 | DB39: =ROUND(ROUND(AT39*CZ39,2),6) -> 1294.77 | DC39: =ROUND(ROUND(AT39*AG39,2),6) -> 4297.8 | DF39: =ROUND(ROUND(AE39,2)*CX39,2) -> 0 | DG39: =ROUND(ROUND(AF39,2)*CX39,2) -> 1.29 | DH39: =ROUND(ROUND(AG39,2)*CX39,2) -> 4.3 | DI39: =ROUND(ROUND(AH39,2)*CX39,2) -> 0 | DJ39: =DG39+DH39 -> 5.59 | DK39: 1 | DL39: 4-100-040 | DM39: 4 | DN39: чел.-ч. | DO39: 1
A40: =ROW(Source!A33) -> 33 | B40: 38182922 | C40: 38183769 | D40: 35412918 | E40: 1 | F40: 1 | G40: 1 | H40: 3 | I40: 01.7.06.03-0002 | J40: ФСБЦ-2022, 01.7.06.03-0002, приказ Минстроя России от 18.05.2022 г. № 378/пр | K40: Ленты антикоррозионные из ПВХ с липким слоем с одной стороны для изоляции трубопроводов, цвет черный, ширина 450 мм, толщина 0,4 мм | L40: 1327 | N40: 1005 | O40: м2 | P40: м2 | Q40: 1 | W40: 0 | X40: 1711398520 | Y40: =AT40 -> 478 | AA40: 123.6 | AB40: 0 | AC40: 0 | AD40: 0 | AE40: 62.74 | AF40: 0 | AG40: 0 | AH40: 0 | AI40: 1.97 | AJ40: 1 | AK40: 1 | AL40: 1 | AM40: 2 | AN40: 0 | AO40: 0 | AP40: 0 | AQ40: 1 | AR40: 0 | AT40: 478 | AV40: 0 | AW40: 2 | AX40: 38183776 | AY40: 1 | AZ40: 0 | BA40: 40 | BB40: 1 | BC40: 0 | BD40: 0 | BE40: 0 | BF40: 0 | BG40: 0 | BH40: 0 | BI40: 0 | BJ40: 29989.72 | BK40: 0 | BL40: 0 | BM40: 0 | BN40: 0 | BO40: 0 | BP40: 1 | BQ40: 29989.72 | BR40: 0 | BS40: 0 | BT40: 0 | BU40: 0 | BV40: 0 | BW40: 1 | CV40: 0 | CW40: 0 | CX40: =ROUND(Y40*Source!I33,7) -> 0.478 | CY40: =AA40 -> 123.6 | CZ40: =AE40 -> 62.74 | DA40: =AI40 -> 1.97 | DB40: =ROUND(ROUND(AT40*CZ40,2),6) -> 29989.72 | DC40: =ROUND(ROUND(AT40*AG40,2),6) -> 0 | DF40: =ROUND(ROUND(AE40*AI40,2)*CX40,2) -> 59.08 | DG40: =ROUND(ROUND(AF40,2)*CX40,2) -> 0 | DH40: =ROUND(ROUND(AG40,2)*CX40,2) -> 0 | DI40: =ROUND(ROUND(AH40,2)*CX40,2) -> 0 | DJ40: =DF40 -> 59.08 | DK40: 0 | DM40: 0 | DO40: 0
A41: =ROW(Source!A33) -> 33 | B41: 38182922 | C41: 38183769 | D41: 35415424 | E41: 1 | F41: 1 | G41: 1 | H41: 3 | I41: 01.7.20.08-0021 | J41: ФСБЦ-2022, 01.7.20.08-0021, приказ Минстроя России от 18.05.2022 г. № 378/пр | K41: Брезент с огнеупорной пропиткой | L41: 1327 | N41: 1005 | O41: м2 | P41: м2 | Q41: 1 | W41: 0 | X41: 2050518453 | Y41: =AT41 -> 0.8 | AA41: 174.97 | AB41: 0 | AC41: 0 | AD41: 0 | AE41: 108.68 | AF41: 0 | AG41: 0 | AH41: 0 | AI41: 1.61 | AJ41: 1 | AK41: 1 | AL41: 1 | AM41: 2 | AN41: 0 | AO41: 0 | AP41: 0 | AQ41: 1 | AR41: 0 | AT41: 0.8 | AV41: 0 | AW41: 2 | AX41: 38183777 | AY41: 1 | AZ41: 0 | BA41: 41 | BB41: 1 | BC41: 0 | BD41: 0 | BE41: 0 | BF41: 0 | BG41: 0 | BH41: 0 | BI41: 0 | BJ41: 86.944 | BK41: 0 | BL41: 0 | BM41: 0 | BN41: 0 | BO41: 0 | BP41: 1 | BQ41: 86.944 | BR41: 0 | BS41: 0 | BT41: 0 | BU41: 0 | BV41: 0 | BW41: 1 | CV41: 0 | CW41: 0 | CX41: =ROUND(Y41*Source!I33,7) -> 0.0008 | CY41: =AA41 -> 174.97 | CZ41: =AE41 -> 108.68 | DA41: =AI41 -> 1.61 | DB41: =ROUND(ROUND(AT41*CZ41,2),6) -> 86.94 | DC41: =ROUND(ROUND(AT41*AG41,2),6) -> 0 | DF41: =ROUND(ROUND(AE41*AI41,2)*CX41,2) -> 0.14 | DG41: =ROUND(ROUND(AF41,2)*CX41,2) -> 0 | DH41: =ROUND(ROUND(AG41,2)*CX41,2) -> 0 | DI41: =ROUND(ROUND(AH41,2)*CX41,2) -> 0 | DJ41: =DF41 -> 0.14 | DK41: 0 | DM41: 0 | DO41: 0
A42: =ROW(Source!A33) -> 33 | B42: 38182922 | C42: 38183769 | D42: 35415437 | E42: 1 | F42: 1 | G42: 1 | H42: 3 | I42: 01.7.20.08-0162 | J42: ФСБЦ-2022, 01.7.20.08-0162, приказ Минстроя России от 18.05.2022 г. № 378/пр | K42: Ткань мешочная, ширина 950 мм, поверхностная плотность 190 г/м2 | L42: 1330 | N42: 1005 | O42: 10 м2 | P42: 10 м2 | Q42: 10 | W42: 0 | X42: -1756344661 | Y42: =AT42 -> 0.1 | AA42: 953.18 | AB42: 0 | AC42: 0 | AD42: 0 | AE42: 592.04 | AF42: 0 | AG42: 0 | AH42: 0 | AI42: 1.61 | AJ42: 1 | AK42: 1 | AL42: 1 | AM42: 2 | AN42: 0 | AO42: 0 | AP42: 0 | AQ42: 1 | AR42: 0 | AT42: 0.1 | AV42: 0 | AW42: 2 | AX42: 38183778 | AY42: 1 | AZ42: 0 | BA42: 42 | BB42: 1 | BC42: 0 | BD42: 0 | BE42: 0 | BF42: 0 | BG42: 0 | BH42: 0 | BI42: 0 | BJ42: 59.204 | BK42: 0 | BL42: 0 | BM42: 0 | BN42: 0 | BO42: 0 | BP42: 1 | BQ42: 59.204 | BR42: 0 | BS42: 0 | BT42: 0 | BU42: 0 | BV42: 0 | BW42: 1 | CV42: 0 | CW42: 0 | CX42: =ROUND(Y42*Source!I33,7) -> 0.0001 | CY42: =AA42 -> 953.18 | CZ42: =AE42 -> 592.04 | DA42: =AI42 -> 1.61 | DB42: =ROUND(ROUND(AT42*CZ42,2),6) -> 59.2 | DC42: =ROUND(ROUND(AT42*AG42,2),6) -> 0 | DF42: =ROUND(ROUND(AE42*AI42,2)*CX42,2) -> 0.1 | DG42: =ROUND(ROUND(AF42,2)*CX42,2) -> 0 | DH42: =ROUND(ROUND(AG42,2)*CX42,2) -> 0 | DI42: =ROUND(ROUND(AH42,2)*CX42,2) -> 0 | DJ42: =DF42 -> 0.1 | DK42: 0 | DM42: 0 | DO42: 0
A43: =ROW(Source!A33) -> 33 | B43: 38182922 | C43: 38183769 | D43: 35425233 | E43: 1 | F43: 1 | G43: 1 | H43: 3 | I43: 12.1.02.15-0041 | J43: ФСБЦ-2022, 12.1.02.15-0041, приказ Минстроя России от 18.05.2022 г. № 378/пр | K43: Материал рулонный гидроизоляционный изол, резино-битумный, без полимерных добавок | L43: 1327 | N43: 1005 | O43: м2 | P43: м2 | Q43: 1 | W43: 0 | X43: -848550540 | Y43: =AT43 -> 850 | AA43: 172.81 | AB43: 0 | AC43: 0 | AD43: 0 | AE43: 126.14 | AF43: 0 | AG43: 0 | AH43: 0 | AI43: 1.37 | AJ43: 1 | AK43: 1 | AL43: 1 | AM43: 0 | AN43: 0 | AO43: 0 | AP43: 1 | AQ43: 0 | AR43: 0 | AT43: 850 | AV43: 0 | AW43: 1 | AX43: -1 | AY43: 0 | AZ43: 0 | BB43: 0 | BC43: 0 | BD43: 0 | BE43: 0 | BF43: 0 | BG43: 0 | BH43: 0 | BI43: 0 | BJ43: 0 | BK43: 0 | BL43: 0 | BM43: 0 | BN43: 0 | BO43: 0 | BP43: 0 | BQ43: 0 | BR43: 0 | BS43: 0 | BT43: 0 | BU43: 0 | BV43: 0 | BW43: 0 | CV43: 0 | CW43: 0 | CX43: =ROUND(Y43*Source!I33,7) -> 0.85 | CY43: =AA43 -> 172.81 | CZ43: =AE43 -> 126.14 | DA43: =AI43 -> 1.37 | DB43: =ROUND(ROUND(AT43*CZ43,2),6) -> 107219 | DC43: =ROUND(ROUND(AT43*AG43,2),6) -> 0 | DF43: =ROUND(ROUND(AE43*AI43,2)*CX43,2) -> 146.89 | DG43: =ROUND(ROUND(AF43,2)*CX43,2) -> 0 | DH43: =ROUND(ROUND(AG43,2)*CX43,2) -> 0 | DI43: =ROUND(ROUND(AH43,2)*CX43,2) -> 0 | DJ43: =DF43 -> 146.89 | DK43: 0 | DM43: 0 | DO43: 0
A44: =ROW(Source!A33) -> 33 | B44: 38182922 | C44: 38183769 | D44: 35431024 | E44: 1 | F44: 1 | G44: 1 | H44: 3 | I44: 14.1.05.03-0011 | J44: ФСБЦ-2022, 14.1.05.03-0011, приказ Минстроя России от 18.05.2022 г. № 378/пр | K44: Клей фенолополивинилацетальный, марка БФ-2Н | L44: 1348 | N44: 1009 | O44: т | P44: т | Q44: 1000 | W44: 0 | X44: 1435964893 | Y44: =AT44 -> 0.0125 | AA44: 686020.2 | AB44: 0 | AC44: 0 | AD44: 0 | AE44: 442593.68 | AF44: 0 | AG44: 0 | AH44: 0 | AI44: 1.55 | AJ44: 1 | AK44: 1 | AL44: 1 | AM44: 2 | AN44: 0 | AO44: 0 | AP44: 0 | AQ44: 1 | AR44: 0 | AT44: 0.0125 | AV44: 0 | AW44: 2 | AX44: 38183780 | AY44: 1 | AZ44: 0 | BA44: 44 | BB44: 1 | BC44: 0 | BD44: 0 | BE44: 0 | BF44: 0 | BG44: 0 | BH44: 0 | BI44: 0 | BJ44: 5532.421 | BK44: 0 | BL44: 0 | BM44: 0 | BN44: 0 | BO44: 0 | BP44: 1 | BQ44: 5532.421 | BR44: 0 | BS44: 0 | BT44: 0 | BU44: 0 | BV44: 0 | BW44: 1 | CV44: 0 | CW44: 0 | CX44: =ROUND(Y44*Source!I33,7) -> 1.25e-05 | CY44: =AA44 -> 686020.2 | CZ44: =AE44 -> 442593.68 | DA44: =AI44 -> 1.55 | DB44: =ROUND(ROUND(AT44*CZ44,2),6) -> 5532.42 | DC44: =ROUND(ROUND(AT44*AG44,2),6) -> 0 | DF44: =ROUND(ROUND(AE44*AI44,2)*CX44,2) -> 8.58 | DG44: =ROUND(ROUND(AF44,2)*CX44,2) -> 0 | DH44: =ROUND(ROUND(AG44,2)*CX44,2) -> 0 | DI44: =ROUND(ROUND(AH44,2)*CX44,2) -> 0 | DJ44: =DF44 -> 8.58 | DK44: 0 | DM44: 0 | DO44: 0
A45: =ROW(Source!A33) -> 33 | B45: 38182922 | C45: 38183769 | D45: 35431433 | E45: 1 | F45: 1 | G45: 1 | H45: 3 | I45: 14.4.01.15-1002 | J45: ФСБЦ-2022, 14.4.01.15-1002, приказ Минстроя России от 18.05.2022 г. № 378/пр | K45: Грунтовка полимерная для повышения адгезии битумно-полимерных мастик и герметиков при герметизации деформационных швов асфальтобетонных и цементобетонных покрытий | L45: 1348 | N45: 1009 | O45: т | P45: т | Q45: 1000 | W45: 0 | X45: 7353553 | Y45: =AT45 -> 1 | AA45: 522975.76 | AB45: 0 | AC45: 0 | AD45: 0 | AE45: 411791.94 | AF45: 0 | AG45: 0 | AH45: 0 | AI45: 1.27 | AJ45: 1 | AK45: 1 | AL45: 1 | AM45: 0 | AN45: 1 | AO45: 0 | AP45: 1 | AQ45: 0 | AR45: 0 | AT45: 1 | AV45: 0 | AW45: 1 | AX45: -1 | AY45: 0 | AZ45: 0 | BB45: 0 | BC45: 0 | BD45: 0 | BE45: 0 | BF45: 0 | BG45: 0 | BH45: 0 | BI45: 0 | BJ45: 0 | BK45: 0 | BL45: 0 | BM45: 0 | BN45: 0 | BO45: 0 | BP45: 0 | BQ45: 0 | BR45: 0 | BS45: 0 | BT45: 0 | BU45: 0 | BV45: 0 | BW45: 0 | CV45: 0 | CW45: 0 | CX45: =ROUND(Y45*Source!I33,7) -> 0.001 | CY45: =AA45 -> 522975.76 | CZ45: =AE45 -> 411791.94 | DA45: =AI45 -> 1.27 | DB45: =ROUND(ROUND(AT45*CZ45,2),6) -> 411791.94 | DC45: =ROUND(ROUND(AT45*AG45,2),6) -> 0 | DF45: =ROUND(ROUND(AE45*AI45,2)*CX45,2) -> 522.98 | DG45: =ROUND(ROUND(AF45,2)*CX45,2) -> 0 | DH45: =ROUND(ROUND(AG45,2)*CX45,2) -> 0 | DI45: =ROUND(ROUND(AH45,2)*CX45,2) -> 0 | DJ45: =DF45 -> 522.98 | DK45: 0 | DM45: 0 | DO45: 0
A46: =ROW(Source!A36) -> 36 | B46: 38182922 | C46: 38183809 | D46: 35338430 | E46: 117 | F46: 1 | G46: 1 | H46: 1 | I46: 1-100-30 | K46: Средний разряд работы 3,0 | L46: 1191 | N46: 1013 | O46: чел.-ч. | P46: чел.-ч. | Q46: 1 | W46: 0 | X46: -1833565283 | Y46: =AT46 -> 12.53 | AA46: 0 | AB46: 0 | AC46: 0 | AD46: 384.36 | AE46: 0 | AF46: 0 | AG46: 0 | AH46: 384.36 | AI46: 1 | AJ46: 1 | AK46: 1 | AL46: 1 | AM46: -2 | AN46: 0 | AO46: 0 | AP46: 0 | AQ46: 1 | AR46: 0 | AT46: 12.53 | AV46: 1 | AW46: 2 | AX46: 38183810 | AY46: 1 | AZ46: 0 | BA46: 45 | BB46: 1 | BC46: 0 | BD46: 0 | BE46: 0 | BF46: 0 | BG46: 0 | BH46: 0 | BI46: 0 | BJ46: 0 | BK46: 0 | BL46: 0 | BM46: 4816.0308 | BN46: 12.53 | BO46: 0 | BP46: 1 | BQ46: 0 | BR46: 0 | BS46: 0 | BT46: 4816.0308 | BU46: 12.53 | BV46: 0 | BW46: 1 | CU46: =ROUND(AT46*Source!I36*AH46*AL46,2) -> 2167.21 | CV46: =ROUND(Y46*Source!I36,7) -> 5.6385 | CW46: 0 | CX46: =ROUND(Y46*Source!I36,7) -> 5.6385 | CY46: =AD46 -> 384.36 | CZ46: =AH46 -> 384.36 | DA46: =AL46 -> 1 | DB46: =ROUND(ROUND(AT46*CZ46,2),6) -> 4816.03 | DC46: =ROUND(ROUND(AT46*AG46,2),6) -> 0 | DF46: =ROUND(ROUND(AE46,2)*CX46,2) -> 0 | DG46: =ROUND(ROUND(AF46,2)*CX46,2) -> 0 | DH46: =ROUND(ROUND(AG46,2)*CX46,2) -> 0 | DI46: =ROUND(ROUND(AH46,2)*CX46,2) -> 2167.21 | DJ46: =DI46 -> 2167.21 | DK46: 1 | DM46: 0 | DO46: 0
A47: =ROW(Source!A36) -> 36 | B47: 38182922 | C47: 38183809 | D47: 35338624 | E47: 117 | F47: 1 | G47: 1 | H47: 1 | I47: 4-100-00 | K47: Затраты труда машинистов | L47: 1191 | N47: 1013 | O47: чел.-ч. | P47: чел.-ч. | Q47: 1 | W47: 0 | X47: -1417349443 | Y47: =AT47 -> 2.62 | AA47: 0 | AB47: 0 | AC47: 0 | AD47: 0 | AE47: 0 | AF47: 0 | AG47: 0 | AH47: 0 | AI47: 1 | AJ47: 1 | AK47: 1 | AL47: 1 | AM47: -2 | AN47: 0 | AO47: 0 | AP47: 0 | AQ47: 1 | AR47: 0 | AT47: 2.62 | AV47: 2 | AW47: 2 | AX47: 38183811 | AY47: 1 | AZ47: 0 | BA47: 46 | BB47: 1 | BC47: 0 | BD47: 0 | BE47: 0 | BF47: 0 | BG47: 0 | BH47: 0 | BI47: 0 | BJ47: 0 | BK47: 0 | BL47: 0 | BM47: 0 | BN47: 0 | BO47: 0 | BP47: 0 | BQ47: 0 | BR47: 0 | BS47: 0 | BT47: 0 | BU47: 0 | BV47: 0 | BW47: 0 | CV47: 0 | CW47: 0 | CX47: =ROUND(Y47*Source!I36,7) -> 1.179 | CY47: =AD47 -> 0 | CZ47: =AH47 -> 0 | DA47: =AL47 -> 1 | DB47: =ROUND(ROUND(AT47*CZ47,2),6) -> 0 | DC47: =ROUND(ROUND(AT47*AG47,2),6) -> 0 | DF47: =ROUND(ROUND(AE47,2)*CX47,2) -> 0 | DG47: =ROUND(ROUND(AF47,2)*CX47,2) -> 0 | DH47: =ROUND(ROUND(AG47,2)*CX47,2) -> 0 | DI47: =ROUND(ROUND(AH47,2)*CX47,2) -> 0 | DJ47: =DI47 -> 0 | DK47: 0 | DM47: 0 | DO47: 0
A48: =ROW(Source!A36) -> 36 | B48: 38182922 | C48: 38183809 | D48: 35345545 | E48: 1 | F48: 1 | G48: 1 | H48: 2 | I48: 91.08.09-023 | J48: ФСЭМ-2022 доп.4, 91.08.09-023, приказ Минстроя России от 27.12.2022 г. № 1133/пр | K48: Трамбовки пневматические при работе от передвижных компрессорных установок | L48: 1368 | N48: 1011 | O48: маш.-ч | P48: маш.-ч | Q48: 1 | W48: 0 | X48: 4789874 | Y48: =AT48 -> 10.5 | AA48: 0 | AB48: 2.7 | AC48: 0 | AD48: 0 | AE48: 0 | AF48: 2.41 | AG48: 0 | AH48: 0 | AI48: 1 | AJ48: 1.12 | AK48: 1 | AL48: 1 | AM48: 2 | AN48: 0 | AO48: 0 | AP48: 0 | AQ48: 1 | AR48: 0 | AT48: 10.5 | AV48: 1 | AW48: 2 | AX48: 38183812 | AY48: 1 | AZ48: 0 | BA48: 47 | BB48: 1 | BC48: 0 | BD48: 0 | BE48: 0 | BF48: 0 | BG48: 0 | BH48: 0 | BI48: 0 | BJ48: 0 | BK48: 25.305 | BL48: 0 | BM48: 0 | BN48: 0 | BO48: 0 | BP48: 1 | BQ48: 0 | BR48: 25.305 | BS48: 0 | BT48: 0 | BU48: 0 | BV48: 0 | BW48: 1 | CV48: 0 | CW48: =ROUND(Y48*Source!I36*DO48,7) -> 0 | CX48: =ROUND(Y48*Source!I36,7) -> 4.725 | CY48: =AB48 -> 2.7 | CZ48: =AF48 -> 2.41 | DA48: =AJ48 -> 1.12 | DB48: =ROUND(ROUND(AT48*CZ48,2),6) -> 25.31 | DC48: =ROUND(ROUND(AT48*AG48,2),6) -> 0 | DF48: =ROUND(ROUND(AE48,2)*CX48,2) -> 0 | DG48: =ROUND(ROUND(AF48*AJ48,2)*CX48,2) -> 12.76 | DH48: =ROUND(ROUND(AG48,2)*CX48,2) -> 0 | DI48: =ROUND(ROUND(AH48,2)*CX48,2) -> 0 | DJ48: =DG48+DH48 -> 12.76 | DK48: 0 | DM48: 0 | DO48: 0
A49: =ROW(Source!A36) -> 36 | B49: 38182922 | C49: 38183809 | D49: 35346217 | E49: 1 | F49: 1 | G49: 1 | H49: 2 | I49: 91.18.01-007 | J49: ФСЭМ-2022 доп.13, 91.18.01-007, приказ Минстроя России от 07.02.2025 г. № 69/пр | K49: Компрессоры винтовые передвижные с двигателем внутреннего сгорания, давление до 0,7 МПа (7 атм), производительность до 5,4 м3/мин | L49: 1368 | N49: 1011 | O49: маш.-ч | P49: маш.-ч | Q49: 1 | W49: 0 | X49: 1282244495 | Y49: =AT49 -> 2.62 | AA49: 0 | AB49: 411.37 | AC49: 432.81 | AD49: 0 | AE49: 0 | AF49: 411.37 | AG49: 432.81 | AH49: 0 | AI49: 1 | AJ49: 1 | AK49: 1 | AL49: 1 | AM49: -2 | AN49: 0 | AO49: 0 | AP49: 0 | AQ49: 1 | AR49: 0 | AT49: 2.62 | AV49: 1 | AW49: 2 | AX49: 38183813 | AY49: 1 | AZ49: 0 | BA49: 48 | BB49: 1 | BC49: 0 | BD49: 0 | BE49: 0 | BF49: 0 | BG49: 0 | BH49: 0 | BI49: 0 | BJ49: 0 | BK49: 1077.7894 | BL49: 1133.9622 | BM49: 0 | BN49: 0 | BO49: 2.62 | BP49: 1 | BQ49: 0 | BR49: 1077.7894 | BS49: 1133.9622 | BT49: 0 | BU49: 0 | BV49: 2.62 | BW49: 1 | CV49: 0 | CW49: =ROUND(Y49*Source!I36*DO49,7) -> 1.179 | CX49: =ROUND(Y49*Source!I36,7) -> 1.179 | CY49: =AB49 -> 411.37 | CZ49: =AF49 -> 411.37 | DA49: =AJ49 -> 1 | DB49: =ROUND(ROUND(AT49*CZ49,2),6) -> 1077.79 | DC49: =ROUND(ROUND(AT49*AG49,2),6) -> 1133.96 | DF49: =ROUND(ROUND(AE49,2)*CX49,2) -> 0 | DG49: =ROUND(ROUND(AF49,2)*CX49,2) -> 485.01 | DH49: =ROUND(ROUND(AG49,2)*CX49,2) -> 510.28 | DI49: =ROUND(ROUND(AH49,2)*CX49,2) -> 0 | DJ49: =DG49+DH49 -> 995.29 | DK49: 1 | DL49: 4-100-040 | DM49: 4 | DN49: чел.-ч. | DO49: 1
A50: =ROW(Source!A37) -> 37 | B50: 38182922 | C50: 38183842 | D50: 20031423 | E50: 117 | F50: 1 | G50: 1 | H50: 1 | I50: 1-100-30 | K50: Средний разряд работы 3,0 | L50: 1191 | N50: 1013 | O50: чел.-ч. | P50: чел.-ч. | Q50: 1 | W50: 0 | X50: -1833565283 | Y50: =AT50 -> 1.86 | AA50: 0 | AB50: 0 | AC50: 0 | AD50: 384.36 | AE50: 0 | AF50: 0 | AG50: 0 | AH50: 384.36 | AI50: 1 | AJ50: 1 | AK50: 1 | AL50: 1 | AM50: -2 | AN50: 0 | AO50: 0 | AP50: 0 | AQ50: 1 | AR50: 0 | AT50: 1.86 | AV50: 1 | AW50: 2 | AX50: 38183848 | AY50: 1 | AZ50: 0 | BA50: 49 | BB50: 1 | BC50: 0 | BD50: 0 | BE50: 0 | BF50: 0 | BG50: 0 | BH50: 0 | BI50: 0 | BJ50: 0 | BK50: 0 | BL50: 0 | BM50: 714.9096 | BN50: 1.86 | BO50: 0 | BP50: 1 | BQ50: 0 | BR50: 0 | BS50: 0 | BT50: 714.9096 | BU50: 1.86 | BV50: 0 | BW50: 1 | CU50: =ROUND(AT50*Source!I37*AH50*AL50,2) -> 3217.09 | CV50: =ROUND(Y50*Source!I37,7) -> 8.37 | CW50: 0 | CX50: =ROUND(Y50*Source!I37,7) -> 8.37 | CY50: =AD50 -> 384.36 | CZ50: =AH50 -> 384.36 | DA50: =AL50 -> 1 | DB50: =ROUND(ROUND(AT50*CZ50,2),6) -> 714.91 | DC50: =ROUND(ROUND(AT50*AG50,2),6) -> 0 | DF50: =ROUND(ROUND(AE50,2)*CX50,2) -> 0 | DG50: =ROUND(ROUND(AF50,2)*CX50,2) -> 0 | DH50: =ROUND(ROUND(AG50,2)*CX50,2) -> 0 | DI50: =ROUND(ROUND(AH50,2)*CX50,2) -> 3217.09 | DJ50: =DI50 -> 3217.09 | DK50: 1 | DM50: 0 | DO50: 0
A51: =ROW(Source!A37) -> 37 | B51: 38182922 | C51: 38183842 | D51: 20031379 | E51: 117 | F51: 1 | G51: 1 | H51: 1 | I51: 4-100-00 | K51: Затраты труда машинистов | L51: 1191 | N51: 1013 | O51: чел.-ч. | P51: чел.-ч. | Q51: 1 | W51: 0 | X51: -1417349443 | Y51: =AT51 -> 0.76 | AA51: 0 | AB51: 0 | AC51: 0 | AD51: 0 | AE51: 0 | AF51: 0 | AG51: 0 | AH51: 0 | AI51: 1 | AJ51: 1 | AK51: 1 | AL51: 1 | AM51: -2 | AN51: 0 | AO51: 0 | AP51: 0 | AQ51: 1 | AR51: 0 | AT51: 0.76 | AV51: 2 | AW51: 2 | AX51: 38183849 | AY51: 1 | AZ51: 0 | BA51: 50 | BB51: 1 | BC51: 0 | BD51: 0 | BE51: 0 | BF51: 0 | BG51: 0 | BH51: 0 | BI51: 0 | BJ51: 0 | BK51: 0 | BL51: 0 | BM51: 0 | BN51: 0 | BO51: 0 | BP51: 0 | BQ51: 0 | BR51: 0 | BS51: 0 | BT51: 0 | BU51: 0 | BV51: 0 | BW51: 0 | CV51: 0 | CW51: 0 | CX51: =ROUND(Y51*Source!I37,7) -> 3.42 | CY51: =AD51 -> 0 | CZ51: =AH51 -> 0 | DA51: =AL51 -> 1 | DB51: =ROUND(ROUND(AT51*CZ51,2),6) -> 0 | DC51: =ROUND(ROUND(AT51*AG51,2),6) -> 0 | DF51: =ROUND(ROUND(AE51,2)*CX51,2) -> 0 | DG51: =ROUND(ROUND(AF51,2)*CX51,2) -> 0 | DH51: =ROUND(ROUND(AG51,2)*CX51,2) -> 0 | DI51: =ROUND(ROUND(AH51,2)*CX51,2) -> 0 | DJ51: =DI51 -> 0 | DK51: 0 | DM51: 0 | DO51: 0
