Workbook

Sheet Сводная
C4: Месяц | D4: ЗП | E4: Подарили | F4: Занял | G4: Расходы | H4: Сальдо
C5: Январь | D5: - | E5: - | F5: - | G5: - | H5: -
C6: Февраль | D6: 100494.4 | E6: 10000 | F6: 0 | G6: 109233.84 | H6: =SUM(D6:F6)-G6 -> 1260.56
C7: Март | D7: 68400 | E7: 0 | F7: 0 | G7: 80331.3 | H7: =SUM(D7:F7)-G7 -> -11931.3
C8: Апрель | D8: 136698 | E8: 10000 | F8: 17000 | G8: 163638.94 | H8: =SUM(D8:F8)-G8 -> 59.06
C9: Май | D9: ='Май 2026'!X3+'Май 2026'!X19 -> 86059.05 | E9: ='Май 2026'!X7+'Май 2026'!X21+'Май 2026'!X34 -> 7000 | F9: ='Май 2026'!X28+'Май 2026'!X29 -> 10000 | G9: ='Май 2026'!W36 -> 105788.06 | H9: =SUM(D9:F9)-G9 -> -2729.01
C10: Июнь | D10: =' Июнь 2026'!X3+' Июнь 2026'!X19 -> 90491.54 | E10: =' Июнь 2026'!X9 -> 15000 | F10: =' Июнь 2026'!X14+' Июнь 2026'!X16 -> 7000 | G10: =' Июнь 2026'!W36 -> 90253.07 | H10: =SUM(D10:F10)-G10 -> 22238.47
C11: Июль | D11: ='Июль 2026'!Y3+'Июль 2026'!Y14+'Июль 2026'!Y21 -> 226341.31 | E11: ='Июль 2026'!Y27 -> 20000 | F11: ='Июль 2026'!Y17+'Июль 2026'!Y19+'Июль 2026'!Y33 -> 35000 | G11: ='Июль 2026'!W38 -> 177971.36 | H11: =SUM(D11:F11)-G11 -> 103369.95
C12: Август | D12: ='Август 2026'!AC4+'Август 2026'!AC20 -> 133443.15 | E12: ='Август 2026'!AC29 -> 1000 | F12: ='Август 2026'!AC21+'Август 2026'!AC34 -> 11000 | G12: ='Август 2026'!AB36 -> 146501.73 | H12: =SUM(D12:F12)-G12 -> -1058.58
C13: Сентябрь | H13: =SUM(D13:F13)-G13 -> 0
C14: Октябрь | H14: =SUM(D14:F14)-G14 -> 0
C15: Ноябрь | H15: =SUM(D15:F15)-G15 -> 0
C16: Декабрь | H16: =SUM(D16:F16)-G16 -> 0
C17: ИТОГО

Sheet Февраль 2026
A1: Доходы - Расходы Февраль 2026
A2: Число | B2: День недели | C2: Магазин | D2: Доставка | E2: Вкус Вилл | F2: Столовая (обед) | G2: Кафе | H2: Алкоголь | I2: Бар/Клуб | J2: Коммуналка / ЖКХ | K2: Теннис | L2: Одежда | M2: Медицина | N2: Такси | O2: Бензин/ Парковка | P2: Аня | Q2: Учеба | R2: Ежемесячны платежи | S2: Другое (повседневное) | T2: Другое (повседневное) | U2: Другое (развлечения) | V2: Итого Расходы | W2: Доходы | X2: Сальдо
A3: 5 | B3: Чт | C3: =183+2168 -> 2351 | D3: 3131 | J3: 450 | N3: 40 | Q3: 14418 | S3: 5000 | V3: =SUM(C3:U3) -> 25390 | W3: 53739.4
A4: 6 | B4: Пт | N4: =131+247 -> 378 | V4: =SUM(C4:U4) -> 378
A5: 7 | B5: Сб | D5: 1110 | I5: 840 | N5: =197+259 -> 456 | V5: =SUM(C5:U5) -> 2406
A6: 8 | B6: Вс | C6: 1006 | N6: =221+171 -> 392 | V6: =SUM(C6:U6) -> 1398
A7: 9 | B7: Пн | C7: 1819 | N7: 224 | S7: 1055 | V7: =SUM(C7:U7) -> 3098
A8: 10 | B8: Вт | C8: 1266.9 | D8: 1345 | N8: 172 | V8: =SUM(C8:U8) -> 2783.9
A9: 11 | B9: Ср | C9: 1403.84 | V9: =SUM(C9:U9) -> 1403.84
A10: 12 | B10: Чт | D10: 959 | V10: =SUM(C10:U10) -> 959
A11: 13 | B11: Пт | C11: =342.99+1260.98 -> 1603.97 | G11: =3980+430 -> 4410 | P11: =773+2000+1767 -> 4540 | V11: =SUM(C11:U11) -> 10553.97
A12: 14 | B12: Сб | C12: =1260.98+678.97 -> 1939.95 | D12: =4500+149 -> 4649 | N12: =543+421 -> 964 | P12: =497 -> 497 | V12: =SUM(C12:U12) -> 8049.95
A13: 15 | B13: Вс | C13: =1569.79 -> 1569.79 | N13: 135 | V13: =SUM(C13:U13) -> 1704.79
A14: 16 | B14: Пн | C14: 1170 | V14: =SUM(C14:U14) -> 1170
A15: 17 | B15: Вт | V15: =SUM(C15:U15) -> 0
A16: 18 | B16: Ср | C16: 200 | N16: 400 | R16: 499 | V16: =SUM(C16:U16) -> 1099
A17: 19 | B17: Чт | V17: =SUM(C17:U17) -> 0 | X17: =W3-SUM(V3:V16) -> -6655.05
A18: 20 | B18: Пт | I18: 1300 | N18: =1587+618 -> 2205 | V18: =SUM(C18:U18) -> 3505 | W18: =30304+16451 -> 46755
A19: 21 | B19: Сб | E19: 2933.48 | G19: =3700+435 -> 4135 | N19: 463 | V19: =SUM(C19:U19) -> 7531.48
A20: 22 | B20: Вс | C20: =968+2181 -> 3149 | P20: 1300 | V20: =SUM(C20:U20) -> 4449
A21: 23 | B21: Пн | V21: =SUM(C21:U21) -> 0 | W21: 10000
A22: 24 | B22: Вт | E22: 1583 | F22: 939 | N22: 515 | V22: =SUM(C22:U22) -> 3037
A23: 25 | B23: Ср | C23: 935 | F23: =1118+770 -> 1888 | N23: =360+381 -> 741 | P23: 100 | S23: =100+650 -> 750 | V23: =SUM(C23:U23) -> 4414
A24: 26 | B24: Чт | E24: 611 | N24: =400+344 -> 744 | P24: 214 | V24: =SUM(C24:U24) -> 1569
A25: 27 | B25: Пт | F25: 700 | H25: 1239.99 | J25: 3974.41 | N25: =349+254+607+400 -> 1610 | U25: =1100+1090+350 -> 2540 | V25: =SUM(C25:U25) -> 10064.4
A26: 28 | B26: Сб | C26: 1577.82 | J26: 3990.69 | L26: =1896+3633 -> 5529 | N26: =233+539 -> 772 | P26: 2400 | V26: =SUM(C26:U26) -> 14269.51
A27: 1 | B27: Вс | D27: 1294 | J27: 1711.25 | N27: 133 | S27: =414+449 -> 863 | V27: =SUM(C27:U27) -> 4001.25
A28: 2 | B28: Пн | F28: =350+1510 -> 1860 | N28: 277 | R28: 700 | V28: =SUM(C28:U28) -> 2837
A29: 3 | B29: Вт | R29: 799 | V29: =SUM(C29:U29) -> 799
A30: 4 | B30: Ср | V30: =SUM(C30:U30) -> 0 | X30: =W18+W21-SUM(V18:V30) -> 278.36
A31: ИТОГО | C31: =SUM(C3:C30) -> 19992.27 | D31: =SUM(D3:D30) -> 12488 | E31: =SUM(E3:E30) -> 5127.48 | F31: =SUM(F3:F30) -> 5387 | G31: =SUM(G3:G30) -> 8545 | H31: =SUM(H3:H30) -> 1239.99 | I31: =SUM(I3:I30) -> 2140 | J31: =SUM(J3:J30) -> 10126.35 | ... U31: =SUM(U3:U30) -> 2540 | V31: =SUM(V3:V26) -> 109233.84 | W31: =SUM(W3:W26) -> 110494.4 | X31: =W31-V31 -> 1260.56

Sheet Март 2026
A1: Доходы - Расходы Март 2026
A2: Число | B2: День недели | C2: Магазин | D2: Вкус Вилл | E2: Доставка | F2: Обед | G2: Кафе | H2: Алкоголь | I2: Бар/Клуб | J2: Коммуналка / ЖКХ | K2: Теннис | L2: Одежда | M2: Медицина | N2: Такси | O2: Бензин/ Парковка | P2: Аня | Q2: Учеба | R2: Ежемесячны платежи | S2: Другое (повседневное) | T2: Другое (повседневное) | U2: Другое (развлечения) | V2: Итого Расходы | W2: Доходы | X2: Сальдо
A3: 5 | B3: Чт | C3: =2497.35+200 -> 2697.35 | N3: 312 | R3: 990 | V3: =SUM(C3:U3) -> 3999.35 | W3: 43724
A4: 6 | B4: Пт | F4: 1610 | N4: =387+364 -> 751 | R4: 199 | S4: =2411.96/2+116.97+2148/2+729 -> 3125.95 | T4: 6000 | V4: =SUM(C4:U4) -> 11685.95
A5: 7 | B5: Сб | G5: =3080+328 -> 3408 | N5: 268 | P5: 8428 | R5: =255+547 -> 802 | V5: =SUM(C5:U5) -> 12906
A6: 8 | B6: Вс | C6: =284+995 -> 1279 | H6: 1117 | N6: 400 | P6: 1330 | V6: =SUM(C6:U6) -> 4126
A7: 9 | B7: Пн | C7: 769 | V7: =SUM(C7:U7) -> 769
A8: 10 | B8: Вт | O8: 302 | V8: =SUM(C8:U8) -> 302
A9: 11 | B9: Ср | D9: 1191 | F9: =1070+109 -> 1179 | N9: 400 | O9: 277 | V9: =SUM(C9:U9) -> 3047
A10: 12 | B10: Чт | F10: =420+700 -> 1120 | G10: =1421+331 -> 1752 | N10: 294 | S10: =387+864 -> 1251 | V10: =SUM(C10:U10) -> 4417
A11: 13 | B11: Пт | F11: =1070+60 -> 1130 | N11: =251+328+262 -> 841 | V11: =SUM(C11:U11) -> 1971
A12: 14 | B12: Сб | G12: 3605 | V12: =SUM(C12:U12) -> 3605
A13: 15 | B13: Вс | C13: =318+2115 -> 2433 | V13: =SUM(C13:U13) -> 2433
A14: 16 | B14: Пн | F14: =350 -> 350 | O14: 291 | V14: =SUM(C14:U14) -> 641
A15: 17 | B15: Вт | F15: 350 | O15: 1000 | V15: =SUM(C15:U15) -> 1350
A16: 18 | B16: Ср | F16: =1080+109+350 -> 1539 | N16: 400 | V16: =SUM(C16:U16) -> 1939
A17: 19 | B17: Чт | N17: =159+358 -> 517 | V17: =SUM(C17:U17) -> 517
A18: 20 | B18: Пт | C18: =220+2225+135 -> 2580 | R18: 499 | S18: 130 | V18: =SUM(C18:U18) -> 3209 | W18: 24676
A19: 21 | B19: Сб | C19: =780+65 -> 845 | R19: =570+120 -> 690 | S19: 4661 | T19: 1200 | V19: =SUM(C19:U19) -> 7396
A20: 22 | B20: Вс | C20: =5500-2600 -> 2900 | S20: 2600 | T20: 600 | V20: =SUM(C20:U20) -> 6100
A21: 23 | B21: Пн | O21: 311 | V21: =SUM(C21:U21) -> 311
A22: 24 | B22: Вт | O22: 295 | S22: 900 | V22: =SUM(C22:U22) -> 1195
A23: 25 | B23: Ср | C23: =633 -> 633 | F23: =392+352 -> 744 | N23: =204+188+400 -> 792 | V23: =SUM(C23:U23) -> 2169
A24: 26 | B24: Чт | V24: =SUM(C24:U24) -> 0
A25: 27 | B25: Пт | C25: 1104 | D25: 856 | N25: =201+182 -> 383 | V25: =SUM(C25:U25) -> 2343
A26: 28 | B26: Сб | D26: 1067 | S26: 132 | V26: =SUM(C26:U26) -> 1199
A27: 29 | B27: Вс | C27: =735+868 -> 1603 | N27: =322+198 -> 520 | V27: =SUM(C27:U27) -> 2123
A28: 30 | B28: Пн | F28: =350 -> 350 | N28: 228 | V28: =SUM(C28:U28) -> 578
A29: 31 | B29: Вт | V29: =SUM(C29:U29) -> 0
A30: 1 | B30: Ср | V30: =SUM(C30:U30) -> 0
A31: 2 | B31: Чт | V31: =SUM(C31:U31) -> 0
A32: ИТОГО | C32: =SUM(C3:C31) -> 16843.35 | D32: =SUM(D3:D31) -> 3114 | E32: =SUM(E3:E31) -> 0 | F32: =SUM(F3:F31) -> 8372 | G32: =SUM(G3:G31) -> 8765 | H32: =SUM(H3:H31) -> 1117 | I32: =SUM(I3:I31) -> 0 | J32: =SUM(J3:J31) -> 0 | ... V32: =SUM(V3:V31) -> 80331.3 | W32: =SUM(W3:W29) -> 68400 | X32: =W32-V32 -> -11931.3

Sheet Апрель 2026
A1: Доходы - Расходы Апрель 2026
A2: Число | B2: День недели | C2: Магазин | D2: Вкус Вилл | E2: Доставка | F2: Обед | G2: Синабон | H2: Кафе | I2: Алкоголь | J2: Бар/Клуб | K2: Коммуналка / ЖКХ | L2: Теннис | M2: Одежда | N2: Медицина | O2: Такси | P2: Бензин/ Парковка | Q2: Аня | R2: Учеба | S2: Ежемесячны платежи | T2: Другое (повседневное) | U2: Другое (повседневное) | V2: Другое (развлечения) | W2: Итого Расходы | X2: Доходы | Y2: Сальдо
A3: 3 | B3: Пт | Q3: =22000+3500 -> 25500 | S3: =4660+702+799 -> 6161 | T3: 7000 | U3: 750 | W3: =SUM(C3:V3) -> 39411 | X3: 100688
A4: 4 | B4: Сб | C4: =100+422+585 -> 1107 | D4: 3679 | H4: =2320+1728 -> 4048 | K4: 3663.22 | N4: 5350 | Q4: 1025 | S4: 100 | U4: 990 | V4: =1320+1330+210 -> 2860 | W4: =SUM(C4:V4) -> 22822.22
A5: 5 | B5: Вс | C5: =3116+382 -> 3498 | I5: 1500 | R5: 9373 | S5: 199 | W5: =SUM(C5:V5) -> 14570
A6: 6 | B6: Пн | C6: 918 | D6: 994 | K6: 3464 | P6: =500+288 -> 788 | S6: 990 | W6: =SUM(C6:V6) -> 7154
A7: 7 | B7: Вт | D7: 714 | P7: =500+280 -> 780 | W7: =SUM(C7:V7) -> 1494
A8: 8 | B8: Ср | F8: 420 | G8: 835 | H8: 285 | W8: =SUM(C8:V8) -> 1540
A9: 9 | B9: Чт | C9: 863 | D9: 710 | O9: 409 | W9: =SUM(C9:V9) -> 1982
A10: 10 | B10: Пт | C10: 319 | D10: 940 | E10: 1895 | G10: 835 | I10: 1034 | O10: 275 | W10: =SUM(C10:V10) -> 5298
A11: 11 | B11: Сб | C11: =790+282 -> 1072 | D11: 1311 | N11: =1500+1900 -> 3400 | O11: =302+243 -> 545 | W11: =SUM(C11:V11) -> 6328 | X11: 5000
A12: 12 | B12: Вс | C12: =69+603 -> 672 | W12: =SUM(C12:V12) -> 672 | X12: 10000
A13: 13 | B13: Пн | W13: =SUM(C13:V13) -> 0
A14: 14 | B14: Вт | C14: 879 | F14: 1080 | G14: 580 | H14: 1261 | O14: 305 | W14: =SUM(C14:V14) -> 4105
A15: 15 | B15: Ср | C15: 700 | F15: 990 | H15: 2200 | O15: 369 | T15: 1400 | W15: =SUM(C15:V15) -> 5659
A16: 16 | B16: Чт | C16: =160+263 -> 423 | T16: 450 | W16: =SUM(C16:V16) -> 873
A17: 17 | B17: Пт | E17: 1116 | O17: 307 | Q17: 800 | W17: =SUM(C17:V17) -> 2223
A18: 18 | B18: Сб | C18: =1357.83+470 -> 1827.83 | O18: 187 | W18: =SUM(C18:V18) -> 2014.83
A19: 19 | B19: Вс | S19: 700 | W19: =SUM(C19:V19) -> 700
A20: Итоги по ЗП: | C20: =SUM(C3:C19) -> 12278.83 | D20: =SUM(D3:D19) -> 8348 | E20: =SUM(E3:E19) -> 3011 | F20: =SUM(F3:F19) -> 2490 | G20: =SUM(G3:G19) -> 2250 | H20: =SUM(H3:H19) -> 7794 | I20: =SUM(I3:I19) -> 2534 | J20: =SUM(J3:J19) -> 0 | ... X20: =SUM(X3:X19) -> 115688 | Y20: =X20-W20 -> -1158.05
A21: 20 | B21: Пн | C21: 2409 | D21: 299 | O21: 187 | S21: =4660+700 -> 5360 | T21: 1634 | W21: =SUM(C21:V21) -> 9889 | X21: 36010
A22: 21 | B22: Вт | C22: 374 | F22: 1080 | H22: 572 | O22: 215 | T22: 3700 | W22: =SUM(C22:V22) -> 5941
A23: 22 | B23: Ср | C23: 1027.89 | G23: 835 | O23: 265 | W23: =SUM(C23:V23) -> 2127.89
A24: 23 | B24: Чт | E24: 1344 | O24: 349 | Q24: 1000 | W24: =SUM(C24:V24) -> 2693
A25: 24 | B25: Пт | C25: 1755 | F25: 1331 | O25: 180 | Q25: 500 | W25: =SUM(C25:V25) -> 3766
A26: 25 | B26: Сб | C26: 525 | D26: 1326 | O26: 251 | Q26: 300 | W26: =SUM(C26:V26) -> 2402
A27: 26 | B27: Вс | D27: 2161 | E27: 1336 | Q27: 151 | W27: =SUM(C27:V27) -> 3648
A28: 27 | B28: Пн | D28: 1417 | O28: =677+345 -> 1022 | W28: =SUM(C28:V28) -> 2439
A29: 28 | B29: Вт | D29: 1796 | G29: 485 | H29: 1360 | O29: =319+442 -> 761 | S29: 249 | W29: =SUM(C29:V29) -> 4651
A30: 29 | B30: Ср | F30: 614 | O30: 207 | W30: =SUM(C30:V30) -> 821 | X30: 10000
A31: 30 | B31: Чт | C31: =90 -> 90 | H31: =1150+165 -> 1315 | P31: 227 | W31: =SUM(C31:V31) -> 1632
A32: 1 | B32: Пт | C32: =1695+809 -> 2504 | D32: 464 | T32: 145 | W32: =SUM(C32:V32) -> 3113
A33: 2 | B33: Сб | C33: =85+547 -> 632 | S33: 799 | T33: 62 | W33: =SUM(C33:V33) -> 1493
A34: 3 | B34: Вс | C34: 363 | T34: 20 | W34: =SUM(C34:V34) -> 383
A35: 4 | B35: Пн | C35: =47+1331 -> 1378 | D35: 89 | P35: 327 | W35: =SUM(C35:V35) -> 1794 | X35: 2000
A36: Итого по Авансу: | C36: =SUM(C21:C35) -> 11057.89 | D36: =SUM(D21:D35) -> 7552 | E36: =SUM(E21:E35) -> 2680 | F36: =SUM(F21:F35) -> 3025 | G36: =SUM(G21:G35) -> 1320 | H36: =SUM(H21:H35) -> 3247 | I36: =SUM(I21:I35) -> 0 | J36: =SUM(J21:J35) -> 0 | ... X36: =SUM(X21:X35) -> 48010 | Y36: =X36-W36 -> 1217.11
A37: ИТОГО по месяцу: | C37: =SUM(C20,C36) -> 23336.72 | D37: =SUM(D20,D36) -> 15900 | E37: =SUM(E20,E36) -> 5691 | F37: =SUM(F20,F36) -> 5515 | G37: =SUM(G20,G36) -> 3570 | H37: =SUM(H20,H36) -> 11041 | I37: =SUM(I20,I36) -> 2534 | J37: =SUM(J20,J36) -> 0 | ... Y37: =SUM(Y20,Y36) -> 59.06

Sheet Май 2026
A1: Доходы - Расходы Май 2026
A2: Число | B2: День недели | C2: Магазин | D2: Вкус Вилл | E2: Доставка | F2: Обед | G2: Синабон | H2: Кафе | I2: Алкоголь | J2: Бар/Клуб | K2: Коммуналка / ЖКХ | L2: Теннис | M2: Одежда | N2: Медицина | O2: Такси | P2: Бензин/ Парковка | Q2: Аня | R2: Учеба | S2: Ежемесячны платежи | T2: Другое (повседневное) | U2: Другое (повседневное) | V2: Другое (развлечения) | W2: Итого Расходы | X2: Доходы | Y2: Сальдо
A3: 5 | B3: Вт | D3: =178+110 -> 288 | P3: =1000+281 -> 1281 | S3: =199+4660+700 -> 5559 | T3: 7000 | W3: =SUM(C3:V3) -> 14128 | X3: 53970.91
A4: 6 | B4: Ср | D4: 110 | H4: =2500+270 -> 2770 | O4: =363+350 -> 713 | W4: =SUM(C4:V4) -> 3593
A5: 7 | B5: Чт | C5: =1497+707 -> 2204 | D5: 520 | F5: =189 -> 189 | I5: 750 | O5: 245 | S5: 990 | W5: =SUM(C5:V5) -> 4898
A6: 8 | B6: Пт | D6: 2122 | H6: 3695 | O6: =350+407+249 -> 1006 | W6: =SUM(C6:V6) -> 6823
A7: 9 | B7: Сб | K7: 1008.31 | W7: =SUM(C7:V7) -> 1008.31 | X7: 3000
A8: 10 | B8: Вс | D8: 2550.04 | K8: 1763.15 | W8: =SUM(C8:V8) -> 4313.19
A9: 11 | B9: Пн | C9: =3150.35+125 -> 3275.35 | D9: =264+1506 -> 1770 | K9: 2244.06 | P9: 1000 | T9: =100+100+400 -> 600 | W9: =SUM(C9:V9) -> 8889.41
A10: 12 | B10: Вт | F10: 1245 | Q10: =1000+1000 -> 2000 | W10: =SUM(C10:V10) -> 3245
A11: 13 | B11: Ср | H11: =210+1009 -> 1219 | P11: 340 | T11: 1479 | W11: =SUM(C11:V11) -> 3038
A12: 14 | B12: Чт | O12: 367 | P12: 285 | T12: 220 | W12: =SUM(C12:V12) -> 872
A13: 15 | B13: Пт | H13: 1220 | P13: 131 | Q13: 1012 | W13: =SUM(C13:V13) -> 2363
A14: 16 | B14: Сб | C14: =384+1318+1214 -> 2916 | D14: 1351.32 | Q14: 450 | W14: =SUM(C14:V14) -> 4717.32
A15: 17 | B15: Вс | C15: 33 | W15: =SUM(C15:V15) -> 33
A16: 18 | B16: Пн | P16: 280 | W16: =SUM(C16:V16) -> 280
A17: 19 | B17: Вт | W17: =SUM(C17:V17) -> 0
A18: Итоги по ЗП: | C18: =SUM(C3:C17) -> 8428.35 | D18: =SUM(D3:D17) -> 8711.36 | E18: =SUM(E3:E17) -> 0 | F18: =SUM(F3:F17) -> 1434 | G18: =SUM(G3:G17) -> 0 | H18: =SUM(H3:H17) -> 8904 | I18: =SUM(I3:I17) -> 750 | J18: =SUM(J3:J17) -> 0 | ... X18: =SUM(X3:X17) -> 56970.91 | Y18: =X18-W18 -> -1230.32
A19: 20 | B19: Ср | C19: 953 | D19: 1805.6 | Q19: 285 | S19: 700 | W19: =SUM(C19:V19) -> 3743.6 | X19: 32088.14
A20: 21 | B20: Чт | D20: =1303+346+262 -> 1911 | O20: =553+689 -> 1242 | T20: 849 | U20: 2000 | W20: =SUM(C20:V20) -> 6002
A21: 22 | B21: Пт | C21: 500 | H21: =1556+2900 -> 4456 | I21: =2101.91-500 -> 1601.91 | P21: 25.18 | T21: 800 | U21: 316 | W21: =SUM(C21:V21) -> 7699.09 | X21: 1000
A22: 23 | B22: Сб | C22: 833 | O22: 332 | W22: =SUM(C22:V22) -> 1165
A23: 24 | B23: Вс | C23: =119+1463 -> 1582 | W23: =SUM(C23:V23) -> 1582
A24: 25 | B24: Пн | C24: =440 -> 440 | J24: 3600 | O24: =397+401 -> 798 | S24: 700 | T24: 200 | W24: =SUM(C24:V24) -> 5738
A25: 26 | B25: Вт | C25: =637 -> 637 | O25: =249+309 -> 558 | T25: 598 | V25: =1555+50 -> 1605 | W25: =SUM(C25:V25) -> 3398
A26: 27 | B26: Ср | W26: =SUM(C26:V26) -> 0
A27: 28 | B27: Чт | H27: 158 | O27: =273+500 -> 773 | S27: =249 -> 249 | W27: =SUM(C27:V27) -> 1180
A28: 29 | B28: Пт | C28: 1121 | D28: 661 | H28: =220+726 -> 946 | L28: =204+233 -> 437 | V28: =390+1100 -> 1490 | W28: =SUM(C28:V28) -> 4655 | X28: 5000
A29: 30 | B29: Сб | C29: =2136 -> 2136 | D29: 1318.68 | E29: 1330 | W29: =SUM(C29:V29) -> 4784.68 | X29: 5000
A30: 31 | B30: Вс | C30: =493.95+190+90+150+1613.51 -> 2537.46 | Q30: 500 | W30: =SUM(C30:V30) -> 3037.46
A31: 1 | B31: Пн | N31: =500+2720 -> 3220 | O31: 241 | S31: =300+841 -> 1141 | W31: =SUM(C31:V31) -> 4602
A32: 2 | B32: Вт | W32: =SUM(C32:V32) -> 0
A33: 3 | B33: Ср | W33: =SUM(C33:V33) -> 0
A34: 4 | B34: Чт | W34: =SUM(C34:V34) -> 0 | X34: 3000
A35: Итого по Авансу: | C35: =SUM(C19:C34) -> 10739.46 | D35: =SUM(D19:D34) -> 5696.28 | E35: =SUM(E19:E34) -> 1330 | F35: =SUM(F19:F34) -> 0 | G35: =SUM(G19:G34) -> 0 | H35: =SUM(H19:H34) -> 5560 | I35: =SUM(I19:I34) -> 1601.91 | J35: =SUM(J19:J34) -> 3600 | ... X35: =SUM(X19:X34) -> 46088.14 | Y35: =X35-W35 -> -1498.69
A36: ИТОГО по месяцу: | C36: =SUM(C18,C35) -> 19167.81 | D36: =SUM(D18,D35) -> 14407.64 | E36: =SUM(E18,E35) -> 1330 | F36: =SUM(F18,F35) -> 1434 | G36: =SUM(G18,G35) -> 0 | H36: =SUM(H18,H35) -> 14464 | I36: =SUM(I18,I35) -> 2351.91 | J36: =SUM(J18,J35) -> 3600 | ... Y36: =SUM(Y18,Y35) -> -2729.01

Sheet  Июнь 2026
A1: Доходы - Расходы Июнь 2026
A2: Число | B2: День недели | C2: Магазин | D2: Вкус Вилл | E2: Доставка | F2: Обед | G2: Синабон | H2: Кафе | I2: Алкоголь | J2: Бар/Клуб | K2: Коммуналка / ЖКХ | L2: Теннис | M2: Одежда | N2: Медицина | O2: Такси | P2: Бензин/ Парковка | Q2: Аня | R2: Учеба | S2: Ежемесячны платежи | T2: Другое (повседневное) | U2: Другое (повседневное) | V2: Другое (развлечения) | W2: Итого Расходы | X2: Доходы | Y2: Сальдо
A3: 5 | B3: Пт | C3: =310+1963+195 -> 2468 | D3: 2091 | F3: 596 | H3: =209 -> 209 | O3: 271 | P3: 1000 | S3: =199 -> 199 | T3: 2300 | V3: =850 -> 850 | W3: =SUM(C3:V3) -> 9984 | X3: =35654.26+22580 -> 58234.26
A4: 6 | B4: Сб | D4: =5183+98 -> 5281 | H4: 1450 | N4: 2000 | Q4: 5700 | S4: 700 | W4: =SUM(C4:V4) -> 15131
A5: 7 | B5: Вс | C5: =280+1103 -> 1383 | H5: 1280 | T5: 1075 | W5: =SUM(C5:V5) -> 3738
A6: 8 | B6: Пн | C6: =155 -> 155 | F6: =700 -> 700 | H6: 1734 | P6: 336 | T6: 990 | W6: =SUM(C6:V6) -> 3915
A7: 9 | B7: Вт | C7: 1707 | P7: =1000+297 -> 1297 | Q7: 400 | W7: =SUM(C7:V7) -> 3404
A8: 10 | B8: Ср | D8: 1261 | F8: =1080+740 -> 1820 | N8: =15454 -> 15454 | Q8: 2630 | S8: 841 | W8: =SUM(C8:V8) -> 22006
A9: 11 | B9: Чт | C9: 1198 | O9: =201+203+153 -> 557 | Q9: 2600 | W9: =SUM(C9:V9) -> 4355 | X9: 15000
A10: 12 | B10: Пт | D10: 1951.75 | E10: 1310 | W10: =SUM(C10:V10) -> 3261.75
A11: 13 | B11: Сб | C11: =391+602 -> 993 | D11: 1090.32 | E11: 4180 | I11: 1413 | O11: 340 | W11: =SUM(C11:V11) -> 8016.32
A12: 14 | B12: Вс | D12: 1743 | O12: 385 | Q12: -1000 | W12: =SUM(C12:V12) -> 1128
A13: 15 | B13: Пн | D13: 152 | O13: 358 | Q13: -300 | S13: 842 | W13: =SUM(C13:V13) -> 1052
A14: 16 | B14: Вт | W14: =SUM(C14:V14) -> 0 | X14: 5000
A15: 17 | B15: Ср | W15: =SUM(C15:V15) -> 0
A16: 18 | B16: Чт | W16: =SUM(C16:V16) -> 0 | X16: 2000
A17: 19 | B17: Пт | D17: 2587 | H17: 1836 | P17: =280+13 -> 293 | S17: 499 | T17: 640 | W17: =SUM(C17:V17) -> 5855
A18: Итоги по ЗП: | C18: =SUM(C3:C17) -> 7904 | D18: =SUM(D3:D17) -> 16157.07 | E18: =SUM(E3:E17) -> 5490 | F18: =SUM(F3:F17) -> 3116 | G18: =SUM(G3:G17) -> 0 | H18: =SUM(H3:H17) -> 6509 | I18: =SUM(I3:I17) -> 1413 | J18: =SUM(J3:J17) -> 0 | ... X18: =SUM(X3:X17) -> 80234.26 | Y18: =X18-W18 -> -1611.81
A19: 20 | B19: Сб | H19: 351 | N19: 7500 | O19: 556 | W19: =SUM(C19:V19) -> 8407 | X19: 32257.28
A20: 21 | B20: Вс | W20: =SUM(C20:V20) -> 0
A21: 22 | B21: Пн | W21: =SUM(C21:V21) -> 0
A22: 23 | B22: Вт | W22: =SUM(C22:V22) -> 0
A23: 24 | B23: Ср | W23: =SUM(C23:V23) -> 0
A24: 25 | B24: Чт | W24: =SUM(C24:V24) -> 0
A25: 26 | B25: Пт | W25: =SUM(C25:V25) -> 0
A26: 27 | B26: Сб | W26: =SUM(C26:V26) -> 0
A27: 28 | B27: Вс | W27: =SUM(C27:V27) -> 0
A28: 29 | B28: Пн | W28: =SUM(C28:V28) -> 0
A29: 30 | B29: Вт | W29: =SUM(C29:V29) -> 0
A30: 31 | B30: Ср | W30: =SUM(C30:V30) -> 0
A31: 1 | B31: Чт | W31: =SUM(C31:V31) -> 0
... A34: 4 | B34: Вс | W34: =SUM(C34:V34) -> 0
A35: Итого по Авансу: | C35: =SUM(C19:C34) -> 0 | D35: =SUM(D19:D34) -> 0 | E35: =SUM(E19:E34) -> 0 | F35: =SUM(F19:F34) -> 0 | G35: =SUM(G19:G34) -> 0 | H35: =SUM(H19:H34) -> 351 | I35: =SUM(I19:I34) -> 0 | J35: =SUM(J19:J34) -> 0 | ... X35: =SUM(X19:X34) -> 32257.28 | Y35: =X35-W35 -> 23850.28
A36: ИТОГО по месяцу: | C36: =SUM(C18,C35) -> 7904 | D36: =SUM(D18,D35) -> 16157.07 | E36: =SUM(E18,E35) -> 5490 | F36: =SUM(F18,F35) -> 3116 | G36: =SUM(G18,G35) -> 0 | H36: =SUM(H18,H35) -> 6860 | I36: =SUM(I18,I35) -> 1413 | J36: =SUM(J18,J35) -> 0 | ... Y36: =SUM(Y18,Y35) -> 22238.47

Sheet Июль 2026
A1: Доходы - Расходы Июль 2026
A2: Число | B2: День недели | C2: Магазин | D2: Вкус Вилл | E2: Доставка | F2: Обед | G2: Синабон | H2: Кафе | I2: Алкоголь | J2: Бар/Клуб | K2: Коммуналка / ЖКХ | L2: Теннис | M2: Одежда | N2: Медицина | O2: Такси | P2: Бензин/ Парковка | Q2: Аня | R2: Учеба | S2: Ежемесячны платежи | T2: Другое (повседневное) | U2: Другое (повседневное) | V2: Другое (развлечения) | W2: Итого Расходы | X2: Арестованные средства | Y2: Доходы | Z2: Сальдо
A3: 3 | B3: Пт | C3: =100 -> 100 | L3: =150+3000 -> 3150 | Q3: =10000 -> 10000 | S3: 799 | W3: =SUM(C3:V3) -> 14049 | X3: 72082.18 | Y3: =(94085+57723.67) -> 151808.67
A4: 4 | B4: Сб | C4: 528.92 | D4: =403+3617.41 -> 4020.41 | H4: =3760 -> 3760 | I4: 1320.98 | O4: =290+215 -> 505 | T4: 398 | W4: =SUM(C4:V4) -> 10533.31
A5: 5 | B5: Вс | C5: =441+815 -> 1256 | S5: 199 | W5: =SUM(C5:V5) -> 1455
A6: 6 | B6: Пн | D6: 628.84 | O6: 225 | V6: 950 | W6: =SUM(C6:V6) -> 1803.84
A7: 7 | B7: Вт | C7: =1534.21+320.4 -> 1854.61 | D7: 292 | F7: 960 | O7: 196 | W7: =SUM(C7:V7) -> 3302.61
A8: 8 | B8: Ср | C8: 233 | Q8: =490+690 -> 1180 | S8: 842 | W8: =SUM(C8:V8) -> 2255 | AC8: Сводные итоги за июль 2026 г.
A9: 9 | B9: Чт | O9: 395 | S9: 700 | W9: =SUM(C9:V9) -> 1095
A10: 10 | B10: Пт | E10: 2500 | O10: =473+161 -> 634 | S10: 990 | T10: 790 | W10: =SUM(C10:V10) -> 4914
A11: 11 | B11: Сб | C11: =132.68+3500 -> 3632.68 | I11: 1000 | W11: =SUM(C11:V11) -> 4632.68 | AC11: Заработал | AG11: =Y3+Y14+Y21 -> 226341.31
A12: 12 | B12: Вс | Q12: 4475 | W12: =SUM(C12:V12) -> 4475 | AC12: Подарили | AG12: =Y27 -> 20000
A13: 13 | B13: Пн | O13: 303 | Q13: 2870 | S13: 842.63 | W13: =SUM(C13:V13) -> 4015.63 | AC13: Взял в долг | AG13: =Y17+Y19 -> 25000
A14: 14 | B14: Вт | C14: =219+2054.78 -> 2273.78 | W14: =SUM(C14:V14) -> 2273.78 | X14: 14878.51 | Y14: 37634 | AC14: Потратил всего | AG14: =W38 -> 177971.36
A15: 15 | B15: Ср | C15: 364 | D15: 584 | O15: 328 | Q15: =1500+1120.98 -> 2620.98 | S15: 200 | W15: =SUM(C15:V15) -> 4096.98 | AC15: Еда | AG15: =SUM(C38:H38) -> 55416.04
A16: 16 | B16: Чт | E16: 2850 | F16: 1080 | M16: 598 | O16: 413 | T16: 1200 | W16: =SUM(C16:V16) -> 6141 | AC16: на Аню | AG16: =Q38 -> 27468.98
A17: 17 | B17: Пт | C17: =700 -> 700 | M17: 7899 | O17: =220 -> 220 | S17: 700 | T17: 800 | U17: =1825+2217+2419 -> 6461 | W17: =SUM(C17:V17) -> 16780 | Y17: 15000
A18: 18 | B18: Сб | D18: 2018.8 | S18: 499 | U18: 8000 | W18: =SUM(C18:V18) -> 10517.8
A19: 19 | B19: Вс | D19: 2376.09 | E19: 3600 | V19: =83+760+400+6869+83+83+1800+850+1033.84+1423+1349+694+83+6000+1800+305 -> 23615.84 | W19: =SUM(C19:V19) -> 29591.93 | Y19: 10000
A20: Итоги по ЗП: | C20: =SUM(C3:C17) -> 10942.99 | D20: =SUM(D3:D17) -> 5525.25 | E20: =SUM(E3:E17) -> 5350 | F20: =SUM(F3:F17) -> 2040 | G20: =SUM(G3:G17) -> 0 | H20: =SUM(H3:H17) -> 3760 | I20: =SUM(I3:I17) -> 2320.98 | J20: =SUM(J3:J17) -> 0 | ... V20: =SUM(V3:V17) -> 950 | W20: =SUM(W3:W19) -> 121932.56 | X20: =SUM(X3:X19) -> 86960.69 | Y20: =SUM(Y3:Y19) -> 214442.67 | Z20: =Y20-W20-X20 -> 5549.42
A21: 20 | B21: Пн | C21: 44 | F21: 1770 | O21: 572 | Q21: 3400 | T21: 856 | W21: =SUM(C21:V21) -> 6642 | Y21: 36898.64
A22: 21 | B22: Вт | C22: =80 -> 80 | D22: 883 | O22: 334 | T22: 79 | W22: =SUM(C22:V22) -> 1376 | X22: 23662.84
A23: 22 | B23: Ср | D23: 162 | F23: 690 | O23: 325 | S23: 843 | W23: =SUM(C23:V23) -> 2020
A24: 23 | B24: Чт | D24: 192 | F24: 1960 | O24: =537+185 -> 722 | Q24: 1000 | W24: =SUM(C24:V24) -> 3874
A25: 24 | B25: Пт | D25: =1377+2099.31-149 -> 3327.31 | H25: 2414 | P25: 152 | V25: 2000 | W25: =SUM(C25:V25) -> 7893.31
A26: 25 | B26: Сб | C26: 3084 | D26: 245 | W26: =SUM(C26:V26) -> 3329
A27: 26 | B27: Вс | C27: 185 | D27: 1332 | E27: 3180 | V27: 2800 | W27: =SUM(C27:V27) -> 7497 | Y27: 20000
A28: 27 | B28: Пн | P28: 338 | S28: 249 | T28: =3790+3780+3004 -> 10574 | W28: =SUM(C28:V28) -> 11161
A29: 28 | B29: Вт | P29: 307 | Q29: 1223 | W29: =SUM(C29:V29) -> 1530
A30: 29 | B30: Ср | F30: 1080 | Q30: =400+300 -> 700 | W30: =SUM(C30:V30) -> 1780
A31: 30 | B31: Чт | W31: =SUM(C31:V31) -> 0
A32: 31 | B32: Пт | W32: =SUM(C32:V32) -> 0
A33: 1 | B33: Сб | W33: =SUM(C33:V33) -> 0 | Y33: 10000
A34: 2 | B34: Вс | S34: 799 | T34: 100 | W34: =SUM(C34:V34) -> 899
A35: 3 | B35: Пн | E35: 2327 | F35: =1610+175.49 -> 1785.49 | O35: 270 | S35: 399 | W35: =SUM(C35:V35) -> 4781.49
A36: 4 | B36: Вт | D36: 327 | H36: 2730 | S36: 199 | W36: =SUM(C36:V36) -> 3256
A37: Итого по Авансу: | C37: =SUM(C21:C36) -> 3393 | D37: =SUM(D21:D36) -> 6468.31 | E37: =SUM(E21:E36) -> 5507 | F37: =SUM(F21:F36) -> 7285.49 | G37: =SUM(G21:G36) -> 0 | H37: =SUM(H21:H36) -> 5144 | I37: =SUM(I21:I36) -> 0 | J37: =SUM(J21:J36) -> 0 | ... Y37: =SUM(Y21:Y36) -> 66898.64 | Z37: =Y37-W37-X37 -> -12803
A38: ИТОГО по месяцу: | C38: =SUM(C20,C37) -> 14335.99 | D38: =SUM(D20,D37) -> 11993.56 | E38: =SUM(E20,E37) -> 10857 | F38: =SUM(F20,F37) -> 9325.49 | G38: =SUM(G20,G37) -> 0 | H38: =SUM(H20,H37) -> 8904 | I38: =SUM(I20,I37) -> 2320.98 | J38: =SUM(J20,J37) -> 0 | ... Z38: =SUM(Z20,Z37) -> -7253.58

Sheet Август 2026
A1: Доходы - Расходы Август 2026
C2: ЕДА | L2: Базовые потребности (на которых не сэкономить) | R2: Отдых, развлечение, быт и излишки (все на чем в теории можно сэкономить) | AB2: ИТОГИ
A3: Число | B3: День недели | C3: Ярче | D3: Магнит/Пятерочка | E3: Перекресток | F3: Вкус Вилл | G3: Яндекс Лавка / Самокат | H3: Доставка из ресторанов | I3: Поход в ресторан | J3: Поход в фаст фуд | K3: Обеды | L3: Коммуналка / ЖКХ | M3: Медицина | N3: Ежемесячные платежи | O3: Другое (повседневное) | P3: Другое (повседневное) | Q3: Дргое (форс-мажорное) | R3: Алкоголь | S3: Теннис | T3: Одежда | U3: Такси | V3: Бензин/ Парковка | W3: Аня | X3: Другое (покупки) | Y3: Другое (покупки) | Z3: Друггое (развлечения) | AA3: Другое (развлечения) | AB3: Итого Расходы | AC3: Доходы | AD3: Сальдо
A4: 5 | B4: Ср | C4: 429.95 | I4: =4660+545 -> 5205 | O4: 100 | P4: 10000 | X4: 1237 | AB4: =SUM(C4:AA4) -> 16971.95 | AC4: =37635+40252.26+18817.85 -> 96705.11
A5: 6 | B5: Чт | F5: 351 | L5: =5748.49+2803.26+2306.38 -> 10858.13 | Q5: 3500 | U5: 294 | W5: 1500 | AB5: =SUM(C5:AA5) -> 16503.13
A6: 7 | B6: Пт | J6: 838 | V6: 158.61 | AB6: =SUM(C6:AA6) -> 996.61
A7: 8 | B7: Сб | F7: 1461 | G7: 821 | I7: =2510+220 -> 2730 | J7: 730 | O7: 100 | Z7: =2626-2500 -> 126 | AB7: =SUM(C7:AA7) -> 5968
A8: 9 | B8: Вс | E8: 2510 | J8: 1534 | W8: =400+1115+3400+1409.98+1800 -> 8124.98 | AB8: =SUM(C8:AA8) -> 12168.98
A9: 10 | B9: Пн | K9: 1860 | N9: =700+990 -> 1690 | P9: 2000 | U9: 420 | AB9: =SUM(C9:AA9) -> 5970
A10: 11 | B10: Вт | Q10: 500 | U10: =207+380 -> 587 | W10: 1180 | X10: 990 | AB10: =SUM(C10:AA10) -> 3257
A11: 12 | B11: Ср | F11: =210+424 -> 634 | W11: 400 | AB11: =SUM(C11:AA11) -> 1034 | AH11: Сводные итоги за август 2026 г.
A12: 13 | B12: Чт | K12: 420 | U12: =399+300 -> 699 | W12: =517+1080+787+83 -> 2467 | AB12: =SUM(C12:AA12) -> 3586
A13: 14 | B13: Пт | I13: =2220+250 -> 2470 | U13: 384 | W13: =2720+315 -> 3035 | AB13: =SUM(C13:AA13) -> 5889
A14: 15 | B14: Сб | C14: 973.94 | H14: 4470 | W14: =1319.99+329 -> 1648.99 | AB14: =SUM(C14:AA14) -> 7092.93 | AH14: Заработал | AL14: =AC4+AC20 -> 133443.15
A15: 16 | B15: Вс | D15: 97.3 | J15: =539.98+147+1271 -> 1957.98 | V15: 2049 | W15: =490+380 -> 870 | X15: 990 | Z15: =170+170+170+170 -> 680 | AB15: =SUM(C15:AA15) -> 6644.28 | AH15: Подарили | AL15: =AC29 -> 1000
A16: 17 | B16: Пн | G16: =354+1199 -> 1553 | I16: 1710 | N16: =700+499 -> 1199 | V16: 313.19 | X16: 330 | AB16: =SUM(C16:AA16) -> 5105.19 | AH16: Взял в долг | AL16: =AC21+AC34 -> 11000
A17: 18 | B17: Вт | V17: 280.97 | AB17: =SUM(C17:AA17) -> 280.97 | AH17: Потратил всего | AL17: =AB36 -> 146501.73
A18: 19 | B18: Ср | U18: =382+190 -> 572 | X18: =384.98 -> 384.98 | AB18: =SUM(C18:AA18) -> 956.98 | AH18: Еда | AL18: =SUM(C36:K36) -> 56967.92
A19: Итоги по ЗП: | C19: =SUM(C4:C18) -> 1403.89 | D19: =SUM(D4:D18) -> 97.3 | E19: =SUM(E4:E18) -> 2510 | F19: =SUM(F4:F18) -> 2446 | G19: =SUM(G4:G18) -> 2374 | H19: =SUM(H4:H18) -> 4470 | I19: =SUM(I4:I18) -> 12115 | J19: =SUM(J4:J18) -> 5059.98 | ... AC19: =SUM(AC4:AC18) -> 96705.11 | AD19: =AC19-AB19 -> 4280.09 | AH19: Базовые потребности | AL19: =SUM(L36:Q36) -> 31394.13
A20: 20 | B20: Чт | C20: =1527.91-1000 -> 527.91 | D20: =399.97 -> 399.97 | K20: =880 -> 880 | R20: 1000 | U20: 311 | W20: =2000+1000 -> 3000 | AB20: =SUM(C20:AA20) -> 6118.88 | AC20: 36738.04 | AH20: на Аню | AL20: =W36 -> 35678.97
A21: 21 | B21: Пт | D21: =231+493.2 -> 724.2 | F21: 104 | I21: =170+1740 -> 1910 | U21: 243 | AB21: =SUM(C21:AA21) -> 2981.2 | AC21: 10000 | AH21: Транспорт | AL21: =SUM(U36:V36) -> 11008.46
A22: 22 | B22: Сб | AB22: =SUM(C22:AA22) -> 0 | AH22: Одежда | AL22: =T36 -> 0
A23: 23 | B23: Вс | J23: =1357+194+197 -> 1748 | R23: =798.27 -> 798.27 | V23: =1707.5-201.49 -> 1506.01 | W23: =329+2500 -> 2829 | AB23: =SUM(C23:AA23) -> 6881.28 | AH23: Необязательные покупки | AL23: =X36 -> 5267.98
A24: 24 | B24: Пн | C24: 785.88 | D24: =589.98 -> 589.98 | H24: 2450 | K24: =1800+196.2 -> 1996.2 | V24: 304.63 | AB24: =SUM(C24:AA24) -> 6126.69
A25: 25 | B25: Вт | K25: =1640+110 -> 1750 | W25: 6000 | AB25: =SUM(C25:AA25) -> 7750
A26: 26 | B26: Ср | N26: =249 -> 249 | W26: =704+500+400 -> 1604 | X26: 950 | AB26: =SUM(C26:AA26) -> 2803
A27: 27 | B27: Чт | C27: 149.96 | K27: =1240 -> 1240 | U27: 313 | X27: 386 | AB27: =SUM(C27:AA27) -> 2088.96
A28: 28 | B28: Пт | U28: 288 | W28: =1180 -> 1180 | Z28: 2000 | AB28: =SUM(C28:AA28) -> 3468
A29: 29 | B29: Сб | C29: =705.95 -> 705.95 | D29: =329.99+356.95+143.98 -> 830.92 | J29: =841 -> 841 | Z29: =1580 -> 1580 | AB29: =SUM(C29:AA29) -> 3957.87 | AC29: 1000
A30: 30 | B30: Вс | J30: =1510 -> 1510 | N30: =799 -> 799 | V30: =1707.5 -> 1707.5 | AB30: =SUM(C30:AA30) -> 4016.5
A31: 31 | B31: Пн | D31: 131.78 | K31: =2450+220 -> 2670 | AB31: =SUM(C31:AA31) -> 2801.78
A32: 1 | B32: Вт | F32: 396 | K32: =1870 -> 1870 | V32: 301.11 | W32: =320+920 -> 1240 | AB32: =SUM(C32:AA32) -> 3807.11
A33: 2 | B33: Ср | N33: 399 | V33: =276.44 -> 276.44 | AB33: =SUM(C33:AA33) -> 675.44
A34: 3 | B34: Чт | W34: =1000+100-500 -> 600 | AB34: =SUM(C34:AA34) -> 600 | AC34: 1000
A35: Итого по Авансу: | C35: =SUM(C20:C34) -> 2169.7 | D35: =SUM(D20:D34) -> 2676.85 | E35: =SUM(E20:E34) -> 0 | F35: =SUM(F20:F34) -> 500 | G35: =SUM(G20:G34) -> 0 | H35: =SUM(H20:H34) -> 2450 | I35: =SUM(I20:I34) -> 1910 | J35: =SUM(J20:J34) -> 4099 | ... AC35: =SUM(AC20:AC34) -> 48738.04 | AD35: =AC35-AB35 -> -5338.67
A36: ИТОГО по месяцу: | C36: =SUM(C19,C35) -> 3573.59 | D36: =SUM(D19,D35) -> 2774.15 | E36: =SUM(E19,E35) -> 2510 | F36: =SUM(F19,F35) -> 2946 | G36: =SUM(G19,G35) -> 2374 | H36: =SUM(H19,H35) -> 6920 | I36: =SUM(I19,I35) -> 14025 | J36: =SUM(J19,J35) -> 9158.98 | ... R36: =SUM(R19,R35) -> 1798.27 | T36: =SUM(T19,T35) -> 0 | U36: =SUM(U19,U35) -> 4111 | V36: =SUM(V19,V35) -> 6897.46 | W36: =SUM(W19,W35) -> 35678.97 | X36: =SUM(X19,X35) -> 5267.98 | Y36: =SUM(Y19,Y35) -> 0 | Z36: =SUM(Z19,Z35) -> 4386 | AA36: =SUM(AA19,AA35) -> 0 | ... AD36: =SUM(AD19,AD35) -> -1058.58

Sheet Сентябрь 2026
A1: Доходы - Расходы Сентябрь 2026
C2: ЕДА | L2: Базовые потребности (на которых не сэкономить) | R2: Отдых, развлечение, быт и излишки (все на чем в теории можно сэкономить) | AB2: ИТОГИ
A3: Число | B3: День недели | C3: Ярче | D3: Магнит / Пятерочка | E3: Перекресток / Метро / Глобус | F3: Вкус Вилл | G3: Яндекс Лавка / Самокат | H3: Доставка из ресторанов | I3: Поход в ресторан | J3: Поход в фаст фуд | K3: Обеды | L3: Коммуналка / ЖКХ | M3: Медицина | N3: Ежемесячные платежи | O3: Другое (повседневное) | P3: Другое (повседневное) | Q3: Дргое (форс-мажорное) | R3: Алкоголь | S3: Теннис | T3: Одежда | U3: Такси | V3: Бензин/ Парковка | W3: Аня | X3: Другое (покупки) | Y3: Другое (покупки) | Z3: Друггое (развлечения) | AA3: Другое (развлечения) | AB3: Итого Расходы | AC3: Доходы | AD3: Сальдо
A4: 4 | B4: Пт | D4: 45.99 | X4: 750 | Y4: 300 | Z4: =3022 -> 3022 | AB4: =SUM(C4:AA4) -> 4117.99 | AC4: =66577.47+18817 -> 85394.47
A5: 5 | B5: Сб | H5: =2730 -> 2730 | J5: 2005 | M5: =350+500 -> 850 | N5: 199 | U5: =236+297 -> 533 | X5: =799 -> 799 | AB5: =SUM(C5:AA5) -> 7116
A6: 6 | B6: Вс | I6: =2230 -> 2230 | T6: =9219 -> 9219 | W6: =5697 -> 5697 | AB6: =SUM(C6:AA6) -> 17146
A7: 7 | B7: Пн | C7: 129.99 | D7: =799.99 -> 799.99 | K7: =1770 -> 1770 | V7: 339.88 | W7: =607 -> 607 | X7: 2000 | Y7: =559.98 -> 559.98 | AB7: =SUM(C7:AA7) -> 6206.84
A8: 8 | B8: Вт | D8: =318 -> 318 | F8: =2881+306 -> 3187 | H8: 310 | K8: =2240 -> 2240 | M8: =1049 -> 1049 | O8: =500 -> 500 | W8: =600 -> 600 | AB8: =SUM(C8:AA8) -> 8204
A9: 9 | B9: Ср | G9: =1745 -> 1745 | K9: 2480 | U9: 306 | W9: =3745 -> 3745 | AB9: =SUM(C9:AA9) -> 8276
A10: 10 | B10: Чт | F10: =89+367 -> 456 | N10: 700 | U10: 269 | AB10: =SUM(C10:AA10) -> 1425 | AC10: 28225.5
A11: 11 | B11: Пт | F11: 681 | K11: =1920+590 -> 2510 | N11: 300 | V11: 147.53 | Z11: 2000 | AB11: =SUM(C11:AA11) -> 5638.53 | AH11: Сводные итоги за август 2026 г.
A12: 12 | B12: Сб | J12: =1560 -> 1560 | Q12: =20000 -> 20000 | T12: =1800+975+2280+5116 -> 10171 | U12: =343+301 -> 644 | X12: =990 -> 990 | AB12: =SUM(C12:AA12) -> 33365
A13: 13 | B13: Вс | E13: 500.98 | F13: =2775 -> 2775 | I13: 1425 | J13: =589.99+189.99 -> 779.98 | R13: =1140 -> 1140 | U13: =235 -> 235 | W13: =2690+1420 -> 4110 | AB13: =SUM(C13:AA13) -> 10965.96
A14: 14 | B14: Пн | F14: =836 -> 836 | G14: =488 -> 488 | V14: =290.53 -> 290.53 | AB14: =SUM(C14:AA14) -> 1614.53 | AH14: Заработал | AL14: =AC4+AC19+AC23+AC10 -> 287751.42
A15: 15 | B15: Вт | I15: =1200 -> 1200 | J15: =1378 -> 1378 | U15: =383 -> 383 | V15: =1999.82 -> 1999.82 | W15: =2000 -> 2000 | AB15: =SUM(C15:AA15) -> 6960.82 | AH15: Подарили | AL15: =AC20 -> 1000
A16: 16 | B16: Ср | N16: =700 -> 700 | V16: =281.97 -> 281.97 | W16: =2500 -> 2500 | AB16: =SUM(C16:AA16) -> 3481.97 | AC16: 5000 | AH16: Взял в долг | AL16: =AC16+AC28+AC34+AC35 -> 60000
A17: 17 | B17: Чт | H17: =1586 -> 1586 | M17: =1417 -> 1417 | N17: =499 -> 499 | Q17: =500 -> 500 | W17: =1000 -> 1000 | AB17: =SUM(C17:AA17) -> 5002 | AH17: ЕДА | AL17: =SUM(C37:K37) -> 121331.08
A18: Итоги по ЗП: | C18: =SUM(C4:C17) -> 129.99 | D18: =SUM(D4:D17) -> 1163.98 | E18: =SUM(E4:E17) -> 500.98 | F18: =SUM(F4:F17) -> 7935 | G18: =SUM(G4:G17) -> 2233 | H18: =SUM(H4:H17) -> 4626 | I18: =SUM(I4:I17) -> 4855 | J18: =SUM(J4:J17) -> 5722.98 | K18: =SUM(K4:K17) -> 9000 | L18: =SUM(L5:L17) -> 0 | M18: =SUM(M5:M17) -> 3316 | N18: =SUM(N5:N17) -> 2398 | O18: =SUM(O5:O17) -> 500 | P18: =SUM(P5:P17) -> 0 | Q18: =SUM(Q5:Q17) -> 20500 | R18: =SUM(R4:R17) -> 1140 | S18: =SUM(S4:S17) -> 0 | T18: =SUM(T4:T17) -> 19390 | U18: =SUM(U4:U17) -> 2370 | V18: =SUM(V4:V17) -> 3059.73 | W18: =SUM(W4:W17) -> 20259 | X18: =SUM(X4:X17) -> 4539 | Y18: =SUM(Y4:Y17) -> 859.98 | ... AC18: =SUM(AC4:AC17) -> 118619.97 | AD18: =AC18-AB18 -> -900.67 | AH18: Базовые потребности | AL18: =SUM(L37:Q37) -> 35695
A19: 18 | B19: Пт | I19: =3390+300 -> 3690 | U19: =275+307 -> 582 | X19: =999 -> 999 | AB19: =SUM(C19:AA19) -> 5271 | AC19: 38575.45 | AH19: на Аню | AL19: =W37 -> 38934
A20: 19 | B20: Сб | F20: =3104.71 -> 3104.71 | I20: =1600+220+2320 -> 4140 | M20: =2000 -> 2000 | W20: =1010 -> 1010 | AB20: =SUM(C20:AA20) -> 10254.71 | AC20: 1000 | AH20: Транспорт | AL20: =SUM(U37:V37) -> 15264.08
A21: 20 | B21: Вс | I21: =1980 -> 1980 | AB21: =SUM(C21:AA21) -> 1980 | AH21: Одежда | AL21: =T37 -> 31093
A22: 21 | B22: Пн | G22: =552 -> 552 | J22: =1197 -> 1197 | K22: =1670 -> 1670 | V22: =291.54 -> 291.54 | AB22: =SUM(C22:AA22) -> 3710.54
A23: 22 | B23: Вт | G23: 374 | I23: =1800+220 -> 2020 | W23: 5000 | AA23: 56000 | AB23: =SUM(C23:AA23) -> 63394 | AC23: =21986+70637+42933 -> 135556
A24: 23 | B24: Ср | F24: =394 -> 394 | J24: =1079 -> 1079 | M24: =702 -> 702 | U24: =644 -> 644 | V24: =2049+108.26+148.04+283.99 -> 2589.29 | X24: =2444+831 -> 3275 | AA24: =8796.64+8813.48 -> 17610.12 | AB24: =SUM(C24:AA24) -> 26293.41
A25: 24 | B25: Чт | F25: =185 -> 185 | U25: =357 -> 357 | AB25: =SUM(C25:AA25) -> 542
A26: 25 | B26: Пт | D26: =815.85 -> 815.85 | F26: =411 -> 411 | J26: =660 -> 660 | K26: =2170 -> 2170 | N26: =249 -> 249 | R26: =1300.98 -> 1300.98 | V26: =249.24 -> 249.24 | AB26: =SUM(C26:AA26) -> 5856.07
A27: 26 | B27: Сб | C27: =222.97+157.22 -> 380.19 | E27: =1135.08+ 2134.94+279.99 -> 3550.01 | M27: =2643 -> 2643 | T27: =6110 -> 6110 | W27: =1398 -> 1398 | AB27: =SUM(C27:AA27) -> 14081.2
A28: 27 | B28: Вс | C28: =912.9 -> 912.9 | AB28: =SUM(C28:AA28) -> 912.9 | AC28: 20000
A29: 28 | B29: Пн | D29: 1239.95 | F29: 438 | V29: =341.89 -> 341.89 | W29: =2000 -> 2000 | AB29: =SUM(C29:AA29) -> 4019.84
A30: 29 | B30: Вт | F30: =162 -> 162 | J30: =1326 -> 1326 | N30: =799 -> 799 | V30: =341.39 -> 341.39 | AB30: =SUM(C30:AA30) -> 2628.39
A31: 30 | B31: Ср | F31: =586 -> 586 | O31: 1200 | P31: =389 -> 389 | T31: =5593 -> 5593 | V31: =2124 -> 2124 | W31: =1515+934+248 -> 2697 | AB31: =SUM(C31:AA31) -> 12589
A32: 1 | B32: Чт | F32: 2323.1 | I32: =4290+463.32 -> 4753.32 | J32: =1360 -> 1360 | K32: =980 -> 980 | O32: =300 -> 300 | U32: =337 -> 337 | W32: =1289+1202 -> 2491 | Z32: =6000 -> 6000 | AB32: =SUM(C32:AA32) -> 18544.42
A33: 2 | B33: Пт | I33: =2839+4140+447.12 -> 7426.12 | N33: =399 -> 399 | R33: =1510.97 -> 1510.97 | U33: =95+95 -> 190 | AB33: =SUM(C33:AA33) -> 9526.09
A34: 3 | B34: Сб | H34: =1564+7651 -> 9215 | I34: =3010+300 -> 3310 | J34: =820 -> 820 | R34: =3528 -> 3528 | W34: =4079 -> 4079 | X34: =300 -> 300 | Z34: =1700 -> 1700 | AB34: =SUM(C34:AA34) -> 22952 | AC34: 20000
A35: 4 | B35: Вс | I35: =5900+651+13880+1508 -> 21939 | N35: =300 -> 300 | U35: =423+526+838 -> 1787 | X35: =375 -> 375 | Z35: =1400 -> 1400 | AB35: =SUM(C35:AA35) -> 25801 | AC35: 15000
A36: Итого по Авансу: | C36: =SUM(C19:C35) -> 1293.09 | D36: =SUM(D19:D35) -> 2055.8 | E36: =SUM(E19:E35) -> 3550.01 | F36: =SUM(F19:F35) -> 7603.81 | G36: =SUM(G19:G35) -> 926 | H36: =SUM(H19:H35) -> 9215 | I36: =SUM(I19:I35) -> 49258.44 | J36: =SUM(J19:J35) -> 6442 | ... AC36: =SUM(AC19:AC35) -> 230131.45 | AD36: =AC36-AB36 -> 1774.88
A37: ИТОГО по месяцу: | C37: =SUM(C18,C36) -> 1423.08 | D37: =SUM(D18,D36) -> 3219.78 | E37: =SUM(E18,E36) -> 4050.99 | F37: =SUM(F18,F36) -> 15538.81 | G37: =SUM(G18,G36) -> 3159 | H37: =SUM(H18,H36) -> 13841 | I37: =SUM(I18,I36) -> 54113.44 | J37: =SUM(J18,J36) -> 12164.98 | ... R37: =SUM(R18,R36) -> 7479.95 | T37: =SUM(T18,T36) -> 31093 | U37: =SUM(U18,U36) -> 6267 | V37: =SUM(V18,V36) -> 8997.08 | W37: =SUM(W18,W36) -> 38934 | X37: =SUM(X18,X36) -> 9488 | Y37: =SUM(Y18,Y36) -> 859.98 | Z37: =SUM(Z18,Z36) -> 14122 | AA37: =SUM(AA18,AA36) -> 73610.12 | ... AD37: =SUM(AD18,AD36) -> 874.21

Sheet Октябрь 2026
A1: Доходы - Расходы Октябрь 2026
C2: ЕДА | L2: Базовые потребности (на которых не сэкономить) | R2: Отдых, развлечение, быт и излишки (все на чем в теории можно сэкономить) | AB2: ИТОГИ
A3: Число | B3: День недели | C3: Ярче | D3: Магнит / Пятерочка | E3: Перекресток / Метро / Глобус | F3: Вкус Вилл | G3: Яндекс Лавка / Самокат | H3: Доставка из ресторанов | I3: Поход в ресторан | J3: Поход в фаст фуд | K3: Обеды | L3: Коммуналка / ЖКХ | M3: Медицина | N3: Ежемесячные платежи | O3: Другое (повседневное) | P3: Другое (повседневное) | Q3: Дргое (форс-мажорное) | R3: Алкоголь | S3: Теннис | T3: Одежда | U3: Такси | V3: Бензин/ Парковка | W3: Аня | X3: Другое (покупки) | Y3: Другое (покупки) | Z3: Друггое (развлечения) | AA3: Другое (развлечения) | AB3: Итого Расходы | AC3: Доходы | AD3: Сальдо
A4: 5 | B4: Пн | E4: 300.96 | I4: =5000+415.8 -> 5415.8 | N4: 199 | U4: =190+190 -> 380 | W4: =1000+3865 -> 4865 | X4: 20000 | AB4: =SUM(C4:AA4) -> 31160.76 | AC4: 142200.86
A5: 6 | B5: Вт | I5: =5020+655+6960+1134 -> 13769 | O5: =1930+3470 -> 5400 | P5: 11093 | U5: =190+190 -> 380 | W5: =4500+11525 -> 16025 | Z5: =1000 -> 1000 | AB5: =SUM(C5:AA5) -> 47667
A6: 7 | B6: Ср | I6: =4210+461 -> 4671 | J6: =290 -> 290 | Q6: =300 -> 300 | U6: =391 -> 391 | X6: =3807 -> 3807 | AB6: =SUM(C6:AA6) -> 9459
A7: 8 | B7: Чт | C7: =273.98 -> 273.98 | D7: =556.94 -> 556.94 | M7: =2001+69 -> 2070 | U7: =182 -> 182 | AB7: =SUM(C7:AA7) -> 3082.92 | AC7: 2000
A8: 9 | B8: Пт | F8: =2946.51 -> 2946.51 | AB8: =SUM(C8:AA8) -> 2946.51
A9: 10 | B9: Сб | C9: =1177.84 -> 1177.84 | X9: =500 -> 500 | AB9: =SUM(C9:AA9) -> 1677.84
A10: 11 | B10: Вс | F10: =1640 -> 1640 | AB10: =SUM(C10:AA10) -> 1640
A11: 12 | B11: Пн | AB11: =SUM(C11:AA11) -> 0 | AH11: Сводные итоги за август 2026 г.
A12: 13 | B12: Вт | AB12: =SUM(C12:AA12) -> 0
A13: 14 | B13: Ср | AB13: =SUM(C13:AA13) -> 0
A14: 15 | B14: Чт | AB14: =SUM(C14:AA14) -> 0 | AH14: Заработал | AL14: =AC4+AC20+AC24+AC10 -> 142200.86
A15: 16 | B15: Пт | AB15: =SUM(C15:AA15) -> 0 | AH15: Подарили | AL15: =AC21 -> 0
A16: 17 | B16: Сб | AB16: =SUM(C16:AA16) -> 0 | AH16: Взял в долг | AL16: =AC16+AC29+AC35+#REF! -> #REF!
A17: 18 | B17: Вс | AB17: =SUM(C17:AA17) -> 0 | AH17: ЕДА | AL17: =SUM(C37:K37) -> 31042.03
A18: 19 | B18: Пн | AB18: =SUM(C18:AA18) -> 0
A19: Итоги по ЗП: | C19: =SUM(C4:C18) -> 1451.82 | D19: =SUM(D4:D18) -> 556.94 | E19: =SUM(E4:E18) -> 300.96 | F19: =SUM(F4:F18) -> 4586.51 | G19: =SUM(G4:G18) -> 0 | H19: =SUM(H4:H18) -> 0 | I19: =SUM(I4:I18) -> 23855.8 | J19: =SUM(J4:J18) -> 290 | K19: =SUM(K4:K18) -> 0 | L19: =SUM(L5:L18) -> 0 | M19: =SUM(M5:M18) -> 2070 | N19: =SUM(N5:N18) -> 0 | O19: =SUM(O5:O18) -> 5400 | P19: =SUM(P5:P18) -> 11093 | Q19: =SUM(Q5:Q18) -> 300 | R19: =SUM(R4:R18) -> 0 | S19: =SUM(S4:S18) -> 0 | T19: =SUM(T4:T18) -> 0 | U19: =SUM(U4:U18) -> 1333 | V19: =SUM(V4:V18) -> 0 | W19: =SUM(W4:W18) -> 20890 | X19: =SUM(X4:X18) -> 24307 | Y19: =SUM(Y4:Y18) -> 0 | ... AB19: =SUM(AB4:AB18) -> 97634.03 | AC19: =SUM(AC4:AC17) -> 144200.86 | AD19: =AC19-AB19 -> 46566.83 | AH19: Базовые потребности | AL19: =SUM(L37:Q37) -> 18863
A20: 20 | B20: Вт | AB20: =SUM(C20:AA20) -> 0 | AH20: на Аню | AL20: =W37 -> 20890
A21: 21 | B21: Ср | AB21: =SUM(C21:AA21) -> 0 | AH21: Транспорт | AL21: =SUM(U37:V37) -> 1333
A22: 22 | B22: Чт | AB22: =SUM(C22:AA22) -> 0 | AH22: Одежда | AL22: =T37 -> 0
A23: 23 | B23: Пт | AB23: =SUM(C23:AA23) -> 0
A24: 24 | B24: Сб | AB24: =SUM(C24:AA24) -> 0
A25: 25 | B25: Вс | AB25: =SUM(C25:AA25) -> 0
A26: 26 | B26: Пн | AB26: =SUM(C26:AA26) -> 0
A27: 27 | B27: Вт | AB27: =SUM(C27:AA27) -> 0
A28: 28 | B28: Ср | AB28: =SUM(C28:AA28) -> 0
A29: 29 | B29: Чт | AB29: =SUM(C29:AA29) -> 0
A30: 30 | B30: Пт | AB30: =SUM(C30:AA30) -> 0
A31: 31 | B31: Сб | AB31: =SUM(C31:AA31) -> 0
A32: 1 | B32: Вс | AB32: =SUM(C32:AA32) -> 0
A33: 2 | B33: Пн | AB33: =SUM(C33:AA33) -> 0
A34: 3 | B34: Вт | AB34: =SUM(C34:AA34) -> 0
A35: 4 | B35: Ср | AB35: =SUM(C35:AA35) -> 0
A36: Итого по Авансу: | C36: =SUM(C20:C35) -> 0 | D36: =SUM(D20:D35) -> 0 | E36: =SUM(E20:E35) -> 0 | F36: =SUM(F20:F35) -> 0 | G36: =SUM(G20:G35) -> 0 | H36: =SUM(H20:H35) -> 0 | I36: =SUM(I20:I35) -> 0 | J36: =SUM(J20:J35) -> 0 | ... AC36: =SUM(AC20:AC35) -> 0 | AD36: =AC36-AB36 -> 0
A37: ИТОГО по месяцу: | C37: =SUM(C19,C36) -> 1451.82 | D37: =SUM(D19,D36) -> 556.94 | E37: =SUM(E19,E36) -> 300.96 | F37: =SUM(F19,F36) -> 4586.51 | G37: =SUM(G19,G36) -> 0 | H37: =SUM(H19,H36) -> 0 | I37: =SUM(I19,I36) -> 23855.8 | J37: =SUM(J19,J36) -> 290 | ... R37: =SUM(R19,R36) -> 0 | T37: =SUM(T19,T36) -> 0 | U37: =SUM(U19,U36) -> 1333 | V37: =SUM(V19,V36) -> 0 | W37: =SUM(W19,W36) -> 20890 | X37: =SUM(X19,X36) -> 24307 | Y37: =SUM(Y19,Y36) -> 0 | Z37: =SUM(Z19,Z36) -> 1000 | AA37: =SUM(AA19,AA36) -> 0 | ... AD37: =SUM(AD19,AD36) -> 46566.83
